Workbook

Sheet From project to product what a
A1: From project to product: what a real launch costs (assumed)
A2: Launch plan · Main Scenario
A4: Variable / dimension | B4: Value
A5: Founder pay per month (one person, USD, assumed) | B5: =4000 -> 4000
A6: Part-time human safety reviewer per month (USD, assumed) | B6: =1000 -> 1000
A7: Legal retainer per month (child privacy, terms, USD, assumed) | B7: =500 -> 500
A8: Marketing and community per month (USD, assumed) | B8: =1500 -> 1500
A9: Insurance per month (cyber and product, USD, assumed) | B9: =150 -> 150
A10: Tools per month (support desk, email, error tracking, USD, assumed) | B10: =150 -> 150
A11: Payment and app-store fees, share of revenue (assumed) | B11: =0.15 -> 0.15
A12: One-time: child-privacy legal setup (consent flow, privacy policy, USD, placeholder) | B12: =8000 -> 8000
A13: One-time: data protection impact assessment (USD, placeholder) | B13: =3000 -> 3000
A14: One-time: security review (USD, placeholder) | B14: =4000 -> 4000
A15: One-time: accessibility audit (USD, placeholder) | B15: =2500 -> 2500
A16: One-time: company, trademark and domain (USD, placeholder) | B16: =1500 -> 1500
A17: One-time: test devices and a testing panel of children with parents (USD, placeholder) | B17: =2500 -> 2500
A18: One-time: human red-team of the safety screen (USD, placeholder) | B18: =2000 -> 2000
A19: Real launch operating cost per month (USD, derived) | B19: ='From project to product what a'!B5+'From project to product what a'!B6+'From project to product what a'!B7+'From project to product what a'!B8+'From project to product what a'!B9+'From project to product what a'!B10 -> 7300
A20: One-time launch cost (USD, derived) | B20: ='From project to product what a'!B12+'From project to product what a'!B13+'From project to product what a'!B14+'From project to product what a'!B15+'From project to product what a'!B16+'From project to product what a'!B17+'From project to product what a'!B18 -> 23500
A21: Cost per story, gated, Pip chooses 4 pictures (USD, estimate) | B21: =0.0199+'Model inputs'!B6+8*0.002 -> 0.1959
A22: Contribution per Household customer per month (USD, derived) | B22: ='Model inputs'!B9*(1-'From project to product what a'!B11)-'Model inputs'!B13*'From project to product what a'!B21-'Model inputs'!B14-'Model inputs'!B10 -> 2.93102
A23: Households needed to cover the real operating cost (derived) | B23: ='From project to product what a'!B19/'From project to product what a'!B22 -> 2490.6005
A24: Months of runway if starting with the one-time cost paid and 100,000 USD raised (derived, no revenue) | B24: =(100000-'From project to product what a'!B20)/'From project to product what a'!B19 -> 10.479452
A25: Household price per month that breaks even at 500 households (USD, derived) | B25: =('From project to product what a'!B19/500+'Model inputs'!B13*'From project to product what a'!B21+'Model inputs'!B14+'Model inputs'!B10)/(1-'From project to product what a'!B11) -> 20.718212

Sheet Model inputs
A1: Model inputs
A2: Integration values are aggregated snapshots; raw source records are not included.
A4: Variables
A5: Variable / segment | B5: Value
A6: Picture cost per story when Pip chooses (USD, estimate) | B6: ='Model inputs'!B16*0.04 -> 0.16
A7: Price per month (USD, assumed) | B7: 0
A8: Price per month (USD, assumed) > Classroom | B8: =29 -> 29
A9: Price per month (USD, assumed) > Household | B9: =6.99 -> 6.99
A10: Safety review cost per household per month (USD, derived) | B10: ='Model inputs'!B17*'Model inputs'!B21 -> 1.2
A11: Stories used per customer (derived) | B11: ='Model inputs'!B22*'Model inputs'!B18 -> 0
A12: Stories used per customer (derived) > Classroom | B12: ='Model inputs'!B23*'Model inputs'!B19 -> 60
A13: Stories used per customer (derived) > Household | B13: ='Model inputs'!B24*'Model inputs'!B20 -> 7.2
A14: Support cost per household per month (USD, derived) | B14: ='Model inputs'!B26/100*'Model inputs'!B15/60*'Model inputs'!B25 -> 0.4
A15: Minutes per support ticket (assumed) | B15: =12 -> 12
A16: Pictures per story when Pip chooses (from the picture budget in config) | B16: =4 -> 4
A17: Safety review cost per story (USD, derived) | B17: ='Model inputs'!B29/100*'Model inputs'!B27/60*'Model inputs'!B28 -> 0.1
A18: Stories included per month (assumed) | B18: 0
A19: Stories included per month (assumed) > Classroom | B19: =100 -> 100
A20: Stories included per month (assumed) > Household | B20: =12 -> 12
A21: Stories per household per month (assumed) | B21: =12 -> 12
A22: Stories used, share of included (assumed) | B22: 0
A23: Stories used, share of included (assumed) > Classroom | B23: =0.6 -> 0.6
A24: Stories used, share of included (assumed) > Household | B24: =0.6 -> 0.6
A25: Support hourly cost (USD, assumed) | B25: =25 -> 25
A26: Support tickets per 100 households per month (assumed) | B26: =8 -> 8
A27: Minutes per flagged story review (assumed) | B27: =10 -> 10
A28: Safety reviewer hourly cost (USD, assumed) | B28: =30 -> 30
A29: Stories flagged for a human look per 100 stories (assumed) | B29: =2 -> 2
A31: Dimensions
A32: Plan | B32: Classroom | C32: Household
