Workbook

Sheet Unit economics by plan, month 6
A1: Unit economics by plan, month 6 (Main vs Growth vs Downside)
A2: Unit economics · Main Scenario
A4: Variable / dimension | B4: 2027-03 | C4: 2027-03 > Growth | D4: 2027-03 > Downside
A5: Ending customers | B5: =SUM('Unit economics by plan, month 6'!B6,'Unit economics by plan, month 6'!B7) -> 77.51602 | C5: =SUM('Unit economics by plan, month 6'!C6,'Unit economics by plan, month 6'!C7) -> 128.01572 | D5: =SUM('Unit economics by plan, month 6'!D6,'Unit economics by plan, month 6'!D7) -> 60.372208
A6: Classroom | B6: ='Unit economics by plan (monthly'!F12+'Unit economics by plan (monthly'!G6-'Unit economics by plan (monthly'!G9 -> 13.89732 | C6: ='Model inputs'!G32+'Model inputs'!H83-'Model inputs'!H16 -> 25.03252 | D6: ='Model inputs'!G29+'Model inputs'!H80-'Model inputs'!H13 -> 12.067535
A7: Household | B7: ='Unit economics by plan (monthly'!F13+'Unit economics by plan (monthly'!G7-'Unit economics by plan (monthly'!G10 -> 63.6187 | C7: ='Model inputs'!G33+'Model inputs'!H84-'Model inputs'!H17 -> 102.9832 | D7: ='Model inputs'!G30+'Model inputs'!H81-'Model inputs'!H14 -> 48.304673
A8: Revenue (USD) | B8: =SUM('Unit economics by plan, month 6'!B9,'Unit economics by plan, month 6'!B10) -> 847.71699 | C8: =SUM('Unit economics by plan, month 6'!C9,'Unit economics by plan, month 6'!C10) -> 1445.7956 | D8: =SUM('Unit economics by plan, month 6'!D9,'Unit economics by plan, month 6'!D10) -> 687.60817
A9: Classroom | B9: ='Unit economics by plan (monthly'!G18+'Unit economics by plan (monthly'!G21 -> 403.02228 | C9: ='Model inputs'!H117+'Model inputs'!H95 -> 725.94307 | D9: ='Model inputs'!H114+'Model inputs'!H92 -> 349.95851
A10: Household | B10: ='Unit economics by plan (monthly'!G19+'Unit economics by plan (monthly'!G22 -> 444.69471 | C10: ='Model inputs'!H118+'Model inputs'!H96 -> 719.85257 | D10: ='Model inputs'!H115+'Model inputs'!H93 -> 337.64967
A11: Infra and inference (USD) | B11: =SUM('Unit economics by plan, month 6'!B12,'Unit economics by plan, month 6'!B13) -> 278.082 | C11: =SUM('Unit economics by plan, month 6'!C12,'Unit economics by plan, month 6'!C13) -> 647.60797 | D11: =SUM('Unit economics by plan, month 6'!D12,'Unit economics by plan, month 6'!D13) -> 406.4699
A12: Classroom | B12: ='Unit economics by plan (monthly'!G27+'Gross profit and margin by plan'!G8 -> 175.23462 | C12: ='Model inputs'!H54+'Model inputs'!H41 -> 429.38166 | D12: ='Model inputs'!H51+'Model inputs'!H38 -> 270.4139
A13: Household | B13: ='Unit economics by plan (monthly'!G28+'Gross profit and margin by plan'!G9 -> 102.84738 | C13: ='Model inputs'!H55+'Model inputs'!H42 -> 218.22631 | D13: ='Model inputs'!H52+'Model inputs'!H39 -> 136.056
A14: Gross profit (USD) | B14: =SUM('Unit economics by plan, month 6'!B15,'Unit economics by plan, month 6'!B16) -> 569.63499 | C14: =SUM('Unit economics by plan, month 6'!C15,'Unit economics by plan, month 6'!C16) -> 798.18766 | D14: =SUM('Unit economics by plan, month 6'!D15,'Unit economics by plan, month 6'!D16) -> 281.13828
A15: Classroom | B15: ='Unit economics by plan, month 6'!B9-'Unit economics by plan, month 6'!B12 -> 227.78766 | C15: ='Unit economics by plan, month 6'!C9-'Unit economics by plan, month 6'!C12 -> 296.56141 | D15: ='Unit economics by plan, month 6'!D9-'Unit economics by plan, month 6'!D12 -> 79.544609
A16: Household | B16: ='Unit economics by plan, month 6'!B10-'Unit economics by plan, month 6'!B13 -> 341.84733 | C16: ='Unit economics by plan, month 6'!C10-'Unit economics by plan, month 6'!C13 -> 501.62625 | D16: ='Unit economics by plan, month 6'!D10-'Unit economics by plan, month 6'!D13 -> 201.59367
A17: Gross margin | B17: =IFERROR('Unit economics by plan, month 6'!B14/'Unit economics by plan, month 6'!B8,0) -> 0.67196363 | C17: =IFERROR('Unit economics by plan, month 6'!C14/'Unit economics by plan, month 6'!C8,0) -> 0.55207503 | D17: =IFERROR('Unit economics by plan, month 6'!D14/'Unit economics by plan, month 6'!D8,0) -> 0.40886407
A18: Classroom | B18: =IFERROR('Unit economics by plan, month 6'!B15/'Unit economics by plan, month 6'!B9,0) -> 0.56519868 | C18: =IFERROR('Unit economics by plan, month 6'!C15/'Unit economics by plan, month 6'!C9,0) -> 0.40851883 | D18: =IFERROR('Unit economics by plan, month 6'!D15/'Unit economics by plan, month 6'!D9,0) -> 0.22729726
A19: Household | B19: =IFERROR('Unit economics by plan, month 6'!B16/'Unit economics by plan, month 6'!B10,0) -> 0.76872362 | C19: =IFERROR('Unit economics by plan, month 6'!C16/'Unit economics by plan, month 6'!C10,0) -> 0.69684582 | D19: =IFERROR('Unit economics by plan, month 6'!D16/'Unit economics by plan, month 6'!D10,0) -> 0.59704981
A20: Clears gross margin bar (1 = yes) | B20: =IF(IF(IF(ISERROR('Unit economics by plan, month 6'!B17>='Model inputs'!O34),'Unit economics by plan, month 6'!B17>='Model inputs'!O34,IF(OR('Unit economics by plan, month 6'!B17="",'Model inputs'!O34=""),"",'Unit economics by plan, month 6'!B17>='Model inputs'!O34))="",FALSE,IF(ISERROR('Unit economics by plan, month 6'!B17>='Model inputs'!O34),'Unit economics by plan, month 6'!B17>='Model inputs'!O34,IF(OR('Unit economics by plan, month 6'!B17="",'Model inputs'!O34=""),"",'Unit economics by plan, month 6'!B17>='Model inputs'!O34))),1,0) -> 1 | C20: =IF(IF(IF(ISERROR('Unit economics by plan, month 6'!C17>='Model inputs'!O36),'Unit economics by plan, month 6'!C17>='Model inputs'!O36,IF(OR('Unit economics by plan, month 6'!C17="",'Model inputs'!O36=""),"",'Unit economics by plan, month 6'!C17>='Model inputs'!O36))="",FALSE,IF(ISERROR('Unit economics by plan, month 6'!C17>='Model inputs'!O36),'Unit economics by plan, month 6'!C17>='Model inputs'!O36,IF(OR('Unit economics by plan, month 6'!C17="",'Model inputs'!O36=""),"",'Unit economics by plan, month 6'!C17>='Model inputs'!O36))),1,0) -> 0 | D20: =IF(IF(IF(ISERROR('Unit economics by plan, month 6'!D17>='Model inputs'!O35),'Unit economics by plan, month 6'!D17>='Model inputs'!O35,IF(OR('Unit economics by plan, month 6'!D17="",'Model inputs'!O35=""),"",'Unit economics by plan, month 6'!D17>='Model inputs'!O35))="",FALSE,IF(ISERROR('Unit economics by plan, month 6'!D17>='Model inputs'!O35),'Unit economics by plan, month 6'!D17>='Model inputs'!O35,IF(OR('Unit economics by plan, month 6'!D17="",'Model inputs'!O35=""),"",'Unit economics by plan, month 6'!D17>='Model inputs'!O35))),1,0) -> 0
A21: Runway in months (0 = not burning cash) | B21: =IF(IF(IF(ISERROR('Model inputs'!H70<0),'Model inputs'!H70<0,IF('Model inputs'!H70="","",'Model inputs'!H70<0))="",FALSE,IF(ISERROR('Model inputs'!H70<0),'Model inputs'!H70<0,IF('Model inputs'!H70="","",'Model inputs'!H70<0))),'Model inputs'!H19/-'Model inputs'!H70,0) -> 0 | C21: =IF(IF(IF(ISERROR('Model inputs'!H72<0),'Model inputs'!H72<0,IF('Model inputs'!H72="","",'Model inputs'!H72<0))="",FALSE,IF(ISERROR('Model inputs'!H72<0),'Model inputs'!H72<0,IF('Model inputs'!H72="","",'Model inputs'!H72<0))),'Model inputs'!H21/-'Model inputs'!H72,0) -> 0 | D21: =IF(IF(IF(ISERROR('Model inputs'!H71<0),'Model inputs'!H71<0,IF('Model inputs'!H71="","",'Model inputs'!H71<0))="",FALSE,IF(ISERROR('Model inputs'!H71<0),'Model inputs'!H71<0,IF('Model inputs'!H71="","",'Model inputs'!H71<0))),'Model inputs'!H20/-'Model inputs'!H71,0) -> 0

Sheet Unit economics by plan (monthly
A1: Unit economics by plan (monthly)
A2: Unit economics · Main Scenario
A4: Variable / dimension | B4: 2026-10 | C4: 2026-11 | D4: 2026-12 | E4: 2027-01 | F4: 2027-02 | G4: 2027-03 | H4: 2027-04 | I4: 2027-05 | J4: 2027-06 | K4: 2027-07 | L4: 2027-08 | M4: 2027-09
A5: New customers | B5: =SUM('Unit economics by plan (monthly'!B6,'Unit economics by plan (monthly'!B7) -> 9 | C5: =SUM('Unit economics by plan (monthly'!C6,'Unit economics by plan (monthly'!C7) -> 9 | D5: =SUM('Unit economics by plan (monthly'!D6,'Unit economics by plan (monthly'!D7) -> 9 | E5: =SUM('Unit economics by plan (monthly'!E6,'Unit economics by plan (monthly'!E7) -> 9 | F5: =SUM('Unit economics by plan (monthly'!F6,'Unit economics by plan (monthly'!F7) -> 9 | G5: =SUM('Unit economics by plan (monthly'!G6,'Unit economics by plan (monthly'!G7) -> 9 | H5: =SUM('Unit economics by plan (monthly'!H6,'Unit economics by plan (monthly'!H7) -> 9 | I5: =SUM('Unit economics by plan (monthly'!I6,'Unit economics by plan (monthly'!I7) -> 9 | ... M5: =SUM('Unit economics by plan (monthly'!M6,'Unit economics by plan (monthly'!M7) -> 9
A6: Classroom | B6: =IF('Model inputs'!O86="","",'Model inputs'!O86) -> 1 | C6: =IF('Model inputs'!O86="","",'Model inputs'!O86) -> 1 | D6: =IF('Model inputs'!O86="","",'Model inputs'!O86) -> 1 | E6: =IF('Model inputs'!O86="","",'Model inputs'!O86) -> 1 | F6: =IF('Model inputs'!O86="","",'Model inputs'!O86) -> 1 | G6: =IF('Model inputs'!O86="","",'Model inputs'!O86) -> 1 | H6: =IF('Model inputs'!O86="","",'Model inputs'!O86) -> 1 | I6: =IF('Model inputs'!O86="","",'Model inputs'!O86) -> 1 | J6: =IF('Model inputs'!O86="","",'Model inputs'!O86) -> 1 | K6: =IF('Model inputs'!O86="","",'Model inputs'!O86) -> 1 | L6: =IF('Model inputs'!O86="","",'Model inputs'!O86) -> 1 | M6: =IF('Model inputs'!O86="","",'Model inputs'!O86) -> 1
A7: Household | B7: =IF('Model inputs'!O87="","",'Model inputs'!O87) -> 8 | C7: =IF('Model inputs'!O87="","",'Model inputs'!O87) -> 8 | D7: =IF('Model inputs'!O87="","",'Model inputs'!O87) -> 8 | E7: =IF('Model inputs'!O87="","",'Model inputs'!O87) -> 8 | F7: =IF('Model inputs'!O87="","",'Model inputs'!O87) -> 8 | G7: =IF('Model inputs'!O87="","",'Model inputs'!O87) -> 8 | H7: =IF('Model inputs'!O87="","",'Model inputs'!O87) -> 8 | I7: =IF('Model inputs'!O87="","",'Model inputs'!O87) -> 8 | J7: =IF('Model inputs'!O87="","",'Model inputs'!O87) -> 8 | K7: =IF('Model inputs'!O87="","",'Model inputs'!O87) -> 8 | L7: =IF('Model inputs'!O87="","",'Model inputs'!O87) -> 8 | M7: =IF('Model inputs'!O87="","",'Model inputs'!O87) -> 8
A8: Churned customers | B8: =SUM('Unit economics by plan (monthly'!B9,'Unit economics by plan (monthly'!B10) -> 3.5 | C8: =SUM('Unit economics by plan (monthly'!C9,'Unit economics by plan (monthly'!C10) -> 3.905 | D8: =SUM('Unit economics by plan (monthly'!D9,'Unit economics by plan (monthly'!D10) -> 4.27865 | E8: =SUM('Unit economics by plan (monthly'!E9,'Unit economics by plan (monthly'!E10) -> 4.6234265 | F8: =SUM('Unit economics by plan (monthly'!F9,'Unit economics by plan (monthly'!F10) -> 4.9416088 | G8: =SUM('Unit economics by plan (monthly'!G9,'Unit economics by plan (monthly'!G10) -> 5.2352949 | H8: =SUM('Unit economics by plan (monthly'!H9,'Unit economics by plan (monthly'!H10) -> 5.5064156 | I8: =SUM('Unit economics by plan (monthly'!I9,'Unit economics by plan (monthly'!I10) -> 5.7567483 | ... M8: =SUM('Unit economics by plan (monthly'!M9,'Unit economics by plan (monthly'!M10) -> 6.5810296
A9: Classroom | B9: ='Model inputs'!B23*'Model inputs'!O63 -> 0.3 | C9: ='Unit economics by plan (monthly'!B12*'Model inputs'!O63 -> 0.321 | D9: ='Unit economics by plan (monthly'!C12*'Model inputs'!O63 -> 0.34137 | E9: ='Unit economics by plan (monthly'!D12*'Model inputs'!O63 -> 0.3611289 | F9: ='Unit economics by plan (monthly'!E12*'Model inputs'!O63 -> 0.38029503 | G9: ='Unit economics by plan (monthly'!F12*'Model inputs'!O63 -> 0.39888618 | H9: ='Unit economics by plan (monthly'!G12*'Model inputs'!O63 -> 0.4169196 | I9: ='Unit economics by plan (monthly'!H12*'Model inputs'!O63 -> 0.43441201 | J9: ='Unit economics by plan (monthly'!I12*'Model inputs'!O63 -> 0.45137965 | K9: ='Unit economics by plan (monthly'!J12*'Model inputs'!O63 -> 0.46783826 | L9: ='Unit economics by plan (monthly'!K12*'Model inputs'!O63 -> 0.48380311 | M9: ='Unit economics by plan (monthly'!L12*'Model inputs'!O63 -> 0.49928902
A10: Household | B10: ='Model inputs'!B24*'Model inputs'!O64 -> 3.2 | C10: ='Unit economics by plan (monthly'!B13*'Model inputs'!O64 -> 3.584 | D10: ='Unit economics by plan (monthly'!C13*'Model inputs'!O64 -> 3.93728 | E10: ='Unit economics by plan (monthly'!D13*'Model inputs'!O64 -> 4.2622976 | F10: ='Unit economics by plan (monthly'!E13*'Model inputs'!O64 -> 4.5613138 | G10: ='Unit economics by plan (monthly'!F13*'Model inputs'!O64 -> 4.8364087 | H10: ='Unit economics by plan (monthly'!G13*'Model inputs'!O64 -> 5.089496 | I10: ='Unit economics by plan (monthly'!H13*'Model inputs'!O64 -> 5.3223363 | J10: ='Unit economics by plan (monthly'!I13*'Model inputs'!O64 -> 5.5365494 | K10: ='Unit economics by plan (monthly'!J13*'Model inputs'!O64 -> 5.7336255 | L10: ='Unit economics by plan (monthly'!K13*'Model inputs'!O64 -> 5.9149354 | M10: ='Unit economics by plan (monthly'!L13*'Model inputs'!O64 -> 6.0817406
A11: Ending customers | B11: =SUM('Unit economics by plan (monthly'!B12,'Unit economics by plan (monthly'!B13) -> 55.5 | C11: =SUM('Unit economics by plan (monthly'!C12,'Unit economics by plan (monthly'!C13) -> 60.595 | D11: =SUM('Unit economics by plan (monthly'!D12,'Unit economics by plan (monthly'!D13) -> 65.31635 | E11: =SUM('Unit economics by plan (monthly'!E12,'Unit economics by plan (monthly'!E13) -> 69.692923 | F11: =SUM('Unit economics by plan (monthly'!F12,'Unit economics by plan (monthly'!F13) -> 73.751315 | G11: =SUM('Unit economics by plan (monthly'!G12,'Unit economics by plan (monthly'!G13) -> 77.51602 | H11: =SUM('Unit economics by plan (monthly'!H12,'Unit economics by plan (monthly'!H13) -> 81.009604 | I11: =SUM('Unit economics by plan (monthly'!I12,'Unit economics by plan (monthly'!I13) -> 84.252856 | ... M11: =SUM('Unit economics by plan (monthly'!M12,'Unit economics by plan (monthly'!M13) -> 95.083695
A12: Classroom | B12: ='Model inputs'!B23+'Unit economics by plan (monthly'!B6-'Unit economics by plan (monthly'!B9 -> 10.7 | C12: ='Unit economics by plan (monthly'!B12+'Unit economics by plan (monthly'!C6-'Unit economics by plan (monthly'!C9 -> 11.379 | D12: ='Unit economics by plan (monthly'!C12+'Unit economics by plan (monthly'!D6-'Unit economics by plan (monthly'!D9 -> 12.03763 | E12: ='Unit economics by plan (monthly'!D12+'Unit economics by plan (monthly'!E6-'Unit economics by plan (monthly'!E9 -> 12.676501 | F12: ='Unit economics by plan (monthly'!E12+'Unit economics by plan (monthly'!F6-'Unit economics by plan (monthly'!F9 -> 13.296206 | G12: ='Unit economics by plan (monthly'!F12+'Unit economics by plan (monthly'!G6-'Unit economics by plan (monthly'!G9 -> 13.89732 | H12: ='Unit economics by plan (monthly'!G12+'Unit economics by plan (monthly'!H6-'Unit economics by plan (monthly'!H9 -> 14.4804 | I12: ='Unit economics by plan (monthly'!H12+'Unit economics by plan (monthly'!I6-'Unit economics by plan (monthly'!I9 -> 15.045988 | J12: ='Unit economics by plan (monthly'!I12+'Unit economics by plan (monthly'!J6-'Unit economics by plan (monthly'!J9 -> 15.594609 | ... M12: ='Unit economics by plan (monthly'!L12+'Unit economics by plan (monthly'!M6-'Unit economics by plan (monthly'!M9 -> 17.143678
A13: Household | B13: ='Model inputs'!B24+'Unit economics by plan (monthly'!B7-'Unit economics by plan (monthly'!B10 -> 44.8 | C13: ='Unit economics by plan (monthly'!B13+'Unit economics by plan (monthly'!C7-'Unit economics by plan (monthly'!C10 -> 49.216 | D13: ='Unit economics by plan (monthly'!C13+'Unit economics by plan (monthly'!D7-'Unit economics by plan (monthly'!D10 -> 53.27872 | E13: ='Unit economics by plan (monthly'!D13+'Unit economics by plan (monthly'!E7-'Unit economics by plan (monthly'!E10 -> 57.016422 | F13: ='Unit economics by plan (monthly'!E13+'Unit economics by plan (monthly'!F7-'Unit economics by plan (monthly'!F10 -> 60.455109 | G13: ='Unit economics by plan (monthly'!F13+'Unit economics by plan (monthly'!G7-'Unit economics by plan (monthly'!G10 -> 63.6187 | H13: ='Unit economics by plan (monthly'!G13+'Unit economics by plan (monthly'!H7-'Unit economics by plan (monthly'!H10 -> 66.529204 | I13: ='Unit economics by plan (monthly'!H13+'Unit economics by plan (monthly'!I7-'Unit economics by plan (monthly'!I10 -> 69.206868 | J13: ='Unit economics by plan (monthly'!I13+'Unit economics by plan (monthly'!J7-'Unit economics by plan (monthly'!J10 -> 71.670318 | ... M13: ='Unit economics by plan (monthly'!L13+'Unit economics by plan (monthly'!M7-'Unit economics by plan (monthly'!M10 -> 77.940017
A14: Stories delivered | B14: =SUM('Unit economics by plan (monthly'!B15,'Unit economics by plan (monthly'!B16) -> 964.56 | C14: =SUM('Unit economics by plan (monthly'!C15,'Unit economics by plan (monthly'!C16) -> 1037.0952 | D14: =SUM('Unit economics by plan (monthly'!D15,'Unit economics by plan (monthly'!D16) -> 1105.8646 | E14: =SUM('Unit economics by plan (monthly'!E15,'Unit economics by plan (monthly'!E16) -> 1171.1083 | F14: =SUM('Unit economics by plan (monthly'!F15,'Unit economics by plan (monthly'!F16) -> 1233.0491 | G14: =SUM('Unit economics by plan (monthly'!G15,'Unit economics by plan (monthly'!G16) -> 1291.8938 | H14: =SUM('Unit economics by plan (monthly'!H15,'Unit economics by plan (monthly'!H16) -> 1347.8343 | I14: =SUM('Unit economics by plan (monthly'!I15,'Unit economics by plan (monthly'!I16) -> 1401.0487 | ... M14: =SUM('Unit economics by plan (monthly'!M15,'Unit economics by plan (monthly'!M16) -> 1589.7888
A15: Classroom | B15: ='Unit economics by plan (monthly'!B12*'Model inputs'!O111 -> 642 | C15: ='Unit economics by plan (monthly'!C12*'Model inputs'!O111 -> 682.74 | D15: ='Unit economics by plan (monthly'!D12*'Model inputs'!O111 -> 722.2578 | E15: ='Unit economics by plan (monthly'!E12*'Model inputs'!O111 -> 760.59007 | F15: ='Unit economics by plan (monthly'!F12*'Model inputs'!O111 -> 797.77236 | G15: ='Unit economics by plan (monthly'!G12*'Model inputs'!O111 -> 833.83919 | H15: ='Unit economics by plan (monthly'!H12*'Model inputs'!O111 -> 868.82402 | I15: ='Unit economics by plan (monthly'!I12*'Model inputs'!O111 -> 902.7593 | J15: ='Unit economics by plan (monthly'!J12*'Model inputs'!O111 -> 935.67652 | K15: ='Unit economics by plan (monthly'!K12*'Model inputs'!O111 -> 967.60622 | L15: ='Unit economics by plan (monthly'!L12*'Model inputs'!O111 -> 998.57804 | M15: ='Unit economics by plan (monthly'!M12*'Model inputs'!O111 -> 1028.6207
A16: Household | B16: ='Unit economics by plan (monthly'!B13*'Model inputs'!O112 -> 322.56 | C16: ='Unit economics by plan (monthly'!C13*'Model inputs'!O112 -> 354.3552 | D16: ='Unit economics by plan (monthly'!D13*'Model inputs'!O112 -> 383.60678 | E16: ='Unit economics by plan (monthly'!E13*'Model inputs'!O112 -> 410.51824 | F16: ='Unit economics by plan (monthly'!F13*'Model inputs'!O112 -> 435.27678 | G16: ='Unit economics by plan (monthly'!G13*'Model inputs'!O112 -> 458.05464 | H16: ='Unit economics by plan (monthly'!H13*'Model inputs'!O112 -> 479.01027 | I16: ='Unit economics by plan (monthly'!I13*'Model inputs'!O112 -> 498.28945 | J16: ='Unit economics by plan (monthly'!J13*'Model inputs'!O112 -> 516.02629 | K16: ='Unit economics by plan (monthly'!K13*'Model inputs'!O112 -> 532.34419 | L16: ='Unit economics by plan (monthly'!L13*'Model inputs'!O112 -> 547.35665 | M16: ='Unit economics by plan (monthly'!M13*'Model inputs'!O112 -> 561.16812
A17: Subscription revenue (USD) | B17: =SUM('Unit economics by plan (monthly'!B18,'Unit economics by plan (monthly'!B19) -> 623.452 | C17: =SUM('Unit economics by plan (monthly'!C18,'Unit economics by plan (monthly'!C19) -> 674.01084 | D17: =SUM('Unit economics by plan (monthly'!D18,'Unit economics by plan (monthly'!D19) -> 721.50952 | E17: =SUM('Unit economics by plan (monthly'!E18,'Unit economics by plan (monthly'!E19) -> 766.16332 | F17: =SUM('Unit economics by plan (monthly'!F18,'Unit economics by plan (monthly'!F19) -> 808.17119 | G17: =SUM('Unit economics by plan (monthly'!G18,'Unit economics by plan (monthly'!G19) -> 847.71699 | H17: =SUM('Unit economics by plan (monthly'!H18,'Unit economics by plan (monthly'!H19) -> 884.97074 | I17: =SUM('Unit economics by plan (monthly'!I18,'Unit economics by plan (monthly'!I19) -> 920.08966 | ... M17: =SUM('Unit economics by plan (monthly'!M18,'Unit economics by plan (monthly'!M19) -> 1041.9674
A18: Classroom | B18: ='Unit economics by plan (monthly'!B12*'Model inputs'!O104 -> 310.3 | C18: ='Unit economics by plan (monthly'!C12*'Model inputs'!O104 -> 329.991 | D18: ='Unit economics by plan (monthly'!D12*'Model inputs'!O104 -> 349.09127 | E18: ='Unit economics by plan (monthly'!E12*'Model inputs'!O104 -> 367.61853 | F18: ='Unit economics by plan (monthly'!F12*'Model inputs'!O104 -> 385.58998 | G18: ='Unit economics by plan (monthly'!G12*'Model inputs'!O104 -> 403.02228 | H18: ='Unit economics by plan (monthly'!H12*'Model inputs'!O104 -> 419.93161 | I18: ='Unit economics by plan (monthly'!I12*'Model inputs'!O104 -> 436.33366 | J18: ='Unit economics by plan (monthly'!J12*'Model inputs'!O104 -> 452.24365 | K18: ='Unit economics by plan (monthly'!K12*'Model inputs'!O104 -> 467.67634 | L18: ='Unit economics by plan (monthly'!L12*'Model inputs'!O104 -> 482.64605 | M18: ='Unit economics by plan (monthly'!M12*'Model inputs'!O104 -> 497.16667
A19: Household | B19: ='Unit economics by plan (monthly'!B13*'Model inputs'!O105 -> 313.152 | C19: ='Unit economics by plan (monthly'!C13*'Model inputs'!O105 -> 344.01984 | D19: ='Unit economics by plan (monthly'!D13*'Model inputs'!O105 -> 372.41825 | E19: ='Unit economics by plan (monthly'!E13*'Model inputs'!O105 -> 398.54479 | F19: ='Unit economics by plan (monthly'!F13*'Model inputs'!O105 -> 422.58121 | G19: ='Unit economics by plan (monthly'!G13*'Model inputs'!O105 -> 444.69471 | H19: ='Unit economics by plan (monthly'!H13*'Model inputs'!O105 -> 465.03914 | I19: ='Unit economics by plan (monthly'!I13*'Model inputs'!O105 -> 483.756 | J19: ='Unit economics by plan (monthly'!J13*'Model inputs'!O105 -> 500.97552 | K19: ='Unit economics by plan (monthly'!K13*'Model inputs'!O105 -> 516.81748 | L19: ='Unit economics by plan (monthly'!L13*'Model inputs'!O105 -> 531.39208 | M19: ='Unit economics by plan (monthly'!M13*'Model inputs'!O105 -> 544.80072
A20: Overage revenue (USD) | B20: =SUM('Unit economics by plan (monthly'!B21,'Unit economics by plan (monthly'!B22) -> 0 | C20: =SUM('Unit economics by plan (monthly'!C21,'Unit economics by plan (monthly'!C22) -> 0 | D20: =SUM('Unit economics by plan (monthly'!D21,'Unit economics by plan (monthly'!D22) -> 0 | E20: =SUM('Unit economics by plan (monthly'!E21,'Unit economics by plan (monthly'!E22) -> 0 | F20: =SUM('Unit economics by plan (monthly'!F21,'Unit economics by plan (monthly'!F22) -> 0 | G20: =SUM('Unit economics by plan (monthly'!G21,'Unit economics by plan (monthly'!G22) -> 0 | H20: =SUM('Unit economics by plan (monthly'!H21,'Unit economics by plan (monthly'!H22) -> 0 | I20: =SUM('Unit economics by plan (monthly'!I21,'Unit economics by plan (monthly'!I22) -> 0 | ... M20: =SUM('Unit economics by plan (monthly'!M21,'Unit economics by plan (monthly'!M22) -> 0
A21: Classroom | B21: ='Unit economics by plan (monthly'!B12*IF(IF(IF(IF(ISERROR('Model inputs'!O111>'Model inputs'!O108),'Model inputs'!O111>'Model inputs'!O108,IF(OR('Model inputs'!O111="",'Model inputs'!O108=""),"",'Model inputs'!O111>'Model inputs'!O108))="",FALSE,IF(ISERROR('Model inputs'!O111>'Model inputs'!O108),'Model inputs'!O111>'Model inputs'!O108,IF(OR('Model inputs'!O111="",'Model inputs'!O108=""),"",'Model inputs'!O111>'Model inputs'!O108))),('Model inputs'!O111-'Model inputs'!O108)*'Model inputs'!O89,0)="",0,IF(IF(IF(ISERROR('Model inputs'!O111>'Model inputs'!O108),'Model inputs'!O111>'Model inputs'!O108,IF(OR('Model inputs'!O111="",'Model inputs'!O108=""),"",'Model inputs'!O111>'Model inputs'!O108))="",FALSE,IF(ISERROR('Model inputs'!O111>'Model inputs'!O108),'Model inputs'!O111>'Model inputs'!O108,IF(OR('Model inputs'!O111="",'Model inputs'!O108=""),"",'Model inputs'!O111>'Model inputs'!O108))),('Model inputs'!O111-'Model inputs'!O108)*'Model inputs'!O89,0)) -> 0 | C21: ='Unit economics by plan (monthly'!C12*IF(IF(IF(IF(ISERROR('Model inputs'!O111>'Model inputs'!O108),'Model inputs'!O111>'Model inputs'!O108,IF(OR('Model inputs'!O111="",'Model inputs'!O108=""),"",'Model inputs'!O111>'Model inputs'!O108))="",FALSE,IF(ISERROR('Model inputs'!O111>'Model inputs'!O108),'Model inputs'!O111>'Model inputs'!O108,IF(OR('Model inputs'!O111="",'Model inputs'!O108=""),"",'Model inputs'!O111>'Model inputs'!O108))),('Model inputs'!O111-'Model inputs'!O108)*'Model inputs'!O89,0)="",0,IF(IF(IF(ISERROR('Model inputs'!O111>'Model inputs'!O108),'Model inputs'!O111>'Model inputs'!O108,IF(OR('Model inputs'!O111="",'Model inputs'!O108=""),"",'Model inputs'!O111>'Model inputs'!O108))="",FALSE,IF(ISERROR('Model inputs'!O111>'Model inputs'!O108),'Model inputs'!O111>'Model inputs'!O108,IF(OR('Model inputs'!O111="",'Model inputs'!O108=""),"",'Model inputs'!O111>'Model inputs'!O108))),('Model inputs'!O111-'Model inputs'!O108)*'Model inputs'!O89,0)) -> 0 | D21: ='Unit economics by plan (monthly'!D12*IF(IF(IF(IF(ISERROR('Model inputs'!O111>'Model inputs'!O108),'Model inputs'!O111>'Model inputs'!O108,IF(OR('Model inputs'!O111="",'Model inputs'!O108=""),"",'Model inputs'!O111>'Model inputs'!O108))="",FALSE,IF(ISERROR('Model inputs'!O111>'Model inputs'!O108),'Model inputs'!O111>'Model inputs'!O108,IF(OR('Model inputs'!O111="",'Model inputs'!O108=""),"",'Model inputs'!O111>'Model inputs'!O108))),('Model inputs'!O111-'Model inputs'!O108)*'Model inputs'!O89,0)="",0,IF(IF(IF(ISERROR('Model inputs'!O111>'Model inputs'!O108),'Model inputs'!O111>'Model inputs'!O108,IF(OR('Model inputs'!O111="",'Model inputs'!O108=""),"",'Model inputs'!O111>'Model inputs'!O108))="",FALSE,IF(ISERROR('Model inputs'!O111>'Model inputs'!O108),'Model inputs'!O111>'Model inputs'!O108,IF(OR('Model inputs'!O111="",'Model inputs'!O108=""),"",'Model inputs'!O111>'Model inputs'!O108))),('Model inputs'!O111-'Model inputs'!O108)*'Model inputs'!O89,0)) -> 0 | E21: ='Unit economics by plan (monthly'!E12*IF(IF(IF(IF(ISERROR('Model inputs'!O111>'Model inputs'!O108),'Model inputs'!O111>'Model inputs'!O108,IF(OR('Model inputs'!O111="",'Model inputs'!O108=""),"",'Model inputs'!O111>'Model inputs'!O108))="",FALSE,IF(ISERROR('Model inputs'!O111>'Model inputs'!O108),'Model inputs'!O111>'Model inputs'!O108,IF(OR('Model inputs'!O111="",'Model inputs'!O108=""),"",'Model inputs'!O111>'Model inputs'!O108))),('Model inputs'!O111-'Model inputs'!O108)*'Model inputs'!O89,0)="",0,IF(IF(IF(ISERROR('Model inputs'!O111>'Model inputs'!O108),'Model inputs'!O111>'Model inputs'!O108,IF(OR('Model inputs'!O111="",'Model inputs'!O108=""),"",'Model inputs'!O111>'Model inputs'!O108))="",FALSE,IF(ISERROR('Model inputs'!O111>'Model inputs'!O108),'Model inputs'!O111>'Model inputs'!O108,IF(OR('Model inputs'!O111="",'Model inputs'!O108=""),"",'Model inputs'!O111>'Model inputs'!O108))),('Model inputs'!O111-'Model inputs'!O108)*'Model inputs'!O89,0)) -> 0 | F21: ='Unit economics by plan (monthly'!F12*IF(IF(IF(IF(ISERROR('Model inputs'!O111>'Model inputs'!O108),'Model inputs'!O111>'Model inputs'!O108,IF(OR('Model inputs'!O111="",'Model inputs'!O108=""),"",'Model inputs'!O111>'Model inputs'!O108))="",FALSE,IF(ISERROR('Model inputs'!O111>'Model inputs'!O108),'Model inputs'!O111>'Model inputs'!O108,IF(OR('Model inputs'!O111="",'Model inputs'!O108=""),"",'Model inputs'!O111>'Model inputs'!O108))),('Model inputs'!O111-'Model inputs'!O108)*'Model inputs'!O89,0)="",0,IF(IF(IF(ISERROR('Model inputs'!O111>'Model inputs'!O108),'Model inputs'!O111>'Model inputs'!O108,IF(OR('Model inputs'!O111="",'Model inputs'!O108=""),"",'Model inputs'!O111>'Model inputs'!O108))="",FALSE,IF(ISERROR('Model inputs'!O111>'Model inputs'!O108),'Model inputs'!O111>'Model inputs'!O108,IF(OR('Model inputs'!O111="",'Model inputs'!O108=""),"",'Model inputs'!O111>'Model inputs'!O108))),('Model inputs'!O111-'Model inputs'!O108)*'Model inputs'!O89,0)) -> 0 | G21: ='Unit economics by plan (monthly'!G12*IF(IF(IF(IF(ISERROR('Model inputs'!O111>'Model inputs'!O108),'Model inputs'!O111>'Model inputs'!O108,IF(OR('Model inputs'!O111="",'Model inputs'!O108=""),"",'Model inputs'!O111>'Model inputs'!O108))="",FALSE,IF(ISERROR('Model inputs'!O111>'Model inputs'!O108),'Model inputs'!O111>'Model inputs'!O108,IF(OR('Model inputs'!O111="",'Model inputs'!O108=""),"",'Model inputs'!O111>'Model inputs'!O108))),('Model inputs'!O111-'Model inputs'!O108)*'Model inputs'!O89,0)="",0,IF(IF(IF(ISERROR('Model inputs'!O111>'Model inputs'!O108),'Model inputs'!O111>'Model inputs'!O108,IF(OR('Model inputs'!O111="",'Model inputs'!O108=""),"",'Model inputs'!O111>'Model inputs'!O108))="",FALSE,IF(ISERROR('Model inputs'!O111>'Model inputs'!O108),'Model inputs'!O111>'Model inputs'!O108,IF(OR('Model inputs'!O111="",'Model inputs'!O108=""),"",'Model inputs'!O111>'Model inputs'!O108))),('Model inputs'!O111-'Model inputs'!O108)*'Model inputs'!O89,0)) -> 0 | H21: ='Unit economics by plan (monthly'!H12*IF(IF(IF(IF(ISERROR('Model inputs'!O111>'Model inputs'!O108),'Model inputs'!O111>'Model inputs'!O108,IF(OR('Model inputs'!O111="",'Model inputs'!O108=""),"",'Model inputs'!O111>'Model inputs'!O108))="",FALSE,IF(ISERROR('Model inputs'!O111>'Model inputs'!O108),'Model inputs'!O111>'Model inputs'!O108,IF(OR('Model inputs'!O111="",'Model inputs'!O108=""),"",'Model inputs'!O111>'Model inputs'!O108))),('Model inputs'!O111-'Model inputs'!O108)*'Model inputs'!O89,0)="",0,IF(IF(IF(ISERROR('Model inputs'!O111>'Model inputs'!O108),'Model inputs'!O111>'Model inputs'!O108,IF(OR('Model inputs'!O111="",'Model inputs'!O108=""),"",'Model inputs'!O111>'Model inputs'!O108))="",FALSE,IF(ISERROR('Model inputs'!O111>'Model inputs'!O108),'Model inputs'!O111>'Model inputs'!O108,IF(OR('Model inputs'!O111="",'Model inputs'!O108=""),"",'Model inputs'!O111>'Model inputs'!O108))),('Model inputs'!O111-'Model inputs'!O108)*'Model inputs'!O89,0)) -> 0 | I21: ='Unit economics by plan (monthly'!I12*IF(IF(IF(IF(ISERROR('Model inputs'!O111>'Model inputs'!O108),'Model inputs'!O111>'Model inputs'!O108,IF(OR('Model inputs'!O111="",'Model inputs'!O108=""),"",'Model inputs'!O111>'Model inputs'!O108))="",FALSE,IF(ISERROR('Model inputs'!O111>'Model inputs'!O108),'Model inputs'!O111>'Model inputs'!O108,IF(OR('Model inputs'!O111="",'Model inputs'!O108=""),"",'Model inputs'!O111>'Model inputs'!O108))),('Model inputs'!O111-'Model inputs'!O108)*'Model inputs'!O89,0)="",0,IF(IF(IF(ISERROR('Model inputs'!O111>'Model inputs'!O108),'Model inputs'!O111>'Model inputs'!O108,IF(OR('Model inputs'!O111="",'Model inputs'!O108=""),"",'Model inputs'!O111>'Model inputs'!O108))="",FALSE,IF(ISERROR('Model inputs'!O111>'Model inputs'!O108),'Model inputs'!O111>'Model inputs'!O108,IF(OR('Model inputs'!O111="",'Model inputs'!O108=""),"",'Model inputs'!O111>'Model inputs'!O108))),('Model inputs'!O111-'Model inputs'!O108)*'Model inputs'!O89,0)) -> 0 | J21: ='Unit economics by plan (monthly'!J12*IF(IF(IF(IF(ISERROR('Model inputs'!O111>'Model inputs'!O108),'Model inputs'!O111>'Model inputs'!O108,IF(OR('Model inputs'!O111="",'Model inputs'!O108=""),"",'Model inputs'!O111>'Model inputs'!O108))="",FALSE,IF(ISERROR('Model inputs'!O111>'Model inputs'!O108),'Model inputs'!O111>'Model inputs'!O108,IF(OR('Model inputs'!O111="",'Model inputs'!O108=""),"",'Model inputs'!O111>'Model inputs'!O108))),('Model inputs'!O111-'Model inputs'!O108)*'Model inputs'!O89,0)="",0,IF(IF(IF(ISERROR('Model inputs'!O111>'Model inputs'!O108),'Model inputs'!O111>'Model inputs'!O108,IF(OR('Model inputs'!O111="",'Model inputs'!O108=""),"",'Model inputs'!O111>'Model inputs'!O108))="",FALSE,IF(ISERROR('Model inputs'!O111>'Model inputs'!O108),'Model inputs'!O111>'Model inputs'!O108,IF(OR('Model inputs'!O111="",'Model inputs'!O108=""),"",'Model inputs'!O111>'Model inputs'!O108))),('Model inputs'!O111-'Model inputs'!O108)*'Model inputs'!O89,0)) -> 0 | K21: ='Unit economics by plan (monthly'!K12*IF(IF(IF(IF(ISERROR('Model inputs'!O111>'Model inputs'!O108),'Model inputs'!O111>'Model inputs'!O108,IF(OR('Model inputs'!O111="",'Model inputs'!O108=""),"",'Model inputs'!O111>'Model inputs'!O108))="",FALSE,IF(ISERROR('Model inputs'!O111>'Model inputs'!O108),'Model inputs'!O111>'Model inputs'!O108,IF(OR('Model inputs'!O111="",'Model inputs'!O108=""),"",'Model inputs'!O111>'Model inputs'!O108))),('Model inputs'!O111-'Model inputs'!O108)*'Model inputs'!O89,0)="",0,IF(IF(IF(ISERROR('Model inputs'!O111>'Model inputs'!O108),'Model inputs'!O111>'Model inputs'!O108,IF(OR('Model inputs'!O111="",'Model inputs'!O108=""),"",'Model inputs'!O111>'Model inputs'!O108))="",FALSE,IF(ISERROR('Model inputs'!O111>'Model inputs'!O108),'Model inputs'!O111>'Model inputs'!O108,IF(OR('Model inputs'!O111="",'Model inputs'!O108=""),"",'Model inputs'!O111>'Model inputs'!O108))),('Model inputs'!O111-'Model inputs'!O108)*'Model inputs'!O89,0)) -> 0 | L21: ='Unit economics by plan (monthly'!L12*IF(IF(IF(IF(ISERROR('Model inputs'!O111>'Model inputs'!O108),'Model inputs'!O111>'Model inputs'!O108,IF(OR('Model inputs'!O111="",'Model inputs'!O108=""),"",'Model inputs'!O111>'Model inputs'!O108))="",FALSE,IF(ISERROR('Model inputs'!O111>'Model inputs'!O108),'Model inputs'!O111>'Model inputs'!O108,IF(OR('Model inputs'!O111="",'Model inputs'!O108=""),"",'Model inputs'!O111>'Model inputs'!O108))),('Model inputs'!O111-'Model inputs'!O108)*'Model inputs'!O89,0)="",0,IF(IF(IF(ISERROR('Model inputs'!O111>'Model inputs'!O108),'Model inputs'!O111>'Model inputs'!O108,IF(OR('Model inputs'!O111="",'Model inputs'!O108=""),"",'Model inputs'!O111>'Model inputs'!O108))="",FALSE,IF(ISERROR('Model inputs'!O111>'Model inputs'!O108),'Model inputs'!O111>'Model inputs'!O108,IF(OR('Model inputs'!O111="",'Model inputs'!O108=""),"",'Model inputs'!O111>'Model inputs'!O108))),('Model inputs'!O111-'Model inputs'!O108)*'Model inputs'!O89,0)) -> 0 | M21: ='Unit economics by plan (monthly'!M12*IF(IF(IF(IF(ISERROR('Model inputs'!O111>'Model inputs'!O108),'Model inputs'!O111>'Model inputs'!O108,IF(OR('Model inputs'!O111="",'Model inputs'!O108=""),"",'Model inputs'!O111>'Model inputs'!O108))="",FALSE,IF(ISERROR('Model inputs'!O111>'Model inputs'!O108),'Model inputs'!O111>'Model inputs'!O108,IF(OR('Model inputs'!O111="",'Model inputs'!O108=""),"",'Model inputs'!O111>'Model inputs'!O108))),('Model inputs'!O111-'Model inputs'!O108)*'Model inputs'!O89,0)="",0,IF(IF(IF(ISERROR('Model inputs'!O111>'Model inputs'!O108),'Model inputs'!O111>'Model inputs'!O108,IF(OR('Model inputs'!O111="",'Model inputs'!O108=""),"",'Model inputs'!O111>'Model inputs'!O108))="",FALSE,IF(ISERROR('Model inputs'!O111>'Model inputs'!O108),'Model inputs'!O111>'Model inputs'!O108,IF(OR('Model inputs'!O111="",'Model inputs'!O108=""),"",'Model inputs'!O111>'Model inputs'!O108))),('Model inputs'!O111-'Model inputs'!O108)*'Model inputs'!O89,0)) -> 0
A22: Household | B22: ='Unit economics by plan (monthly'!B13*IF(IF(IF(IF(ISERROR('Model inputs'!O112>'Model inputs'!O109),'Model inputs'!O112>'Model inputs'!O109,IF(OR('Model inputs'!O112="",'Model inputs'!O109=""),"",'Model inputs'!O112>'Model inputs'!O109))="",FALSE,IF(ISERROR('Model inputs'!O112>'Model inputs'!O109),'Model inputs'!O112>'Model inputs'!O109,IF(OR('Model inputs'!O112="",'Model inputs'!O109=""),"",'Model inputs'!O112>'Model inputs'!O109))),('Model inputs'!O112-'Model inputs'!O109)*'Model inputs'!O90,0)="",0,IF(IF(IF(ISERROR('Model inputs'!O112>'Model inputs'!O109),'Model inputs'!O112>'Model inputs'!O109,IF(OR('Model inputs'!O112="",'Model inputs'!O109=""),"",'Model inputs'!O112>'Model inputs'!O109))="",FALSE,IF(ISERROR('Model inputs'!O112>'Model inputs'!O109),'Model inputs'!O112>'Model inputs'!O109,IF(OR('Model inputs'!O112="",'Model inputs'!O109=""),"",'Model inputs'!O112>'Model inputs'!O109))),('Model inputs'!O112-'Model inputs'!O109)*'Model inputs'!O90,0)) -> 0 | C22: ='Unit economics by plan (monthly'!C13*IF(IF(IF(IF(ISERROR('Model inputs'!O112>'Model inputs'!O109),'Model inputs'!O112>'Model inputs'!O109,IF(OR('Model inputs'!O112="",'Model inputs'!O109=""),"",'Model inputs'!O112>'Model inputs'!O109))="",FALSE,IF(ISERROR('Model inputs'!O112>'Model inputs'!O109),'Model inputs'!O112>'Model inputs'!O109,IF(OR('Model inputs'!O112="",'Model inputs'!O109=""),"",'Model inputs'!O112>'Model inputs'!O109))),('Model inputs'!O112-'Model inputs'!O109)*'Model inputs'!O90,0)="",0,IF(IF(IF(ISERROR('Model inputs'!O112>'Model inputs'!O109),'Model inputs'!O112>'Model inputs'!O109,IF(OR('Model inputs'!O112="",'Model inputs'!O109=""),"",'Model inputs'!O112>'Model inputs'!O109))="",FALSE,IF(ISERROR('Model inputs'!O112>'Model inputs'!O109),'Model inputs'!O112>'Model inputs'!O109,IF(OR('Model inputs'!O112="",'Model inputs'!O109=""),"",'Model inputs'!O112>'Model inputs'!O109))),('Model inputs'!O112-'Model inputs'!O109)*'Model inputs'!O90,0)) -> 0 | D22: ='Unit economics by plan (monthly'!D13*IF(IF(IF(IF(ISERROR('Model inputs'!O112>'Model inputs'!O109),'Model inputs'!O112>'Model inputs'!O109,IF(OR('Model inputs'!O112="",'Model inputs'!O109=""),"",'Model inputs'!O112>'Model inputs'!O109))="",FALSE,IF(ISERROR('Model inputs'!O112>'Model inputs'!O109),'Model inputs'!O112>'Model inputs'!O109,IF(OR('Model inputs'!O112="",'Model inputs'!O109=""),"",'Model inputs'!O112>'Model inputs'!O109))),('Model inputs'!O112-'Model inputs'!O109)*'Model inputs'!O90,0)="",0,IF(IF(IF(ISERROR('Model inputs'!O112>'Model inputs'!O109),'Model inputs'!O112>'Model inputs'!O109,IF(OR('Model inputs'!O112="",'Model inputs'!O109=""),"",'Model inputs'!O112>'Model inputs'!O109))="",FALSE,IF(ISERROR('Model inputs'!O112>'Model inputs'!O109),'Model inputs'!O112>'Model inputs'!O109,IF(OR('Model inputs'!O112="",'Model inputs'!O109=""),"",'Model inputs'!O112>'Model inputs'!O109))),('Model inputs'!O112-'Model inputs'!O109)*'Model inputs'!O90,0)) -> 0 | E22: ='Unit economics by plan (monthly'!E13*IF(IF(IF(IF(ISERROR('Model inputs'!O112>'Model inputs'!O109),'Model inputs'!O112>'Model inputs'!O109,IF(OR('Model inputs'!O112="",'Model inputs'!O109=""),"",'Model inputs'!O112>'Model inputs'!O109))="",FALSE,IF(ISERROR('Model inputs'!O112>'Model inputs'!O109),'Model inputs'!O112>'Model inputs'!O109,IF(OR('Model inputs'!O112="",'Model inputs'!O109=""),"",'Model inputs'!O112>'Model inputs'!O109))),('Model inputs'!O112-'Model inputs'!O109)*'Model inputs'!O90,0)="",0,IF(IF(IF(ISERROR('Model inputs'!O112>'Model inputs'!O109),'Model inputs'!O112>'Model inputs'!O109,IF(OR('Model inputs'!O112="",'Model inputs'!O109=""),"",'Model inputs'!O112>'Model inputs'!O109))="",FALSE,IF(ISERROR('Model inputs'!O112>'Model inputs'!O109),'Model inputs'!O112>'Model inputs'!O109,IF(OR('Model inputs'!O112="",'Model inputs'!O109=""),"",'Model inputs'!O112>'Model inputs'!O109))),('Model inputs'!O112-'Model inputs'!O109)*'Model inputs'!O90,0)) -> 0 | F22: ='Unit economics by plan (monthly'!F13*IF(IF(IF(IF(ISERROR('Model inputs'!O112>'Model inputs'!O109),'Model inputs'!O112>'Model inputs'!O109,IF(OR('Model inputs'!O112="",'Model inputs'!O109=""),"",'Model inputs'!O112>'Model inputs'!O109))="",FALSE,IF(ISERROR('Model inputs'!O112>'Model inputs'!O109),'Model inputs'!O112>'Model inputs'!O109,IF(OR('Model inputs'!O112="",'Model inputs'!O109=""),"",'Model inputs'!O112>'Model inputs'!O109))),('Model inputs'!O112-'Model inputs'!O109)*'Model inputs'!O90,0)="",0,IF(IF(IF(ISERROR('Model inputs'!O112>'Model inputs'!O109),'Model inputs'!O112>'Model inputs'!O109,IF(OR('Model inputs'!O112="",'Model inputs'!O109=""),"",'Model inputs'!O112>'Model inputs'!O109))="",FALSE,IF(ISERROR('Model inputs'!O112>'Model inputs'!O109),'Model inputs'!O112>'Model inputs'!O109,IF(OR('Model inputs'!O112="",'Model inputs'!O109=""),"",'Model inputs'!O112>'Model inputs'!O109))),('Model inputs'!O112-'Model inputs'!O109)*'Model inputs'!O90,0)) -> 0 | G22: ='Unit economics by plan (monthly'!G13*IF(IF(IF(IF(ISERROR('Model inputs'!O112>'Model inputs'!O109),'Model inputs'!O112>'Model inputs'!O109,IF(OR('Model inputs'!O112="",'Model inputs'!O109=""),"",'Model inputs'!O112>'Model inputs'!O109))="",FALSE,IF(ISERROR('Model inputs'!O112>'Model inputs'!O109),'Model inputs'!O112>'Model inputs'!O109,IF(OR('Model inputs'!O112="",'Model inputs'!O109=""),"",'Model inputs'!O112>'Model inputs'!O109))),('Model inputs'!O112-'Model inputs'!O109)*'Model inputs'!O90,0)="",0,IF(IF(IF(ISERROR('Model inputs'!O112>'Model inputs'!O109),'Model inputs'!O112>'Model inputs'!O109,IF(OR('Model inputs'!O112="",'Model inputs'!O109=""),"",'Model inputs'!O112>'Model inputs'!O109))="",FALSE,IF(ISERROR('Model inputs'!O112>'Model inputs'!O109),'Model inputs'!O112>'Model inputs'!O109,IF(OR('Model inputs'!O112="",'Model inputs'!O109=""),"",'Model inputs'!O112>'Model inputs'!O109))),('Model inputs'!O112-'Model inputs'!O109)*'Model inputs'!O90,0)) -> 0 | H22: ='Unit economics by plan (monthly'!H13*IF(IF(IF(IF(ISERROR('Model inputs'!O112>'Model inputs'!O109),'Model inputs'!O112>'Model inputs'!O109,IF(OR('Model inputs'!O112="",'Model inputs'!O109=""),"",'Model inputs'!O112>'Model inputs'!O109))="",FALSE,IF(ISERROR('Model inputs'!O112>'Model inputs'!O109),'Model inputs'!O112>'Model inputs'!O109,IF(OR('Model inputs'!O112="",'Model inputs'!O109=""),"",'Model inputs'!O112>'Model inputs'!O109))),('Model inputs'!O112-'Model inputs'!O109)*'Model inputs'!O90,0)="",0,IF(IF(IF(ISERROR('Model inputs'!O112>'Model inputs'!O109),'Model inputs'!O112>'Model inputs'!O109,IF(OR('Model inputs'!O112="",'Model inputs'!O109=""),"",'Model inputs'!O112>'Model inputs'!O109))="",FALSE,IF(ISERROR('Model inputs'!O112>'Model inputs'!O109),'Model inputs'!O112>'Model inputs'!O109,IF(OR('Model inputs'!O112="",'Model inputs'!O109=""),"",'Model inputs'!O112>'Model inputs'!O109))),('Model inputs'!O112-'Model inputs'!O109)*'Model inputs'!O90,0)) -> 0 | I22: ='Unit economics by plan (monthly'!I13*IF(IF(IF(IF(ISERROR('Model inputs'!O112>'Model inputs'!O109),'Model inputs'!O112>'Model inputs'!O109,IF(OR('Model inputs'!O112="",'Model inputs'!O109=""),"",'Model inputs'!O112>'Model inputs'!O109))="",FALSE,IF(ISERROR('Model inputs'!O112>'Model inputs'!O109),'Model inputs'!O112>'Model inputs'!O109,IF(OR('Model inputs'!O112="",'Model inputs'!O109=""),"",'Model inputs'!O112>'Model inputs'!O109))),('Model inputs'!O112-'Model inputs'!O109)*'Model inputs'!O90,0)="",0,IF(IF(IF(ISERROR('Model inputs'!O112>'Model inputs'!O109),'Model inputs'!O112>'Model inputs'!O109,IF(OR('Model inputs'!O112="",'Model inputs'!O109=""),"",'Model inputs'!O112>'Model inputs'!O109))="",FALSE,IF(ISERROR('Model inputs'!O112>'Model inputs'!O109),'Model inputs'!O112>'Model inputs'!O109,IF(OR('Model inputs'!O112="",'Model inputs'!O109=""),"",'Model inputs'!O112>'Model inputs'!O109))),('Model inputs'!O112-'Model inputs'!O109)*'Model inputs'!O90,0)) -> 0 | J22: ='Unit economics by plan (monthly'!J13*IF(IF(IF(IF(ISERROR('Model inputs'!O112>'Model inputs'!O109),'Model inputs'!O112>'Model inputs'!O109,IF(OR('Model inputs'!O112="",'Model inputs'!O109=""),"",'Model inputs'!O112>'Model inputs'!O109))="",FALSE,IF(ISERROR('Model inputs'!O112>'Model inputs'!O109),'Model inputs'!O112>'Model inputs'!O109,IF(OR('Model inputs'!O112="",'Model inputs'!O109=""),"",'Model inputs'!O112>'Model inputs'!O109))),('Model inputs'!O112-'Model inputs'!O109)*'Model inputs'!O90,0)="",0,IF(IF(IF(ISERROR('Model inputs'!O112>'Model inputs'!O109),'Model inputs'!O112>'Model inputs'!O109,IF(OR('Model inputs'!O112="",'Model inputs'!O109=""),"",'Model inputs'!O112>'Model inputs'!O109))="",FALSE,IF(ISERROR('Model inputs'!O112>'Model inputs'!O109),'Model inputs'!O112>'Model inputs'!O109,IF(OR('Model inputs'!O112="",'Model inputs'!O109=""),"",'Model inputs'!O112>'Model inputs'!O109))),('Model inputs'!O112-'Model inputs'!O109)*'Model inputs'!O90,0)) -> 0 | K22: ='Unit economics by plan (monthly'!K13*IF(IF(IF(IF(ISERROR('Model inputs'!O112>'Model inputs'!O109),'Model inputs'!O112>'Model inputs'!O109,IF(OR('Model inputs'!O112="",'Model inputs'!O109=""),"",'Model inputs'!O112>'Model inputs'!O109))="",FALSE,IF(ISERROR('Model inputs'!O112>'Model inputs'!O109),'Model inputs'!O112>'Model inputs'!O109,IF(OR('Model inputs'!O112="",'Model inputs'!O109=""),"",'Model inputs'!O112>'Model inputs'!O109))),('Model inputs'!O112-'Model inputs'!O109)*'Model inputs'!O90,0)="",0,IF(IF(IF(ISERROR('Model inputs'!O112>'Model inputs'!O109),'Model inputs'!O112>'Model inputs'!O109,IF(OR('Model inputs'!O112="",'Model inputs'!O109=""),"",'Model inputs'!O112>'Model inputs'!O109))="",FALSE,IF(ISERROR('Model inputs'!O112>'Model inputs'!O109),'Model inputs'!O112>'Model inputs'!O109,IF(OR('Model inputs'!O112="",'Model inputs'!O109=""),"",'Model inputs'!O112>'Model inputs'!O109))),('Model inputs'!O112-'Model inputs'!O109)*'Model inputs'!O90,0)) -> 0 | L22: ='Unit economics by plan (monthly'!L13*IF(IF(IF(IF(ISERROR('Model inputs'!O112>'Model inputs'!O109),'Model inputs'!O112>'Model inputs'!O109,IF(OR('Model inputs'!O112="",'Model inputs'!O109=""),"",'Model inputs'!O112>'Model inputs'!O109))="",FALSE,IF(ISERROR('Model inputs'!O112>'Model inputs'!O109),'Model inputs'!O112>'Model inputs'!O109,IF(OR('Model inputs'!O112="",'Model inputs'!O109=""),"",'Model inputs'!O112>'Model inputs'!O109))),('Model inputs'!O112-'Model inputs'!O109)*'Model inputs'!O90,0)="",0,IF(IF(IF(ISERROR('Model inputs'!O112>'Model inputs'!O109),'Model inputs'!O112>'Model inputs'!O109,IF(OR('Model inputs'!O112="",'Model inputs'!O109=""),"",'Model inputs'!O112>'Model inputs'!O109))="",FALSE,IF(ISERROR('Model inputs'!O112>'Model inputs'!O109),'Model inputs'!O112>'Model inputs'!O109,IF(OR('Model inputs'!O112="",'Model inputs'!O109=""),"",'Model inputs'!O112>'Model inputs'!O109))),('Model inputs'!O112-'Model inputs'!O109)*'Model inputs'!O90,0)) -> 0 | M22: ='Unit economics by plan (monthly'!M13*IF(IF(IF(IF(ISERROR('Model inputs'!O112>'Model inputs'!O109),'Model inputs'!O112>'Model inputs'!O109,IF(OR('Model inputs'!O112="",'Model inputs'!O109=""),"",'Model inputs'!O112>'Model inputs'!O109))="",FALSE,IF(ISERROR('Model inputs'!O112>'Model inputs'!O109),'Model inputs'!O112>'Model inputs'!O109,IF(OR('Model inputs'!O112="",'Model inputs'!O109=""),"",'Model inputs'!O112>'Model inputs'!O109))),('Model inputs'!O112-'Model inputs'!O109)*'Model inputs'!O90,0)="",0,IF(IF(IF(ISERROR('Model inputs'!O112>'Model inputs'!O109),'Model inputs'!O112>'Model inputs'!O109,IF(OR('Model inputs'!O112="",'Model inputs'!O109=""),"",'Model inputs'!O112>'Model inputs'!O109))="",FALSE,IF(ISERROR('Model inputs'!O112>'Model inputs'!O109),'Model inputs'!O112>'Model inputs'!O109,IF(OR('Model inputs'!O112="",'Model inputs'!O109=""),"",'Model inputs'!O112>'Model inputs'!O109))),('Model inputs'!O112-'Model inputs'!O109)*'Model inputs'!O90,0)) -> 0
A23: Revenue (USD) | B23: =SUM('Unit economics by plan (monthly'!B24,'Unit economics by plan (monthly'!B25) -> 623.452 | C23: =SUM('Unit economics by plan (monthly'!C24,'Unit economics by plan (monthly'!C25) -> 674.01084 | D23: =SUM('Unit economics by plan (monthly'!D24,'Unit economics by plan (monthly'!D25) -> 721.50952 | E23: =SUM('Unit economics by plan (monthly'!E24,'Unit economics by plan (monthly'!E25) -> 766.16332 | F23: =SUM('Unit economics by plan (monthly'!F24,'Unit economics by plan (monthly'!F25) -> 808.17119 | G23: =SUM('Unit economics by plan (monthly'!G24,'Unit economics by plan (monthly'!G25) -> 847.71699 | H23: =SUM('Unit economics by plan (monthly'!H24,'Unit economics by plan (monthly'!H25) -> 884.97074 | I23: =SUM('Unit economics by plan (monthly'!I24,'Unit economics by plan (monthly'!I25) -> 920.08966 | ... M23: =SUM('Unit economics by plan (monthly'!M24,'Unit economics by plan (monthly'!M25) -> 1041.9674
A24: Classroom | B24: ='Unit economics by plan (monthly'!B18+'Unit economics by plan (monthly'!B21 -> 310.3 | C24: ='Unit economics by plan (monthly'!C18+'Unit economics by plan (monthly'!C21 -> 329.991 | D24: ='Unit economics by plan (monthly'!D18+'Unit economics by plan (monthly'!D21 -> 349.09127 | E24: ='Unit economics by plan (monthly'!E18+'Unit economics by plan (monthly'!E21 -> 367.61853 | F24: ='Unit economics by plan (monthly'!F18+'Unit economics by plan (monthly'!F21 -> 385.58998 | G24: ='Unit economics by plan (monthly'!G18+'Unit economics by plan (monthly'!G21 -> 403.02228 | H24: ='Unit economics by plan (monthly'!H18+'Unit economics by plan (monthly'!H21 -> 419.93161 | I24: ='Unit economics by plan (monthly'!I18+'Unit economics by plan (monthly'!I21 -> 436.33366 | ... M24: ='Unit economics by plan (monthly'!M18+'Unit economics by plan (monthly'!M21 -> 497.16667
A25: Household | B25: ='Unit economics by plan (monthly'!B19+'Unit economics by plan (monthly'!B22 -> 313.152 | C25: ='Unit economics by plan (monthly'!C19+'Unit economics by plan (monthly'!C22 -> 344.01984 | D25: ='Unit economics by plan (monthly'!D19+'Unit economics by plan (monthly'!D22 -> 372.41825 | E25: ='Unit economics by plan (monthly'!E19+'Unit economics by plan (monthly'!E22 -> 398.54479 | F25: ='Unit economics by plan (monthly'!F19+'Unit economics by plan (monthly'!F22 -> 422.58121 | G25: ='Unit economics by plan (monthly'!G19+'Unit economics by plan (monthly'!G22 -> 444.69471 | H25: ='Unit economics by plan (monthly'!H19+'Unit economics by plan (monthly'!H22 -> 465.03914 | I25: ='Unit economics by plan (monthly'!I19+'Unit economics by plan (monthly'!I22 -> 483.756 | ... M25: ='Unit economics by plan (monthly'!M19+'Unit economics by plan (monthly'!M22 -> 544.80072
A26: Inference cost (USD, estimate) | B26: =SUM('Unit economics by plan (monthly'!B27,'Unit economics by plan (monthly'!B28) -> 188.9573 | C26: =SUM('Unit economics by plan (monthly'!C27,'Unit economics by plan (monthly'!C28) -> 203.16695 | D26: =SUM('Unit economics by plan (monthly'!D27,'Unit economics by plan (monthly'!D28) -> 216.63887 | E26: =SUM('Unit economics by plan (monthly'!E27,'Unit economics by plan (monthly'!E28) -> 229.42012 | F26: =SUM('Unit economics by plan (monthly'!F27,'Unit economics by plan (monthly'!F28) -> 241.55433 | G26: =SUM('Unit economics by plan (monthly'!G27,'Unit economics by plan (monthly'!G28) -> 253.082 | H26: =SUM('Unit economics by plan (monthly'!H27,'Unit economics by plan (monthly'!H28) -> 264.04074 | I26: =SUM('Unit economics by plan (monthly'!I27,'Unit economics by plan (monthly'!I28) -> 274.46545 | ... M26: =SUM('Unit economics by plan (monthly'!M27,'Unit economics by plan (monthly'!M28) -> 311.43963
A27: Classroom | B27: ='Unit economics by plan (monthly'!B15*'Model inputs'!O18 -> 125.7678 | C27: ='Unit economics by plan (monthly'!C15*'Model inputs'!O18 -> 133.74877 | D27: ='Unit economics by plan (monthly'!D15*'Model inputs'!O18 -> 141.4903 | E27: ='Unit economics by plan (monthly'!E15*'Model inputs'!O18 -> 148.99959 | F27: ='Unit economics by plan (monthly'!F15*'Model inputs'!O18 -> 156.28361 | G27: ='Unit economics by plan (monthly'!G15*'Model inputs'!O18 -> 163.3491 | H27: ='Unit economics by plan (monthly'!H15*'Model inputs'!O18 -> 170.20262 | I27: ='Unit economics by plan (monthly'!I15*'Model inputs'!O18 -> 176.85055 | J27: ='Unit economics by plan (monthly'!J15*'Model inputs'!O18 -> 183.29903 | K27: ='Unit economics by plan (monthly'!K15*'Model inputs'!O18 -> 189.55406 | L27: ='Unit economics by plan (monthly'!L15*'Model inputs'!O18 -> 195.62144 | M27: ='Unit economics by plan (monthly'!M15*'Model inputs'!O18 -> 201.50679
A28: Household | B28: ='Unit economics by plan (monthly'!B16*'Model inputs'!O18 -> 63.189504 | C28: ='Unit economics by plan (monthly'!C16*'Model inputs'!O18 -> 69.418184 | D28: ='Unit economics by plan (monthly'!D16*'Model inputs'!O18 -> 75.148569 | E28: ='Unit economics by plan (monthly'!E16*'Model inputs'!O18 -> 80.420523 | F28: ='Unit economics by plan (monthly'!F16*'Model inputs'!O18 -> 85.270722 | G28: ='Unit economics by plan (monthly'!G16*'Model inputs'!O18 -> 89.732904 | H28: ='Unit economics by plan (monthly'!H16*'Model inputs'!O18 -> 93.838112 | I28: ='Unit economics by plan (monthly'!I16*'Model inputs'!O18 -> 97.614903 | J28: ='Unit economics by plan (monthly'!J16*'Model inputs'!O18 -> 101.08955 | K28: ='Unit economics by plan (monthly'!K16*'Model inputs'!O18 -> 104.28623 | L28: ='Unit economics by plan (monthly'!L16*'Model inputs'!O18 -> 107.22717 | M28: ='Unit economics by plan (monthly'!M16*'Model inputs'!O18 -> 109.93283

Sheet Gross profit and margin by plan
A1: Gross profit and margin by plan (monthly)
A2: Unit economics · Main Scenario
A4: Variable / dimension | B4: 2026-10 | C4: 2026-11 | D4: 2026-12 | E4: 2027-01 | F4: 2027-02 | G4: 2027-03 | H4: 2027-04 | I4: 2027-05 | J4: 2027-06 | K4: 2027-07 | L4: 2027-08 | M4: 2027-09
A5: Spans per month (derived) | B5: ='Unit economics by plan (monthly'!B14*'Model inputs'!O106 -> 144684 | C5: ='Unit economics by plan (monthly'!C14*'Model inputs'!O106 -> 155564.28 | D5: ='Unit economics by plan (monthly'!D14*'Model inputs'!O106 -> 165879.69 | E5: ='Unit economics by plan (monthly'!E14*'Model inputs'!O106 -> 175666.25 | F5: ='Unit economics by plan (monthly'!F14*'Model inputs'!O106 -> 184957.37 | G5: ='Unit economics by plan (monthly'!G14*'Model inputs'!O106 -> 193784.07 | H5: ='Unit economics by plan (monthly'!H14*'Model inputs'!O106 -> 202175.14 | I5: ='Unit economics by plan (monthly'!I14*'Model inputs'!O106 -> 210157.31 | J5: ='Unit economics by plan (monthly'!J14*'Model inputs'!O106 -> 217755.42 | K5: ='Unit economics by plan (monthly'!K14*'Model inputs'!O106 -> 224992.56 | L5: ='Unit economics by plan (monthly'!L14*'Model inputs'!O106 -> 231890.2 | M5: ='Unit economics by plan (monthly'!M14*'Model inputs'!O106 -> 238468.32
A6: neatlogs bill (USD, derived) | B6: =IF(IF(IF(ISERROR('Model inputs'!O65=1),'Model inputs'!O65=1,IF('Model inputs'!O65="","",'Model inputs'!O65=1))="",FALSE,IF(ISERROR('Model inputs'!O65=1),'Model inputs'!O65=1,IF('Model inputs'!O65="","",'Model inputs'!O65=1))),0,IF(IF(IF(ISERROR('Gross profit and margin by plan'!B5<='Model inputs'!O66),'Gross profit and margin by plan'!B5<='Model inputs'!O66,IF(OR('Gross profit and margin by plan'!B5="",'Model inputs'!O66=""),"",'Gross profit and margin by plan'!B5<='Model inputs'!O66))="",FALSE,IF(ISERROR('Gross profit and margin by plan'!B5<='Model inputs'!O66),'Gross profit and margin by plan'!B5<='Model inputs'!O66,IF(OR('Gross profit and margin by plan'!B5="",'Model inputs'!O66=""),"",'Gross profit and margin by plan'!B5<='Model inputs'!O66))),0,IF(IF(IF(ISERROR('Gross profit and margin by plan'!B5<='Model inputs'!O68),'Gross profit and margin by plan'!B5<='Model inputs'!O68,IF(OR('Gross profit and margin by plan'!B5="",'Model inputs'!O68=""),"",'Gross profit and margin by plan'!B5<='Model inputs'!O68))="",FALSE,IF(ISERROR('Gross profit and margin by plan'!B5<='Model inputs'!O68),'Gross profit and margin by plan'!B5<='Model inputs'!O68,IF(OR('Gross profit and margin by plan'!B5="",'Model inputs'!O68=""),"",'Gross profit and margin by plan'!B5<='Model inputs'!O68))),IF('Model inputs'!O69="","",'Model inputs'!O69),'Model inputs'!O69+CEILING(('Gross profit and margin by plan'!B5-'Model inputs'!O68)/100000,1)*'Model inputs'!O67))) -> 0 | C6: =IF(IF(IF(ISERROR('Model inputs'!O65=1),'Model inputs'!O65=1,IF('Model inputs'!O65="","",'Model inputs'!O65=1))="",FALSE,IF(ISERROR('Model inputs'!O65=1),'Model inputs'!O65=1,IF('Model inputs'!O65="","",'Model inputs'!O65=1))),0,IF(IF(IF(ISERROR('Gross profit and margin by plan'!C5<='Model inputs'!O66),'Gross profit and margin by plan'!C5<='Model inputs'!O66,IF(OR('Gross profit and margin by plan'!C5="",'Model inputs'!O66=""),"",'Gross profit and margin by plan'!C5<='Model inputs'!O66))="",FALSE,IF(ISERROR('Gross profit and margin by plan'!C5<='Model inputs'!O66),'Gross profit and margin by plan'!C5<='Model inputs'!O66,IF(OR('Gross profit and margin by plan'!C5="",'Model inputs'!O66=""),"",'Gross profit and margin by plan'!C5<='Model inputs'!O66))),0,IF(IF(IF(ISERROR('Gross profit and margin by plan'!C5<='Model inputs'!O68),'Gross profit and margin by plan'!C5<='Model inputs'!O68,IF(OR('Gross profit and margin by plan'!C5="",'Model inputs'!O68=""),"",'Gross profit and margin by plan'!C5<='Model inputs'!O68))="",FALSE,IF(ISERROR('Gross profit and margin by plan'!C5<='Model inputs'!O68),'Gross profit and margin by plan'!C5<='Model inputs'!O68,IF(OR('Gross profit and margin by plan'!C5="",'Model inputs'!O68=""),"",'Gross profit and margin by plan'!C5<='Model inputs'!O68))),IF('Model inputs'!O69="","",'Model inputs'!O69),'Model inputs'!O69+CEILING(('Gross profit and margin by plan'!C5-'Model inputs'!O68)/100000,1)*'Model inputs'!O67))) -> 0 | D6: =IF(IF(IF(ISERROR('Model inputs'!O65=1),'Model inputs'!O65=1,IF('Model inputs'!O65="","",'Model inputs'!O65=1))="",FALSE,IF(ISERROR('Model inputs'!O65=1),'Model inputs'!O65=1,IF('Model inputs'!O65="","",'Model inputs'!O65=1))),0,IF(IF(IF(ISERROR('Gross profit and margin by plan'!D5<='Model inputs'!O66),'Gross profit and margin by plan'!D5<='Model inputs'!O66,IF(OR('Gross profit and margin by plan'!D5="",'Model inputs'!O66=""),"",'Gross profit and margin by plan'!D5<='Model inputs'!O66))="",FALSE,IF(ISERROR('Gross profit and margin by plan'!D5<='Model inputs'!O66),'Gross profit and margin by plan'!D5<='Model inputs'!O66,IF(OR('Gross profit and margin by plan'!D5="",'Model inputs'!O66=""),"",'Gross profit and margin by plan'!D5<='Model inputs'!O66))),0,IF(IF(IF(ISERROR('Gross profit and margin by plan'!D5<='Model inputs'!O68),'Gross profit and margin by plan'!D5<='Model inputs'!O68,IF(OR('Gross profit and margin by plan'!D5="",'Model inputs'!O68=""),"",'Gross profit and margin by plan'!D5<='Model inputs'!O68))="",FALSE,IF(ISERROR('Gross profit and margin by plan'!D5<='Model inputs'!O68),'Gross profit and margin by plan'!D5<='Model inputs'!O68,IF(OR('Gross profit and margin by plan'!D5="",'Model inputs'!O68=""),"",'Gross profit and margin by plan'!D5<='Model inputs'!O68))),IF('Model inputs'!O69="","",'Model inputs'!O69),'Model inputs'!O69+CEILING(('Gross profit and margin by plan'!D5-'Model inputs'!O68)/100000,1)*'Model inputs'!O67))) -> 0 | E6: =IF(IF(IF(ISERROR('Model inputs'!O65=1),'Model inputs'!O65=1,IF('Model inputs'!O65="","",'Model inputs'!O65=1))="",FALSE,IF(ISERROR('Model inputs'!O65=1),'Model inputs'!O65=1,IF('Model inputs'!O65="","",'Model inputs'!O65=1))),0,IF(IF(IF(ISERROR('Gross profit and margin by plan'!E5<='Model inputs'!O66),'Gross profit and margin by plan'!E5<='Model inputs'!O66,IF(OR('Gross profit and margin by plan'!E5="",'Model inputs'!O66=""),"",'Gross profit and margin by plan'!E5<='Model inputs'!O66))="",FALSE,IF(ISERROR('Gross profit and margin by plan'!E5<='Model inputs'!O66),'Gross profit and margin by plan'!E5<='Model inputs'!O66,IF(OR('Gross profit and margin by plan'!E5="",'Model inputs'!O66=""),"",'Gross profit and margin by plan'!E5<='Model inputs'!O66))),0,IF(IF(IF(ISERROR('Gross profit and margin by plan'!E5<='Model inputs'!O68),'Gross profit and margin by plan'!E5<='Model inputs'!O68,IF(OR('Gross profit and margin by plan'!E5="",'Model inputs'!O68=""),"",'Gross profit and margin by plan'!E5<='Model inputs'!O68))="",FALSE,IF(ISERROR('Gross profit and margin by plan'!E5<='Model inputs'!O68),'Gross profit and margin by plan'!E5<='Model inputs'!O68,IF(OR('Gross profit and margin by plan'!E5="",'Model inputs'!O68=""),"",'Gross profit and margin by plan'!E5<='Model inputs'!O68))),IF('Model inputs'!O69="","",'Model inputs'!O69),'Model inputs'!O69+CEILING(('Gross profit and margin by plan'!E5-'Model inputs'!O68)/100000,1)*'Model inputs'!O67))) -> 0 | F6: =IF(IF(IF(ISERROR('Model inputs'!O65=1),'Model inputs'!O65=1,IF('Model inputs'!O65="","",'Model inputs'!O65=1))="",FALSE,IF(ISERROR('Model inputs'!O65=1),'Model inputs'!O65=1,IF('Model inputs'!O65="","",'Model inputs'!O65=1))),0,IF(IF(IF(ISERROR('Gross profit and margin by plan'!F5<='Model inputs'!O66),'Gross profit and margin by plan'!F5<='Model inputs'!O66,IF(OR('Gross profit and margin by plan'!F5="",'Model inputs'!O66=""),"",'Gross profit and margin by plan'!F5<='Model inputs'!O66))="",FALSE,IF(ISERROR('Gross profit and margin by plan'!F5<='Model inputs'!O66),'Gross profit and margin by plan'!F5<='Model inputs'!O66,IF(OR('Gross profit and margin by plan'!F5="",'Model inputs'!O66=""),"",'Gross profit and margin by plan'!F5<='Model inputs'!O66))),0,IF(IF(IF(ISERROR('Gross profit and margin by plan'!F5<='Model inputs'!O68),'Gross profit and margin by plan'!F5<='Model inputs'!O68,IF(OR('Gross profit and margin by plan'!F5="",'Model inputs'!O68=""),"",'Gross profit and margin by plan'!F5<='Model inputs'!O68))="",FALSE,IF(ISERROR('Gross profit and margin by plan'!F5<='Model inputs'!O68),'Gross profit and margin by plan'!F5<='Model inputs'!O68,IF(OR('Gross profit and margin by plan'!F5="",'Model inputs'!O68=""),"",'Gross profit and margin by plan'!F5<='Model inputs'!O68))),IF('Model inputs'!O69="","",'Model inputs'!O69),'Model inputs'!O69+CEILING(('Gross profit and margin by plan'!F5-'Model inputs'!O68)/100000,1)*'Model inputs'!O67))) -> 0 | G6: =IF(IF(IF(ISERROR('Model inputs'!O65=1),'Model inputs'!O65=1,IF('Model inputs'!O65="","",'Model inputs'!O65=1))="",FALSE,IF(ISERROR('Model inputs'!O65=1),'Model inputs'!O65=1,IF('Model inputs'!O65="","",'Model inputs'!O65=1))),0,IF(IF(IF(ISERROR('Gross profit and margin by plan'!G5<='Model inputs'!O66),'Gross profit and margin by plan'!G5<='Model inputs'!O66,IF(OR('Gross profit and margin by plan'!G5="",'Model inputs'!O66=""),"",'Gross profit and margin by plan'!G5<='Model inputs'!O66))="",FALSE,IF(ISERROR('Gross profit and margin by plan'!G5<='Model inputs'!O66),'Gross profit and margin by plan'!G5<='Model inputs'!O66,IF(OR('Gross profit and margin by plan'!G5="",'Model inputs'!O66=""),"",'Gross profit and margin by plan'!G5<='Model inputs'!O66))),0,IF(IF(IF(ISERROR('Gross profit and margin by plan'!G5<='Model inputs'!O68),'Gross profit and margin by plan'!G5<='Model inputs'!O68,IF(OR('Gross profit and margin by plan'!G5="",'Model inputs'!O68=""),"",'Gross profit and margin by plan'!G5<='Model inputs'!O68))="",FALSE,IF(ISERROR('Gross profit and margin by plan'!G5<='Model inputs'!O68),'Gross profit and margin by plan'!G5<='Model inputs'!O68,IF(OR('Gross profit and margin by plan'!G5="",'Model inputs'!O68=""),"",'Gross profit and margin by plan'!G5<='Model inputs'!O68))),IF('Model inputs'!O69="","",'Model inputs'!O69),'Model inputs'!O69+CEILING(('Gross profit and margin by plan'!G5-'Model inputs'!O68)/100000,1)*'Model inputs'!O67))) -> 0 | H6: =IF(IF(IF(ISERROR('Model inputs'!O65=1),'Model inputs'!O65=1,IF('Model inputs'!O65="","",'Model inputs'!O65=1))="",FALSE,IF(ISERROR('Model inputs'!O65=1),'Model inputs'!O65=1,IF('Model inputs'!O65="","",'Model inputs'!O65=1))),0,IF(IF(IF(ISERROR('Gross profit and margin by plan'!H5<='Model inputs'!O66),'Gross profit and margin by plan'!H5<='Model inputs'!O66,IF(OR('Gross profit and margin by plan'!H5="",'Model inputs'!O66=""),"",'Gross profit and margin by plan'!H5<='Model inputs'!O66))="",FALSE,IF(ISERROR('Gross profit and margin by plan'!H5<='Model inputs'!O66),'Gross profit and margin by plan'!H5<='Model inputs'!O66,IF(OR('Gross profit and margin by plan'!H5="",'Model inputs'!O66=""),"",'Gross profit and margin by plan'!H5<='Model inputs'!O66))),0,IF(IF(IF(ISERROR('Gross profit and margin by plan'!H5<='Model inputs'!O68),'Gross profit and margin by plan'!H5<='Model inputs'!O68,IF(OR('Gross profit and margin by plan'!H5="",'Model inputs'!O68=""),"",'Gross profit and margin by plan'!H5<='Model inputs'!O68))="",FALSE,IF(ISERROR('Gross profit and margin by plan'!H5<='Model inputs'!O68),'Gross profit and margin by plan'!H5<='Model inputs'!O68,IF(OR('Gross profit and margin by plan'!H5="",'Model inputs'!O68=""),"",'Gross profit and margin by plan'!H5<='Model inputs'!O68))),IF('Model inputs'!O69="","",'Model inputs'!O69),'Model inputs'!O69+CEILING(('Gross profit and margin by plan'!H5-'Model inputs'!O68)/100000,1)*'Model inputs'!O67))) -> 0 | I6: =IF(IF(IF(ISERROR('Model inputs'!O65=1),'Model inputs'!O65=1,IF('Model inputs'!O65="","",'Model inputs'!O65=1))="",FALSE,IF(ISERROR('Model inputs'!O65=1),'Model inputs'!O65=1,IF('Model inputs'!O65="","",'Model inputs'!O65=1))),0,IF(IF(IF(ISERROR('Gross profit and margin by plan'!I5<='Model inputs'!O66),'Gross profit and margin by plan'!I5<='Model inputs'!O66,IF(OR('Gross profit and margin by plan'!I5="",'Model inputs'!O66=""),"",'Gross profit and margin by plan'!I5<='Model inputs'!O66))="",FALSE,IF(ISERROR('Gross profit and margin by plan'!I5<='Model inputs'!O66),'Gross profit and margin by plan'!I5<='Model inputs'!O66,IF(OR('Gross profit and margin by plan'!I5="",'Model inputs'!O66=""),"",'Gross profit and margin by plan'!I5<='Model inputs'!O66))),0,IF(IF(IF(ISERROR('Gross profit and margin by plan'!I5<='Model inputs'!O68),'Gross profit and margin by plan'!I5<='Model inputs'!O68,IF(OR('Gross profit and margin by plan'!I5="",'Model inputs'!O68=""),"",'Gross profit and margin by plan'!I5<='Model inputs'!O68))="",FALSE,IF(ISERROR('Gross profit and margin by plan'!I5<='Model inputs'!O68),'Gross profit and margin by plan'!I5<='Model inputs'!O68,IF(OR('Gross profit and margin by plan'!I5="",'Model inputs'!O68=""),"",'Gross profit and margin by plan'!I5<='Model inputs'!O68))),IF('Model inputs'!O69="","",'Model inputs'!O69),'Model inputs'!O69+CEILING(('Gross profit and margin by plan'!I5-'Model inputs'!O68)/100000,1)*'Model inputs'!O67))) -> 0 | J6: =IF(IF(IF(ISERROR('Model inputs'!O65=1),'Model inputs'!O65=1,IF('Model inputs'!O65="","",'Model inputs'!O65=1))="",FALSE,IF(ISERROR('Model inputs'!O65=1),'Model inputs'!O65=1,IF('Model inputs'!O65="","",'Model inputs'!O65=1))),0,IF(IF(IF(ISERROR('Gross profit and margin by plan'!J5<='Model inputs'!O66),'Gross profit and margin by plan'!J5<='Model inputs'!O66,IF(OR('Gross profit and margin by plan'!J5="",'Model inputs'!O66=""),"",'Gross profit and margin by plan'!J5<='Model inputs'!O66))="",FALSE,IF(ISERROR('Gross profit and margin by plan'!J5<='Model inputs'!O66),'Gross profit and margin by plan'!J5<='Model inputs'!O66,IF(OR('Gross profit and margin by plan'!J5="",'Model inputs'!O66=""),"",'Gross profit and margin by plan'!J5<='Model inputs'!O66))),0,IF(IF(IF(ISERROR('Gross profit and margin by plan'!J5<='Model inputs'!O68),'Gross profit and margin by plan'!J5<='Model inputs'!O68,IF(OR('Gross profit and margin by plan'!J5="",'Model inputs'!O68=""),"",'Gross profit and margin by plan'!J5<='Model inputs'!O68))="",FALSE,IF(ISERROR('Gross profit and margin by plan'!J5<='Model inputs'!O68),'Gross profit and margin by plan'!J5<='Model inputs'!O68,IF(OR('Gross profit and margin by plan'!J5="",'Model inputs'!O68=""),"",'Gross profit and margin by plan'!J5<='Model inputs'!O68))),IF('Model inputs'!O69="","",'Model inputs'!O69),'Model inputs'!O69+CEILING(('Gross profit and margin by plan'!J5-'Model inputs'!O68)/100000,1)*'Model inputs'!O67))) -> 0 | K6: =IF(IF(IF(ISERROR('Model inputs'!O65=1),'Model inputs'!O65=1,IF('Model inputs'!O65="","",'Model inputs'!O65=1))="",FALSE,IF(ISERROR('Model inputs'!O65=1),'Model inputs'!O65=1,IF('Model inputs'!O65="","",'Model inputs'!O65=1))),0,IF(IF(IF(ISERROR('Gross profit and margin by plan'!K5<='Model inputs'!O66),'Gross profit and margin by plan'!K5<='Model inputs'!O66,IF(OR('Gross profit and margin by plan'!K5="",'Model inputs'!O66=""),"",'Gross profit and margin by plan'!K5<='Model inputs'!O66))="",FALSE,IF(ISERROR('Gross profit and margin by plan'!K5<='Model inputs'!O66),'Gross profit and margin by plan'!K5<='Model inputs'!O66,IF(OR('Gross profit and margin by plan'!K5="",'Model inputs'!O66=""),"",'Gross profit and margin by plan'!K5<='Model inputs'!O66))),0,IF(IF(IF(ISERROR('Gross profit and margin by plan'!K5<='Model inputs'!O68),'Gross profit and margin by plan'!K5<='Model inputs'!O68,IF(OR('Gross profit and margin by plan'!K5="",'Model inputs'!O68=""),"",'Gross profit and margin by plan'!K5<='Model inputs'!O68))="",FALSE,IF(ISERROR('Gross profit and margin by plan'!K5<='Model inputs'!O68),'Gross profit and margin by plan'!K5<='Model inputs'!O68,IF(OR('Gross profit and margin by plan'!K5="",'Model inputs'!O68=""),"",'Gross profit and margin by plan'!K5<='Model inputs'!O68))),IF('Model inputs'!O69="","",'Model inputs'!O69),'Model inputs'!O69+CEILING(('Gross profit and margin by plan'!K5-'Model inputs'!O68)/100000,1)*'Model inputs'!O67))) -> 0 | L6: =IF(IF(IF(ISERROR('Model inputs'!O65=1),'Model inputs'!O65=1,IF('Model inputs'!O65="","",'Model inputs'!O65=1))="",FALSE,IF(ISERROR('Model inputs'!O65=1),'Model inputs'!O65=1,IF('Model inputs'!O65="","",'Model inputs'!O65=1))),0,IF(IF(IF(ISERROR('Gross profit and margin by plan'!L5<='Model inputs'!O66),'Gross profit and margin by plan'!L5<='Model inputs'!O66,IF(OR('Gross profit and margin by plan'!L5="",'Model inputs'!O66=""),"",'Gross profit and margin by plan'!L5<='Model inputs'!O66))="",FALSE,IF(ISERROR('Gross profit and margin by plan'!L5<='Model inputs'!O66),'Gross profit and margin by plan'!L5<='Model inputs'!O66,IF(OR('Gross profit and margin by plan'!L5="",'Model inputs'!O66=""),"",'Gross profit and margin by plan'!L5<='Model inputs'!O66))),0,IF(IF(IF(ISERROR('Gross profit and margin by plan'!L5<='Model inputs'!O68),'Gross profit and margin by plan'!L5<='Model inputs'!O68,IF(OR('Gross profit and margin by plan'!L5="",'Model inputs'!O68=""),"",'Gross profit and margin by plan'!L5<='Model inputs'!O68))="",FALSE,IF(ISERROR('Gross profit and margin by plan'!L5<='Model inputs'!O68),'Gross profit and margin by plan'!L5<='Model inputs'!O68,IF(OR('Gross profit and margin by plan'!L5="",'Model inputs'!O68=""),"",'Gross profit and margin by plan'!L5<='Model inputs'!O68))),IF('Model inputs'!O69="","",'Model inputs'!O69),'Model inputs'!O69+CEILING(('Gross profit and margin by plan'!L5-'Model inputs'!O68)/100000,1)*'Model inputs'!O67))) -> 0 | M6: =IF(IF(IF(ISERROR('Model inputs'!O65=1),'Model inputs'!O65=1,IF('Model inputs'!O65="","",'Model inputs'!O65=1))="",FALSE,IF(ISERROR('Model inputs'!O65=1),'Model inputs'!O65=1,IF('Model inputs'!O65="","",'Model inputs'!O65=1))),0,IF(IF(IF(ISERROR('Gross profit and margin by plan'!M5<='Model inputs'!O66),'Gross profit and margin by plan'!M5<='Model inputs'!O66,IF(OR('Gross profit and margin by plan'!M5="",'Model inputs'!O66=""),"",'Gross profit and margin by plan'!M5<='Model inputs'!O66))="",FALSE,IF(ISERROR('Gross profit and margin by plan'!M5<='Model inputs'!O66),'Gross profit and margin by plan'!M5<='Model inputs'!O66,IF(OR('Gross profit and margin by plan'!M5="",'Model inputs'!O66=""),"",'Gross profit and margin by plan'!M5<='Model inputs'!O66))),0,IF(IF(IF(ISERROR('Gross profit and margin by plan'!M5<='Model inputs'!O68),'Gross profit and margin by plan'!M5<='Model inputs'!O68,IF(OR('Gross profit and margin by plan'!M5="",'Model inputs'!O68=""),"",'Gross profit and margin by plan'!M5<='Model inputs'!O68))="",FALSE,IF(ISERROR('Gross profit and margin by plan'!M5<='Model inputs'!O68),'Gross profit and margin by plan'!M5<='Model inputs'!O68,IF(OR('Gross profit and margin by plan'!M5="",'Model inputs'!O68=""),"",'Gross profit and margin by plan'!M5<='Model inputs'!O68))),IF('Model inputs'!O69="","",'Model inputs'!O69),'Model inputs'!O69+CEILING(('Gross profit and margin by plan'!M5-'Model inputs'!O68)/100000,1)*'Model inputs'!O67))) -> 0
A7: Hosting and neatlogs allocated by revenue (USD) | B7: =SUM('Gross profit and margin by plan'!B8,'Gross profit and margin by plan'!B9) -> 25 | C7: =SUM('Gross profit and margin by plan'!C8,'Gross profit and margin by plan'!C9) -> 25 | D7: =SUM('Gross profit and margin by plan'!D8,'Gross profit and margin by plan'!D9) -> 25 | E7: =SUM('Gross profit and margin by plan'!E8,'Gross profit and margin by plan'!E9) -> 25 | F7: =SUM('Gross profit and margin by plan'!F8,'Gross profit and margin by plan'!F9) -> 25 | G7: =SUM('Gross profit and margin by plan'!G8,'Gross profit and margin by plan'!G9) -> 25 | H7: =SUM('Gross profit and margin by plan'!H8,'Gross profit and margin by plan'!H9) -> 25 | I7: =SUM('Gross profit and margin by plan'!I8,'Gross profit and margin by plan'!I9) -> 25 | ... M7: =SUM('Gross profit and margin by plan'!M8,'Gross profit and margin by plan'!M9) -> 25
A8: Classroom | B8: =('Model inputs'!O49+'Gross profit and margin by plan'!B6)*IFERROR('Unit economics by plan (monthly'!B24/SUM('Unit economics by plan (monthly'!B24,'Unit economics by plan (monthly'!B25),0) -> 12.442818 | C8: =('Model inputs'!O49+'Gross profit and margin by plan'!C6)*IFERROR('Unit economics by plan (monthly'!C24/SUM('Unit economics by plan (monthly'!C24,'Unit economics by plan (monthly'!C25),0) -> 12.239825 | D8: =('Model inputs'!O49+'Gross profit and margin by plan'!D6)*IFERROR('Unit economics by plan (monthly'!D24/SUM('Unit economics by plan (monthly'!D24,'Unit economics by plan (monthly'!D25),0) -> 12.095865 | E8: =('Model inputs'!O49+'Gross profit and margin by plan'!E6)*IFERROR('Unit economics by plan (monthly'!E24/SUM('Unit economics by plan (monthly'!E24,'Unit economics by plan (monthly'!E25),0) -> 11.995436 | F8: =('Model inputs'!O49+'Gross profit and margin by plan'!F6)*IFERROR('Unit economics by plan (monthly'!F24/SUM('Unit economics by plan (monthly'!F24,'Unit economics by plan (monthly'!F25),0) -> 11.927856 | G8: =('Model inputs'!O49+'Gross profit and margin by plan'!G6)*IFERROR('Unit economics by plan, month 6'!B9/SUM('Unit economics by plan, month 6'!B9,'Unit economics by plan, month 6'!B10),0) -> 11.88552 | H8: =('Model inputs'!O49+'Gross profit and margin by plan'!H6)*IFERROR('Unit economics by plan (monthly'!H24/SUM('Unit economics by plan (monthly'!H24,'Unit economics by plan (monthly'!H25),0) -> 11.862867 | I8: =('Model inputs'!O49+'Gross profit and margin by plan'!I6)*IFERROR('Unit economics by plan (monthly'!I24/SUM('Unit economics by plan (monthly'!I24,'Unit economics by plan (monthly'!I25),0) -> 11.855737 | J8: =('Model inputs'!O49+'Gross profit and margin by plan'!J6)*IFERROR('Unit economics by plan (monthly'!J24/SUM('Unit economics by plan (monthly'!J24,'Unit economics by plan (monthly'!J25),0) -> 11.860957 | K8: =('Model inputs'!O49+'Gross profit and margin by plan'!K6)*IFERROR('Unit economics by plan (monthly'!K24/SUM('Unit economics by plan (monthly'!K24,'Unit economics by plan (monthly'!K25),0) -> 11.876061 | L8: =('Model inputs'!O49+'Gross profit and margin by plan'!L6)*IFERROR('Unit economics by plan (monthly'!L24/SUM('Unit economics by plan (monthly'!L24,'Unit economics by plan (monthly'!L25),0) -> 11.89911 | M8: =('Model inputs'!O49+'Gross profit and margin by plan'!M6)*IFERROR('Unit economics by plan (monthly'!M24/SUM('Unit economics by plan (monthly'!M24,'Unit economics by plan (monthly'!M25),0) -> 11.928556
A9: Household | B9: =('Model inputs'!O49+'Gross profit and margin by plan'!B6)*IFERROR('Unit economics by plan (monthly'!B25/SUM('Unit economics by plan (monthly'!B24,'Unit economics by plan (monthly'!B25),0) -> 12.557182 | C9: =('Model inputs'!O49+'Gross profit and margin by plan'!C6)*IFERROR('Unit economics by plan (monthly'!C25/SUM('Unit economics by plan (monthly'!C24,'Unit economics by plan (monthly'!C25),0) -> 12.760175 | D9: =('Model inputs'!O49+'Gross profit and margin by plan'!D6)*IFERROR('Unit economics by plan (monthly'!D25/SUM('Unit economics by plan (monthly'!D24,'Unit economics by plan (monthly'!D25),0) -> 12.904135 | E9: =('Model inputs'!O49+'Gross profit and margin by plan'!E6)*IFERROR('Unit economics by plan (monthly'!E25/SUM('Unit economics by plan (monthly'!E24,'Unit economics by plan (monthly'!E25),0) -> 13.004564 | F9: =('Model inputs'!O49+'Gross profit and margin by plan'!F6)*IFERROR('Unit economics by plan (monthly'!F25/SUM('Unit economics by plan (monthly'!F24,'Unit economics by plan (monthly'!F25),0) -> 13.072144 | G9: =('Model inputs'!O49+'Gross profit and margin by plan'!G6)*IFERROR('Unit economics by plan, month 6'!B10/SUM('Unit economics by plan, month 6'!B9,'Unit economics by plan, month 6'!B10),0) -> 13.11448 | H9: =('Model inputs'!O49+'Gross profit and margin by plan'!H6)*IFERROR('Unit economics by plan (monthly'!H25/SUM('Unit economics by plan (monthly'!H24,'Unit economics by plan (monthly'!H25),0) -> 13.137133 | I9: =('Model inputs'!O49+'Gross profit and margin by plan'!I6)*IFERROR('Unit economics by plan (monthly'!I25/SUM('Unit economics by plan (monthly'!I24,'Unit economics by plan (monthly'!I25),0) -> 13.144263 | J9: =('Model inputs'!O49+'Gross profit and margin by plan'!J6)*IFERROR('Unit economics by plan (monthly'!J25/SUM('Unit economics by plan (monthly'!J24,'Unit economics by plan (monthly'!J25),0) -> 13.139043 | K9: =('Model inputs'!O49+'Gross profit and margin by plan'!K6)*IFERROR('Unit economics by plan (monthly'!K25/SUM('Unit economics by plan (monthly'!K24,'Unit economics by plan (monthly'!K25),0) -> 13.123939 | L9: =('Model inputs'!O49+'Gross profit and margin by plan'!L6)*IFERROR('Unit economics by plan (monthly'!L25/SUM('Unit economics by plan (monthly'!L24,'Unit economics by plan (monthly'!L25),0) -> 13.10089 | M9: =('Model inputs'!O49+'Gross profit and margin by plan'!M6)*IFERROR('Unit economics by plan (monthly'!M25/SUM('Unit economics by plan (monthly'!M24,'Unit economics by plan (monthly'!M25),0) -> 13.071444
A10: Infra and inference (USD) | B10: =SUM('Gross profit and margin by plan'!B11,'Gross profit and margin by plan'!B12) -> 213.9573 | C10: =SUM('Gross profit and margin by plan'!C11,'Gross profit and margin by plan'!C12) -> 228.16695 | D10: =SUM('Gross profit and margin by plan'!D11,'Gross profit and margin by plan'!D12) -> 241.63887 | E10: =SUM('Gross profit and margin by plan'!E11,'Gross profit and margin by plan'!E12) -> 254.42012 | F10: =SUM('Gross profit and margin by plan'!F11,'Gross profit and margin by plan'!F12) -> 266.55433 | G10: =SUM('Gross profit and margin by plan'!G11,'Gross profit and margin by plan'!G12) -> 278.082 | H10: =SUM('Gross profit and margin by plan'!H11,'Gross profit and margin by plan'!H12) -> 289.04074 | I10: =SUM('Gross profit and margin by plan'!I11,'Gross profit and margin by plan'!I12) -> 299.46545 | ... M10: =SUM('Gross profit and margin by plan'!M11,'Gross profit and margin by plan'!M12) -> 336.43963
A11: Classroom | B11: ='Unit economics by plan (monthly'!B27+'Gross profit and margin by plan'!B8 -> 138.21062 | C11: ='Unit economics by plan (monthly'!C27+'Gross profit and margin by plan'!C8 -> 145.98859 | D11: ='Unit economics by plan (monthly'!D27+'Gross profit and margin by plan'!D8 -> 153.58617 | E11: ='Unit economics by plan (monthly'!E27+'Gross profit and margin by plan'!E8 -> 160.99503 | F11: ='Unit economics by plan (monthly'!F27+'Gross profit and margin by plan'!F8 -> 168.21146 | G11: ='Unit economics by plan (monthly'!G27+'Gross profit and margin by plan'!G8 -> 175.23462 | H11: ='Unit economics by plan (monthly'!H27+'Gross profit and margin by plan'!H8 -> 182.06549 | I11: ='Unit economics by plan (monthly'!I27+'Gross profit and margin by plan'!I8 -> 188.70628 | ... M11: ='Unit economics by plan (monthly'!M27+'Gross profit and margin by plan'!M8 -> 213.43535
A12: Household | B12: ='Unit economics by plan (monthly'!B28+'Gross profit and margin by plan'!B9 -> 75.746686 | C12: ='Unit economics by plan (monthly'!C28+'Gross profit and margin by plan'!C9 -> 82.178358 | D12: ='Unit economics by plan (monthly'!D28+'Gross profit and margin by plan'!D9 -> 88.052704 | E12: ='Unit economics by plan (monthly'!E28+'Gross profit and margin by plan'!E9 -> 93.425087 | F12: ='Unit economics by plan (monthly'!F28+'Gross profit and margin by plan'!F9 -> 98.342866 | G12: ='Unit economics by plan (monthly'!G28+'Gross profit and margin by plan'!G9 -> 102.84738 | H12: ='Unit economics by plan (monthly'!H28+'Gross profit and margin by plan'!H9 -> 106.97524 | I12: ='Unit economics by plan (monthly'!I28+'Gross profit and margin by plan'!I9 -> 110.75917 | ... M12: ='Unit economics by plan (monthly'!M28+'Gross profit and margin by plan'!M9 -> 123.00428
A13: Gross profit (USD) | B13: =SUM('Gross profit and margin by plan'!B14,'Gross profit and margin by plan'!B15) -> 409.4947 | C13: =SUM('Gross profit and margin by plan'!C14,'Gross profit and margin by plan'!C15) -> 445.84389 | D13: =SUM('Gross profit and margin by plan'!D14,'Gross profit and margin by plan'!D15) -> 479.87065 | E13: =SUM('Gross profit and margin by plan'!E14,'Gross profit and margin by plan'!E15) -> 511.74321 | F13: =SUM('Gross profit and margin by plan'!F14,'Gross profit and margin by plan'!F15) -> 541.61686 | G13: =SUM('Gross profit and margin by plan'!G14,'Gross profit and margin by plan'!G15) -> 569.63499 | H13: =SUM('Gross profit and margin by plan'!H14,'Gross profit and margin by plan'!H15) -> 595.93001 | I13: =SUM('Gross profit and margin by plan'!I14,'Gross profit and margin by plan'!I15) -> 620.62422 | ... M13: =SUM('Gross profit and margin by plan'!M14,'Gross profit and margin by plan'!M15) -> 705.52776
A14: Classroom | B14: ='Unit economics by plan (monthly'!B24-'Gross profit and margin by plan'!B11 -> 172.08938 | C14: ='Unit economics by plan (monthly'!C24-'Gross profit and margin by plan'!C11 -> 184.00241 | D14: ='Unit economics by plan (monthly'!D24-'Gross profit and margin by plan'!D11 -> 195.5051 | E14: ='Unit economics by plan (monthly'!E24-'Gross profit and margin by plan'!E11 -> 206.6235 | F14: ='Unit economics by plan (monthly'!F24-'Gross profit and margin by plan'!F11 -> 217.37851 | G14: ='Unit economics by plan, month 6'!B9-'Gross profit and margin by plan'!G11 -> 227.78766 | H14: ='Unit economics by plan (monthly'!H24-'Gross profit and margin by plan'!H11 -> 237.86612 | I14: ='Unit economics by plan (monthly'!I24-'Gross profit and margin by plan'!I11 -> 247.62738 | J14: ='Unit economics by plan (monthly'!J24-'Gross profit and margin by plan'!J11 -> 257.08366 | K14: ='Unit economics by plan (monthly'!K24-'Gross profit and margin by plan'!K11 -> 266.24622 | L14: ='Unit economics by plan (monthly'!L24-'Gross profit and margin by plan'!L11 -> 275.1255 | M14: ='Unit economics by plan (monthly'!M24-'Gross profit and margin by plan'!M11 -> 283.73132
A15: Household | B15: ='Unit economics by plan (monthly'!B25-'Gross profit and margin by plan'!B12 -> 237.40531 | C15: ='Unit economics by plan (monthly'!C25-'Gross profit and margin by plan'!C12 -> 261.84148 | D15: ='Unit economics by plan (monthly'!D25-'Gross profit and margin by plan'!D12 -> 284.36555 | E15: ='Unit economics by plan (monthly'!E25-'Gross profit and margin by plan'!E12 -> 305.11971 | F15: ='Unit economics by plan (monthly'!F25-'Gross profit and margin by plan'!F12 -> 324.23834 | G15: ='Unit economics by plan, month 6'!B10-'Gross profit and margin by plan'!G12 -> 341.84733 | H15: ='Unit economics by plan (monthly'!H25-'Gross profit and margin by plan'!H12 -> 358.06389 | I15: ='Unit economics by plan (monthly'!I25-'Gross profit and margin by plan'!I12 -> 372.99684 | J15: ='Unit economics by plan (monthly'!J25-'Gross profit and margin by plan'!J12 -> 386.74693 | K15: ='Unit economics by plan (monthly'!K25-'Gross profit and margin by plan'!K12 -> 399.40732 | L15: ='Unit economics by plan (monthly'!L25-'Gross profit and margin by plan'!L12 -> 411.06403 | M15: ='Unit economics by plan (monthly'!M25-'Gross profit and margin by plan'!M12 -> 421.79644
A16: Gross margin | B16: =IFERROR('Gross profit and margin by plan'!B13/'Unit economics by plan (monthly'!B23,0) -> 0.65681832 | C16: =IFERROR('Gross profit and margin by plan'!C13/'Unit economics by plan (monthly'!C23,0) -> 0.66147881 | D16: =IFERROR('Gross profit and margin by plan'!D13/'Unit economics by plan (monthly'!D23,0) -> 0.66509261 | E16: =IFERROR('Gross profit and margin by plan'!E13/'Unit economics by plan (monthly'!E23,0) -> 0.66792966 | F16: =IFERROR('Gross profit and margin by plan'!F13/'Unit economics by plan (monthly'!F23,0) -> 0.67017591 | G16: =IFERROR('Gross profit and margin by plan'!G13/'Unit economics by plan, month 6'!B8,0) -> 0.67196363 | H16: =IFERROR('Gross profit and margin by plan'!H13/'Unit economics by plan (monthly'!H23,0) -> 0.6733895 | I16: =IFERROR('Gross profit and margin by plan'!I13/'Unit economics by plan (monthly'!I23,0) -> 0.6745258 | J16: =IFERROR('Gross profit and margin by plan'!J13/'Unit economics by plan (monthly'!J23,0) -> 0.67542766 | K16: =IFERROR('Gross profit and margin by plan'!K13/'Unit economics by plan (monthly'!K23,0) -> 0.67613785 | L16: =IFERROR('Gross profit and margin by plan'!L13/'Unit economics by plan (monthly'!L23,0) -> 0.67669006 | M16: =IFERROR('Gross profit and margin by plan'!M13/'Unit economics by plan (monthly'!M23,0) -> 0.67711117
A17: Classroom | B17: =IFERROR('Gross profit and margin by plan'!B14/'Unit economics by plan (monthly'!B24,0) -> 0.55459034 | C17: =IFERROR('Gross profit and margin by plan'!C14/'Unit economics by plan (monthly'!C24,0) -> 0.55759826 | D17: =IFERROR('Gross profit and margin by plan'!D14/'Unit economics by plan (monthly'!D24,0) -> 0.56004008 | E17: =IFERROR('Gross profit and margin by plan'!E14/'Unit economics by plan (monthly'!E24,0) -> 0.56205954 | F17: =IFERROR('Gross profit and margin by plan'!F14/'Unit economics by plan (monthly'!F24,0) -> 0.56375561 | G17: =IFERROR('Gross profit and margin by plan'!G14/'Unit economics by plan, month 6'!B9,0) -> 0.56519868 | H17: =IFERROR('Gross profit and margin by plan'!H14/'Unit economics by plan (monthly'!H24,0) -> 0.56644013 | I17: =IFERROR('Gross profit and margin by plan'!I14/'Unit economics by plan (monthly'!I24,0) -> 0.56751839 | J17: =IFERROR('Gross profit and margin by plan'!J14/'Unit economics by plan (monthly'!J24,0) -> 0.56846274 | K17: =IFERROR('Gross profit and margin by plan'!K14/'Unit economics by plan (monthly'!K24,0) -> 0.5692959 | L17: =IFERROR('Gross profit and margin by plan'!L14/'Unit economics by plan (monthly'!L24,0) -> 0.57003575 | M17: =IFERROR('Gross profit and margin by plan'!M14/'Unit economics by plan (monthly'!M24,0) -> 0.57069658
A18: Household | B18: =IFERROR('Gross profit and margin by plan'!B15/'Unit economics by plan (monthly'!B25,0) -> 0.75811527 | C18: =IFERROR('Gross profit and margin by plan'!C15/'Unit economics by plan (monthly'!C25,0) -> 0.7611232 | D18: =IFERROR('Gross profit and margin by plan'!D15/'Unit economics by plan (monthly'!D25,0) -> 0.76356501 | E18: =IFERROR('Gross profit and margin by plan'!E15/'Unit economics by plan (monthly'!E25,0) -> 0.76558447 | F18: =IFERROR('Gross profit and margin by plan'!F15/'Unit economics by plan (monthly'!F25,0) -> 0.76728055 | G18: =IFERROR('Gross profit and margin by plan'!G15/'Unit economics by plan, month 6'!B10,0) -> 0.76872362 | H18: =IFERROR('Gross profit and margin by plan'!H15/'Unit economics by plan (monthly'!H25,0) -> 0.76996507 | I18: =IFERROR('Gross profit and margin by plan'!I15/'Unit economics by plan (monthly'!I25,0) -> 0.77104333 | J18: =IFERROR('Gross profit and margin by plan'!J15/'Unit economics by plan (monthly'!J25,0) -> 0.77198768 | K18: =IFERROR('Gross profit and margin by plan'!K15/'Unit economics by plan (monthly'!K25,0) -> 0.77282083 | L18: =IFERROR('Gross profit and margin by plan'!L15/'Unit economics by plan (monthly'!L25,0) -> 0.77356069 | M18: =IFERROR('Gross profit and margin by plan'!M15/'Unit economics by plan (monthly'!M25,0) -> 0.77422152
A19: Clears gross margin bar (1 = yes) | B19: =IF(IF(IF(ISERROR('Gross profit and margin by plan'!B16>='Model inputs'!O34),'Gross profit and margin by plan'!B16>='Model inputs'!O34,IF(OR('Gross profit and margin by plan'!B16="",'Model inputs'!O34=""),"",'Gross profit and margin by plan'!B16>='Model inputs'!O34))="",FALSE,IF(ISERROR('Gross profit and margin by plan'!B16>='Model inputs'!O34),'Gross profit and margin by plan'!B16>='Model inputs'!O34,IF(OR('Gross profit and margin by plan'!B16="",'Model inputs'!O34=""),"",'Gross profit and margin by plan'!B16>='Model inputs'!O34))),1,0) -> 1 | C19: =IF(IF(IF(ISERROR('Gross profit and margin by plan'!C16>='Model inputs'!O34),'Gross profit and margin by plan'!C16>='Model inputs'!O34,IF(OR('Gross profit and margin by plan'!C16="",'Model inputs'!O34=""),"",'Gross profit and margin by plan'!C16>='Model inputs'!O34))="",FALSE,IF(ISERROR('Gross profit and margin by plan'!C16>='Model inputs'!O34),'Gross profit and margin by plan'!C16>='Model inputs'!O34,IF(OR('Gross profit and margin by plan'!C16="",'Model inputs'!O34=""),"",'Gross profit and margin by plan'!C16>='Model inputs'!O34))),1,0) -> 1 | D19: =IF(IF(IF(ISERROR('Gross profit and margin by plan'!D16>='Model inputs'!O34),'Gross profit and margin by plan'!D16>='Model inputs'!O34,IF(OR('Gross profit and margin by plan'!D16="",'Model inputs'!O34=""),"",'Gross profit and margin by plan'!D16>='Model inputs'!O34))="",FALSE,IF(ISERROR('Gross profit and margin by plan'!D16>='Model inputs'!O34),'Gross profit and margin by plan'!D16>='Model inputs'!O34,IF(OR('Gross profit and margin by plan'!D16="",'Model inputs'!O34=""),"",'Gross profit and margin by plan'!D16>='Model inputs'!O34))),1,0) -> 1 | E19: =IF(IF(IF(ISERROR('Gross profit and margin by plan'!E16>='Model inputs'!O34),'Gross profit and margin by plan'!E16>='Model inputs'!O34,IF(OR('Gross profit and margin by plan'!E16="",'Model inputs'!O34=""),"",'Gross profit and margin by plan'!E16>='Model inputs'!O34))="",FALSE,IF(ISERROR('Gross profit and margin by plan'!E16>='Model inputs'!O34),'Gross profit and margin by plan'!E16>='Model inputs'!O34,IF(OR('Gross profit and margin by plan'!E16="",'Model inputs'!O34=""),"",'Gross profit and margin by plan'!E16>='Model inputs'!O34))),1,0) -> 1 | F19: =IF(IF(IF(ISERROR('Gross profit and margin by plan'!F16>='Model inputs'!O34),'Gross profit and margin by plan'!F16>='Model inputs'!O34,IF(OR('Gross profit and margin by plan'!F16="",'Model inputs'!O34=""),"",'Gross profit and margin by plan'!F16>='Model inputs'!O34))="",FALSE,IF(ISERROR('Gross profit and margin by plan'!F16>='Model inputs'!O34),'Gross profit and margin by plan'!F16>='Model inputs'!O34,IF(OR('Gross profit and margin by plan'!F16="",'Model inputs'!O34=""),"",'Gross profit and margin by plan'!F16>='Model inputs'!O34))),1,0) -> 1 | G19: =IF(IF(IF(ISERROR('Gross profit and margin by plan'!G16>='Model inputs'!O34),'Gross profit and margin by plan'!G16>='Model inputs'!O34,IF(OR('Gross profit and margin by plan'!G16="",'Model inputs'!O34=""),"",'Gross profit and margin by plan'!G16>='Model inputs'!O34))="",FALSE,IF(ISERROR('Gross profit and margin by plan'!G16>='Model inputs'!O34),'Gross profit and margin by plan'!G16>='Model inputs'!O34,IF(OR('Gross profit and margin by plan'!G16="",'Model inputs'!O34=""),"",'Gross profit and margin by plan'!G16>='Model inputs'!O34))),1,0) -> 1 | H19: =IF(IF(IF(ISERROR('Gross profit and margin by plan'!H16>='Model inputs'!O34),'Gross profit and margin by plan'!H16>='Model inputs'!O34,IF(OR('Gross profit and margin by plan'!H16="",'Model inputs'!O34=""),"",'Gross profit and margin by plan'!H16>='Model inputs'!O34))="",FALSE,IF(ISERROR('Gross profit and margin by plan'!H16>='Model inputs'!O34),'Gross profit and margin by plan'!H16>='Model inputs'!O34,IF(OR('Gross profit and margin by plan'!H16="",'Model inputs'!O34=""),"",'Gross profit and margin by plan'!H16>='Model inputs'!O34))),1,0) -> 1 | I19: =IF(IF(IF(ISERROR('Gross profit and margin by plan'!I16>='Model inputs'!O34),'Gross profit and margin by plan'!I16>='Model inputs'!O34,IF(OR('Gross profit and margin by plan'!I16="",'Model inputs'!O34=""),"",'Gross profit and margin by plan'!I16>='Model inputs'!O34))="",FALSE,IF(ISERROR('Gross profit and margin by plan'!I16>='Model inputs'!O34),'Gross profit and margin by plan'!I16>='Model inputs'!O34,IF(OR('Gross profit and margin by plan'!I16="",'Model inputs'!O34=""),"",'Gross profit and margin by plan'!I16>='Model inputs'!O34))),1,0) -> 1 | J19: =IF(IF(IF(ISERROR('Gross profit and margin by plan'!J16>='Model inputs'!O34),'Gross profit and margin by plan'!J16>='Model inputs'!O34,IF(OR('Gross profit and margin by plan'!J16="",'Model inputs'!O34=""),"",'Gross profit and margin by plan'!J16>='Model inputs'!O34))="",FALSE,IF(ISERROR('Gross profit and margin by plan'!J16>='Model inputs'!O34),'Gross profit and margin by plan'!J16>='Model inputs'!O34,IF(OR('Gross profit and margin by plan'!J16="",'Model inputs'!O34=""),"",'Gross profit and margin by plan'!J16>='Model inputs'!O34))),1,0) -> 1 | K19: =IF(IF(IF(ISERROR('Gross profit and margin by plan'!K16>='Model inputs'!O34),'Gross profit and margin by plan'!K16>='Model inputs'!O34,IF(OR('Gross profit and margin by plan'!K16="",'Model inputs'!O34=""),"",'Gross profit and margin by plan'!K16>='Model inputs'!O34))="",FALSE,IF(ISERROR('Gross profit and margin by plan'!K16>='Model inputs'!O34),'Gross profit and margin by plan'!K16>='Model inputs'!O34,IF(OR('Gross profit and margin by plan'!K16="",'Model inputs'!O34=""),"",'Gross profit and margin by plan'!K16>='Model inputs'!O34))),1,0) -> 1 | L19: =IF(IF(IF(ISERROR('Gross profit and margin by plan'!L16>='Model inputs'!O34),'Gross profit and margin by plan'!L16>='Model inputs'!O34,IF(OR('Gross profit and margin by plan'!L16="",'Model inputs'!O34=""),"",'Gross profit and margin by plan'!L16>='Model inputs'!O34))="",FALSE,IF(ISERROR('Gross profit and margin by plan'!L16>='Model inputs'!O34),'Gross profit and margin by plan'!L16>='Model inputs'!O34,IF(OR('Gross profit and margin by plan'!L16="",'Model inputs'!O34=""),"",'Gross profit and margin by plan'!L16>='Model inputs'!O34))),1,0) -> 1 | M19: =IF(IF(IF(ISERROR('Gross profit and margin by plan'!M16>='Model inputs'!O34),'Gross profit and margin by plan'!M16>='Model inputs'!O34,IF(OR('Gross profit and margin by plan'!M16="",'Model inputs'!O34=""),"",'Gross profit and margin by plan'!M16>='Model inputs'!O34))="",FALSE,IF(ISERROR('Gross profit and margin by plan'!M16>='Model inputs'!O34),'Gross profit and margin by plan'!M16>='Model inputs'!O34,IF(OR('Gross profit and margin by plan'!M16="",'Model inputs'!O34=""),"",'Gross profit and margin by plan'!M16>='Model inputs'!O34))),1,0) -> 1

Sheet Model inputs
A1: Model inputs
A2: Integration values are aggregated snapshots; raw source records are not included.
A4: Variables
A5: Variable / segment | B5: 2026-09 | C5: 2026-10 | D5: 2026-11 | E5: 2026-12 | F5: 2027-01 | G5: 2027-02 | H5: 2027-03 | I5: 2027-04 | J5: 2027-05 | K5: 2027-06 | L5: 2027-07 | M5: 2027-08 | N5: 2027-09 | O5: Value
A6: Churned customers | B6: =SUM('Model inputs'!B7,'Model inputs'!B8) -> 0 | C6: =SUM('Model inputs'!C7,'Model inputs'!C8) -> 3.5 | D6: =SUM('Model inputs'!D7,'Model inputs'!D8) -> 3.905 | E6: =SUM('Model inputs'!E7,'Model inputs'!E8) -> 4.27865 | F6: =SUM('Model inputs'!F7,'Model inputs'!F8) -> 4.6234265 | G6: =SUM('Model inputs'!G7,'Model inputs'!G8) -> 4.9416088 | H6: =SUM('Model inputs'!H7,'Model inputs'!H8) -> 5.2352949
A7: Churned customers > Classroom | B7: =0 -> 0 | C7: ='Model inputs'!B23*'Model inputs'!O63 -> 0.3 | D7: ='Model inputs'!C23*'Model inputs'!O63 -> 0.321 | E7: ='Model inputs'!D23*'Model inputs'!O63 -> 0.34137 | F7: ='Model inputs'!E23*'Model inputs'!O63 -> 0.3611289 | G7: ='Model inputs'!F23*'Model inputs'!O63 -> 0.38029503 | H7: ='Model inputs'!G23*'Model inputs'!O63 -> 0.39888618
A8: Churned customers > Household | B8: =0 -> 0 | C8: ='Model inputs'!B24*'Model inputs'!O64 -> 3.2 | D8: ='Model inputs'!C24*'Model inputs'!O64 -> 3.584 | E8: ='Model inputs'!D24*'Model inputs'!O64 -> 3.93728 | F8: ='Model inputs'!E24*'Model inputs'!O64 -> 4.2622976 | G8: ='Model inputs'!F24*'Model inputs'!O64 -> 4.5613138 | H8: ='Model inputs'!G24*'Model inputs'!O64 -> 4.8364087
A9: Churned customers | B9: =IF('Model inputs'!B6="","",'Model inputs'!B6) -> 0 | C9: =IF('Model inputs'!C6="","",'Model inputs'!C6) -> 3.5 | D9: =IF('Model inputs'!D6="","",'Model inputs'!D6) -> 3.905 | E9: =IF('Model inputs'!E6="","",'Model inputs'!E6) -> 4.27865 | F9: =IF('Model inputs'!F6="","",'Model inputs'!F6) -> 4.6234265 | G9: =IF('Model inputs'!G6="","",'Model inputs'!G6) -> 4.9416088 | H9: =IF('Model inputs'!H6="","",'Model inputs'!H6) -> 5.2352949 | I9: =SUM('Model inputs'!I10,'Model inputs'!I11) -> 5.5064156 | J9: =SUM('Model inputs'!J10,'Model inputs'!J11) -> 5.7567483 | K9: =SUM('Model inputs'!K10,'Model inputs'!K11) -> 5.9879291 | L9: =SUM('Model inputs'!L10,'Model inputs'!L11) -> 6.2014637 | M9: =SUM('Model inputs'!M10,'Model inputs'!M11) -> 6.3987385 | N9: =SUM('Model inputs'!N10,'Model inputs'!N11) -> 6.5810296
A10: Churned customers > Classroom | B10: =IF('Model inputs'!B7="","",'Model inputs'!B7) -> 0 | C10: =IF('Model inputs'!C7="","",'Model inputs'!C7) -> 0.3 | D10: =IF('Model inputs'!D7="","",'Model inputs'!D7) -> 0.321 | E10: =IF('Model inputs'!E7="","",'Model inputs'!E7) -> 0.34137 | F10: =IF('Model inputs'!F7="","",'Model inputs'!F7) -> 0.3611289 | G10: =IF('Model inputs'!G7="","",'Model inputs'!G7) -> 0.38029503 | H10: =IF('Model inputs'!H7="","",'Model inputs'!H7) -> 0.39888618 | I10: ='Model inputs'!H23*'Model inputs'!O63 -> 0.4169196 | J10: ='Model inputs'!I26*'Model inputs'!O63 -> 0.43441201 | K10: ='Model inputs'!J26*'Model inputs'!O63 -> 0.45137965 | L10: ='Model inputs'!K26*'Model inputs'!O63 -> 0.46783826 | M10: ='Model inputs'!L26*'Model inputs'!O63 -> 0.48380311 | N10: ='Model inputs'!M26*'Model inputs'!O63 -> 0.49928902
A11: Churned customers > Household | B11: =IF('Model inputs'!B8="","",'Model inputs'!B8) -> 0 | C11: =IF('Model inputs'!C8="","",'Model inputs'!C8) -> 3.2 | D11: =IF('Model inputs'!D8="","",'Model inputs'!D8) -> 3.584 | E11: =IF('Model inputs'!E8="","",'Model inputs'!E8) -> 3.93728 | F11: =IF('Model inputs'!F8="","",'Model inputs'!F8) -> 4.2622976 | G11: =IF('Model inputs'!G8="","",'Model inputs'!G8) -> 4.5613138 | H11: =IF('Model inputs'!H8="","",'Model inputs'!H8) -> 4.8364087 | I11: ='Model inputs'!H24*'Model inputs'!O64 -> 5.089496 | J11: ='Model inputs'!I27*'Model inputs'!O64 -> 5.3223363 | K11: ='Model inputs'!J27*'Model inputs'!O64 -> 5.5365494 | L11: ='Model inputs'!K27*'Model inputs'!O64 -> 5.7336255 | M11: ='Model inputs'!L27*'Model inputs'!O64 -> 5.9149354 | N11: ='Model inputs'!M27*'Model inputs'!O64 -> 6.0817406
A12: Churned customers | B12: =SUM('Model inputs'!B13,'Model inputs'!B14) -> 0 | C12: =SUM('Model inputs'!C13,'Model inputs'!C14) -> 6.6 | D12: =SUM('Model inputs'!D13,'Model inputs'!D14) -> 6.924 | E12: =SUM('Model inputs'!E13,'Model inputs'!E14) -> 7.20156 | F12: =SUM('Model inputs'!F13,'Model inputs'!F14) -> 7.4395164 | G12: =SUM('Model inputs'!G13,'Model inputs'!G14) -> 7.6436879 | H12: =SUM('Model inputs'!H13,'Model inputs'!H14) -> 7.8190278
A13: Churned customers > Classroom | B13: ='Model inputs'!B7 -> 0 | C13: ='Model inputs'!B29*'Model inputs'!O190 -> 0.6 | D13: ='Model inputs'!C29*'Model inputs'!O190 -> 0.624 | E13: ='Model inputs'!D29*'Model inputs'!O190 -> 0.64656 | F13: ='Model inputs'!E29*'Model inputs'!O190 -> 0.6677664 | G13: ='Model inputs'!F29*'Model inputs'!O190 -> 0.68770042 | H13: ='Model inputs'!G29*'Model inputs'!O190 -> 0.70643839
A14: Churned customers > Household | B14: ='Model inputs'!B8 -> 0 | C14: ='Model inputs'!B30*'Model inputs'!O191 -> 6 | D14: ='Model inputs'!C30*'Model inputs'!O191 -> 6.3 | E14: ='Model inputs'!D30*'Model inputs'!O191 -> 6.555 | F14: ='Model inputs'!E30*'Model inputs'!O191 -> 6.77175 | G14: ='Model inputs'!F30*'Model inputs'!O191 -> 6.9559875 | H14: ='Model inputs'!G30*'Model inputs'!O191 -> 7.1125894
A15: Churned customers | B15: =SUM('Model inputs'!B16,'Model inputs'!B17) -> 0 | C15: =SUM('Model inputs'!C16,'Model inputs'!C17) -> 3.5 | D15: =SUM('Model inputs'!D16,'Model inputs'!D17) -> 4.605 | E15: =SUM('Model inputs'!E16,'Model inputs'!E17) -> 5.62565 | F15: =SUM('Model inputs'!F16,'Model inputs'!F17) -> 6.5685765 | G15: =SUM('Model inputs'!G16,'Model inputs'!G17) -> 7.4398795 | H15: =SUM('Model inputs'!H16,'Model inputs'!H17) -> 8.2451746
A16: Churned customers > Classroom | B16: ='Model inputs'!B7 -> 0 | C16: ='Model inputs'!B32*'Model inputs'!O193 -> 0.3 | D16: ='Model inputs'!C32*'Model inputs'!O193 -> 0.381 | E16: ='Model inputs'!D32*'Model inputs'!O193 -> 0.45957 | F16: ='Model inputs'!E32*'Model inputs'!O193 -> 0.5357829 | G16: ='Model inputs'!F32*'Model inputs'!O193 -> 0.60970941 | H16: ='Model inputs'!G32*'Model inputs'!O193 -> 0.68141813
A17: Churned customers > Household | B17: ='Model inputs'!B8 -> 0 | C17: ='Model inputs'!B33*'Model inputs'!O194 -> 3.2 | D17: ='Model inputs'!C33*'Model inputs'!O194 -> 4.224 | E17: ='Model inputs'!D33*'Model inputs'!O194 -> 5.16608 | F17: ='Model inputs'!E33*'Model inputs'!O194 -> 6.0327936 | G17: ='Model inputs'!F33*'Model inputs'!O194 -> 6.8301701 | H17: ='Model inputs'!G33*'Model inputs'!O194 -> 7.5637565
A18: Cost per story, selected policy (USD, estimate) · Unit economics by plan (monthly) | O18: =SUM('Model inputs'!O234,'Model inputs'!O235)+SUM('Model inputs'!O230,'Model inputs'!O231,'Model inputs'!O232) -> 0.1959
A19: Ending cash (USD) · Main Scenario | H19: ='Model inputs'!G166+'Model inputs'!H70 -> 4658.2043
A20: Ending cash (USD) · Downside | H20: ='Model inputs'!G167+'Model inputs'!H71 -> 3275.3837
A21: Ending cash (USD) · Growth | H21: ='Model inputs'!G168+'Model inputs'!H72 -> 5331.6683
A22: Ending customers | B22: =SUM('Model inputs'!B23,'Model inputs'!B24) -> 50 | C22: =SUM('Model inputs'!C23,'Model inputs'!C24) -> 55.5 | D22: =SUM('Model inputs'!D23,'Model inputs'!D24) -> 60.595 | E22: =SUM('Model inputs'!E23,'Model inputs'!E24) -> 65.31635 | F22: =SUM('Model inputs'!F23,'Model inputs'!F24) -> 69.692923 | G22: =SUM('Model inputs'!G23,'Model inputs'!G24) -> 73.751315 | H22: =SUM('Model inputs'!H23,'Model inputs'!H24) -> 77.51602
A23: Ending customers > Classroom | B23: =IF('Model inputs'!O237="","",'Model inputs'!O237) -> 10 | C23: ='Model inputs'!B23+'Model inputs'!C74-'Model inputs'!C7 -> 10.7 | D23: ='Model inputs'!C23+'Model inputs'!D74-'Model inputs'!D7 -> 11.379 | E23: ='Model inputs'!D23+'Model inputs'!E74-'Model inputs'!E7 -> 12.03763 | F23: ='Model inputs'!E23+'Model inputs'!F74-'Model inputs'!F7 -> 12.676501 | G23: ='Model inputs'!F23+'Model inputs'!G74-'Model inputs'!G7 -> 13.296206 | H23: ='Model inputs'!G23+'Model inputs'!H74-'Model inputs'!H7 -> 13.89732
A24: Ending customers > Household | B24: =IF('Model inputs'!O238="","",'Model inputs'!O238) -> 40 | C24: ='Model inputs'!B24+'Model inputs'!C75-'Model inputs'!C8 -> 44.8 | D24: ='Model inputs'!C24+'Model inputs'!D75-'Model inputs'!D8 -> 49.216 | E24: ='Model inputs'!D24+'Model inputs'!E75-'Model inputs'!E8 -> 53.27872 | F24: ='Model inputs'!E24+'Model inputs'!F75-'Model inputs'!F8 -> 57.016422 | G24: ='Model inputs'!F24+'Model inputs'!G75-'Model inputs'!G8 -> 60.455109 | H24: ='Model inputs'!G24+'Model inputs'!H75-'Model inputs'!H8 -> 63.6187
A25: Ending customers | B25: =IF('Model inputs'!B22="","",'Model inputs'!B22) -> 50 | C25: =IF('Model inputs'!C22="","",'Model inputs'!C22) -> 55.5 | D25: =IF('Model inputs'!D22="","",'Model inputs'!D22) -> 60.595 | E25: =IF('Model inputs'!E22="","",'Model inputs'!E22) -> 65.31635 | F25: =IF('Model inputs'!F22="","",'Model inputs'!F22) -> 69.692923 | G25: =IF('Model inputs'!G22="","",'Model inputs'!G22) -> 73.751315 | H25: =IF('Model inputs'!H22="","",'Model inputs'!H22) -> 77.51602 | I25: =SUM('Model inputs'!I26,'Model inputs'!I27) -> 81.009604 | J25: =SUM('Model inputs'!J26,'Model inputs'!J27) -> 84.252856 | K25: =SUM('Model inputs'!K26,'Model inputs'!K27) -> 87.264927 | L25: =SUM('Model inputs'!L26,'Model inputs'!L27) -> 90.063463 | M25: =SUM('Model inputs'!M26,'Model inputs'!M27) -> 92.664725 | N25: =SUM('Model inputs'!N26,'Model inputs'!N27) -> 95.083695
A26: Ending customers > Classroom | B26: =IF('Model inputs'!B23="","",'Model inputs'!B23) -> 10 | C26: =IF('Model inputs'!C23="","",'Model inputs'!C23) -> 10.7 | D26: =IF('Model inputs'!D23="","",'Model inputs'!D23) -> 11.379 | E26: =IF('Model inputs'!E23="","",'Model inputs'!E23) -> 12.03763 | F26: =IF('Model inputs'!F23="","",'Model inputs'!F23) -> 12.676501 | G26: =IF('Model inputs'!G23="","",'Model inputs'!G23) -> 13.296206 | H26: =IF('Model inputs'!H23="","",'Model inputs'!H23) -> 13.89732 | I26: ='Model inputs'!H23+'Model inputs'!I77-'Model inputs'!I10 -> 14.4804 | J26: ='Model inputs'!I26+'Model inputs'!J77-'Model inputs'!J10 -> 15.045988 | K26: ='Model inputs'!J26+'Model inputs'!K77-'Model inputs'!K10 -> 15.594609 | L26: ='Model inputs'!K26+'Model inputs'!L77-'Model inputs'!L10 -> 16.12677 | M26: ='Model inputs'!L26+'Model inputs'!M77-'Model inputs'!M10 -> 16.642967 | N26: ='Model inputs'!M26+'Model inputs'!N77-'Model inputs'!N10 -> 17.143678
A27: Ending customers > Household | B27: =IF('Model inputs'!B24="","",'Model inputs'!B24) -> 40 | C27: =IF('Model inputs'!C24="","",'Model inputs'!C24) -> 44.8 | D27: =IF('Model inputs'!D24="","",'Model inputs'!D24) -> 49.216 | E27: =IF('Model inputs'!E24="","",'Model inputs'!E24) -> 53.27872 | F27: =IF('Model inputs'!F24="","",'Model inputs'!F24) -> 57.016422 | G27: =IF('Model inputs'!G24="","",'Model inputs'!G24) -> 60.455109 | H27: =IF('Model inputs'!H24="","",'Model inputs'!H24) -> 63.6187 | I27: ='Model inputs'!H24+'Model inputs'!I78-'Model inputs'!I11 -> 66.529204 | J27: ='Model inputs'!I27+'Model inputs'!J78-'Model inputs'!J11 -> 69.206868 | K27: ='Model inputs'!J27+'Model inputs'!K78-'Model inputs'!K11 -> 71.670318 | L27: ='Model inputs'!K27+'Model inputs'!L78-'Model inputs'!L11 -> 73.936693 | M27: ='Model inputs'!L27+'Model inputs'!M78-'Model inputs'!M11 -> 76.021757 | N27: ='Model inputs'!M27+'Model inputs'!N78-'Model inputs'!N11 -> 77.940017
A28: Ending customers | B28: =SUM('Model inputs'!B29,'Model inputs'!B30) -> 50 | C28: =SUM('Model inputs'!C29,'Model inputs'!C30) -> 52.4 | D28: =SUM('Model inputs'!D29,'Model inputs'!D30) -> 54.476 | E28: =SUM('Model inputs'!E29,'Model inputs'!E30) -> 56.27444 | F28: =SUM('Model inputs'!F29,'Model inputs'!F30) -> 57.834924 | G28: =SUM('Model inputs'!G29,'Model inputs'!G30) -> 59.191236 | H28: =SUM('Model inputs'!H29,'Model inputs'!H30) -> 60.372208
A29: Ending customers > Classroom | B29: =IF('Model inputs'!O240="","",'Model inputs'!O240) -> 10 | C29: ='Model inputs'!B29+'Model inputs'!C80-'Model inputs'!C13 -> 10.4 | D29: ='Model inputs'!C29+'Model inputs'!D80-'Model inputs'!D13 -> 10.776 | E29: ='Model inputs'!D29+'Model inputs'!E80-'Model inputs'!E13 -> 11.12944 | F29: ='Model inputs'!E29+'Model inputs'!F80-'Model inputs'!F13 -> 11.461674 | G29: ='Model inputs'!F29+'Model inputs'!G80-'Model inputs'!G13 -> 11.773973 | H29: ='Model inputs'!G29+'Model inputs'!H80-'Model inputs'!H13 -> 12.067535
A30: Ending customers > Household | B30: =IF('Model inputs'!O241="","",'Model inputs'!O241) -> 40 | C30: ='Model inputs'!B30+'Model inputs'!C81-'Model inputs'!C14 -> 42 | D30: ='Model inputs'!C30+'Model inputs'!D81-'Model inputs'!D14 -> 43.7 | E30: ='Model inputs'!D30+'Model inputs'!E81-'Model inputs'!E14 -> 45.145 | F30: ='Model inputs'!E30+'Model inputs'!F81-'Model inputs'!F14 -> 46.37325 | G30: ='Model inputs'!F30+'Model inputs'!G81-'Model inputs'!G14 -> 47.417263 | H30: ='Model inputs'!G30+'Model inputs'!H81-'Model inputs'!H14 -> 48.304673
A31: Ending customers | B31: =SUM('Model inputs'!B32,'Model inputs'!B33) -> 50 | C31: =SUM('Model inputs'!C32,'Model inputs'!C33) -> 65.5 | D31: =SUM('Model inputs'!D32,'Model inputs'!D33) -> 79.895 | E31: =SUM('Model inputs'!E32,'Model inputs'!E33) -> 93.26935 | F31: =SUM('Model inputs'!F32,'Model inputs'!F33) -> 105.70077 | G31: =SUM('Model inputs'!G32,'Model inputs'!G33) -> 117.26089 | H31: =SUM('Model inputs'!H32,'Model inputs'!H33) -> 128.01572
A32: Ending customers > Classroom | B32: =IF('Model inputs'!O243="","",'Model inputs'!O243) -> 10 | C32: ='Model inputs'!B32+'Model inputs'!C83-'Model inputs'!C16 -> 12.7 | D32: ='Model inputs'!C32+'Model inputs'!D83-'Model inputs'!D16 -> 15.319 | E32: ='Model inputs'!D32+'Model inputs'!E83-'Model inputs'!E16 -> 17.85943 | F32: ='Model inputs'!E32+'Model inputs'!F83-'Model inputs'!F16 -> 20.323647 | G32: ='Model inputs'!F32+'Model inputs'!G83-'Model inputs'!G16 -> 22.713938 | H32: ='Model inputs'!G32+'Model inputs'!H83-'Model inputs'!H16 -> 25.03252
A33: Ending customers > Household | B33: =IF('Model inputs'!O244="","",'Model inputs'!O244) -> 40 | C33: ='Model inputs'!B33+'Model inputs'!C84-'Model inputs'!C17 -> 52.8 | D33: ='Model inputs'!C33+'Model inputs'!D84-'Model inputs'!D17 -> 64.576 | E33: ='Model inputs'!D33+'Model inputs'!E84-'Model inputs'!E17 -> 75.40992 | F33: ='Model inputs'!E33+'Model inputs'!F84-'Model inputs'!F17 -> 85.377126 | G33: ='Model inputs'!F33+'Model inputs'!G84-'Model inputs'!G17 -> 94.546956 | H33: ='Model inputs'!G33+'Model inputs'!H84-'Model inputs'!H17 -> 102.9832
A34: Gross margin bar (ours, stated) · Main Scenario | O34: =0.6 -> 0.6
A35: Gross margin bar (ours, stated) · Downside | O35: ='Model inputs'!O34 -> 0.6
A36: Gross margin bar (ours, stated) · Growth | O36: ='Model inputs'!O34 -> 0.6
A37: Hosting and neatlogs allocated by revenue (USD) | B37: =SUM('Model inputs'!B38,'Model inputs'!B39) -> 0 | C37: =SUM('Model inputs'!C38,'Model inputs'!C39) -> 25 | D37: =SUM('Model inputs'!D38,'Model inputs'!D39) -> 25 | E37: =SUM('Model inputs'!E38,'Model inputs'!E39) -> 25 | F37: =SUM('Model inputs'!F38,'Model inputs'!F39) -> 25 | G37: =SUM('Model inputs'!G38,'Model inputs'!G39) -> 25 | H37: =SUM('Model inputs'!H38,'Model inputs'!H39) -> 25
A38: Hosting and neatlogs allocated by revenue (USD) > Classroom | B38: ='Model inputs'!B44 -> 0 | C38: =('Model inputs'!O178+'Model inputs'!C197)*IFERROR('Model inputs'!C132/SUM('Model inputs'!C132,'Model inputs'!C133),0) -> 12.668436 | D38: =('Model inputs'!O178+'Model inputs'!D197)*IFERROR('Model inputs'!D132/SUM('Model inputs'!D132,'Model inputs'!D133),0) -> 12.642423 | E38: =('Model inputs'!O178+'Model inputs'!E197)*IFERROR('Model inputs'!E132/SUM('Model inputs'!E132,'Model inputs'!E133),0) -> 12.640804 | F38: =('Model inputs'!O178+'Model inputs'!F197)*IFERROR('Model inputs'!F132/SUM('Model inputs'!F132,'Model inputs'!F133),0) -> 12.656874 | G38: =('Model inputs'!O178+'Model inputs'!G197)*IFERROR('Model inputs'!G132/SUM('Model inputs'!G132,'Model inputs'!G133),0) -> 12.685739 | H38: =('Model inputs'!O178+'Model inputs'!H197)*IFERROR('Model inputs'!H132/SUM('Model inputs'!H132,'Model inputs'!H133),0) -> 12.723762
A39: Hosting and neatlogs allocated by revenue (USD) > Household | B39: ='Model inputs'!B45 -> 0 | C39: =('Model inputs'!O178+'Model inputs'!C197)*IFERROR('Model inputs'!C133/SUM('Model inputs'!C132,'Model inputs'!C133),0) -> 12.331564 | D39: =('Model inputs'!O178+'Model inputs'!D197)*IFERROR('Model inputs'!D133/SUM('Model inputs'!D132,'Model inputs'!D133),0) -> 12.357577 | E39: =('Model inputs'!O178+'Model inputs'!E197)*IFERROR('Model inputs'!E133/SUM('Model inputs'!E132,'Model inputs'!E133),0) -> 12.359196 | F39: =('Model inputs'!O178+'Model inputs'!F197)*IFERROR('Model inputs'!F133/SUM('Model inputs'!F132,'Model inputs'!F133),0) -> 12.343126 | G39: =('Model inputs'!O178+'Model inputs'!G197)*IFERROR('Model inputs'!G133/SUM('Model inputs'!G132,'Model inputs'!G133),0) -> 12.314261 | H39: =('Model inputs'!O178+'Model inputs'!H197)*IFERROR('Model inputs'!H133/SUM('Model inputs'!H132,'Model inputs'!H133),0) -> 12.276238
A40: Hosting and neatlogs allocated by revenue (USD) | B40: =SUM('Model inputs'!B41,'Model inputs'!B42) -> 0 | C40: =SUM('Model inputs'!C41,'Model inputs'!C42) -> 25 | D40: =SUM('Model inputs'!D41,'Model inputs'!D42) -> 25 | E40: =SUM('Model inputs'!E41,'Model inputs'!E42) -> 25 | F40: =SUM('Model inputs'!F41,'Model inputs'!F42) -> 25 | G40: =SUM('Model inputs'!G41,'Model inputs'!G42) -> 25 | H40: =SUM('Model inputs'!H41,'Model inputs'!H42) -> 25
A41: Hosting and neatlogs allocated by revenue (USD) > Classroom | B41: ='Model inputs'!B44 -> 0 | C41: =('Model inputs'!O179+'Model inputs'!C198)*IFERROR('Model inputs'!C135/SUM('Model inputs'!C135,'Model inputs'!C136),0) -> 12.486913 | D41: =('Model inputs'!O179+'Model inputs'!D198)*IFERROR('Model inputs'!D135/SUM('Model inputs'!D135,'Model inputs'!D136),0) -> 12.400417 | E41: =('Model inputs'!O179+'Model inputs'!E198)*IFERROR('Model inputs'!E135/SUM('Model inputs'!E135,'Model inputs'!E136),0) -> 12.390053 | F41: =('Model inputs'!O179+'Model inputs'!F198)*IFERROR('Model inputs'!F135/SUM('Model inputs'!F135,'Model inputs'!F136),0) -> 12.422014 | G41: =('Model inputs'!O179+'Model inputs'!G198)*IFERROR('Model inputs'!G135/SUM('Model inputs'!G135,'Model inputs'!G136),0) -> 12.479359 | H41: =('Model inputs'!O179+'Model inputs'!H198)*IFERROR('Model inputs'!H135/SUM('Model inputs'!H135,'Model inputs'!H136),0) -> 12.552657
A42: Hosting and neatlogs allocated by revenue (USD) > Household | B42: ='Model inputs'!B45 -> 0 | C42: =('Model inputs'!O179+'Model inputs'!C198)*IFERROR('Model inputs'!C136/SUM('Model inputs'!C135,'Model inputs'!C136),0) -> 12.513087 | D42: =('Model inputs'!O179+'Model inputs'!D198)*IFERROR('Model inputs'!D136/SUM('Model inputs'!D135,'Model inputs'!D136),0) -> 12.599583 | E42: =('Model inputs'!O179+'Model inputs'!E198)*IFERROR('Model inputs'!E136/SUM('Model inputs'!E135,'Model inputs'!E136),0) -> 12.609947 | F42: =('Model inputs'!O179+'Model inputs'!F198)*IFERROR('Model inputs'!F136/SUM('Model inputs'!F135,'Model inputs'!F136),0) -> 12.577986 | G42: =('Model inputs'!O179+'Model inputs'!G198)*IFERROR('Model inputs'!G136/SUM('Model inputs'!G135,'Model inputs'!G136),0) -> 12.520641 | H42: =('Model inputs'!O179+'Model inputs'!H198)*IFERROR('Model inputs'!H136/SUM('Model inputs'!H135,'Model inputs'!H136),0) -> 12.447343
A43: Hosting and neatlogs allocated by revenue (USD) | B43: =SUM('Model inputs'!B44,'Model inputs'!B45) -> 0 | C43: =SUM('Model inputs'!C44,'Model inputs'!C45) -> 25 | D43: =SUM('Model inputs'!D44,'Model inputs'!D45) -> 25 | E43: =SUM('Model inputs'!E44,'Model inputs'!E45) -> 25 | F43: =SUM('Model inputs'!F44,'Model inputs'!F45) -> 25 | G43: =SUM('Model inputs'!G44,'Model inputs'!G45) -> 25 | H43: =SUM('Model inputs'!H44,'Model inputs'!H45) -> 25
A44: Hosting and neatlogs allocated by revenue (USD) > Classroom | B44: =0 -> 0 | C44: =('Model inputs'!O49+'Model inputs'!C195)*IFERROR('Model inputs'!C126/SUM('Model inputs'!C126,'Model inputs'!C127),0) -> 12.442818 | D44: =('Model inputs'!O49+'Model inputs'!D195)*IFERROR('Model inputs'!D126/SUM('Model inputs'!D126,'Model inputs'!D127),0) -> 12.239825 | E44: =('Model inputs'!O49+'Model inputs'!E195)*IFERROR('Model inputs'!E126/SUM('Model inputs'!E126,'Model inputs'!E127),0) -> 12.095865 | F44: =('Model inputs'!O49+'Model inputs'!F195)*IFERROR('Model inputs'!F126/SUM('Model inputs'!F126,'Model inputs'!F127),0) -> 11.995436 | G44: =('Model inputs'!O49+'Model inputs'!G195)*IFERROR('Model inputs'!G126/SUM('Model inputs'!G126,'Model inputs'!G127),0) -> 11.927856 | H44: =('Model inputs'!O49+'Model inputs'!H195)*IFERROR('Model inputs'!H126/SUM('Model inputs'!H126,'Model inputs'!H127),0) -> 11.88552
A45: Hosting and neatlogs allocated by revenue (USD) > Household | B45: =0 -> 0 | C45: =('Model inputs'!O49+'Model inputs'!C195)*IFERROR('Model inputs'!C127/SUM('Model inputs'!C126,'Model inputs'!C127),0) -> 12.557182 | D45: =('Model inputs'!O49+'Model inputs'!D195)*IFERROR('Model inputs'!D127/SUM('Model inputs'!D126,'Model inputs'!D127),0) -> 12.760175 | E45: =('Model inputs'!O49+'Model inputs'!E195)*IFERROR('Model inputs'!E127/SUM('Model inputs'!E126,'Model inputs'!E127),0) -> 12.904135 | F45: =('Model inputs'!O49+'Model inputs'!F195)*IFERROR('Model inputs'!F127/SUM('Model inputs'!F126,'Model inputs'!F127),0) -> 13.004564 | G45: =('Model inputs'!O49+'Model inputs'!G195)*IFERROR('Model inputs'!G127/SUM('Model inputs'!G126,'Model inputs'!G127),0) -> 13.072144 | H45: =('Model inputs'!O49+'Model inputs'!H195)*IFERROR('Model inputs'!H127/SUM('Model inputs'!H126,'Model inputs'!H127),0) -> 13.11448
A46: Hosting and neatlogs allocated by revenue (USD) | B46: =IF('Model inputs'!B43="","",'Model inputs'!B43) -> 0 | C46: =IF('Model inputs'!C43="","",'Model inputs'!C43) -> 25 | D46: =IF('Model inputs'!D43="","",'Model inputs'!D43) -> 25 | E46: =IF('Model inputs'!E43="","",'Model inputs'!E43) -> 25 | F46: =IF('Model inputs'!F43="","",'Model inputs'!F43) -> 25 | G46: =IF('Model inputs'!G43="","",'Model inputs'!G43) -> 25 | H46: =IF('Model inputs'!H43="","",'Model inputs'!H43) -> 25 | I46: =SUM('Model inputs'!I47,'Model inputs'!I48) -> 25 | J46: =SUM('Model inputs'!J47,'Model inputs'!J48) -> 25 | K46: =SUM('Model inputs'!K47,'Model inputs'!K48) -> 25 | L46: =SUM('Model inputs'!L47,'Model inputs'!L48) -> 25 | M46: =SUM('Model inputs'!M47,'Model inputs'!M48) -> 25 | N46: =SUM('Model inputs'!N47,'Model inputs'!N48) -> 25
A47: Hosting and neatlogs allocated by revenue (USD) > Classroom | B47: =IF('Model inputs'!B44="","",'Model inputs'!B44) -> 0 | C47: =IF('Model inputs'!C44="","",'Model inputs'!C44) -> 12.442818 | D47: =IF('Model inputs'!D44="","",'Model inputs'!D44) -> 12.239825 | E47: =IF('Model inputs'!E44="","",'Model inputs'!E44) -> 12.095865 | F47: =IF('Model inputs'!F44="","",'Model inputs'!F44) -> 11.995436 | G47: =IF('Model inputs'!G44="","",'Model inputs'!G44) -> 11.927856 | H47: =IF('Model inputs'!H44="","",'Model inputs'!H44) -> 11.88552 | I47: =('Model inputs'!O49+'Model inputs'!I196)*IFERROR('Model inputs'!I129/SUM('Model inputs'!I129,'Model inputs'!I130),0) -> 11.862867 | J47: =('Model inputs'!O49+'Model inputs'!J196)*IFERROR('Model inputs'!J129/SUM('Model inputs'!J129,'Model inputs'!J130),0) -> 11.855737 | K47: =('Model inputs'!O49+'Model inputs'!K196)*IFERROR('Model inputs'!K129/SUM('Model inputs'!K129,'Model inputs'!K130),0) -> 11.860957 | L47: =('Model inputs'!O49+'Model inputs'!L196)*IFERROR('Model inputs'!L129/SUM('Model inputs'!L129,'Model inputs'!L130),0) -> 11.876061 | M47: =('Model inputs'!O49+'Model inputs'!M196)*IFERROR('Model inputs'!M129/SUM('Model inputs'!M129,'Model inputs'!M130),0) -> 11.89911 | N47: =('Model inputs'!O49+'Model inputs'!N196)*IFERROR('Model inputs'!N129/SUM('Model inputs'!N129,'Model inputs'!N130),0) -> 11.928556
A48: Hosting and neatlogs allocated by revenue (USD) > Household | B48: =IF('Model inputs'!B45="","",'Model inputs'!B45) -> 0 | C48: =IF('Model inputs'!C45="","",'Model inputs'!C45) -> 12.557182 | D48: =IF('Model inputs'!D45="","",'Model inputs'!D45) -> 12.760175 | E48: =IF('Model inputs'!E45="","",'Model inputs'!E45) -> 12.904135 | F48: =IF('Model inputs'!F45="","",'Model inputs'!F45) -> 13.004564 | G48: =IF('Model inputs'!G45="","",'Model inputs'!G45) -> 13.072144 | H48: =IF('Model inputs'!H45="","",'Model inputs'!H45) -> 13.11448 | I48: =('Model inputs'!O49+'Model inputs'!I196)*IFERROR('Model inputs'!I130/SUM('Model inputs'!I129,'Model inputs'!I130),0) -> 13.137133 | J48: =('Model inputs'!O49+'Model inputs'!J196)*IFERROR('Model inputs'!J130/SUM('Model inputs'!J129,'Model inputs'!J130),0) -> 13.144263 | K48: =('Model inputs'!O49+'Model inputs'!K196)*IFERROR('Model inputs'!K130/SUM('Model inputs'!K129,'Model inputs'!K130),0) -> 13.139043 | L48: =('Model inputs'!O49+'Model inputs'!L196)*IFERROR('Model inputs'!L130/SUM('Model inputs'!L129,'Model inputs'!L130),0) -> 13.123939 | M48: =('Model inputs'!O49+'Model inputs'!M196)*IFERROR('Model inputs'!M130/SUM('Model inputs'!M129,'Model inputs'!M130),0) -> 13.10089 | N48: =('Model inputs'!O49+'Model inputs'!N196)*IFERROR('Model inputs'!N130/SUM('Model inputs'!N129,'Model inputs'!N130),0) -> 13.071444
A49: Hosting per month (USD, assumed) · Gross profit and margin by plan (monthly) | O49: =25 -> 25
A50: Inference cost (USD, estimate) | B50: =SUM('Model inputs'!B51,'Model inputs'!B52) -> 0 | C50: =SUM('Model inputs'!C51,'Model inputs'!C52) -> 329.70576 | D50: =SUM('Model inputs'!D51,'Model inputs'!D52) -> 342.09108 | E50: =SUM('Model inputs'!E51,'Model inputs'!E52) -> 353.34122 | F50: =SUM('Model inputs'!F51,'Model inputs'!F52) -> 363.5831 | G50: =SUM('Model inputs'!G51,'Model inputs'!G52) -> 372.92721 | H50: =SUM('Model inputs'!H51,'Model inputs'!H52) -> 381.4699
A51: Inference cost (USD, estimate) > Classroom | B51: ='Model inputs'!B57 -> 0 | C51: ='Model inputs'!C249*'Model inputs'!O164 -> 222.0816 | D51: ='Model inputs'!D249*'Model inputs'!O164 -> 230.1107 | E51: ='Model inputs'!E249*'Model inputs'!O164 -> 237.65806 | F51: ='Model inputs'!F249*'Model inputs'!O164 -> 244.75258 | G51: ='Model inputs'!G249*'Model inputs'!O164 -> 251.42142 | H51: ='Model inputs'!H249*'Model inputs'!O164 -> 257.69014
A52: Inference cost (USD, estimate) > Household | B52: ='Model inputs'!B58 -> 0 | C52: ='Model inputs'!C250*'Model inputs'!O164 -> 107.62416 | D52: ='Model inputs'!D250*'Model inputs'!O164 -> 111.98038 | E52: ='Model inputs'!E250*'Model inputs'!O164 -> 115.68316 | F52: ='Model inputs'!F250*'Model inputs'!O164 -> 118.83053 | G52: ='Model inputs'!G250*'Model inputs'!O164 -> 121.50579 | H52: ='Model inputs'!H250*'Model inputs'!O164 -> 123.77976
A53: Inference cost (USD, estimate) | B53: =SUM('Model inputs'!B54,'Model inputs'!B55) -> 0 | C53: =SUM('Model inputs'!C54,'Model inputs'!C55) -> 316.97795 | D53: =SUM('Model inputs'!D54,'Model inputs'!D55) -> 384.1188 | E53: =SUM('Model inputs'!E54,'Model inputs'!E55) -> 448.06889 | F53: =SUM('Model inputs'!F54,'Model inputs'!F55) -> 509.01808 | G53: =SUM('Model inputs'!G54,'Model inputs'!G55) -> 567.14297 | H53: =SUM('Model inputs'!H54,'Model inputs'!H55) -> 622.60797
A54: Inference cost (USD, estimate) > Classroom | B54: ='Model inputs'!B57 -> 0 | C54: ='Model inputs'!C252*'Model inputs'!O165 -> 211.47405 | D54: ='Model inputs'!D252*'Model inputs'!O165 -> 255.08433 | E54: ='Model inputs'!E252*'Model inputs'!O165 -> 297.3863 | F54: ='Model inputs'!F252*'Model inputs'!O165 -> 338.41921 | G54: ='Model inputs'!G252*'Model inputs'!O165 -> 378.22113 | H54: ='Model inputs'!H252*'Model inputs'!O165 -> 416.829
A55: Inference cost (USD, estimate) > Household | B55: ='Model inputs'!B58 -> 0 | C55: ='Model inputs'!C253*'Model inputs'!O165 -> 105.5039 | D55: ='Model inputs'!D253*'Model inputs'!O165 -> 129.03447 | E55: ='Model inputs'!E253*'Model inputs'!O165 -> 150.68259 | F55: ='Model inputs'!F253*'Model inputs'!O165 -> 170.59887 | G55: ='Model inputs'!G253*'Model inputs'!O165 -> 188.92184 | H55: ='Model inputs'!H253*'Model inputs'!O165 -> 205.77897
A56: Inference cost (USD, estimate) | B56: =SUM('Model inputs'!B57,'Model inputs'!B58) -> 0 | C56: =SUM('Model inputs'!C57,'Model inputs'!C58) -> 188.9573 | D56: =SUM('Model inputs'!D57,'Model inputs'!D58) -> 203.16695 | E56: =SUM('Model inputs'!E57,'Model inputs'!E58) -> 216.63887 | F56: =SUM('Model inputs'!F57,'Model inputs'!F58) -> 229.42012 | G56: =SUM('Model inputs'!G57,'Model inputs'!G58) -> 241.55433 | H56: =SUM('Model inputs'!H57,'Model inputs'!H58) -> 253.082
A57: Inference cost (USD, estimate) > Classroom | B57: =0 -> 0 | C57: ='Model inputs'!C150*'Model inputs'!O18 -> 125.7678 | D57: ='Model inputs'!D150*'Model inputs'!O18 -> 133.74877 | E57: ='Model inputs'!E150*'Model inputs'!O18 -> 141.4903 | F57: ='Model inputs'!F150*'Model inputs'!O18 -> 148.99959 | G57: ='Model inputs'!G150*'Model inputs'!O18 -> 156.28361 | H57: ='Model inputs'!H150*'Model inputs'!O18 -> 163.3491
A58: Inference cost (USD, estimate) > Household | B58: =0 -> 0 | C58: ='Model inputs'!C151*'Model inputs'!O18 -> 63.189504 | D58: ='Model inputs'!D151*'Model inputs'!O18 -> 69.418184 | E58: ='Model inputs'!E151*'Model inputs'!O18 -> 75.148569 | F58: ='Model inputs'!F151*'Model inputs'!O18 -> 80.420523 | G58: ='Model inputs'!G151*'Model inputs'!O18 -> 85.270722 | H58: ='Model inputs'!H151*'Model inputs'!O18 -> 89.732904
A59: Inference cost (USD, estimate) | B59: =IF('Model inputs'!B56="","",'Model inputs'!B56) -> 0 | C59: =IF('Model inputs'!C56="","",'Model inputs'!C56) -> 188.9573 | D59: =IF('Model inputs'!D56="","",'Model inputs'!D56) -> 203.16695 | E59: =IF('Model inputs'!E56="","",'Model inputs'!E56) -> 216.63887 | F59: =IF('Model inputs'!F56="","",'Model inputs'!F56) -> 229.42012 | G59: =IF('Model inputs'!G56="","",'Model inputs'!G56) -> 241.55433 | H59: =IF('Model inputs'!H56="","",'Model inputs'!H56) -> 253.082 | I59: =SUM('Model inputs'!I60,'Model inputs'!I61) -> 264.04074 | J59: =SUM('Model inputs'!J60,'Model inputs'!J61) -> 274.46545 | K59: =SUM('Model inputs'!K60,'Model inputs'!K61) -> 284.38858 | L59: =SUM('Model inputs'!L60,'Model inputs'!L61) -> 293.84029 | M59: =SUM('Model inputs'!M60,'Model inputs'!M61) -> 302.84861 | N59: =SUM('Model inputs'!N60,'Model inputs'!N61) -> 311.43963
A60: Inference cost (USD, estimate) > Classroom | B60: =IF('Model inputs'!B57="","",'Model inputs'!B57) -> 0 | C60: =IF('Model inputs'!C57="","",'Model inputs'!C57) -> 125.7678 | D60: =IF('Model inputs'!D57="","",'Model inputs'!D57) -> 133.74877 | E60: =IF('Model inputs'!E57="","",'Model inputs'!E57) -> 141.4903 | F60: =IF('Model inputs'!F57="","",'Model inputs'!F57) -> 148.99959 | G60: =IF('Model inputs'!G57="","",'Model inputs'!G57) -> 156.28361 | H60: =IF('Model inputs'!H57="","",'Model inputs'!H57) -> 163.3491 | I60: ='Model inputs'!I150*'Model inputs'!O18 -> 170.20262 | J60: ='Model inputs'!J150*'Model inputs'!O18 -> 176.85055 | K60: ='Model inputs'!K150*'Model inputs'!O18 -> 183.29903 | L60: ='Model inputs'!L150*'Model inputs'!O18 -> 189.55406 | M60: ='Model inputs'!M150*'Model inputs'!O18 -> 195.62144 | N60: ='Model inputs'!N150*'Model inputs'!O18 -> 201.50679
A61: Inference cost (USD, estimate) > Household | B61: =IF('Model inputs'!B58="","",'Model inputs'!B58) -> 0 | C61: =IF('Model inputs'!C58="","",'Model inputs'!C58) -> 63.189504 | D61: =IF('Model inputs'!D58="","",'Model inputs'!D58) -> 69.418184 | E61: =IF('Model inputs'!E58="","",'Model inputs'!E58) -> 75.148569 | F61: =IF('Model inputs'!F58="","",'Model inputs'!F58) -> 80.420523 | G61: =IF('Model inputs'!G58="","",'Model inputs'!G58) -> 85.270722 | H61: =IF('Model inputs'!H58="","",'Model inputs'!H58) -> 89.732904 | I61: ='Model inputs'!I151*'Model inputs'!O18 -> 93.838112 | J61: ='Model inputs'!J151*'Model inputs'!O18 -> 97.614903 | K61: ='Model inputs'!K151*'Model inputs'!O18 -> 101.08955 | L61: ='Model inputs'!L151*'Model inputs'!O18 -> 104.28623 | M61: ='Model inputs'!M151*'Model inputs'!O18 -> 107.22717 | N61: ='Model inputs'!N151*'Model inputs'!O18 -> 109.93283
A62: Monthly churn (assumed) | O62: 0
A63: Monthly churn (assumed) > Classroom | O63: =0.03 -> 0.03
A64: Monthly churn (assumed) > Household | O64: =0.08 -> 0.08
A65: neatlogs covered by hackathon credits (1 = yes, assumed) · Gross profit and margin by plan (monthly) | O65: =1 -> 1
A66: neatlogs Free plan span cap (published price, unverified for credits) · Gross profit and margin by plan (monthly) | O66: =100000 -> 100000
A67: neatlogs price per extra 100k spans (USD, published price) · Gross profit and margin by plan (monthly) | O67: =10 -> 10
A68: neatlogs Starter plan included spans (published price) · Gross profit and margin by plan (monthly) | O68: =250000 -> 250000
A69: neatlogs Starter plan price per month (USD, published price) · Gross profit and margin by plan (monthly) | O69: =99 -> 99
A70: Net cash flow (USD) · Main Scenario | H70: ='Model inputs'!H137-'Model inputs'!H208 -> 519.63499
A71: Net cash flow (USD) · Downside | H71: ='Model inputs'!H143-'Model inputs'!H209 -> 231.13828
A72: Net cash flow (USD) · Growth | H72: ='Model inputs'!H146-'Model inputs'!H210 -> 748.18766
A73: New customers | B73: =SUM('Model inputs'!B74,'Model inputs'!B75) -> 0 | C73: =SUM('Model inputs'!C74,'Model inputs'!C75) -> 9 | D73: =SUM('Model inputs'!D74,'Model inputs'!D75) -> 9 | E73: =SUM('Model inputs'!E74,'Model inputs'!E75) -> 9 | F73: =SUM('Model inputs'!F74,'Model inputs'!F75) -> 9 | G73: =SUM('Model inputs'!G74,'Model inputs'!G75) -> 9 | H73: =SUM('Model inputs'!H74,'Model inputs'!H75) -> 9
A74: New customers > Classroom | B74: =0 -> 0 | C74: =IF('Model inputs'!O86="","",'Model inputs'!O86) -> 1 | D74: =IF('Model inputs'!O86="","",'Model inputs'!O86) -> 1 | E74: =IF('Model inputs'!O86="","",'Model inputs'!O86) -> 1 | F74: =IF('Model inputs'!O86="","",'Model inputs'!O86) -> 1 | G74: =IF('Model inputs'!O86="","",'Model inputs'!O86) -> 1 | H74: =IF('Model inputs'!O86="","",'Model inputs'!O86) -> 1
A75: New customers > Household | B75: =0 -> 0 | C75: =IF('Model inputs'!O87="","",'Model inputs'!O87) -> 8 | D75: =IF('Model inputs'!O87="","",'Model inputs'!O87) -> 8 | E75: =IF('Model inputs'!O87="","",'Model inputs'!O87) -> 8 | F75: =IF('Model inputs'!O87="","",'Model inputs'!O87) -> 8 | G75: =IF('Model inputs'!O87="","",'Model inputs'!O87) -> 8 | H75: =IF('Model inputs'!O87="","",'Model inputs'!O87) -> 8
A76: New customers | B76: =IF('Model inputs'!B73="","",'Model inputs'!B73) -> 0 | C76: =IF('Model inputs'!C73="","",'Model inputs'!C73) -> 9 | D76: =IF('Model inputs'!D73="","",'Model inputs'!D73) -> 9 | E76: =IF('Model inputs'!E73="","",'Model inputs'!E73) -> 9 | F76: =IF('Model inputs'!F73="","",'Model inputs'!F73) -> 9 | G76: =IF('Model inputs'!G73="","",'Model inputs'!G73) -> 9 | H76: =IF('Model inputs'!H73="","",'Model inputs'!H73) -> 9 | I76: =SUM('Model inputs'!I77,'Model inputs'!I78) -> 9 | J76: =SUM('Model inputs'!J77,'Model inputs'!J78) -> 9 | K76: =SUM('Model inputs'!K77,'Model inputs'!K78) -> 9 | L76: =SUM('Model inputs'!L77,'Model inputs'!L78) -> 9 | M76: =SUM('Model inputs'!M77,'Model inputs'!M78) -> 9 | N76: =SUM('Model inputs'!N77,'Model inputs'!N78) -> 9
A77: New customers > Classroom | B77: =IF('Model inputs'!B74="","",'Model inputs'!B74) -> 0 | C77: =IF('Model inputs'!C74="","",'Model inputs'!C74) -> 1 | D77: =IF('Model inputs'!D74="","",'Model inputs'!D74) -> 1 | E77: =IF('Model inputs'!E74="","",'Model inputs'!E74) -> 1 | F77: =IF('Model inputs'!F74="","",'Model inputs'!F74) -> 1 | G77: =IF('Model inputs'!G74="","",'Model inputs'!G74) -> 1 | H77: =IF('Model inputs'!H74="","",'Model inputs'!H74) -> 1 | I77: =IF('Model inputs'!O86="","",'Model inputs'!O86) -> 1 | J77: =IF('Model inputs'!O86="","",'Model inputs'!O86) -> 1 | K77: =IF('Model inputs'!O86="","",'Model inputs'!O86) -> 1 | L77: =IF('Model inputs'!O86="","",'Model inputs'!O86) -> 1 | M77: =IF('Model inputs'!O86="","",'Model inputs'!O86) -> 1 | N77: =IF('Model inputs'!O86="","",'Model inputs'!O86) -> 1
A78: New customers > Household | B78: =IF('Model inputs'!B75="","",'Model inputs'!B75) -> 0 | C78: =IF('Model inputs'!C75="","",'Model inputs'!C75) -> 8 | D78: =IF('Model inputs'!D75="","",'Model inputs'!D75) -> 8 | E78: =IF('Model inputs'!E75="","",'Model inputs'!E75) -> 8 | F78: =IF('Model inputs'!F75="","",'Model inputs'!F75) -> 8 | G78: =IF('Model inputs'!G75="","",'Model inputs'!G75) -> 8 | H78: =IF('Model inputs'!H75="","",'Model inputs'!H75) -> 8 | I78: =IF('Model inputs'!O87="","",'Model inputs'!O87) -> 8 | J78: =IF('Model inputs'!O87="","",'Model inputs'!O87) -> 8 | K78: =IF('Model inputs'!O87="","",'Model inputs'!O87) -> 8 | L78: =IF('Model inputs'!O87="","",'Model inputs'!O87) -> 8 | M78: =IF('Model inputs'!O87="","",'Model inputs'!O87) -> 8 | N78: =IF('Model inputs'!O87="","",'Model inputs'!O87) -> 8
A79: New customers | B79: =SUM('Model inputs'!B80,'Model inputs'!B81) -> 0 | C79: =SUM('Model inputs'!C80,'Model inputs'!C81) -> 9 | D79: =SUM('Model inputs'!D80,'Model inputs'!D81) -> 9 | E79: =SUM('Model inputs'!E80,'Model inputs'!E81) -> 9 | F79: =SUM('Model inputs'!F80,'Model inputs'!F81) -> 9 | G79: =SUM('Model inputs'!G80,'Model inputs'!G81) -> 9 | H79: =SUM('Model inputs'!H80,'Model inputs'!H81) -> 9
A80: New customers > Classroom | B80: ='Model inputs'!B74 -> 0 | C80: =IF('Model inputs'!O203="","",'Model inputs'!O203) -> 1 | D80: =IF('Model inputs'!O203="","",'Model inputs'!O203) -> 1 | E80: =IF('Model inputs'!O203="","",'Model inputs'!O203) -> 1 | F80: =IF('Model inputs'!O203="","",'Model inputs'!O203) -> 1 | G80: =IF('Model inputs'!O203="","",'Model inputs'!O203) -> 1 | H80: =IF('Model inputs'!O203="","",'Model inputs'!O203) -> 1
A81: New customers > Household | B81: ='Model inputs'!B75 -> 0 | C81: =IF('Model inputs'!O204="","",'Model inputs'!O204) -> 8 | D81: =IF('Model inputs'!O204="","",'Model inputs'!O204) -> 8 | E81: =IF('Model inputs'!O204="","",'Model inputs'!O204) -> 8 | F81: =IF('Model inputs'!O204="","",'Model inputs'!O204) -> 8 | G81: =IF('Model inputs'!O204="","",'Model inputs'!O204) -> 8 | H81: =IF('Model inputs'!O204="","",'Model inputs'!O204) -> 8
A82: New customers | B82: =SUM('Model inputs'!B83,'Model inputs'!B84) -> 0 | C82: =SUM('Model inputs'!C83,'Model inputs'!C84) -> 19 | D82: =SUM('Model inputs'!D83,'Model inputs'!D84) -> 19 | E82: =SUM('Model inputs'!E83,'Model inputs'!E84) -> 19 | F82: =SUM('Model inputs'!F83,'Model inputs'!F84) -> 19 | G82: =SUM('Model inputs'!G83,'Model inputs'!G84) -> 19 | H82: =SUM('Model inputs'!H83,'Model inputs'!H84) -> 19
A83: New customers > Classroom | B83: ='Model inputs'!B74 -> 0 | C83: =IF('Model inputs'!O206="","",'Model inputs'!O206) -> 3 | D83: =IF('Model inputs'!O206="","",'Model inputs'!O206) -> 3 | E83: =IF('Model inputs'!O206="","",'Model inputs'!O206) -> 3 | F83: =IF('Model inputs'!O206="","",'Model inputs'!O206) -> 3 | G83: =IF('Model inputs'!O206="","",'Model inputs'!O206) -> 3 | H83: =IF('Model inputs'!O206="","",'Model inputs'!O206) -> 3
A84: New customers > Household | B84: ='Model inputs'!B75 -> 0 | C84: =IF('Model inputs'!O207="","",'Model inputs'!O207) -> 16 | D84: =IF('Model inputs'!O207="","",'Model inputs'!O207) -> 16 | E84: =IF('Model inputs'!O207="","",'Model inputs'!O207) -> 16 | F84: =IF('Model inputs'!O207="","",'Model inputs'!O207) -> 16 | G84: =IF('Model inputs'!O207="","",'Model inputs'!O207) -> 16 | H84: =IF('Model inputs'!O207="","",'Model inputs'!O207) -> 16
A85: New customers per month (assumed) | O85: 0
A86: New customers per month (assumed) > Classroom | O86: =1 -> 1
A87: New customers per month (assumed) > Household | O87: =8 -> 8
A88: Overage price per extra story (USD, assumed) | O88: 0
A89: Overage price per extra story (USD, assumed) > Classroom | O89: =0.25 -> 0.25
A90: Overage price per extra story (USD, assumed) > Household | O90: =0.6 -> 0.6
A91: Overage revenue (USD) | B91: =SUM('Model inputs'!B92,'Model inputs'!B93) -> 0 | C91: =SUM('Model inputs'!C92,'Model inputs'!C93) -> 0 | D91: =SUM('Model inputs'!D92,'Model inputs'!D93) -> 0 | E91: =SUM('Model inputs'!E92,'Model inputs'!E93) -> 0 | F91: =SUM('Model inputs'!F92,'Model inputs'!F93) -> 0 | G91: =SUM('Model inputs'!G92,'Model inputs'!G93) -> 0 | H91: =SUM('Model inputs'!H92,'Model inputs'!H93) -> 0
A92: Overage revenue (USD) > Classroom | B92: ='Model inputs'!B98 -> 0 | C92: ='Model inputs'!C29*IF(IF(IF(IF(ISERROR('Model inputs'!O261>'Model inputs'!O255),'Model inputs'!O261>'Model inputs'!O255,IF(OR('Model inputs'!O261="",'Model inputs'!O255=""),"",'Model inputs'!O261>'Model inputs'!O255))="",FALSE,IF(ISERROR('Model inputs'!O261>'Model inputs'!O255),'Model inputs'!O261>'Model inputs'!O255,IF(OR('Model inputs'!O261="",'Model inputs'!O255=""),"",'Model inputs'!O261>'Model inputs'!O255))),('Model inputs'!O261-'Model inputs'!O255)*'Model inputs'!O212,0)="",0,IF(IF(IF(ISERROR('Model inputs'!O261>'Model inputs'!O255),'Model inputs'!O261>'Model inputs'!O255,IF(OR('Model inputs'!O261="",'Model inputs'!O255=""),"",'Model inputs'!O261>'Model inputs'!O255))="",FALSE,IF(ISERROR('Model inputs'!O261>'Model inputs'!O255),'Model inputs'!O261>'Model inputs'!O255,IF(OR('Model inputs'!O261="",'Model inputs'!O255=""),"",'Model inputs'!O261>'Model inputs'!O255))),('Model inputs'!O261-'Model inputs'!O255)*'Model inputs'!O212,0)) -> 0 | D92: ='Model inputs'!D29*IF(IF(IF(IF(ISERROR('Model inputs'!O261>'Model inputs'!O255),'Model inputs'!O261>'Model inputs'!O255,IF(OR('Model inputs'!O261="",'Model inputs'!O255=""),"",'Model inputs'!O261>'Model inputs'!O255))="",FALSE,IF(ISERROR('Model inputs'!O261>'Model inputs'!O255),'Model inputs'!O261>'Model inputs'!O255,IF(OR('Model inputs'!O261="",'Model inputs'!O255=""),"",'Model inputs'!O261>'Model inputs'!O255))),('Model inputs'!O261-'Model inputs'!O255)*'Model inputs'!O212,0)="",0,IF(IF(IF(ISERROR('Model inputs'!O261>'Model inputs'!O255),'Model inputs'!O261>'Model inputs'!O255,IF(OR('Model inputs'!O261="",'Model inputs'!O255=""),"",'Model inputs'!O261>'Model inputs'!O255))="",FALSE,IF(ISERROR('Model inputs'!O261>'Model inputs'!O255),'Model inputs'!O261>'Model inputs'!O255,IF(OR('Model inputs'!O261="",'Model inputs'!O255=""),"",'Model inputs'!O261>'Model inputs'!O255))),('Model inputs'!O261-'Model inputs'!O255)*'Model inputs'!O212,0)) -> 0 | E92: ='Model inputs'!E29*IF(IF(IF(IF(ISERROR('Model inputs'!O261>'Model inputs'!O255),'Model inputs'!O261>'Model inputs'!O255,IF(OR('Model inputs'!O261="",'Model inputs'!O255=""),"",'Model inputs'!O261>'Model inputs'!O255))="",FALSE,IF(ISERROR('Model inputs'!O261>'Model inputs'!O255),'Model inputs'!O261>'Model inputs'!O255,IF(OR('Model inputs'!O261="",'Model inputs'!O255=""),"",'Model inputs'!O261>'Model inputs'!O255))),('Model inputs'!O261-'Model inputs'!O255)*'Model inputs'!O212,0)="",0,IF(IF(IF(ISERROR('Model inputs'!O261>'Model inputs'!O255),'Model inputs'!O261>'Model inputs'!O255,IF(OR('Model inputs'!O261="",'Model inputs'!O255=""),"",'Model inputs'!O261>'Model inputs'!O255))="",FALSE,IF(ISERROR('Model inputs'!O261>'Model inputs'!O255),'Model inputs'!O261>'Model inputs'!O255,IF(OR('Model inputs'!O261="",'Model inputs'!O255=""),"",'Model inputs'!O261>'Model inputs'!O255))),('Model inputs'!O261-'Model inputs'!O255)*'Model inputs'!O212,0)) -> 0 | F92: ='Model inputs'!F29*IF(IF(IF(IF(ISERROR('Model inputs'!O261>'Model inputs'!O255),'Model inputs'!O261>'Model inputs'!O255,IF(OR('Model inputs'!O261="",'Model inputs'!O255=""),"",'Model inputs'!O261>'Model inputs'!O255))="",FALSE,IF(ISERROR('Model inputs'!O261>'Model inputs'!O255),'Model inputs'!O261>'Model inputs'!O255,IF(OR('Model inputs'!O261="",'Model inputs'!O255=""),"",'Model inputs'!O261>'Model inputs'!O255))),('Model inputs'!O261-'Model inputs'!O255)*'Model inputs'!O212,0)="",0,IF(IF(IF(ISERROR('Model inputs'!O261>'Model inputs'!O255),'Model inputs'!O261>'Model inputs'!O255,IF(OR('Model inputs'!O261="",'Model inputs'!O255=""),"",'Model inputs'!O261>'Model inputs'!O255))="",FALSE,IF(ISERROR('Model inputs'!O261>'Model inputs'!O255),'Model inputs'!O261>'Model inputs'!O255,IF(OR('Model inputs'!O261="",'Model inputs'!O255=""),"",'Model inputs'!O261>'Model inputs'!O255))),('Model inputs'!O261-'Model inputs'!O255)*'Model inputs'!O212,0)) -> 0 | G92: ='Model inputs'!G29*IF(IF(IF(IF(ISERROR('Model inputs'!O261>'Model inputs'!O255),'Model inputs'!O261>'Model inputs'!O255,IF(OR('Model inputs'!O261="",'Model inputs'!O255=""),"",'Model inputs'!O261>'Model inputs'!O255))="",FALSE,IF(ISERROR('Model inputs'!O261>'Model inputs'!O255),'Model inputs'!O261>'Model inputs'!O255,IF(OR('Model inputs'!O261="",'Model inputs'!O255=""),"",'Model inputs'!O261>'Model inputs'!O255))),('Model inputs'!O261-'Model inputs'!O255)*'Model inputs'!O212,0)="",0,IF(IF(IF(ISERROR('Model inputs'!O261>'Model inputs'!O255),'Model inputs'!O261>'Model inputs'!O255,IF(OR('Model inputs'!O261="",'Model inputs'!O255=""),"",'Model inputs'!O261>'Model inputs'!O255))="",FALSE,IF(ISERROR('Model inputs'!O261>'Model inputs'!O255),'Model inputs'!O261>'Model inputs'!O255,IF(OR('Model inputs'!O261="",'Model inputs'!O255=""),"",'Model inputs'!O261>'Model inputs'!O255))),('Model inputs'!O261-'Model inputs'!O255)*'Model inputs'!O212,0)) -> 0 | H92: ='Model inputs'!H29*IF(IF(IF(IF(ISERROR('Model inputs'!O261>'Model inputs'!O255),'Model inputs'!O261>'Model inputs'!O255,IF(OR('Model inputs'!O261="",'Model inputs'!O255=""),"",'Model inputs'!O261>'Model inputs'!O255))="",FALSE,IF(ISERROR('Model inputs'!O261>'Model inputs'!O255),'Model inputs'!O261>'Model inputs'!O255,IF(OR('Model inputs'!O261="",'Model inputs'!O255=""),"",'Model inputs'!O261>'Model inputs'!O255))),('Model inputs'!O261-'Model inputs'!O255)*'Model inputs'!O212,0)="",0,IF(IF(IF(ISERROR('Model inputs'!O261>'Model inputs'!O255),'Model inputs'!O261>'Model inputs'!O255,IF(OR('Model inputs'!O261="",'Model inputs'!O255=""),"",'Model inputs'!O261>'Model inputs'!O255))="",FALSE,IF(ISERROR('Model inputs'!O261>'Model inputs'!O255),'Model inputs'!O261>'Model inputs'!O255,IF(OR('Model inputs'!O261="",'Model inputs'!O255=""),"",'Model inputs'!O261>'Model inputs'!O255))),('Model inputs'!O261-'Model inputs'!O255)*'Model inputs'!O212,0)) -> 0
A93: Overage revenue (USD) > Household | B93: ='Model inputs'!B99 -> 0 | C93: ='Model inputs'!C30*IF(IF(IF(IF(ISERROR('Model inputs'!O262>'Model inputs'!O256),'Model inputs'!O262>'Model inputs'!O256,IF(OR('Model inputs'!O262="",'Model inputs'!O256=""),"",'Model inputs'!O262>'Model inputs'!O256))="",FALSE,IF(ISERROR('Model inputs'!O262>'Model inputs'!O256),'Model inputs'!O262>'Model inputs'!O256,IF(OR('Model inputs'!O262="",'Model inputs'!O256=""),"",'Model inputs'!O262>'Model inputs'!O256))),('Model inputs'!O262-'Model inputs'!O256)*'Model inputs'!O213,0)="",0,IF(IF(IF(ISERROR('Model inputs'!O262>'Model inputs'!O256),'Model inputs'!O262>'Model inputs'!O256,IF(OR('Model inputs'!O262="",'Model inputs'!O256=""),"",'Model inputs'!O262>'Model inputs'!O256))="",FALSE,IF(ISERROR('Model inputs'!O262>'Model inputs'!O256),'Model inputs'!O262>'Model inputs'!O256,IF(OR('Model inputs'!O262="",'Model inputs'!O256=""),"",'Model inputs'!O262>'Model inputs'!O256))),('Model inputs'!O262-'Model inputs'!O256)*'Model inputs'!O213,0)) -> 0 | D93: ='Model inputs'!D30*IF(IF(IF(IF(ISERROR('Model inputs'!O262>'Model inputs'!O256),'Model inputs'!O262>'Model inputs'!O256,IF(OR('Model inputs'!O262="",'Model inputs'!O256=""),"",'Model inputs'!O262>'Model inputs'!O256))="",FALSE,IF(ISERROR('Model inputs'!O262>'Model inputs'!O256),'Model inputs'!O262>'Model inputs'!O256,IF(OR('Model inputs'!O262="",'Model inputs'!O256=""),"",'Model inputs'!O262>'Model inputs'!O256))),('Model inputs'!O262-'Model inputs'!O256)*'Model inputs'!O213,0)="",0,IF(IF(IF(ISERROR('Model inputs'!O262>'Model inputs'!O256),'Model inputs'!O262>'Model inputs'!O256,IF(OR('Model inputs'!O262="",'Model inputs'!O256=""),"",'Model inputs'!O262>'Model inputs'!O256))="",FALSE,IF(ISERROR('Model inputs'!O262>'Model inputs'!O256),'Model inputs'!O262>'Model inputs'!O256,IF(OR('Model inputs'!O262="",'Model inputs'!O256=""),"",'Model inputs'!O262>'Model inputs'!O256))),('Model inputs'!O262-'Model inputs'!O256)*'Model inputs'!O213,0)) -> 0 | E93: ='Model inputs'!E30*IF(IF(IF(IF(ISERROR('Model inputs'!O262>'Model inputs'!O256),'Model inputs'!O262>'Model inputs'!O256,IF(OR('Model inputs'!O262="",'Model inputs'!O256=""),"",'Model inputs'!O262>'Model inputs'!O256))="",FALSE,IF(ISERROR('Model inputs'!O262>'Model inputs'!O256),'Model inputs'!O262>'Model inputs'!O256,IF(OR('Model inputs'!O262="",'Model inputs'!O256=""),"",'Model inputs'!O262>'Model inputs'!O256))),('Model inputs'!O262-'Model inputs'!O256)*'Model inputs'!O213,0)="",0,IF(IF(IF(ISERROR('Model inputs'!O262>'Model inputs'!O256),'Model inputs'!O262>'Model inputs'!O256,IF(OR('Model inputs'!O262="",'Model inputs'!O256=""),"",'Model inputs'!O262>'Model inputs'!O256))="",FALSE,IF(ISERROR('Model inputs'!O262>'Model inputs'!O256),'Model inputs'!O262>'Model inputs'!O256,IF(OR('Model inputs'!O262="",'Model inputs'!O256=""),"",'Model inputs'!O262>'Model inputs'!O256))),('Model inputs'!O262-'Model inputs'!O256)*'Model inputs'!O213,0)) -> 0 | F93: ='Model inputs'!F30*IF(IF(IF(IF(ISERROR('Model inputs'!O262>'Model inputs'!O256),'Model inputs'!O262>'Model inputs'!O256,IF(OR('Model inputs'!O262="",'Model inputs'!O256=""),"",'Model inputs'!O262>'Model inputs'!O256))="",FALSE,IF(ISERROR('Model inputs'!O262>'Model inputs'!O256),'Model inputs'!O262>'Model inputs'!O256,IF(OR('Model inputs'!O262="",'Model inputs'!O256=""),"",'Model inputs'!O262>'Model inputs'!O256))),('Model inputs'!O262-'Model inputs'!O256)*'Model inputs'!O213,0)="",0,IF(IF(IF(ISERROR('Model inputs'!O262>'Model inputs'!O256),'Model inputs'!O262>'Model inputs'!O256,IF(OR('Model inputs'!O262="",'Model inputs'!O256=""),"",'Model inputs'!O262>'Model inputs'!O256))="",FALSE,IF(ISERROR('Model inputs'!O262>'Model inputs'!O256),'Model inputs'!O262>'Model inputs'!O256,IF(OR('Model inputs'!O262="",'Model inputs'!O256=""),"",'Model inputs'!O262>'Model inputs'!O256))),('Model inputs'!O262-'Model inputs'!O256)*'Model inputs'!O213,0)) -> 0 | G93: ='Model inputs'!G30*IF(IF(IF(IF(ISERROR('Model inputs'!O262>'Model inputs'!O256),'Model inputs'!O262>'Model inputs'!O256,IF(OR('Model inputs'!O262="",'Model inputs'!O256=""),"",'Model inputs'!O262>'Model inputs'!O256))="",FALSE,IF(ISERROR('Model inputs'!O262>'Model inputs'!O256),'Model inputs'!O262>'Model inputs'!O256,IF(OR('Model inputs'!O262="",'Model inputs'!O256=""),"",'Model inputs'!O262>'Model inputs'!O256))),('Model inputs'!O262-'Model inputs'!O256)*'Model inputs'!O213,0)="",0,IF(IF(IF(ISERROR('Model inputs'!O262>'Model inputs'!O256),'Model inputs'!O262>'Model inputs'!O256,IF(OR('Model inputs'!O262="",'Model inputs'!O256=""),"",'Model inputs'!O262>'Model inputs'!O256))="",FALSE,IF(ISERROR('Model inputs'!O262>'Model inputs'!O256),'Model inputs'!O262>'Model inputs'!O256,IF(OR('Model inputs'!O262="",'Model inputs'!O256=""),"",'Model inputs'!O262>'Model inputs'!O256))),('Model inputs'!O262-'Model inputs'!O256)*'Model inputs'!O213,0)) -> 0 | H93: ='Model inputs'!H30*IF(IF(IF(IF(ISERROR('Model inputs'!O262>'Model inputs'!O256),'Model inputs'!O262>'Model inputs'!O256,IF(OR('Model inputs'!O262="",'Model inputs'!O256=""),"",'Model inputs'!O262>'Model inputs'!O256))="",FALSE,IF(ISERROR('Model inputs'!O262>'Model inputs'!O256),'Model inputs'!O262>'Model inputs'!O256,IF(OR('Model inputs'!O262="",'Model inputs'!O256=""),"",'Model inputs'!O262>'Model inputs'!O256))),('Model inputs'!O262-'Model inputs'!O256)*'Model inputs'!O213,0)="",0,IF(IF(IF(ISERROR('Model inputs'!O262>'Model inputs'!O256),'Model inputs'!O262>'Model inputs'!O256,IF(OR('Model inputs'!O262="",'Model inputs'!O256=""),"",'Model inputs'!O262>'Model inputs'!O256))="",FALSE,IF(ISERROR('Model inputs'!O262>'Model inputs'!O256),'Model inputs'!O262>'Model inputs'!O256,IF(OR('Model inputs'!O262="",'Model inputs'!O256=""),"",'Model inputs'!O262>'Model inputs'!O256))),('Model inputs'!O262-'Model inputs'!O256)*'Model inputs'!O213,0)) -> 0
A94: Overage revenue (USD) | B94: =SUM('Model inputs'!B95,'Model inputs'!B96) -> 0 | C94: =SUM('Model inputs'!C95,'Model inputs'!C96) -> 0 | D94: =SUM('Model inputs'!D95,'Model inputs'!D96) -> 0 | E94: =SUM('Model inputs'!E95,'Model inputs'!E96) -> 0 | F94: =SUM('Model inputs'!F95,'Model inputs'!F96) -> 0 | G94: =SUM('Model inputs'!G95,'Model inputs'!G96) -> 0 | H94: =SUM('Model inputs'!H95,'Model inputs'!H96) -> 0
A95: Overage revenue (USD) > Classroom | B95: ='Model inputs'!B98 -> 0 | C95: ='Model inputs'!C32*IF(IF(IF(IF(ISERROR('Model inputs'!O264>'Model inputs'!O258),'Model inputs'!O264>'Model inputs'!O258,IF(OR('Model inputs'!O264="",'Model inputs'!O258=""),"",'Model inputs'!O264>'Model inputs'!O258))="",FALSE,IF(ISERROR('Model inputs'!O264>'Model inputs'!O258),'Model inputs'!O264>'Model inputs'!O258,IF(OR('Model inputs'!O264="",'Model inputs'!O258=""),"",'Model inputs'!O264>'Model inputs'!O258))),('Model inputs'!O264-'Model inputs'!O258)*'Model inputs'!O215,0)="",0,IF(IF(IF(ISERROR('Model inputs'!O264>'Model inputs'!O258),'Model inputs'!O264>'Model inputs'!O258,IF(OR('Model inputs'!O264="",'Model inputs'!O258=""),"",'Model inputs'!O264>'Model inputs'!O258))="",FALSE,IF(ISERROR('Model inputs'!O264>'Model inputs'!O258),'Model inputs'!O264>'Model inputs'!O258,IF(OR('Model inputs'!O264="",'Model inputs'!O258=""),"",'Model inputs'!O264>'Model inputs'!O258))),('Model inputs'!O264-'Model inputs'!O258)*'Model inputs'!O215,0)) -> 0 | D95: ='Model inputs'!D32*IF(IF(IF(IF(ISERROR('Model inputs'!O264>'Model inputs'!O258),'Model inputs'!O264>'Model inputs'!O258,IF(OR('Model inputs'!O264="",'Model inputs'!O258=""),"",'Model inputs'!O264>'Model inputs'!O258))="",FALSE,IF(ISERROR('Model inputs'!O264>'Model inputs'!O258),'Model inputs'!O264>'Model inputs'!O258,IF(OR('Model inputs'!O264="",'Model inputs'!O258=""),"",'Model inputs'!O264>'Model inputs'!O258))),('Model inputs'!O264-'Model inputs'!O258)*'Model inputs'!O215,0)="",0,IF(IF(IF(ISERROR('Model inputs'!O264>'Model inputs'!O258),'Model inputs'!O264>'Model inputs'!O258,IF(OR('Model inputs'!O264="",'Model inputs'!O258=""),"",'Model inputs'!O264>'Model inputs'!O258))="",FALSE,IF(ISERROR('Model inputs'!O264>'Model inputs'!O258),'Model inputs'!O264>'Model inputs'!O258,IF(OR('Model inputs'!O264="",'Model inputs'!O258=""),"",'Model inputs'!O264>'Model inputs'!O258))),('Model inputs'!O264-'Model inputs'!O258)*'Model inputs'!O215,0)) -> 0 | E95: ='Model inputs'!E32*IF(IF(IF(IF(ISERROR('Model inputs'!O264>'Model inputs'!O258),'Model inputs'!O264>'Model inputs'!O258,IF(OR('Model inputs'!O264="",'Model inputs'!O258=""),"",'Model inputs'!O264>'Model inputs'!O258))="",FALSE,IF(ISERROR('Model inputs'!O264>'Model inputs'!O258),'Model inputs'!O264>'Model inputs'!O258,IF(OR('Model inputs'!O264="",'Model inputs'!O258=""),"",'Model inputs'!O264>'Model inputs'!O258))),('Model inputs'!O264-'Model inputs'!O258)*'Model inputs'!O215,0)="",0,IF(IF(IF(ISERROR('Model inputs'!O264>'Model inputs'!O258),'Model inputs'!O264>'Model inputs'!O258,IF(OR('Model inputs'!O264="",'Model inputs'!O258=""),"",'Model inputs'!O264>'Model inputs'!O258))="",FALSE,IF(ISERROR('Model inputs'!O264>'Model inputs'!O258),'Model inputs'!O264>'Model inputs'!O258,IF(OR('Model inputs'!O264="",'Model inputs'!O258=""),"",'Model inputs'!O264>'Model inputs'!O258))),('Model inputs'!O264-'Model inputs'!O258)*'Model inputs'!O215,0)) -> 0 | F95: ='Model inputs'!F32*IF(IF(IF(IF(ISERROR('Model inputs'!O264>'Model inputs'!O258),'Model inputs'!O264>'Model inputs'!O258,IF(OR('Model inputs'!O264="",'Model inputs'!O258=""),"",'Model inputs'!O264>'Model inputs'!O258))="",FALSE,IF(ISERROR('Model inputs'!O264>'Model inputs'!O258),'Model inputs'!O264>'Model inputs'!O258,IF(OR('Model inputs'!O264="",'Model inputs'!O258=""),"",'Model inputs'!O264>'Model inputs'!O258))),('Model inputs'!O264-'Model inputs'!O258)*'Model inputs'!O215,0)="",0,IF(IF(IF(ISERROR('Model inputs'!O264>'Model inputs'!O258),'Model inputs'!O264>'Model inputs'!O258,IF(OR('Model inputs'!O264="",'Model inputs'!O258=""),"",'Model inputs'!O264>'Model inputs'!O258))="",FALSE,IF(ISERROR('Model inputs'!O264>'Model inputs'!O258),'Model inputs'!O264>'Model inputs'!O258,IF(OR('Model inputs'!O264="",'Model inputs'!O258=""),"",'Model inputs'!O264>'Model inputs'!O258))),('Model inputs'!O264-'Model inputs'!O258)*'Model inputs'!O215,0)) -> 0 | G95: ='Model inputs'!G32*IF(IF(IF(IF(ISERROR('Model inputs'!O264>'Model inputs'!O258),'Model inputs'!O264>'Model inputs'!O258,IF(OR('Model inputs'!O264="",'Model inputs'!O258=""),"",'Model inputs'!O264>'Model inputs'!O258))="",FALSE,IF(ISERROR('Model inputs'!O264>'Model inputs'!O258),'Model inputs'!O264>'Model inputs'!O258,IF(OR('Model inputs'!O264="",'Model inputs'!O258=""),"",'Model inputs'!O264>'Model inputs'!O258))),('Model inputs'!O264-'Model inputs'!O258)*'Model inputs'!O215,0)="",0,IF(IF(IF(ISERROR('Model inputs'!O264>'Model inputs'!O258),'Model inputs'!O264>'Model inputs'!O258,IF(OR('Model inputs'!O264="",'Model inputs'!O258=""),"",'Model inputs'!O264>'Model inputs'!O258))="",FALSE,IF(ISERROR('Model inputs'!O264>'Model inputs'!O258),'Model inputs'!O264>'Model inputs'!O258,IF(OR('Model inputs'!O264="",'Model inputs'!O258=""),"",'Model inputs'!O264>'Model inputs'!O258))),('Model inputs'!O264-'Model inputs'!O258)*'Model inputs'!O215,0)) -> 0 | H95: ='Model inputs'!H32*IF(IF(IF(IF(ISERROR('Model inputs'!O264>'Model inputs'!O258),'Model inputs'!O264>'Model inputs'!O258,IF(OR('Model inputs'!O264="",'Model inputs'!O258=""),"",'Model inputs'!O264>'Model inputs'!O258))="",FALSE,IF(ISERROR('Model inputs'!O264>'Model inputs'!O258),'Model inputs'!O264>'Model inputs'!O258,IF(OR('Model inputs'!O264="",'Model inputs'!O258=""),"",'Model inputs'!O264>'Model inputs'!O258))),('Model inputs'!O264-'Model inputs'!O258)*'Model inputs'!O215,0)="",0,IF(IF(IF(ISERROR('Model inputs'!O264>'Model inputs'!O258),'Model inputs'!O264>'Model inputs'!O258,IF(OR('Model inputs'!O264="",'Model inputs'!O258=""),"",'Model inputs'!O264>'Model inputs'!O258))="",FALSE,IF(ISERROR('Model inputs'!O264>'Model inputs'!O258),'Model inputs'!O264>'Model inputs'!O258,IF(OR('Model inputs'!O264="",'Model inputs'!O258=""),"",'Model inputs'!O264>'Model inputs'!O258))),('Model inputs'!O264-'Model inputs'!O258)*'Model inputs'!O215,0)) -> 0
A96: Overage revenue (USD) > Household | B96: ='Model inputs'!B99 -> 0 | C96: ='Model inputs'!C33*IF(IF(IF(IF(ISERROR('Model inputs'!O265>'Model inputs'!O259),'Model inputs'!O265>'Model inputs'!O259,IF(OR('Model inputs'!O265="",'Model inputs'!O259=""),"",'Model inputs'!O265>'Model inputs'!O259))="",FALSE,IF(ISERROR('Model inputs'!O265>'Model inputs'!O259),'Model inputs'!O265>'Model inputs'!O259,IF(OR('Model inputs'!O265="",'Model inputs'!O259=""),"",'Model inputs'!O265>'Model inputs'!O259))),('Model inputs'!O265-'Model inputs'!O259)*'Model inputs'!O216,0)="",0,IF(IF(IF(ISERROR('Model inputs'!O265>'Model inputs'!O259),'Model inputs'!O265>'Model inputs'!O259,IF(OR('Model inputs'!O265="",'Model inputs'!O259=""),"",'Model inputs'!O265>'Model inputs'!O259))="",FALSE,IF(ISERROR('Model inputs'!O265>'Model inputs'!O259),'Model inputs'!O265>'Model inputs'!O259,IF(OR('Model inputs'!O265="",'Model inputs'!O259=""),"",'Model inputs'!O265>'Model inputs'!O259))),('Model inputs'!O265-'Model inputs'!O259)*'Model inputs'!O216,0)) -> 0 | D96: ='Model inputs'!D33*IF(IF(IF(IF(ISERROR('Model inputs'!O265>'Model inputs'!O259),'Model inputs'!O265>'Model inputs'!O259,IF(OR('Model inputs'!O265="",'Model inputs'!O259=""),"",'Model inputs'!O265>'Model inputs'!O259))="",FALSE,IF(ISERROR('Model inputs'!O265>'Model inputs'!O259),'Model inputs'!O265>'Model inputs'!O259,IF(OR('Model inputs'!O265="",'Model inputs'!O259=""),"",'Model inputs'!O265>'Model inputs'!O259))),('Model inputs'!O265-'Model inputs'!O259)*'Model inputs'!O216,0)="",0,IF(IF(IF(ISERROR('Model inputs'!O265>'Model inputs'!O259),'Model inputs'!O265>'Model inputs'!O259,IF(OR('Model inputs'!O265="",'Model inputs'!O259=""),"",'Model inputs'!O265>'Model inputs'!O259))="",FALSE,IF(ISERROR('Model inputs'!O265>'Model inputs'!O259),'Model inputs'!O265>'Model inputs'!O259,IF(OR('Model inputs'!O265="",'Model inputs'!O259=""),"",'Model inputs'!O265>'Model inputs'!O259))),('Model inputs'!O265-'Model inputs'!O259)*'Model inputs'!O216,0)) -> 0 | E96: ='Model inputs'!E33*IF(IF(IF(IF(ISERROR('Model inputs'!O265>'Model inputs'!O259),'Model inputs'!O265>'Model inputs'!O259,IF(OR('Model inputs'!O265="",'Model inputs'!O259=""),"",'Model inputs'!O265>'Model inputs'!O259))="",FALSE,IF(ISERROR('Model inputs'!O265>'Model inputs'!O259),'Model inputs'!O265>'Model inputs'!O259,IF(OR('Model inputs'!O265="",'Model inputs'!O259=""),"",'Model inputs'!O265>'Model inputs'!O259))),('Model inputs'!O265-'Model inputs'!O259)*'Model inputs'!O216,0)="",0,IF(IF(IF(ISERROR('Model inputs'!O265>'Model inputs'!O259),'Model inputs'!O265>'Model inputs'!O259,IF(OR('Model inputs'!O265="",'Model inputs'!O259=""),"",'Model inputs'!O265>'Model inputs'!O259))="",FALSE,IF(ISERROR('Model inputs'!O265>'Model inputs'!O259),'Model inputs'!O265>'Model inputs'!O259,IF(OR('Model inputs'!O265="",'Model inputs'!O259=""),"",'Model inputs'!O265>'Model inputs'!O259))),('Model inputs'!O265-'Model inputs'!O259)*'Model inputs'!O216,0)) -> 0 | F96: ='Model inputs'!F33*IF(IF(IF(IF(ISERROR('Model inputs'!O265>'Model inputs'!O259),'Model inputs'!O265>'Model inputs'!O259,IF(OR('Model inputs'!O265="",'Model inputs'!O259=""),"",'Model inputs'!O265>'Model inputs'!O259))="",FALSE,IF(ISERROR('Model inputs'!O265>'Model inputs'!O259),'Model inputs'!O265>'Model inputs'!O259,IF(OR('Model inputs'!O265="",'Model inputs'!O259=""),"",'Model inputs'!O265>'Model inputs'!O259))),('Model inputs'!O265-'Model inputs'!O259)*'Model inputs'!O216,0)="",0,IF(IF(IF(ISERROR('Model inputs'!O265>'Model inputs'!O259),'Model inputs'!O265>'Model inputs'!O259,IF(OR('Model inputs'!O265="",'Model inputs'!O259=""),"",'Model inputs'!O265>'Model inputs'!O259))="",FALSE,IF(ISERROR('Model inputs'!O265>'Model inputs'!O259),'Model inputs'!O265>'Model inputs'!O259,IF(OR('Model inputs'!O265="",'Model inputs'!O259=""),"",'Model inputs'!O265>'Model inputs'!O259))),('Model inputs'!O265-'Model inputs'!O259)*'Model inputs'!O216,0)) -> 0 | G96: ='Model inputs'!G33*IF(IF(IF(IF(ISERROR('Model inputs'!O265>'Model inputs'!O259),'Model inputs'!O265>'Model inputs'!O259,IF(OR('Model inputs'!O265="",'Model inputs'!O259=""),"",'Model inputs'!O265>'Model inputs'!O259))="",FALSE,IF(ISERROR('Model inputs'!O265>'Model inputs'!O259),'Model inputs'!O265>'Model inputs'!O259,IF(OR('Model inputs'!O265="",'Model inputs'!O259=""),"",'Model inputs'!O265>'Model inputs'!O259))),('Model inputs'!O265-'Model inputs'!O259)*'Model inputs'!O216,0)="",0,IF(IF(IF(ISERROR('Model inputs'!O265>'Model inputs'!O259),'Model inputs'!O265>'Model inputs'!O259,IF(OR('Model inputs'!O265="",'Model inputs'!O259=""),"",'Model inputs'!O265>'Model inputs'!O259))="",FALSE,IF(ISERROR('Model inputs'!O265>'Model inputs'!O259),'Model inputs'!O265>'Model inputs'!O259,IF(OR('Model inputs'!O265="",'Model inputs'!O259=""),"",'Model inputs'!O265>'Model inputs'!O259))),('Model inputs'!O265-'Model inputs'!O259)*'Model inputs'!O216,0)) -> 0 | H96: ='Model inputs'!H33*IF(IF(IF(IF(ISERROR('Model inputs'!O265>'Model inputs'!O259),'Model inputs'!O265>'Model inputs'!O259,IF(OR('Model inputs'!O265="",'Model inputs'!O259=""),"",'Model inputs'!O265>'Model inputs'!O259))="",FALSE,IF(ISERROR('Model inputs'!O265>'Model inputs'!O259),'Model inputs'!O265>'Model inputs'!O259,IF(OR('Model inputs'!O265="",'Model inputs'!O259=""),"",'Model inputs'!O265>'Model inputs'!O259))),('Model inputs'!O265-'Model inputs'!O259)*'Model inputs'!O216,0)="",0,IF(IF(IF(ISERROR('Model inputs'!O265>'Model inputs'!O259),'Model inputs'!O265>'Model inputs'!O259,IF(OR('Model inputs'!O265="",'Model inputs'!O259=""),"",'Model inputs'!O265>'Model inputs'!O259))="",FALSE,IF(ISERROR('Model inputs'!O265>'Model inputs'!O259),'Model inputs'!O265>'Model inputs'!O259,IF(OR('Model inputs'!O265="",'Model inputs'!O259=""),"",'Model inputs'!O265>'Model inputs'!O259))),('Model inputs'!O265-'Model inputs'!O259)*'Model inputs'!O216,0)) -> 0
A97: Overage revenue (USD) | B97: =SUM('Model inputs'!B98,'Model inputs'!B99) -> 0 | C97: =SUM('Model inputs'!C98,'Model inputs'!C99) -> 0 | D97: =SUM('Model inputs'!D98,'Model inputs'!D99) -> 0 | E97: =SUM('Model inputs'!E98,'Model inputs'!E99) -> 0 | F97: =SUM('Model inputs'!F98,'Model inputs'!F99) -> 0 | G97: =SUM('Model inputs'!G98,'Model inputs'!G99) -> 0 | H97: =SUM('Model inputs'!H98,'Model inputs'!H99) -> 0
A98: Overage revenue (USD) > Classroom | B98: =0 -> 0 | C98: ='Model inputs'!C23*IF(IF(IF(IF(ISERROR('Model inputs'!O111>'Model inputs'!O108),'Model inputs'!O111>'Model inputs'!O108,IF(OR('Model inputs'!O111="",'Model inputs'!O108=""),"",'Model inputs'!O111>'Model inputs'!O108))="",FALSE,IF(ISERROR('Model inputs'!O111>'Model inputs'!O108),'Model inputs'!O111>'Model inputs'!O108,IF(OR('Model inputs'!O111="",'Model inputs'!O108=""),"",'Model inputs'!O111>'Model inputs'!O108))),('Model inputs'!O111-'Model inputs'!O108)*'Model inputs'!O89,0)="",0,IF(IF(IF(ISERROR('Model inputs'!O111>'Model inputs'!O108),'Model inputs'!O111>'Model inputs'!O108,IF(OR('Model inputs'!O111="",'Model inputs'!O108=""),"",'Model inputs'!O111>'Model inputs'!O108))="",FALSE,IF(ISERROR('Model inputs'!O111>'Model inputs'!O108),'Model inputs'!O111>'Model inputs'!O108,IF(OR('Model inputs'!O111="",'Model inputs'!O108=""),"",'Model inputs'!O111>'Model inputs'!O108))),('Model inputs'!O111-'Model inputs'!O108)*'Model inputs'!O89,0)) -> 0 | D98: ='Model inputs'!D23*IF(IF(IF(IF(ISERROR('Model inputs'!O111>'Model inputs'!O108),'Model inputs'!O111>'Model inputs'!O108,IF(OR('Model inputs'!O111="",'Model inputs'!O108=""),"",'Model inputs'!O111>'Model inputs'!O108))="",FALSE,IF(ISERROR('Model inputs'!O111>'Model inputs'!O108),'Model inputs'!O111>'Model inputs'!O108,IF(OR('Model inputs'!O111="",'Model inputs'!O108=""),"",'Model inputs'!O111>'Model inputs'!O108))),('Model inputs'!O111-'Model inputs'!O108)*'Model inputs'!O89,0)="",0,IF(IF(IF(ISERROR('Model inputs'!O111>'Model inputs'!O108),'Model inputs'!O111>'Model inputs'!O108,IF(OR('Model inputs'!O111="",'Model inputs'!O108=""),"",'Model inputs'!O111>'Model inputs'!O108))="",FALSE,IF(ISERROR('Model inputs'!O111>'Model inputs'!O108),'Model inputs'!O111>'Model inputs'!O108,IF(OR('Model inputs'!O111="",'Model inputs'!O108=""),"",'Model inputs'!O111>'Model inputs'!O108))),('Model inputs'!O111-'Model inputs'!O108)*'Model inputs'!O89,0)) -> 0 | E98: ='Model inputs'!E23*IF(IF(IF(IF(ISERROR('Model inputs'!O111>'Model inputs'!O108),'Model inputs'!O111>'Model inputs'!O108,IF(OR('Model inputs'!O111="",'Model inputs'!O108=""),"",'Model inputs'!O111>'Model inputs'!O108))="",FALSE,IF(ISERROR('Model inputs'!O111>'Model inputs'!O108),'Model inputs'!O111>'Model inputs'!O108,IF(OR('Model inputs'!O111="",'Model inputs'!O108=""),"",'Model inputs'!O111>'Model inputs'!O108))),('Model inputs'!O111-'Model inputs'!O108)*'Model inputs'!O89,0)="",0,IF(IF(IF(ISERROR('Model inputs'!O111>'Model inputs'!O108),'Model inputs'!O111>'Model inputs'!O108,IF(OR('Model inputs'!O111="",'Model inputs'!O108=""),"",'Model inputs'!O111>'Model inputs'!O108))="",FALSE,IF(ISERROR('Model inputs'!O111>'Model inputs'!O108),'Model inputs'!O111>'Model inputs'!O108,IF(OR('Model inputs'!O111="",'Model inputs'!O108=""),"",'Model inputs'!O111>'Model inputs'!O108))),('Model inputs'!O111-'Model inputs'!O108)*'Model inputs'!O89,0)) -> 0 | F98: ='Model inputs'!F23*IF(IF(IF(IF(ISERROR('Model inputs'!O111>'Model inputs'!O108),'Model inputs'!O111>'Model inputs'!O108,IF(OR('Model inputs'!O111="",'Model inputs'!O108=""),"",'Model inputs'!O111>'Model inputs'!O108))="",FALSE,IF(ISERROR('Model inputs'!O111>'Model inputs'!O108),'Model inputs'!O111>'Model inputs'!O108,IF(OR('Model inputs'!O111="",'Model inputs'!O108=""),"",'Model inputs'!O111>'Model inputs'!O108))),('Model inputs'!O111-'Model inputs'!O108)*'Model inputs'!O89,0)="",0,IF(IF(IF(ISERROR('Model inputs'!O111>'Model inputs'!O108),'Model inputs'!O111>'Model inputs'!O108,IF(OR('Model inputs'!O111="",'Model inputs'!O108=""),"",'Model inputs'!O111>'Model inputs'!O108))="",FALSE,IF(ISERROR('Model inputs'!O111>'Model inputs'!O108),'Model inputs'!O111>'Model inputs'!O108,IF(OR('Model inputs'!O111="",'Model inputs'!O108=""),"",'Model inputs'!O111>'Model inputs'!O108))),('Model inputs'!O111-'Model inputs'!O108)*'Model inputs'!O89,0)) -> 0 | G98: ='Model inputs'!G23*IF(IF(IF(IF(ISERROR('Model inputs'!O111>'Model inputs'!O108),'Model inputs'!O111>'Model inputs'!O108,IF(OR('Model inputs'!O111="",'Model inputs'!O108=""),"",'Model inputs'!O111>'Model inputs'!O108))="",FALSE,IF(ISERROR('Model inputs'!O111>'Model inputs'!O108),'Model inputs'!O111>'Model inputs'!O108,IF(OR('Model inputs'!O111="",'Model inputs'!O108=""),"",'Model inputs'!O111>'Model inputs'!O108))),('Model inputs'!O111-'Model inputs'!O108)*'Model inputs'!O89,0)="",0,IF(IF(IF(ISERROR('Model inputs'!O111>'Model inputs'!O108),'Model inputs'!O111>'Model inputs'!O108,IF(OR('Model inputs'!O111="",'Model inputs'!O108=""),"",'Model inputs'!O111>'Model inputs'!O108))="",FALSE,IF(ISERROR('Model inputs'!O111>'Model inputs'!O108),'Model inputs'!O111>'Model inputs'!O108,IF(OR('Model inputs'!O111="",'Model inputs'!O108=""),"",'Model inputs'!O111>'Model inputs'!O108))),('Model inputs'!O111-'Model inputs'!O108)*'Model inputs'!O89,0)) -> 0 | H98: ='Model inputs'!H23*IF(IF(IF(IF(ISERROR('Model inputs'!O111>'Model inputs'!O108),'Model inputs'!O111>'Model inputs'!O108,IF(OR('Model inputs'!O111="",'Model inputs'!O108=""),"",'Model inputs'!O111>'Model inputs'!O108))="",FALSE,IF(ISERROR('Model inputs'!O111>'Model inputs'!O108),'Model inputs'!O111>'Model inputs'!O108,IF(OR('Model inputs'!O111="",'Model inputs'!O108=""),"",'Model inputs'!O111>'Model inputs'!O108))),('Model inputs'!O111-'Model inputs'!O108)*'Model inputs'!O89,0)="",0,IF(IF(IF(ISERROR('Model inputs'!O111>'Model inputs'!O108),'Model inputs'!O111>'Model inputs'!O108,IF(OR('Model inputs'!O111="",'Model inputs'!O108=""),"",'Model inputs'!O111>'Model inputs'!O108))="",FALSE,IF(ISERROR('Model inputs'!O111>'Model inputs'!O108),'Model inputs'!O111>'Model inputs'!O108,IF(OR('Model inputs'!O111="",'Model inputs'!O108=""),"",'Model inputs'!O111>'Model inputs'!O108))),('Model inputs'!O111-'Model inputs'!O108)*'Model inputs'!O89,0)) -> 0
A99: Overage revenue (USD) > Household | B99: =0 -> 0 | C99: ='Model inputs'!C24*IF(IF(IF(IF(ISERROR('Model inputs'!O112>'Model inputs'!O109),'Model inputs'!O112>'Model inputs'!O109,IF(OR('Model inputs'!O112="",'Model inputs'!O109=""),"",'Model inputs'!O112>'Model inputs'!O109))="",FALSE,IF(ISERROR('Model inputs'!O112>'Model inputs'!O109),'Model inputs'!O112>'Model inputs'!O109,IF(OR('Model inputs'!O112="",'Model inputs'!O109=""),"",'Model inputs'!O112>'Model inputs'!O109))),('Model inputs'!O112-'Model inputs'!O109)*'Model inputs'!O90,0)="",0,IF(IF(IF(ISERROR('Model inputs'!O112>'Model inputs'!O109),'Model inputs'!O112>'Model inputs'!O109,IF(OR('Model inputs'!O112="",'Model inputs'!O109=""),"",'Model inputs'!O112>'Model inputs'!O109))="",FALSE,IF(ISERROR('Model inputs'!O112>'Model inputs'!O109),'Model inputs'!O112>'Model inputs'!O109,IF(OR('Model inputs'!O112="",'Model inputs'!O109=""),"",'Model inputs'!O112>'Model inputs'!O109))),('Model inputs'!O112-'Model inputs'!O109)*'Model inputs'!O90,0)) -> 0 | D99: ='Model inputs'!D24*IF(IF(IF(IF(ISERROR('Model inputs'!O112>'Model inputs'!O109),'Model inputs'!O112>'Model inputs'!O109,IF(OR('Model inputs'!O112="",'Model inputs'!O109=""),"",'Model inputs'!O112>'Model inputs'!O109))="",FALSE,IF(ISERROR('Model inputs'!O112>'Model inputs'!O109),'Model inputs'!O112>'Model inputs'!O109,IF(OR('Model inputs'!O112="",'Model inputs'!O109=""),"",'Model inputs'!O112>'Model inputs'!O109))),('Model inputs'!O112-'Model inputs'!O109)*'Model inputs'!O90,0)="",0,IF(IF(IF(ISERROR('Model inputs'!O112>'Model inputs'!O109),'Model inputs'!O112>'Model inputs'!O109,IF(OR('Model inputs'!O112="",'Model inputs'!O109=""),"",'Model inputs'!O112>'Model inputs'!O109))="",FALSE,IF(ISERROR('Model inputs'!O112>'Model inputs'!O109),'Model inputs'!O112>'Model inputs'!O109,IF(OR('Model inputs'!O112="",'Model inputs'!O109=""),"",'Model inputs'!O112>'Model inputs'!O109))),('Model inputs'!O112-'Model inputs'!O109)*'Model inputs'!O90,0)) -> 0 | E99: ='Model inputs'!E24*IF(IF(IF(IF(ISERROR('Model inputs'!O112>'Model inputs'!O109),'Model inputs'!O112>'Model inputs'!O109,IF(OR('Model inputs'!O112="",'Model inputs'!O109=""),"",'Model inputs'!O112>'Model inputs'!O109))="",FALSE,IF(ISERROR('Model inputs'!O112>'Model inputs'!O109),'Model inputs'!O112>'Model inputs'!O109,IF(OR('Model inputs'!O112="",'Model inputs'!O109=""),"",'Model inputs'!O112>'Model inputs'!O109))),('Model inputs'!O112-'Model inputs'!O109)*'Model inputs'!O90,0)="",0,IF(IF(IF(ISERROR('Model inputs'!O112>'Model inputs'!O109),'Model inputs'!O112>'Model inputs'!O109,IF(OR('Model inputs'!O112="",'Model inputs'!O109=""),"",'Model inputs'!O112>'Model inputs'!O109))="",FALSE,IF(ISERROR('Model inputs'!O112>'Model inputs'!O109),'Model inputs'!O112>'Model inputs'!O109,IF(OR('Model inputs'!O112="",'Model inputs'!O109=""),"",'Model inputs'!O112>'Model inputs'!O109))),('Model inputs'!O112-'Model inputs'!O109)*'Model inputs'!O90,0)) -> 0 | F99: ='Model inputs'!F24*IF(IF(IF(IF(ISERROR('Model inputs'!O112>'Model inputs'!O109),'Model inputs'!O112>'Model inputs'!O109,IF(OR('Model inputs'!O112="",'Model inputs'!O109=""),"",'Model inputs'!O112>'Model inputs'!O109))="",FALSE,IF(ISERROR('Model inputs'!O112>'Model inputs'!O109),'Model inputs'!O112>'Model inputs'!O109,IF(OR('Model inputs'!O112="",'Model inputs'!O109=""),"",'Model inputs'!O112>'Model inputs'!O109))),('Model inputs'!O112-'Model inputs'!O109)*'Model inputs'!O90,0)="",0,IF(IF(IF(ISERROR('Model inputs'!O112>'Model inputs'!O109),'Model inputs'!O112>'Model inputs'!O109,IF(OR('Model inputs'!O112="",'Model inputs'!O109=""),"",'Model inputs'!O112>'Model inputs'!O109))="",FALSE,IF(ISERROR('Model inputs'!O112>'Model inputs'!O109),'Model inputs'!O112>'Model inputs'!O109,IF(OR('Model inputs'!O112="",'Model inputs'!O109=""),"",'Model inputs'!O112>'Model inputs'!O109))),('Model inputs'!O112-'Model inputs'!O109)*'Model inputs'!O90,0)) -> 0 | G99: ='Model inputs'!G24*IF(IF(IF(IF(ISERROR('Model inputs'!O112>'Model inputs'!O109),'Model inputs'!O112>'Model inputs'!O109,IF(OR('Model inputs'!O112="",'Model inputs'!O109=""),"",'Model inputs'!O112>'Model inputs'!O109))="",FALSE,IF(ISERROR('Model inputs'!O112>'Model inputs'!O109),'Model inputs'!O112>'Model inputs'!O109,IF(OR('Model inputs'!O112="",'Model inputs'!O109=""),"",'Model inputs'!O112>'Model inputs'!O109))),('Model inputs'!O112-'Model inputs'!O109)*'Model inputs'!O90,0)="",0,IF(IF(IF(ISERROR('Model inputs'!O112>'Model inputs'!O109),'Model inputs'!O112>'Model inputs'!O109,IF(OR('Model inputs'!O112="",'Model inputs'!O109=""),"",'Model inputs'!O112>'Model inputs'!O109))="",FALSE,IF(ISERROR('Model inputs'!O112>'Model inputs'!O109),'Model inputs'!O112>'Model inputs'!O109,IF(OR('Model inputs'!O112="",'Model inputs'!O109=""),"",'Model inputs'!O112>'Model inputs'!O109))),('Model inputs'!O112-'Model inputs'!O109)*'Model inputs'!O90,0)) -> 0 | H99: ='Model inputs'!H24*IF(IF(IF(IF(ISERROR('Model inputs'!O112>'Model inputs'!O109),'Model inputs'!O112>'Model inputs'!O109,IF(OR('Model inputs'!O112="",'Model inputs'!O109=""),"",'Model inputs'!O112>'Model inputs'!O109))="",FALSE,IF(ISERROR('Model inputs'!O112>'Model inputs'!O109),'Model inputs'!O112>'Model inputs'!O109,IF(OR('Model inputs'!O112="",'Model inputs'!O109=""),"",'Model inputs'!O112>'Model inputs'!O109))),('Model inputs'!O112-'Model inputs'!O109)*'Model inputs'!O90,0)="",0,IF(IF(IF(ISERROR('Model inputs'!O112>'Model inputs'!O109),'Model inputs'!O112>'Model inputs'!O109,IF(OR('Model inputs'!O112="",'Model inputs'!O109=""),"",'Model inputs'!O112>'Model inputs'!O109))="",FALSE,IF(ISERROR('Model inputs'!O112>'Model inputs'!O109),'Model inputs'!O112>'Model inputs'!O109,IF(OR('Model inputs'!O112="",'Model inputs'!O109=""),"",'Model inputs'!O112>'Model inputs'!O109))),('Model inputs'!O112-'Model inputs'!O109)*'Model inputs'!O90,0)) -> 0
A100: Overage revenue (USD) | B100: =IF('Model inputs'!B97="","",'Model inputs'!B97) -> 0 | C100: =IF('Model inputs'!C97="","",'Model inputs'!C97) -> 0 | D100: =IF('Model inputs'!D97="","",'Model inputs'!D97) -> 0 | E100: =IF('Model inputs'!E97="","",'Model inputs'!E97) -> 0 | F100: =IF('Model inputs'!F97="","",'Model inputs'!F97) -> 0 | G100: =IF('Model inputs'!G97="","",'Model inputs'!G97) -> 0 | H100: =IF('Model inputs'!H97="","",'Model inputs'!H97) -> 0 | I100: =SUM('Model inputs'!I101,'Model inputs'!I102) -> 0 | J100: =SUM('Model inputs'!J101,'Model inputs'!J102) -> 0 | K100: =SUM('Model inputs'!K101,'Model inputs'!K102) -> 0 | L100: =SUM('Model inputs'!L101,'Model inputs'!L102) -> 0 | M100: =SUM('Model inputs'!M101,'Model inputs'!M102) -> 0 | N100: =SUM('Model inputs'!N101,'Model inputs'!N102) -> 0
A101: Overage revenue (USD) > Classroom | B101: =IF('Model inputs'!B98="","",'Model inputs'!B98) -> 0 | C101: =IF('Model inputs'!C98="","",'Model inputs'!C98) -> 0 | D101: =IF('Model inputs'!D98="","",'Model inputs'!D98) -> 0 | E101: =IF('Model inputs'!E98="","",'Model inputs'!E98) -> 0 | F101: =IF('Model inputs'!F98="","",'Model inputs'!F98) -> 0 | G101: =IF('Model inputs'!G98="","",'Model inputs'!G98) -> 0 | H101: =IF('Model inputs'!H98="","",'Model inputs'!H98) -> 0 | I101: ='Model inputs'!I26*IF(IF(IF(IF(ISERROR('Model inputs'!O111>'Model inputs'!O108),'Model inputs'!O111>'Model inputs'!O108,IF(OR('Model inputs'!O111="",'Model inputs'!O108=""),"",'Model inputs'!O111>'Model inputs'!O108))="",FALSE,IF(ISERROR('Model inputs'!O111>'Model inputs'!O108),'Model inputs'!O111>'Model inputs'!O108,IF(OR('Model inputs'!O111="",'Model inputs'!O108=""),"",'Model inputs'!O111>'Model inputs'!O108))),('Model inputs'!O111-'Model inputs'!O108)*'Model inputs'!O89,0)="",0,IF(IF(IF(ISERROR('Model inputs'!O111>'Model inputs'!O108),'Model inputs'!O111>'Model inputs'!O108,IF(OR('Model inputs'!O111="",'Model inputs'!O108=""),"",'Model inputs'!O111>'Model inputs'!O108))="",FALSE,IF(ISERROR('Model inputs'!O111>'Model inputs'!O108),'Model inputs'!O111>'Model inputs'!O108,IF(OR('Model inputs'!O111="",'Model inputs'!O108=""),"",'Model inputs'!O111>'Model inputs'!O108))),('Model inputs'!O111-'Model inputs'!O108)*'Model inputs'!O89,0)) -> 0 | J101: ='Model inputs'!J26*IF(IF(IF(IF(ISERROR('Model inputs'!O111>'Model inputs'!O108),'Model inputs'!O111>'Model inputs'!O108,IF(OR('Model inputs'!O111="",'Model inputs'!O108=""),"",'Model inputs'!O111>'Model inputs'!O108))="",FALSE,IF(ISERROR('Model inputs'!O111>'Model inputs'!O108),'Model inputs'!O111>'Model inputs'!O108,IF(OR('Model inputs'!O111="",'Model inputs'!O108=""),"",'Model inputs'!O111>'Model inputs'!O108))),('Model inputs'!O111-'Model inputs'!O108)*'Model inputs'!O89,0)="",0,IF(IF(IF(ISERROR('Model inputs'!O111>'Model inputs'!O108),'Model inputs'!O111>'Model inputs'!O108,IF(OR('Model inputs'!O111="",'Model inputs'!O108=""),"",'Model inputs'!O111>'Model inputs'!O108))="",FALSE,IF(ISERROR('Model inputs'!O111>'Model inputs'!O108),'Model inputs'!O111>'Model inputs'!O108,IF(OR('Model inputs'!O111="",'Model inputs'!O108=""),"",'Model inputs'!O111>'Model inputs'!O108))),('Model inputs'!O111-'Model inputs'!O108)*'Model inputs'!O89,0)) -> 0 | K101: ='Model inputs'!K26*IF(IF(IF(IF(ISERROR('Model inputs'!O111>'Model inputs'!O108),'Model inputs'!O111>'Model inputs'!O108,IF(OR('Model inputs'!O111="",'Model inputs'!O108=""),"",'Model inputs'!O111>'Model inputs'!O108))="",FALSE,IF(ISERROR('Model inputs'!O111>'Model inputs'!O108),'Model inputs'!O111>'Model inputs'!O108,IF(OR('Model inputs'!O111="",'Model inputs'!O108=""),"",'Model inputs'!O111>'Model inputs'!O108))),('Model inputs'!O111-'Model inputs'!O108)*'Model inputs'!O89,0)="",0,IF(IF(IF(ISERROR('Model inputs'!O111>'Model inputs'!O108),'Model inputs'!O111>'Model inputs'!O108,IF(OR('Model inputs'!O111="",'Model inputs'!O108=""),"",'Model inputs'!O111>'Model inputs'!O108))="",FALSE,IF(ISERROR('Model inputs'!O111>'Model inputs'!O108),'Model inputs'!O111>'Model inputs'!O108,IF(OR('Model inputs'!O111="",'Model inputs'!O108=""),"",'Model inputs'!O111>'Model inputs'!O108))),('Model inputs'!O111-'Model inputs'!O108)*'Model inputs'!O89,0)) -> 0 | L101: ='Model inputs'!L26*IF(IF(IF(IF(ISERROR('Model inputs'!O111>'Model inputs'!O108),'Model inputs'!O111>'Model inputs'!O108,IF(OR('Model inputs'!O111="",'Model inputs'!O108=""),"",'Model inputs'!O111>'Model inputs'!O108))="",FALSE,IF(ISERROR('Model inputs'!O111>'Model inputs'!O108),'Model inputs'!O111>'Model inputs'!O108,IF(OR('Model inputs'!O111="",'Model inputs'!O108=""),"",'Model inputs'!O111>'Model inputs'!O108))),('Model inputs'!O111-'Model inputs'!O108)*'Model inputs'!O89,0)="",0,IF(IF(IF(ISERROR('Model inputs'!O111>'Model inputs'!O108),'Model inputs'!O111>'Model inputs'!O108,IF(OR('Model inputs'!O111="",'Model inputs'!O108=""),"",'Model inputs'!O111>'Model inputs'!O108))="",FALSE,IF(ISERROR('Model inputs'!O111>'Model inputs'!O108),'Model inputs'!O111>'Model inputs'!O108,IF(OR('Model inputs'!O111="",'Model inputs'!O108=""),"",'Model inputs'!O111>'Model inputs'!O108))),('Model inputs'!O111-'Model inputs'!O108)*'Model inputs'!O89,0)) -> 0 | M101: ='Model inputs'!M26*IF(IF(IF(IF(ISERROR('Model inputs'!O111>'Model inputs'!O108),'Model inputs'!O111>'Model inputs'!O108,IF(OR('Model inputs'!O111="",'Model inputs'!O108=""),"",'Model inputs'!O111>'Model inputs'!O108))="",FALSE,IF(ISERROR('Model inputs'!O111>'Model inputs'!O108),'Model inputs'!O111>'Model inputs'!O108,IF(OR('Model inputs'!O111="",'Model inputs'!O108=""),"",'Model inputs'!O111>'Model inputs'!O108))),('Model inputs'!O111-'Model inputs'!O108)*'Model inputs'!O89,0)="",0,IF(IF(IF(ISERROR('Model inputs'!O111>'Model inputs'!O108),'Model inputs'!O111>'Model inputs'!O108,IF(OR('Model inputs'!O111="",'Model inputs'!O108=""),"",'Model inputs'!O111>'Model inputs'!O108))="",FALSE,IF(ISERROR('Model inputs'!O111>'Model inputs'!O108),'Model inputs'!O111>'Model inputs'!O108,IF(OR('Model inputs'!O111="",'Model inputs'!O108=""),"",'Model inputs'!O111>'Model inputs'!O108))),('Model inputs'!O111-'Model inputs'!O108)*'Model inputs'!O89,0)) -> 0 | N101: ='Model inputs'!N26*IF(IF(IF(IF(ISERROR('Model inputs'!O111>'Model inputs'!O108),'Model inputs'!O111>'Model inputs'!O108,IF(OR('Model inputs'!O111="",'Model inputs'!O108=""),"",'Model inputs'!O111>'Model inputs'!O108))="",FALSE,IF(ISERROR('Model inputs'!O111>'Model inputs'!O108),'Model inputs'!O111>'Model inputs'!O108,IF(OR('Model inputs'!O111="",'Model inputs'!O108=""),"",'Model inputs'!O111>'Model inputs'!O108))),('Model inputs'!O111-'Model inputs'!O108)*'Model inputs'!O89,0)="",0,IF(IF(IF(ISERROR('Model inputs'!O111>'Model inputs'!O108),'Model inputs'!O111>'Model inputs'!O108,IF(OR('Model inputs'!O111="",'Model inputs'!O108=""),"",'Model inputs'!O111>'Model inputs'!O108))="",FALSE,IF(ISERROR('Model inputs'!O111>'Model inputs'!O108),'Model inputs'!O111>'Model inputs'!O108,IF(OR('Model inputs'!O111="",'Model inputs'!O108=""),"",'Model inputs'!O111>'Model inputs'!O108))),('Model inputs'!O111-'Model inputs'!O108)*'Model inputs'!O89,0)) -> 0
...

Sheet Export notes
A1: Export notes
A2: These cells hold the value cfo.ai calculated instead of a formula. They do not recalculate when you edit an input.
A4: Sheet | B4: Cell | C4: Variable | D4: Period | E4: Scenario | F4: Why
A5: Model inputs | B5: O367 | C5: Share of gated uplift paid (derived) | E5: Main Scenario | F5: It reads Verification policy, which this workbook does not contain.
A6: Model inputs | B6: O418 | C6: Share of gated uplift paid (derived) | E6: Downside | F6: It reads Verification policy, which this workbook does not contain.
A7: Model inputs | B7: O421 | C7: Share of gated uplift paid (derived) | E7: Growth | F7: It reads Verification policy, which this workbook does not contain.
