Workbook

Sheet Plan assumptions
A1: Plan assumptions
A2: Assumptions · Main Scenario
A4: Variable / dimension | B4: Price per month (USD, assumed) | C4: Stories included per month (assumed) | D4: Overage price per extra story (USD, assumed) | E4: Starting customers (assumed) | F4: New customers per month (assumed) | G4: Monthly churn (assumed) | H4: Stories used, share of included (assumed) | I4: Stories used per customer (derived)
A5: Classroom | B5: =29 -> 29 | C5: =100 -> 100 | D5: =0.25 -> 0.25 | E5: =10 -> 10 | F5: =1 -> 1 | G5: =0.03 -> 0.03 | H5: =0.6 -> 0.6 | I5: ='Plan assumptions'!H5*'Plan assumptions'!C5 -> 60
A6: Household | B6: =6.99 -> 6.99 | C6: =12 -> 12 | D6: =0.6 -> 0.6 | E6: =40 -> 40 | F6: =8 -> 8 | G6: =0.08 -> 0.08 | H6: =0.6 -> 0.6 | I6: ='Plan assumptions'!H6*'Plan assumptions'!C6 -> 7.2

Sheet Cost per story inputs
A1: Cost per story inputs
A2: Assumptions · Main Scenario
A4: Variable / dimension | B4: Cost input value | C4: Cost input unit | D4: Cost input status | E4: Cost input basis
A5: Narration price per page | B5: =0.002 -> 0.002 | C5: ="USD per page" -> USD per page | D5: ="assumed" -> assumed | E5: ="Assumed narration cost per page. Not measured." -> Assumed narration cost per page. Not measured.
A6: Pages per story | B6: =8 -> 8 | C6: ="pages" -> pages | D6: ="assumed" -> assumed | E6: ="Product design: 8 pages per story (one picture and one narration clip per page at most)." -> Product design: 8 pages per story (one picture and one narration clip per page at most).
A7: Picture price each | B7: =0.04 -> 0.04 | C7: ="USD per picture" -> USD per picture | D7: ="assumed" -> assumed | E7: ="Assumed list price per generated picture (repo config). Not measured: neatlogs does not price image spans (it measured only about 0.04 USD for a whole illustrated story whose pictures we estimate at 0.32). The true figure is on the Google Cloud bill." -> Assumed list price per generated picture (repo config). Not measured: neatlogs does not price image spans (it measured only about 0.04 USD for a whole illustrated story whose pictures we estimate at 0.32). The true figure is on the Google Cloud bill.
A8: Sampled share of gated uplift | B8: =0.7 -> 0.7 | C8: ="share of (B1 minus B0)" -> share of (B1 minus B0) | D8: ="assumed" -> assumed | E8: ="Assumed: sampled verification pays 70% of the gated uplift. Not measured." -> Assumed: sampled verification pays 70% of the gated uplift. Not measured.
A9: Text and verification B0 ungated | B9: =0.0097 -> 0.0097 | C9: ="USD per story" -> USD per story | D9: ="measured" -> measured | E9: ="Measured by neatlogs: mean total cost of 28 sweep-2-p2 B0 traces read through the neatlogs API on 10 Oct 2026 (evidence/neatlogs/20261010-2010-IST-measured-vs-estimated-cost.json). Our token estimate was 0.0083. Text only; excludes pictures and narration." -> Measured by neatlogs: mean total cost of 28 sweep-2-p2 B0 traces read through the neatlogs API on 10 Oct 2026 (evidence/neatlogs/20261010-2010-IST-measured-vs-estimated-cost.json). Our token estimate was 0.0083. Text only; excludes pictures and narration.
A10: Text and verification B1 gated | B10: =0.0199 -> 0.0199 | C10: ="USD per story" -> USD per story | D10: ="measured" -> measured | E10: ="Measured by neatlogs: mean total cost of 28 sweep-2-p2 B1 traces (14 sweep-6 B1 traces gave 0.0201). Our token estimate was 0.0162, so it was about 20% low. Text and verification only; excludes pictures and narration; neatlogs does not price image or narration spans. A verified quiz after the story adds about 0.004 (token estimate, 26 stories, 11 Oct: 0.0204 against 0.0162 without a quiz); not yet measured by neatlogs and not included in this value." -> Measured by neatlogs: mean total cost of 28 sweep-2-p2 B1 traces (14 sweep-6 B1 traces gave 0.0201). Our token estimate was 0.0162, so it was about 20% low. Text and verification only; excludes pictures and narration; neatlogs does not price image or narration spans. A verified quiz after the story adds about 0.004 (token estimate, 26 stories, 11 Oct: 0.0204 against 0.0162 without a quiz); not yet measured by neatlogs and not included in this value.

Sheet Verification policy settings
A1: Verification policy settings
A2: Assumptions · Main Scenario
A4: Variable / dimension | B4: Verification policy selected (1 = yes, assumed) | C4: Share of gated uplift paid (derived) | D4: Text and verification cost per story (USD, derived) | E4: Selected text and verification cost (USD, derived)
A5: Sampled | B5: =0 -> 0 | C5: =IF(EXACT("Sampled","Verify all"),1,IF('Cost per story inputs'!B8="","",'Cost per story inputs'!B8)) -> 0.7 | D5: ='Cost per story inputs'!B9+'Verification policy settings'!C5*('Cost per story inputs'!B10-'Cost per story inputs'!B9) -> 0.01684 | E5: ='Verification policy settings'!D5*'Verification policy settings'!B5 -> 0
A6: Verify all | B6: =1 -> 1 | C6: =IF(EXACT("Verify all","Verify all"),1,IF('Cost per story inputs'!B8="","",'Cost per story inputs'!B8)) -> 1 | D6: ='Cost per story inputs'!B9+'Verification policy settings'!C6*('Cost per story inputs'!B10-'Cost per story inputs'!B9) -> 0.0199 | E6: ='Verification policy settings'!D6*'Verification policy settings'!B6 -> 0.0199

Sheet Illustration policy settings
A1: Illustration policy settings
A2: Assumptions · Main Scenario
A4: Variable / dimension | B4: Illustration policy selected (1 = yes, assumed) | C4: Pictures per story (policy) | D4: Picture and narration cost per story (USD, derived) | E4: Selected picture and narration cost (USD, derived)
A5: Full (8 pictures) | B5: =0 -> 0 | C5: =8 -> 8 | D5: ='Illustration policy settings'!C5*'Cost per story inputs'!B7+'Cost per story inputs'!B5*'Cost per story inputs'!B6 -> 0.336 | E5: ='Illustration policy settings'!D5*'Illustration policy settings'!B5 -> 0
A6: Half (4 pictures) | B6: =1 -> 1 | C6: =4 -> 4 | D6: ='Illustration policy settings'!C6*'Cost per story inputs'!B7+'Cost per story inputs'!B5*'Cost per story inputs'!B6 -> 0.176 | E6: ='Illustration policy settings'!D6*'Illustration policy settings'!B6 -> 0.176
A7: Text only (0) | B7: =0 -> 0 | C7: =0 -> 0 | D7: ='Illustration policy settings'!C7*'Cost per story inputs'!B7+'Cost per story inputs'!B5*'Cost per story inputs'!B6 -> 0.016 | E7: ='Illustration policy settings'!D7*'Illustration policy settings'!B7 -> 0

Sheet Other costs and cash inputs
A1: Other costs and cash inputs
A2: Assumptions · Main Scenario
A4: Variable / dimension | B4: Value
A5: Hosting per month (USD, assumed) | B5: =25 -> 25
A6: Other fixed costs per month (USD, assumed) | B6: =50 -> 50
A7: Starting cash (USD, assumed) | B7: =2000 -> 2000
A8: neatlogs covered by hackathon credits (1 = yes, assumed) | B8: =1 -> 1
A9: Spans per story (assumed placeholder) | B9: =150 -> 150
A10: neatlogs Free plan span cap (published price, unverified for credits) | B10: =100000 -> 100000
A11: neatlogs Starter plan price per month (USD, published price) | B11: =99 -> 99
A12: neatlogs Starter plan included spans (published price) | B12: =250000 -> 250000
A13: neatlogs price per extra 100k spans (USD, published price) | B13: =10 -> 10
A14: Gross margin bar (ours, stated) | B14: =0.6 -> 0.6

Sheet Launch operating costs (assumed
A1: Launch operating costs (assumed, for real children's use)
A2: Assumptions · Main Scenario
A4: Variable / dimension | B4: Value
A5: Support tickets per 100 households per month (assumed) | B5: =8 -> 8
A6: Minutes per support ticket (assumed) | B6: =12 -> 12
A7: Support hourly cost (USD, assumed) | B7: =25 -> 25
A8: Stories flagged for a human look per 100 stories (assumed) | B8: =2 -> 2
A9: Minutes per flagged story review (assumed) | B9: =10 -> 10
A10: Safety reviewer hourly cost (USD, assumed) | B10: =30 -> 30
A11: Stories per household per month (assumed) | B11: =12 -> 12
A12: Child-privacy compliance per year (USD, placeholder, not legal advice) | B12: =6000 -> 6000
A13: Households sharing the compliance cost (assumed) | B13: =500 -> 500
A14: Pictures per story when Pip chooses (from the picture budget in config) | B14: =4 -> 4
A15: One video clip, 4 s, Veo 3.1 Lite (USD, list price estimate) | B15: =0.2 -> 0.2
A16: Support cost per household per month (USD, derived) | B16: ='Launch operating costs (assumed'!B5/100*'Launch operating costs (assumed'!B6/60*'Launch operating costs (assumed'!B7 -> 0.4
A17: Safety review cost per story (USD, derived) | B17: ='Launch operating costs (assumed'!B8/100*'Launch operating costs (assumed'!B9/60*'Launch operating costs (assumed'!B10 -> 0.1
A18: Safety review cost per household per month (USD, derived) | B18: ='Launch operating costs (assumed'!B17*'Launch operating costs (assumed'!B11 -> 1.2
A19: Compliance cost per household per month (USD, derived) | B19: ='Launch operating costs (assumed'!B12/12/'Launch operating costs (assumed'!B13 -> 1
A20: Launch operating cost per household per month (USD, derived) | B20: ='Launch operating costs (assumed'!B16+'Launch operating costs (assumed'!B18+'Launch operating costs (assumed'!B19 -> 2.6
A21: Picture cost per story when Pip chooses (USD, estimate) | B21: ='Launch operating costs (assumed'!B14*0.04 -> 0.16
A22: Video clip per story with one clip and a 1.4 retry allowance (USD, estimate) | B22: ='Launch operating costs (assumed'!B15*1.4 -> 0.28
A23: Launch operating cost as a share of the Household price (derived) | B23: ='Launch operating costs (assumed'!B20/'Plan assumptions'!B6 -> 0.37195994
A24: Video clips per story (0 = deterministic motion only, as today) | B24: =0 -> 0
A25: Seconds per video clip (assumed) | B25: =4 -> 4
A26: Video model price per second (USD, list price estimate) | B26: =0.05 -> 0.05
A27: Video retry allowance (x clips made per clip kept, assumed) | B27: =1.4 -> 1.4
A28: Clip check cost per clip (USD, two judges, estimate) | B28: =0.02 -> 0.02
A29: Video cost per story (USD, derived) | B29: ='Launch operating costs (assumed'!B24*('Launch operating costs (assumed'!B25*'Launch operating costs (assumed'!B26*'Launch operating costs (assumed'!B27+'Launch operating costs (assumed'!B28) -> 0
A30: Video add-on price per story that keeps the margin bar on the video alone (USD, derived) | B30: ='Launch operating costs (assumed'!B29/(1-'Other costs and cash inputs'!B14) -> 0

Sheet Model inputs
A1: Model inputs
A2: Integration values are aggregated snapshots; raw source records are not included.
A4: Variables
A5: Variable / segment | B5: Value
A6: Price per month (USD, assumed) | B6: 0
A7: Price per month (USD, assumed) > Classroom | B7: ='Plan assumptions'!B5 -> 29
A8: Price per month (USD, assumed) > Household | B8: ='Plan assumptions'!B6 -> 6.99
A10: Dimensions
A11: Plan | B11: Classroom | C11: Household
