Workbook

Sheet Cash and runway, month 12 (Main
A1: Cash and runway, month 12 (Main vs Growth vs Downside)
A2: Cash and runway · Main Scenario
A4: Variable / dimension | B4: 2027-09 | C4: 2027-09 > Growth | D4: 2027-09 > Downside
A5: Gross profit (USD) | B5: =SUM('Model inputs'!N10,'Model inputs'!N11) -> 705.52776 | C5: =SUM('Model inputs'!N16,'Model inputs'!N17) -> 1143.45 | D5: =SUM('Model inputs'!N13,'Model inputs'!N14) -> 305.91145
A6: Other fixed costs (USD) | B6: =IF('Model inputs'!O24="","",'Model inputs'!O24) -> 50 | C6: =IF('Model inputs'!O26="","",'Model inputs'!O26) -> 50 | D6: =IF('Model inputs'!O25="","",'Model inputs'!O25) -> 50
A7: Net cash flow (USD) | B7: ='Cash and runway, month 12 (Main'!B5-'Cash and runway, month 12 (Main'!B6 -> 655.52776 | C7: ='Cash and runway, month 12 (Main'!C5-'Cash and runway, month 12 (Main'!C6 -> 1093.45 | D7: ='Cash and runway, month 12 (Main'!D5-'Cash and runway, month 12 (Main'!D6 -> 255.91145
A8: Ending cash (USD) | B8: ='Cash and runway (monthly)'!L8+'Cash and runway, month 12 (Main'!B7 -> 8275.9599 | C8: ='Model inputs'!M8+'Cash and runway, month 12 (Main'!C7 -> 11089.106 | D8: ='Model inputs'!M7+'Cash and runway, month 12 (Main'!D7 -> 4757.3516
A9: Runway in months (0 = not burning cash) | B9: =IF(IF(IF(ISERROR('Cash and runway, month 12 (Main'!B7<0),'Cash and runway, month 12 (Main'!B7<0,IF('Cash and runway, month 12 (Main'!B7="","",'Cash and runway, month 12 (Main'!B7<0))="",FALSE,IF(ISERROR('Cash and runway, month 12 (Main'!B7<0),'Cash and runway, month 12 (Main'!B7<0,IF('Cash and runway, month 12 (Main'!B7="","",'Cash and runway, month 12 (Main'!B7<0))),'Cash and runway, month 12 (Main'!B8/-'Cash and runway, month 12 (Main'!B7,0) -> 0 | C9: =IF(IF(IF(ISERROR('Cash and runway, month 12 (Main'!C7<0),'Cash and runway, month 12 (Main'!C7<0,IF('Cash and runway, month 12 (Main'!C7="","",'Cash and runway, month 12 (Main'!C7<0))="",FALSE,IF(ISERROR('Cash and runway, month 12 (Main'!C7<0),'Cash and runway, month 12 (Main'!C7<0,IF('Cash and runway, month 12 (Main'!C7="","",'Cash and runway, month 12 (Main'!C7<0))),'Cash and runway, month 12 (Main'!C8/-'Cash and runway, month 12 (Main'!C7,0) -> 0 | D9: =IF(IF(IF(ISERROR('Cash and runway, month 12 (Main'!D7<0),'Cash and runway, month 12 (Main'!D7<0,IF('Cash and runway, month 12 (Main'!D7="","",'Cash and runway, month 12 (Main'!D7<0))="",FALSE,IF(ISERROR('Cash and runway, month 12 (Main'!D7<0),'Cash and runway, month 12 (Main'!D7<0,IF('Cash and runway, month 12 (Main'!D7="","",'Cash and runway, month 12 (Main'!D7<0))),'Cash and runway, month 12 (Main'!D8/-'Cash and runway, month 12 (Main'!D7,0) -> 0

Sheet Cash and runway (monthly)
A1: Cash and runway (monthly)
A2: Cash and runway · Main Scenario
A4: Variable / dimension | B4: 2026-10 | C4: 2026-11 | D4: 2026-12 | E4: 2027-01 | F4: 2027-02 | G4: 2027-03 | H4: 2027-04 | I4: 2027-05 | J4: 2027-06 | K4: 2027-07 | L4: 2027-08 | M4: 2027-09
A5: Gross profit (USD) | B5: =SUM('Model inputs'!C10,'Model inputs'!C11) -> 409.4947 | C5: =SUM('Model inputs'!D10,'Model inputs'!D11) -> 445.84389 | D5: =SUM('Model inputs'!E10,'Model inputs'!E11) -> 479.87065 | E5: =SUM('Model inputs'!F10,'Model inputs'!F11) -> 511.74321 | F5: =SUM('Model inputs'!G10,'Model inputs'!G11) -> 541.61686 | G5: =SUM('Model inputs'!H10,'Model inputs'!H11) -> 569.63499 | H5: =SUM('Model inputs'!I10,'Model inputs'!I11) -> 595.93001 | I5: =SUM('Model inputs'!J10,'Model inputs'!J11) -> 620.62422 | ... M5: =SUM('Model inputs'!N10,'Model inputs'!N11) -> 705.52776
A6: Other fixed costs (USD) | B6: =IF('Model inputs'!O24="","",'Model inputs'!O24) -> 50 | C6: =IF('Model inputs'!O24="","",'Model inputs'!O24) -> 50 | D6: =IF('Model inputs'!O24="","",'Model inputs'!O24) -> 50 | E6: =IF('Model inputs'!O24="","",'Model inputs'!O24) -> 50 | F6: =IF('Model inputs'!O24="","",'Model inputs'!O24) -> 50 | G6: =IF('Model inputs'!O24="","",'Model inputs'!O24) -> 50 | H6: =IF('Model inputs'!O24="","",'Model inputs'!O24) -> 50 | I6: =IF('Model inputs'!O24="","",'Model inputs'!O24) -> 50 | J6: =IF('Model inputs'!O24="","",'Model inputs'!O24) -> 50 | K6: =IF('Model inputs'!O24="","",'Model inputs'!O24) -> 50 | L6: =IF('Model inputs'!O24="","",'Model inputs'!O24) -> 50 | M6: =IF('Model inputs'!O24="","",'Model inputs'!O24) -> 50
A7: Net cash flow (USD) | B7: ='Cash and runway (monthly)'!B5-'Cash and runway (monthly)'!B6 -> 359.4947 | C7: ='Cash and runway (monthly)'!C5-'Cash and runway (monthly)'!C6 -> 395.84389 | D7: ='Cash and runway (monthly)'!D5-'Cash and runway (monthly)'!D6 -> 429.87065 | E7: ='Cash and runway (monthly)'!E5-'Cash and runway (monthly)'!E6 -> 461.74321 | F7: ='Cash and runway (monthly)'!F5-'Cash and runway (monthly)'!F6 -> 491.61686 | G7: ='Cash and runway (monthly)'!G5-'Cash and runway (monthly)'!G6 -> 519.63499 | H7: ='Cash and runway (monthly)'!H5-'Cash and runway (monthly)'!H6 -> 545.93001 | I7: ='Cash and runway (monthly)'!I5-'Cash and runway (monthly)'!I6 -> 570.62422 | ... M7: ='Cash and runway (monthly)'!M5-'Cash and runway (monthly)'!M6 -> 655.52776
A8: Ending cash (USD) | B8: ='Model inputs'!B6+'Cash and runway (monthly)'!B7 -> 2359.4947 | C8: ='Cash and runway (monthly)'!B8+'Cash and runway (monthly)'!C7 -> 2755.3386 | D8: ='Cash and runway (monthly)'!C8+'Cash and runway (monthly)'!D7 -> 3185.2092 | E8: ='Cash and runway (monthly)'!D8+'Cash and runway (monthly)'!E7 -> 3646.9524 | F8: ='Cash and runway (monthly)'!E8+'Cash and runway (monthly)'!F7 -> 4138.5693 | G8: ='Cash and runway (monthly)'!F8+'Cash and runway (monthly)'!G7 -> 4658.2043 | H8: ='Cash and runway (monthly)'!G8+'Cash and runway (monthly)'!H7 -> 5204.1343 | I8: ='Cash and runway (monthly)'!H8+'Cash and runway (monthly)'!I7 -> 5774.7585 | J8: ='Cash and runway (monthly)'!I8+'Cash and runway (monthly)'!J7 -> 6368.5891 | ... M8: ='Cash and runway (monthly)'!L8+'Cash and runway (monthly)'!M7 -> 8275.9599
A9: Runway in months (0 = not burning cash) | B9: =IF(IF(IF(ISERROR('Cash and runway (monthly)'!B7<0),'Cash and runway (monthly)'!B7<0,IF('Cash and runway (monthly)'!B7="","",'Cash and runway (monthly)'!B7<0))="",FALSE,IF(ISERROR('Cash and runway (monthly)'!B7<0),'Cash and runway (monthly)'!B7<0,IF('Cash and runway (monthly)'!B7="","",'Cash and runway (monthly)'!B7<0))),'Cash and runway (monthly)'!B8/-'Cash and runway (monthly)'!B7,0) -> 0 | C9: =IF(IF(IF(ISERROR('Cash and runway (monthly)'!C7<0),'Cash and runway (monthly)'!C7<0,IF('Cash and runway (monthly)'!C7="","",'Cash and runway (monthly)'!C7<0))="",FALSE,IF(ISERROR('Cash and runway (monthly)'!C7<0),'Cash and runway (monthly)'!C7<0,IF('Cash and runway (monthly)'!C7="","",'Cash and runway (monthly)'!C7<0))),'Cash and runway (monthly)'!C8/-'Cash and runway (monthly)'!C7,0) -> 0 | D9: =IF(IF(IF(ISERROR('Cash and runway (monthly)'!D7<0),'Cash and runway (monthly)'!D7<0,IF('Cash and runway (monthly)'!D7="","",'Cash and runway (monthly)'!D7<0))="",FALSE,IF(ISERROR('Cash and runway (monthly)'!D7<0),'Cash and runway (monthly)'!D7<0,IF('Cash and runway (monthly)'!D7="","",'Cash and runway (monthly)'!D7<0))),'Cash and runway (monthly)'!D8/-'Cash and runway (monthly)'!D7,0) -> 0 | E9: =IF(IF(IF(ISERROR('Cash and runway (monthly)'!E7<0),'Cash and runway (monthly)'!E7<0,IF('Cash and runway (monthly)'!E7="","",'Cash and runway (monthly)'!E7<0))="",FALSE,IF(ISERROR('Cash and runway (monthly)'!E7<0),'Cash and runway (monthly)'!E7<0,IF('Cash and runway (monthly)'!E7="","",'Cash and runway (monthly)'!E7<0))),'Cash and runway (monthly)'!E8/-'Cash and runway (monthly)'!E7,0) -> 0 | F9: =IF(IF(IF(ISERROR('Cash and runway (monthly)'!F7<0),'Cash and runway (monthly)'!F7<0,IF('Cash and runway (monthly)'!F7="","",'Cash and runway (monthly)'!F7<0))="",FALSE,IF(ISERROR('Cash and runway (monthly)'!F7<0),'Cash and runway (monthly)'!F7<0,IF('Cash and runway (monthly)'!F7="","",'Cash and runway (monthly)'!F7<0))),'Cash and runway (monthly)'!F8/-'Cash and runway (monthly)'!F7,0) -> 0 | G9: =IF(IF(IF(ISERROR('Cash and runway (monthly)'!G7<0),'Cash and runway (monthly)'!G7<0,IF('Cash and runway (monthly)'!G7="","",'Cash and runway (monthly)'!G7<0))="",FALSE,IF(ISERROR('Cash and runway (monthly)'!G7<0),'Cash and runway (monthly)'!G7<0,IF('Cash and runway (monthly)'!G7="","",'Cash and runway (monthly)'!G7<0))),'Cash and runway (monthly)'!G8/-'Cash and runway (monthly)'!G7,0) -> 0 | H9: =IF(IF(IF(ISERROR('Cash and runway (monthly)'!H7<0),'Cash and runway (monthly)'!H7<0,IF('Cash and runway (monthly)'!H7="","",'Cash and runway (monthly)'!H7<0))="",FALSE,IF(ISERROR('Cash and runway (monthly)'!H7<0),'Cash and runway (monthly)'!H7<0,IF('Cash and runway (monthly)'!H7="","",'Cash and runway (monthly)'!H7<0))),'Cash and runway (monthly)'!H8/-'Cash and runway (monthly)'!H7,0) -> 0 | I9: =IF(IF(IF(ISERROR('Cash and runway (monthly)'!I7<0),'Cash and runway (monthly)'!I7<0,IF('Cash and runway (monthly)'!I7="","",'Cash and runway (monthly)'!I7<0))="",FALSE,IF(ISERROR('Cash and runway (monthly)'!I7<0),'Cash and runway (monthly)'!I7<0,IF('Cash and runway (monthly)'!I7="","",'Cash and runway (monthly)'!I7<0))),'Cash and runway (monthly)'!I8/-'Cash and runway (monthly)'!I7,0) -> 0 | ... M9: =IF(IF(IF(ISERROR('Cash and runway (monthly)'!M7<0),'Cash and runway (monthly)'!M7<0,IF('Cash and runway (monthly)'!M7="","",'Cash and runway (monthly)'!M7<0))="",FALSE,IF(ISERROR('Cash and runway (monthly)'!M7<0),'Cash and runway (monthly)'!M7<0,IF('Cash and runway (monthly)'!M7="","",'Cash and runway (monthly)'!M7<0))),'Cash and runway (monthly)'!M8/-'Cash and runway (monthly)'!M7,0) -> 0

Sheet Model inputs
A1: Model inputs
A2: Integration values are aggregated snapshots; raw source records are not included.
A4: Variables
A5: Variable / segment | B5: 2026-09 | C5: 2026-10 | D5: 2026-11 | E5: 2026-12 | F5: 2027-01 | G5: 2027-02 | H5: 2027-03 | I5: 2027-04 | J5: 2027-05 | K5: 2027-06 | L5: 2027-07 | M5: 2027-08 | N5: 2027-09 | O5: Value
A6: Ending cash (USD) · Main Scenario | B6: =IF('Model inputs'!O45="","",'Model inputs'!O45) -> 2000 | C6: ='Model inputs'!B6+'Model inputs'!C18 -> 2359.4947 | D6: ='Model inputs'!C6+'Model inputs'!D18 -> 2755.3386 | E6: ='Model inputs'!D6+'Model inputs'!E18 -> 3185.2092 | F6: ='Model inputs'!E6+'Model inputs'!F18 -> 3646.9524 | G6: ='Model inputs'!F6+'Model inputs'!G18 -> 4138.5693 | H6: ='Model inputs'!G6+'Model inputs'!H18 -> 4658.2043 | I6: ='Model inputs'!H6+'Model inputs'!I18 -> 5204.1343 | J6: ='Model inputs'!I6+'Model inputs'!J18 -> 5774.7585 | ... N6: ='Model inputs'!M6+'Model inputs'!N18 -> 8275.9599
A7: Ending cash (USD) · Downside | B7: =IF('Model inputs'!O46="","",'Model inputs'!O46) -> 2000 | C7: ='Model inputs'!B7+'Model inputs'!C19 -> 2190.4742 | D7: ='Model inputs'!C7+'Model inputs'!D19 -> 2391.3502 | E7: ='Model inputs'!D7+'Model inputs'!E19 -> 2601.3262 | F7: ='Model inputs'!E7+'Model inputs'!F19 -> 2819.2807 | G7: ='Model inputs'!F7+'Model inputs'!G19 -> 3044.2454 | H7: ='Model inputs'!G7+'Model inputs'!H19 -> 3275.3837 | I7: ='Model inputs'!H7+'Model inputs'!I19 -> 3511.9715 | J7: ='Model inputs'!I7+'Model inputs'!J19 -> 3753.3814 | ... N7: ='Model inputs'!M7+'Model inputs'!N19 -> 4757.3516
A8: Ending cash (USD) · Growth | B8: =IF('Model inputs'!O47="","",'Model inputs'!O47) -> 2000 | C8: ='Model inputs'!B8+'Model inputs'!C20 -> 2345.394 | D8: ='Model inputs'!C8+'Model inputs'!D20 -> 2781.9125 | E8: ='Model inputs'!D8+'Model inputs'!E20 -> 3303.8824 | F8: ='Model inputs'!E8+'Model inputs'!F20 -> 3906.0362 | G8: ='Model inputs'!F8+'Model inputs'!G20 -> 4583.4807 | H8: ='Model inputs'!G8+'Model inputs'!H20 -> 5331.6683 | I8: ='Model inputs'!H8+'Model inputs'!I20 -> 6146.3713 | J8: ='Model inputs'!I8+'Model inputs'!J20 -> 7023.657 | ... N8: ='Model inputs'!M8+'Model inputs'!N20 -> 11089.106
A9: Gross profit (USD) | B9: =SUM('Model inputs'!B10,'Model inputs'!B11) -> 0 | C9: =SUM('Model inputs'!C10,'Model inputs'!C11) -> 409.4947 | D9: =SUM('Model inputs'!D10,'Model inputs'!D11) -> 445.84389 | E9: =SUM('Model inputs'!E10,'Model inputs'!E11) -> 479.87065 | F9: =SUM('Model inputs'!F10,'Model inputs'!F11) -> 511.74321 | G9: =SUM('Model inputs'!G10,'Model inputs'!G11) -> 541.61686 | H9: =SUM('Model inputs'!H10,'Model inputs'!H11) -> 569.63499 | I9: =SUM('Model inputs'!I10,'Model inputs'!I11) -> 595.93001 | ... N9: =SUM('Model inputs'!N10,'Model inputs'!N11) -> 705.52776
A10: Gross profit (USD) > Classroom | B10: =0 -> 0 | C10: ='Model inputs'!C37-'Model inputs'!C28 -> 172.08938 | D10: ='Model inputs'!D37-'Model inputs'!D28 -> 184.00241 | E10: ='Model inputs'!E37-'Model inputs'!E28 -> 195.5051 | F10: ='Model inputs'!F37-'Model inputs'!F28 -> 206.6235 | G10: ='Model inputs'!G37-'Model inputs'!G28 -> 217.37851 | H10: ='Model inputs'!H37-'Model inputs'!H28 -> 227.78766 | I10: ='Model inputs'!I37-'Model inputs'!I28 -> 237.86612 | J10: ='Model inputs'!J37-'Model inputs'!J28 -> 247.62738 | ... N10: ='Model inputs'!N37-'Model inputs'!N28 -> 283.73132
A11: Gross profit (USD) > Household | B11: =0 -> 0 | C11: ='Model inputs'!C38-'Model inputs'!C29 -> 237.40531 | D11: ='Model inputs'!D38-'Model inputs'!D29 -> 261.84148 | E11: ='Model inputs'!E38-'Model inputs'!E29 -> 284.36555 | F11: ='Model inputs'!F38-'Model inputs'!F29 -> 305.11971 | G11: ='Model inputs'!G38-'Model inputs'!G29 -> 324.23834 | H11: ='Model inputs'!H38-'Model inputs'!H29 -> 341.84733 | I11: ='Model inputs'!I38-'Model inputs'!I29 -> 358.06389 | J11: ='Model inputs'!J38-'Model inputs'!J29 -> 372.99684 | ... N11: ='Model inputs'!N38-'Model inputs'!N29 -> 421.79644
A12: Gross profit (USD) | B12: =SUM('Model inputs'!B13,'Model inputs'!B14) -> 0 | C12: =SUM('Model inputs'!C13,'Model inputs'!C14) -> 240.47424 | D12: =SUM('Model inputs'!D13,'Model inputs'!D14) -> 250.87592 | E12: =SUM('Model inputs'!E13,'Model inputs'!E14) -> 259.97609 | F12: =SUM('Model inputs'!F13,'Model inputs'!F14) -> 267.95445 | G12: =SUM('Model inputs'!G13,'Model inputs'!G14) -> 274.96468 | H12: =SUM('Model inputs'!H13,'Model inputs'!H14) -> 281.13828 | I12: =SUM('Model inputs'!I13,'Model inputs'!I14) -> 286.58785 | ... N12: =SUM('Model inputs'!N13,'Model inputs'!N14) -> 305.91145
A13: Gross profit (USD) > Classroom | B13: ='Model inputs'!B10 -> 0 | C13: ='Model inputs'!C40-'Model inputs'!C31 -> 66.849964 | D13: ='Model inputs'!D40-'Model inputs'!D31 -> 69.750873 | E13: ='Model inputs'!E40-'Model inputs'!E31 -> 72.454894 | F13: ='Model inputs'!F40-'Model inputs'!F31 -> 74.979082 | G13: ='Model inputs'!G40-'Model inputs'!G31 -> 77.33806 | H13: ='Model inputs'!H40-'Model inputs'!H31 -> 79.544609 | I13: ='Model inputs'!I40-'Model inputs'!I31 -> 81.610057 | J13: ='Model inputs'!J40-'Model inputs'!J31 -> 83.544561 | ... N13: ='Model inputs'!N40-'Model inputs'!N31 -> 90.145049
A14: Gross profit (USD) > Household | B14: ='Model inputs'!B11 -> 0 | C14: ='Model inputs'!C41-'Model inputs'!C32 -> 173.62428 | D14: ='Model inputs'!D41-'Model inputs'!D32 -> 181.12505 | E14: ='Model inputs'!E41-'Model inputs'!E32 -> 187.52119 | F14: ='Model inputs'!F41-'Model inputs'!F32 -> 192.97537 | G14: ='Model inputs'!G41-'Model inputs'!G32 -> 197.62662 | H14: ='Model inputs'!H41-'Model inputs'!H32 -> 201.59367 | I14: ='Model inputs'!I41-'Model inputs'!I32 -> 204.97779 | J14: ='Model inputs'!J41-'Model inputs'!J32 -> 207.86531 | ... N14: ='Model inputs'!N41-'Model inputs'!N32 -> 215.7664
A15: Gross profit (USD) | B15: =SUM('Model inputs'!B16,'Model inputs'!B17) -> 0 | C15: =SUM('Model inputs'!C16,'Model inputs'!C17) -> 395.39405 | D15: =SUM('Model inputs'!D16,'Model inputs'!D17) -> 486.51844 | E15: =SUM('Model inputs'!E16,'Model inputs'!E17) -> 571.96992 | F15: =SUM('Model inputs'!F16,'Model inputs'!F17) -> 652.1538 | G15: =SUM('Model inputs'!G16,'Model inputs'!G17) -> 727.44445 | H15: =SUM('Model inputs'!H16,'Model inputs'!H17) -> 798.18766 | I15: =SUM('Model inputs'!I16,'Model inputs'!I17) -> 864.70297 | ... N15: =SUM('Model inputs'!N16,'Model inputs'!N17) -> 1143.45
A16: Gross profit (USD) > Classroom | B16: ='Model inputs'!B10 -> 0 | C16: ='Model inputs'!C43-'Model inputs'!C34 -> 144.33904 | D16: ='Model inputs'!D43-'Model inputs'!D34 -> 176.76625 | E16: ='Model inputs'!E43-'Model inputs'!E34 -> 208.14712 | F16: ='Model inputs'!F43-'Model inputs'!F34 -> 238.54454 | G16: ='Model inputs'!G43-'Model inputs'!G34 -> 268.0037 | H16: ='Model inputs'!H43-'Model inputs'!H34 -> 296.56141 | I16: ='Model inputs'!I43-'Model inputs'!I34 -> 324.2499 | J16: ='Model inputs'!J43-'Model inputs'!J34 -> 351.09856 | ... N16: ='Model inputs'!N43-'Model inputs'!N34 -> 450.62206
A17: Gross profit (USD) > Household | B17: ='Model inputs'!B11 -> 0 | C17: ='Model inputs'!C44-'Model inputs'!C35 -> 251.05501 | D17: ='Model inputs'!D44-'Model inputs'!D35 -> 309.75219 | E17: ='Model inputs'!E44-'Model inputs'!E35 -> 363.8228 | F17: ='Model inputs'!F44-'Model inputs'!F35 -> 413.60926 | G17: ='Model inputs'!G44-'Model inputs'!G35 -> 459.44075 | H17: ='Model inputs'!H44-'Model inputs'!H35 -> 501.62625 | I17: ='Model inputs'!I44-'Model inputs'!I35 -> 540.45307 | J17: ='Model inputs'!J44-'Model inputs'!J35 -> 576.18711 | ... N17: ='Model inputs'!N44-'Model inputs'!N35 -> 692.82791
A18: Net cash flow (USD) · Main Scenario | B18: 0 | C18: ='Model inputs'!C9-'Model inputs'!C21 -> 359.4947 | D18: ='Model inputs'!D9-'Model inputs'!D21 -> 395.84389 | E18: ='Model inputs'!E9-'Model inputs'!E21 -> 429.87065 | F18: ='Model inputs'!F9-'Model inputs'!F21 -> 461.74321 | G18: ='Model inputs'!G9-'Model inputs'!G21 -> 491.61686 | H18: ='Model inputs'!H9-'Model inputs'!H21 -> 519.63499 | I18: ='Model inputs'!I9-'Model inputs'!I21 -> 545.93001 | J18: ='Model inputs'!J9-'Model inputs'!J21 -> 570.62422 | ... N18: ='Model inputs'!N9-'Model inputs'!N21 -> 655.52776
A19: Net cash flow (USD) · Downside | B19: 0 | C19: ='Model inputs'!C12-'Model inputs'!C22 -> 190.47424 | D19: ='Model inputs'!D12-'Model inputs'!D22 -> 200.87592 | E19: ='Model inputs'!E12-'Model inputs'!E22 -> 209.97609 | F19: ='Model inputs'!F12-'Model inputs'!F22 -> 217.95445 | G19: ='Model inputs'!G12-'Model inputs'!G22 -> 224.96468 | H19: ='Model inputs'!H12-'Model inputs'!H22 -> 231.13828 | I19: ='Model inputs'!I12-'Model inputs'!I22 -> 236.58785 | J19: ='Model inputs'!J12-'Model inputs'!J22 -> 241.40988 | ... N19: ='Model inputs'!N12-'Model inputs'!N22 -> 255.91145
A20: Net cash flow (USD) · Growth | B20: 0 | C20: ='Model inputs'!C15-'Model inputs'!C23 -> 345.39405 | D20: ='Model inputs'!D15-'Model inputs'!D23 -> 436.51844 | E20: ='Model inputs'!E15-'Model inputs'!E23 -> 521.96992 | F20: ='Model inputs'!F15-'Model inputs'!F23 -> 602.1538 | G20: ='Model inputs'!G15-'Model inputs'!G23 -> 677.44445 | H20: ='Model inputs'!H15-'Model inputs'!H23 -> 748.18766 | I20: ='Model inputs'!I15-'Model inputs'!I23 -> 814.70297 | J20: ='Model inputs'!J15-'Model inputs'!J23 -> 877.28566 | ... N20: ='Model inputs'!N15-'Model inputs'!N23 -> 1093.45
A21: Other fixed costs (USD) · Main Scenario | B21: 0 | C21: =IF('Model inputs'!O24="","",'Model inputs'!O24) -> 50 | D21: =IF('Model inputs'!O24="","",'Model inputs'!O24) -> 50 | E21: =IF('Model inputs'!O24="","",'Model inputs'!O24) -> 50 | F21: =IF('Model inputs'!O24="","",'Model inputs'!O24) -> 50 | G21: =IF('Model inputs'!O24="","",'Model inputs'!O24) -> 50 | H21: =IF('Model inputs'!O24="","",'Model inputs'!O24) -> 50 | I21: =IF('Model inputs'!O24="","",'Model inputs'!O24) -> 50 | J21: =IF('Model inputs'!O24="","",'Model inputs'!O24) -> 50 | K21: =IF('Model inputs'!O24="","",'Model inputs'!O24) -> 50 | L21: =IF('Model inputs'!O24="","",'Model inputs'!O24) -> 50 | M21: =IF('Model inputs'!O24="","",'Model inputs'!O24) -> 50 | N21: =IF('Model inputs'!O24="","",'Model inputs'!O24) -> 50
A22: Other fixed costs (USD) · Downside | B22: 0 | C22: =IF('Model inputs'!O25="","",'Model inputs'!O25) -> 50 | D22: =IF('Model inputs'!O25="","",'Model inputs'!O25) -> 50 | E22: =IF('Model inputs'!O25="","",'Model inputs'!O25) -> 50 | F22: =IF('Model inputs'!O25="","",'Model inputs'!O25) -> 50 | G22: =IF('Model inputs'!O25="","",'Model inputs'!O25) -> 50 | H22: =IF('Model inputs'!O25="","",'Model inputs'!O25) -> 50 | I22: =IF('Model inputs'!O25="","",'Model inputs'!O25) -> 50 | J22: =IF('Model inputs'!O25="","",'Model inputs'!O25) -> 50 | K22: =IF('Model inputs'!O25="","",'Model inputs'!O25) -> 50 | L22: =IF('Model inputs'!O25="","",'Model inputs'!O25) -> 50 | M22: =IF('Model inputs'!O25="","",'Model inputs'!O25) -> 50 | N22: =IF('Model inputs'!O25="","",'Model inputs'!O25) -> 50
A23: Other fixed costs (USD) · Growth | B23: 0 | C23: =IF('Model inputs'!O26="","",'Model inputs'!O26) -> 50 | D23: =IF('Model inputs'!O26="","",'Model inputs'!O26) -> 50 | E23: =IF('Model inputs'!O26="","",'Model inputs'!O26) -> 50 | F23: =IF('Model inputs'!O26="","",'Model inputs'!O26) -> 50 | G23: =IF('Model inputs'!O26="","",'Model inputs'!O26) -> 50 | H23: =IF('Model inputs'!O26="","",'Model inputs'!O26) -> 50 | I23: =IF('Model inputs'!O26="","",'Model inputs'!O26) -> 50 | J23: =IF('Model inputs'!O26="","",'Model inputs'!O26) -> 50 | K23: =IF('Model inputs'!O26="","",'Model inputs'!O26) -> 50 | L23: =IF('Model inputs'!O26="","",'Model inputs'!O26) -> 50 | M23: =IF('Model inputs'!O26="","",'Model inputs'!O26) -> 50 | N23: =IF('Model inputs'!O26="","",'Model inputs'!O26) -> 50
A24: Other fixed costs per month (USD, assumed) · Main Scenario | O24: =50 -> 50
A25: Other fixed costs per month (USD, assumed) · Downside | O25: ='Model inputs'!O24 -> 50
A26: Other fixed costs per month (USD, assumed) · Growth | O26: ='Model inputs'!O24 -> 50
A27: Infra and inference (USD) | B27: =SUM('Model inputs'!B28,'Model inputs'!B29) -> 0 | C27: =SUM('Model inputs'!C28,'Model inputs'!C29) -> 213.9573 | D27: =SUM('Model inputs'!D28,'Model inputs'!D29) -> 228.16695 | E27: =SUM('Model inputs'!E28,'Model inputs'!E29) -> 241.63887 | F27: =SUM('Model inputs'!F28,'Model inputs'!F29) -> 254.42012 | G27: =SUM('Model inputs'!G28,'Model inputs'!G29) -> 266.55433 | H27: =SUM('Model inputs'!H28,'Model inputs'!H29) -> 278.082 | I27: =SUM('Model inputs'!I28,'Model inputs'!I29) -> 289.04074 | ... N27: =SUM('Model inputs'!N28,'Model inputs'!N29) -> 336.43963
A28: Infra and inference (USD) > Classroom | B28: =0 -> 0 | C28: ='Model inputs'!C58+'Model inputs'!C49 -> 138.21062 | D28: ='Model inputs'!D58+'Model inputs'!D49 -> 145.98859 | E28: ='Model inputs'!E58+'Model inputs'!E49 -> 153.58617 | F28: ='Model inputs'!F58+'Model inputs'!F49 -> 160.99503 | G28: ='Model inputs'!G58+'Model inputs'!G49 -> 168.21146 | H28: ='Model inputs'!H58+'Model inputs'!H49 -> 175.23462 | I28: ='Model inputs'!I58+'Model inputs'!I49 -> 182.06549 | J28: ='Model inputs'!J58+'Model inputs'!J49 -> 188.70628 | ... N28: ='Model inputs'!N58+'Model inputs'!N49 -> 213.43535
A29: Infra and inference (USD) > Household | B29: =0 -> 0 | C29: ='Model inputs'!C59+'Model inputs'!C50 -> 75.746686 | D29: ='Model inputs'!D59+'Model inputs'!D50 -> 82.178358 | E29: ='Model inputs'!E59+'Model inputs'!E50 -> 88.052704 | F29: ='Model inputs'!F59+'Model inputs'!F50 -> 93.425087 | G29: ='Model inputs'!G59+'Model inputs'!G50 -> 98.342866 | H29: ='Model inputs'!H59+'Model inputs'!H50 -> 102.84738 | I29: ='Model inputs'!I59+'Model inputs'!I50 -> 106.97524 | J29: ='Model inputs'!J59+'Model inputs'!J50 -> 110.75917 | ... N29: ='Model inputs'!N59+'Model inputs'!N50 -> 123.00428
A30: Infra and inference (USD) | B30: =SUM('Model inputs'!B31,'Model inputs'!B32) -> 0 | C30: =SUM('Model inputs'!C31,'Model inputs'!C32) -> 354.70576 | D30: =SUM('Model inputs'!D31,'Model inputs'!D32) -> 367.09108 | E30: =SUM('Model inputs'!E31,'Model inputs'!E32) -> 378.34122 | F30: =SUM('Model inputs'!F31,'Model inputs'!F32) -> 388.5831 | G30: =SUM('Model inputs'!G31,'Model inputs'!G32) -> 397.92721 | H30: =SUM('Model inputs'!H31,'Model inputs'!H32) -> 406.4699 | I30: =SUM('Model inputs'!I31,'Model inputs'!I32) -> 414.29536 | ... N30: =SUM('Model inputs'!N31,'Model inputs'!N32) -> 444.9537
A31: Infra and inference (USD) > Classroom | B31: ='Model inputs'!B28 -> 0 | C31: ='Model inputs'!C61+'Model inputs'!C52 -> 234.75004 | D31: ='Model inputs'!D61+'Model inputs'!D52 -> 242.75313 | E31: ='Model inputs'!E61+'Model inputs'!E52 -> 250.29887 | F31: ='Model inputs'!F61+'Model inputs'!F52 -> 257.40945 | G31: ='Model inputs'!G61+'Model inputs'!G52 -> 264.10716 | H31: ='Model inputs'!H61+'Model inputs'!H52 -> 270.4139 | I31: ='Model inputs'!I61+'Model inputs'!I52 -> 276.35094 | J31: ='Model inputs'!J61+'Model inputs'!J52 -> 281.93878 | ... N31: ='Model inputs'!N61+'Model inputs'!N52 -> 301.17702
A32: Infra and inference (USD) > Household | B32: ='Model inputs'!B29 -> 0 | C32: ='Model inputs'!C62+'Model inputs'!C53 -> 119.95572 | D32: ='Model inputs'!D62+'Model inputs'!D53 -> 124.33795 | E32: ='Model inputs'!E62+'Model inputs'!E53 -> 128.04236 | F32: ='Model inputs'!F62+'Model inputs'!F53 -> 131.17365 | G32: ='Model inputs'!G62+'Model inputs'!G53 -> 133.82005 | H32: ='Model inputs'!H62+'Model inputs'!H53 -> 136.056 | I32: ='Model inputs'!I62+'Model inputs'!I53 -> 137.94442 | J32: ='Model inputs'!J62+'Model inputs'!J53 -> 139.53857 | ... N32: ='Model inputs'!N62+'Model inputs'!N53 -> 143.77667
A33: Infra and inference (USD) | B33: =SUM('Model inputs'!B34,'Model inputs'!B35) -> 0 | C33: =SUM('Model inputs'!C34,'Model inputs'!C35) -> 341.97795 | D33: =SUM('Model inputs'!D34,'Model inputs'!D35) -> 409.1188 | E33: =SUM('Model inputs'!E34,'Model inputs'!E35) -> 473.06889 | F33: =SUM('Model inputs'!F34,'Model inputs'!F35) -> 534.01808 | G33: =SUM('Model inputs'!G34,'Model inputs'!G35) -> 592.14297 | H33: =SUM('Model inputs'!H34,'Model inputs'!H35) -> 647.60797 | I33: =SUM('Model inputs'!I34,'Model inputs'!I35) -> 700.56616 | ... N33: =SUM('Model inputs'!N34,'Model inputs'!N35) -> 932.42337
A34: Infra and inference (USD) > Classroom | B34: ='Model inputs'!B28 -> 0 | C34: ='Model inputs'!C64+'Model inputs'!C55 -> 223.96096 | D34: ='Model inputs'!D64+'Model inputs'!D55 -> 267.48475 | E34: ='Model inputs'!E64+'Model inputs'!E55 -> 309.77635 | F34: ='Model inputs'!F64+'Model inputs'!F55 -> 350.84122 | G34: ='Model inputs'!G64+'Model inputs'!G55 -> 390.70049 | H34: ='Model inputs'!H64+'Model inputs'!H55 -> 429.38166 | I34: ='Model inputs'!I64+'Model inputs'!I55 -> 466.91487 | J34: ='Model inputs'!J64+'Model inputs'!J55 -> 503.33127 | ... N34: ='Model inputs'!N64+'Model inputs'!N55 -> 638.44938
A35: Infra and inference (USD) > Household | B35: ='Model inputs'!B29 -> 0 | C35: ='Model inputs'!C65+'Model inputs'!C56 -> 118.01699 | D35: ='Model inputs'!D65+'Model inputs'!D56 -> 141.63405 | E35: ='Model inputs'!E65+'Model inputs'!E56 -> 163.29254 | F35: ='Model inputs'!F65+'Model inputs'!F56 -> 183.17685 | G35: ='Model inputs'!G65+'Model inputs'!G56 -> 201.44248 | H35: ='Model inputs'!H65+'Model inputs'!H56 -> 218.22631 | I35: ='Model inputs'!I65+'Model inputs'!I56 -> 233.65129 | J35: ='Model inputs'!J65+'Model inputs'!J56 -> 247.82891 | ... N35: ='Model inputs'!N65+'Model inputs'!N56 -> 293.974
A36: Revenue (USD) | B36: =SUM('Model inputs'!B37,'Model inputs'!B38) -> 0 | C36: =SUM('Model inputs'!C37,'Model inputs'!C38) -> 623.452 | D36: =SUM('Model inputs'!D37,'Model inputs'!D38) -> 674.01084 | E36: =SUM('Model inputs'!E37,'Model inputs'!E38) -> 721.50952 | F36: =SUM('Model inputs'!F37,'Model inputs'!F38) -> 766.16332 | G36: =SUM('Model inputs'!G37,'Model inputs'!G38) -> 808.17119 | H36: =SUM('Model inputs'!H37,'Model inputs'!H38) -> 847.71699 | I36: =SUM('Model inputs'!I37,'Model inputs'!I38) -> 884.97074 | ... N36: =SUM('Model inputs'!N37,'Model inputs'!N38) -> 1041.9674
A37: Revenue (USD) > Classroom | B37: =0 -> 0 | C37: ='Model inputs'!C76+'Model inputs'!C67 -> 310.3 | D37: ='Model inputs'!D76+'Model inputs'!D67 -> 329.991 | E37: ='Model inputs'!E76+'Model inputs'!E67 -> 349.09127 | F37: ='Model inputs'!F76+'Model inputs'!F67 -> 367.61853 | G37: ='Model inputs'!G76+'Model inputs'!G67 -> 385.58998 | H37: ='Model inputs'!H76+'Model inputs'!H67 -> 403.02228 | I37: ='Model inputs'!I76+'Model inputs'!I67 -> 419.93161 | J37: ='Model inputs'!J76+'Model inputs'!J67 -> 436.33366 | ... N37: ='Model inputs'!N76+'Model inputs'!N67 -> 497.16667
A38: Revenue (USD) > Household | B38: =0 -> 0 | C38: ='Model inputs'!C77+'Model inputs'!C68 -> 313.152 | D38: ='Model inputs'!D77+'Model inputs'!D68 -> 344.01984 | E38: ='Model inputs'!E77+'Model inputs'!E68 -> 372.41825 | F38: ='Model inputs'!F77+'Model inputs'!F68 -> 398.54479 | G38: ='Model inputs'!G77+'Model inputs'!G68 -> 422.58121 | H38: ='Model inputs'!H77+'Model inputs'!H68 -> 444.69471 | I38: ='Model inputs'!I77+'Model inputs'!I68 -> 465.03914 | J38: ='Model inputs'!J77+'Model inputs'!J68 -> 483.756 | ... N38: ='Model inputs'!N77+'Model inputs'!N68 -> 544.80072
A39: Revenue (USD) | B39: =SUM('Model inputs'!B40,'Model inputs'!B41) -> 0 | C39: =SUM('Model inputs'!C40,'Model inputs'!C41) -> 595.18 | D39: =SUM('Model inputs'!D40,'Model inputs'!D41) -> 617.967 | E39: =SUM('Model inputs'!E40,'Model inputs'!E41) -> 638.31731 | F39: =SUM('Model inputs'!F40,'Model inputs'!F41) -> 656.53755 | G39: =SUM('Model inputs'!G40,'Model inputs'!G41) -> 672.89189 | H39: =SUM('Model inputs'!H40,'Model inputs'!H41) -> 687.60817 | I39: =SUM('Model inputs'!I40,'Model inputs'!I41) -> 700.88321 | ... N39: =SUM('Model inputs'!N40,'Model inputs'!N41) -> 750.86514
A40: Revenue (USD) > Classroom | B40: ='Model inputs'!B37 -> 0 | C40: ='Model inputs'!C79+'Model inputs'!C70 -> 301.6 | D40: ='Model inputs'!D79+'Model inputs'!D70 -> 312.504 | E40: ='Model inputs'!E79+'Model inputs'!E70 -> 322.75376 | F40: ='Model inputs'!F79+'Model inputs'!F70 -> 332.38853 | G40: ='Model inputs'!G79+'Model inputs'!G70 -> 341.44522 | H40: ='Model inputs'!H79+'Model inputs'!H70 -> 349.95851 | I40: ='Model inputs'!I79+'Model inputs'!I70 -> 357.961 | J40: ='Model inputs'!J79+'Model inputs'!J70 -> 365.48334 | ... N40: ='Model inputs'!N79+'Model inputs'!N70 -> 391.32207
A41: Revenue (USD) > Household | B41: ='Model inputs'!B38 -> 0 | C41: ='Model inputs'!C80+'Model inputs'!C71 -> 293.58 | D41: ='Model inputs'!D80+'Model inputs'!D71 -> 305.463 | E41: ='Model inputs'!E80+'Model inputs'!E71 -> 315.56355 | F41: ='Model inputs'!F80+'Model inputs'!F71 -> 324.14902 | G41: ='Model inputs'!G80+'Model inputs'!G71 -> 331.44666 | H41: ='Model inputs'!H80+'Model inputs'!H71 -> 337.64967 | I41: ='Model inputs'!I80+'Model inputs'!I71 -> 342.92222 | J41: ='Model inputs'!J80+'Model inputs'!J71 -> 347.40388 | ... N41: ='Model inputs'!N80+'Model inputs'!N71 -> 359.54307
A42: Revenue (USD) | B42: =SUM('Model inputs'!B43,'Model inputs'!B44) -> 0 | C42: =SUM('Model inputs'!C43,'Model inputs'!C44) -> 737.372 | D42: =SUM('Model inputs'!D43,'Model inputs'!D44) -> 895.63724 | E42: =SUM('Model inputs'!E43,'Model inputs'!E44) -> 1045.0388 | F42: =SUM('Model inputs'!F43,'Model inputs'!F44) -> 1186.1719 | G42: =SUM('Model inputs'!G43,'Model inputs'!G44) -> 1319.5874 | H42: =SUM('Model inputs'!H43,'Model inputs'!H44) -> 1445.7956 | I42: =SUM('Model inputs'!I43,'Model inputs'!I44) -> 1565.2691 | ... N42: =SUM('Model inputs'!N43,'Model inputs'!N44) -> 2075.8733
A43: Revenue (USD) > Classroom | B43: ='Model inputs'!B37 -> 0 | C43: ='Model inputs'!C82+'Model inputs'!C73 -> 368.3 | D43: ='Model inputs'!D82+'Model inputs'!D73 -> 444.251 | E43: ='Model inputs'!E82+'Model inputs'!E73 -> 517.92347 | F43: ='Model inputs'!F82+'Model inputs'!F73 -> 589.38577 | G43: ='Model inputs'!G82+'Model inputs'!G73 -> 658.70419 | H43: ='Model inputs'!H82+'Model inputs'!H73 -> 725.94307 | I43: ='Model inputs'!I82+'Model inputs'!I73 -> 791.16478 | J43: ='Model inputs'!J82+'Model inputs'!J73 -> 854.42983 | ... N43: ='Model inputs'!N82+'Model inputs'!N73 -> 1089.0714
A44: Revenue (USD) > Household | B44: ='Model inputs'!B38 -> 0 | C44: ='Model inputs'!C83+'Model inputs'!C74 -> 369.072 | D44: ='Model inputs'!D83+'Model inputs'!D74 -> 451.38624 | E44: ='Model inputs'!E83+'Model inputs'!E74 -> 527.11534 | F44: ='Model inputs'!F83+'Model inputs'!F74 -> 596.78611 | G44: ='Model inputs'!G83+'Model inputs'!G74 -> 660.88322 | H44: ='Model inputs'!H83+'Model inputs'!H74 -> 719.85257 | I44: ='Model inputs'!I83+'Model inputs'!I74 -> 774.10436 | J44: ='Model inputs'!J83+'Model inputs'!J74 -> 824.01601 | ... N44: ='Model inputs'!N83+'Model inputs'!N74 -> 986.80191
A45: Starting cash (USD, assumed) · Main Scenario | O45: =2000 -> 2000
A46: Starting cash (USD, assumed) · Downside | O46: ='Model inputs'!O45 -> 2000
A47: Starting cash (USD, assumed) · Growth | O47: ='Model inputs'!O45 -> 2000
A48: Hosting and neatlogs allocated by revenue (USD) | B48: =SUM('Model inputs'!B49,'Model inputs'!B50) -> 0 | C48: =SUM('Model inputs'!C49,'Model inputs'!C50) -> 25 | D48: =SUM('Model inputs'!D49,'Model inputs'!D50) -> 25 | E48: =SUM('Model inputs'!E49,'Model inputs'!E50) -> 25 | F48: =SUM('Model inputs'!F49,'Model inputs'!F50) -> 25 | G48: =SUM('Model inputs'!G49,'Model inputs'!G50) -> 25 | H48: =SUM('Model inputs'!H49,'Model inputs'!H50) -> 25 | I48: =SUM('Model inputs'!I49,'Model inputs'!I50) -> 25 | ... N48: =SUM('Model inputs'!N49,'Model inputs'!N50) -> 25
A49: Hosting and neatlogs allocated by revenue (USD) > Classroom | B49: =0 -> 0 | C49: =('Model inputs'!O96+'Model inputs'!C99)*IFERROR('Model inputs'!C37/SUM('Model inputs'!C37,'Model inputs'!C38),0) -> 12.442818 | D49: =('Model inputs'!O96+'Model inputs'!D99)*IFERROR('Model inputs'!D37/SUM('Model inputs'!D37,'Model inputs'!D38),0) -> 12.239825 | E49: =('Model inputs'!O96+'Model inputs'!E99)*IFERROR('Model inputs'!E37/SUM('Model inputs'!E37,'Model inputs'!E38),0) -> 12.095865 | F49: =('Model inputs'!O96+'Model inputs'!F99)*IFERROR('Model inputs'!F37/SUM('Model inputs'!F37,'Model inputs'!F38),0) -> 11.995436 | G49: =('Model inputs'!O96+'Model inputs'!G99)*IFERROR('Model inputs'!G37/SUM('Model inputs'!G37,'Model inputs'!G38),0) -> 11.927856 | H49: =('Model inputs'!O96+'Model inputs'!H99)*IFERROR('Model inputs'!H37/SUM('Model inputs'!H37,'Model inputs'!H38),0) -> 11.88552 | I49: =('Model inputs'!O96+'Model inputs'!I99)*IFERROR('Model inputs'!I37/SUM('Model inputs'!I37,'Model inputs'!I38),0) -> 11.862867 | J49: =('Model inputs'!O96+'Model inputs'!J99)*IFERROR('Model inputs'!J37/SUM('Model inputs'!J37,'Model inputs'!J38),0) -> 11.855737 | K49: =('Model inputs'!O96+'Model inputs'!K99)*IFERROR('Model inputs'!K37/SUM('Model inputs'!K37,'Model inputs'!K38),0) -> 11.860957 | L49: =('Model inputs'!O96+'Model inputs'!L99)*IFERROR('Model inputs'!L37/SUM('Model inputs'!L37,'Model inputs'!L38),0) -> 11.876061 | M49: =('Model inputs'!O96+'Model inputs'!M99)*IFERROR('Model inputs'!M37/SUM('Model inputs'!M37,'Model inputs'!M38),0) -> 11.89911 | N49: =('Model inputs'!O96+'Model inputs'!N99)*IFERROR('Model inputs'!N37/SUM('Model inputs'!N37,'Model inputs'!N38),0) -> 11.928556
A50: Hosting and neatlogs allocated by revenue (USD) > Household | B50: =0 -> 0 | C50: =('Model inputs'!O96+'Model inputs'!C99)*IFERROR('Model inputs'!C38/SUM('Model inputs'!C37,'Model inputs'!C38),0) -> 12.557182 | D50: =('Model inputs'!O96+'Model inputs'!D99)*IFERROR('Model inputs'!D38/SUM('Model inputs'!D37,'Model inputs'!D38),0) -> 12.760175 | E50: =('Model inputs'!O96+'Model inputs'!E99)*IFERROR('Model inputs'!E38/SUM('Model inputs'!E37,'Model inputs'!E38),0) -> 12.904135 | F50: =('Model inputs'!O96+'Model inputs'!F99)*IFERROR('Model inputs'!F38/SUM('Model inputs'!F37,'Model inputs'!F38),0) -> 13.004564 | G50: =('Model inputs'!O96+'Model inputs'!G99)*IFERROR('Model inputs'!G38/SUM('Model inputs'!G37,'Model inputs'!G38),0) -> 13.072144 | H50: =('Model inputs'!O96+'Model inputs'!H99)*IFERROR('Model inputs'!H38/SUM('Model inputs'!H37,'Model inputs'!H38),0) -> 13.11448 | I50: =('Model inputs'!O96+'Model inputs'!I99)*IFERROR('Model inputs'!I38/SUM('Model inputs'!I37,'Model inputs'!I38),0) -> 13.137133 | J50: =('Model inputs'!O96+'Model inputs'!J99)*IFERROR('Model inputs'!J38/SUM('Model inputs'!J37,'Model inputs'!J38),0) -> 13.144263 | K50: =('Model inputs'!O96+'Model inputs'!K99)*IFERROR('Model inputs'!K38/SUM('Model inputs'!K37,'Model inputs'!K38),0) -> 13.139043 | L50: =('Model inputs'!O96+'Model inputs'!L99)*IFERROR('Model inputs'!L38/SUM('Model inputs'!L37,'Model inputs'!L38),0) -> 13.123939 | M50: =('Model inputs'!O96+'Model inputs'!M99)*IFERROR('Model inputs'!M38/SUM('Model inputs'!M37,'Model inputs'!M38),0) -> 13.10089 | N50: =('Model inputs'!O96+'Model inputs'!N99)*IFERROR('Model inputs'!N38/SUM('Model inputs'!N37,'Model inputs'!N38),0) -> 13.071444
A51: Hosting and neatlogs allocated by revenue (USD) | B51: =SUM('Model inputs'!B52,'Model inputs'!B53) -> 0 | C51: =SUM('Model inputs'!C52,'Model inputs'!C53) -> 25 | D51: =SUM('Model inputs'!D52,'Model inputs'!D53) -> 25 | E51: =SUM('Model inputs'!E52,'Model inputs'!E53) -> 25 | F51: =SUM('Model inputs'!F52,'Model inputs'!F53) -> 25 | G51: =SUM('Model inputs'!G52,'Model inputs'!G53) -> 25 | H51: =SUM('Model inputs'!H52,'Model inputs'!H53) -> 25 | I51: =SUM('Model inputs'!I52,'Model inputs'!I53) -> 25 | ... N51: =SUM('Model inputs'!N52,'Model inputs'!N53) -> 25
A52: Hosting and neatlogs allocated by revenue (USD) > Classroom | B52: ='Model inputs'!B49 -> 0 | C52: =('Model inputs'!O97+'Model inputs'!C100)*IFERROR('Model inputs'!C40/SUM('Model inputs'!C40,'Model inputs'!C41),0) -> 12.668436 | D52: =('Model inputs'!O97+'Model inputs'!D100)*IFERROR('Model inputs'!D40/SUM('Model inputs'!D40,'Model inputs'!D41),0) -> 12.642423 | E52: =('Model inputs'!O97+'Model inputs'!E100)*IFERROR('Model inputs'!E40/SUM('Model inputs'!E40,'Model inputs'!E41),0) -> 12.640804 | F52: =('Model inputs'!O97+'Model inputs'!F100)*IFERROR('Model inputs'!F40/SUM('Model inputs'!F40,'Model inputs'!F41),0) -> 12.656874 | G52: =('Model inputs'!O97+'Model inputs'!G100)*IFERROR('Model inputs'!G40/SUM('Model inputs'!G40,'Model inputs'!G41),0) -> 12.685739 | H52: =('Model inputs'!O97+'Model inputs'!H100)*IFERROR('Model inputs'!H40/SUM('Model inputs'!H40,'Model inputs'!H41),0) -> 12.723762 | I52: =('Model inputs'!O97+'Model inputs'!I100)*IFERROR('Model inputs'!I40/SUM('Model inputs'!I40,'Model inputs'!I41),0) -> 12.768211 | J52: =('Model inputs'!O97+'Model inputs'!J100)*IFERROR('Model inputs'!J40/SUM('Model inputs'!J40,'Model inputs'!J41),0) -> 12.817011 | K52: =('Model inputs'!O97+'Model inputs'!K100)*IFERROR('Model inputs'!K40/SUM('Model inputs'!K40,'Model inputs'!K41),0) -> 12.868575 | L52: =('Model inputs'!O97+'Model inputs'!L100)*IFERROR('Model inputs'!L40/SUM('Model inputs'!L40,'Model inputs'!L41),0) -> 12.921688 | M52: =('Model inputs'!O97+'Model inputs'!M100)*IFERROR('Model inputs'!M40/SUM('Model inputs'!M40,'Model inputs'!M41),0) -> 12.975414 | N52: =('Model inputs'!O97+'Model inputs'!N100)*IFERROR('Model inputs'!N40/SUM('Model inputs'!N40,'Model inputs'!N41),0) -> 13.02904
A53: Hosting and neatlogs allocated by revenue (USD) > Household | B53: ='Model inputs'!B50 -> 0 | C53: =('Model inputs'!O97+'Model inputs'!C100)*IFERROR('Model inputs'!C41/SUM('Model inputs'!C40,'Model inputs'!C41),0) -> 12.331564 | D53: =('Model inputs'!O97+'Model inputs'!D100)*IFERROR('Model inputs'!D41/SUM('Model inputs'!D40,'Model inputs'!D41),0) -> 12.357577 | E53: =('Model inputs'!O97+'Model inputs'!E100)*IFERROR('Model inputs'!E41/SUM('Model inputs'!E40,'Model inputs'!E41),0) -> 12.359196 | F53: =('Model inputs'!O97+'Model inputs'!F100)*IFERROR('Model inputs'!F41/SUM('Model inputs'!F40,'Model inputs'!F41),0) -> 12.343126 | G53: =('Model inputs'!O97+'Model inputs'!G100)*IFERROR('Model inputs'!G41/SUM('Model inputs'!G40,'Model inputs'!G41),0) -> 12.314261 | H53: =('Model inputs'!O97+'Model inputs'!H100)*IFERROR('Model inputs'!H41/SUM('Model inputs'!H40,'Model inputs'!H41),0) -> 12.276238 | I53: =('Model inputs'!O97+'Model inputs'!I100)*IFERROR('Model inputs'!I41/SUM('Model inputs'!I40,'Model inputs'!I41),0) -> 12.231789 | J53: =('Model inputs'!O97+'Model inputs'!J100)*IFERROR('Model inputs'!J41/SUM('Model inputs'!J40,'Model inputs'!J41),0) -> 12.182989 | K53: =('Model inputs'!O97+'Model inputs'!K100)*IFERROR('Model inputs'!K41/SUM('Model inputs'!K40,'Model inputs'!K41),0) -> 12.131425 | L53: =('Model inputs'!O97+'Model inputs'!L100)*IFERROR('Model inputs'!L41/SUM('Model inputs'!L40,'Model inputs'!L41),0) -> 12.078312 | M53: =('Model inputs'!O97+'Model inputs'!M100)*IFERROR('Model inputs'!M41/SUM('Model inputs'!M40,'Model inputs'!M41),0) -> 12.024586 | N53: =('Model inputs'!O97+'Model inputs'!N100)*IFERROR('Model inputs'!N41/SUM('Model inputs'!N40,'Model inputs'!N41),0) -> 11.97096
A54: Hosting and neatlogs allocated by revenue (USD) | B54: =SUM('Model inputs'!B55,'Model inputs'!B56) -> 0 | C54: =SUM('Model inputs'!C55,'Model inputs'!C56) -> 25 | D54: =SUM('Model inputs'!D55,'Model inputs'!D56) -> 25 | E54: =SUM('Model inputs'!E55,'Model inputs'!E56) -> 25 | F54: =SUM('Model inputs'!F55,'Model inputs'!F56) -> 25 | G54: =SUM('Model inputs'!G55,'Model inputs'!G56) -> 25 | H54: =SUM('Model inputs'!H55,'Model inputs'!H56) -> 25 | I54: =SUM('Model inputs'!I55,'Model inputs'!I56) -> 25 | ... N54: =SUM('Model inputs'!N55,'Model inputs'!N56) -> 25
A55: Hosting and neatlogs allocated by revenue (USD) > Classroom | B55: ='Model inputs'!B49 -> 0 | C55: =('Model inputs'!O98+'Model inputs'!C101)*IFERROR('Model inputs'!C43/SUM('Model inputs'!C43,'Model inputs'!C44),0) -> 12.486913 | D55: =('Model inputs'!O98+'Model inputs'!D101)*IFERROR('Model inputs'!D43/SUM('Model inputs'!D43,'Model inputs'!D44),0) -> 12.400417 | E55: =('Model inputs'!O98+'Model inputs'!E101)*IFERROR('Model inputs'!E43/SUM('Model inputs'!E43,'Model inputs'!E44),0) -> 12.390053 | F55: =('Model inputs'!O98+'Model inputs'!F101)*IFERROR('Model inputs'!F43/SUM('Model inputs'!F43,'Model inputs'!F44),0) -> 12.422014 | G55: =('Model inputs'!O98+'Model inputs'!G101)*IFERROR('Model inputs'!G43/SUM('Model inputs'!G43,'Model inputs'!G44),0) -> 12.479359 | H55: =('Model inputs'!O98+'Model inputs'!H101)*IFERROR('Model inputs'!H43/SUM('Model inputs'!H43,'Model inputs'!H44),0) -> 12.552657 | I55: =('Model inputs'!O98+'Model inputs'!I101)*IFERROR('Model inputs'!I43/SUM('Model inputs'!I43,'Model inputs'!I44),0) -> 12.636242 | J55: =('Model inputs'!O98+'Model inputs'!J101)*IFERROR('Model inputs'!J43/SUM('Model inputs'!J43,'Model inputs'!J44),0) -> 12.726503 | K55: =('Model inputs'!O98+'Model inputs'!K101)*IFERROR('Model inputs'!K43/SUM('Model inputs'!K43,'Model inputs'!K44),0) -> 12.821032 | L55: =('Model inputs'!O98+'Model inputs'!L101)*IFERROR('Model inputs'!L43/SUM('Model inputs'!L43,'Model inputs'!L44),0) -> 12.918165 | M55: =('Model inputs'!O98+'Model inputs'!M101)*IFERROR('Model inputs'!M43/SUM('Model inputs'!M43,'Model inputs'!M44),0) -> 13.016717 | N55: =('Model inputs'!O98+'Model inputs'!N101)*IFERROR('Model inputs'!N43/SUM('Model inputs'!N43,'Model inputs'!N44),0) -> 13.115822
A56: Hosting and neatlogs allocated by revenue (USD) > Household | B56: ='Model inputs'!B50 -> 0 | C56: =('Model inputs'!O98+'Model inputs'!C101)*IFERROR('Model inputs'!C44/SUM('Model inputs'!C43,'Model inputs'!C44),0) -> 12.513087 | D56: =('Model inputs'!O98+'Model inputs'!D101)*IFERROR('Model inputs'!D44/SUM('Model inputs'!D43,'Model inputs'!D44),0) -> 12.599583 | E56: =('Model inputs'!O98+'Model inputs'!E101)*IFERROR('Model inputs'!E44/SUM('Model inputs'!E43,'Model inputs'!E44),0) -> 12.609947 | F56: =('Model inputs'!O98+'Model inputs'!F101)*IFERROR('Model inputs'!F44/SUM('Model inputs'!F43,'Model inputs'!F44),0) -> 12.577986 | G56: =('Model inputs'!O98+'Model inputs'!G101)*IFERROR('Model inputs'!G44/SUM('Model inputs'!G43,'Model inputs'!G44),0) -> 12.520641 | H56: =('Model inputs'!O98+'Model inputs'!H101)*IFERROR('Model inputs'!H44/SUM('Model inputs'!H43,'Model inputs'!H44),0) -> 12.447343 | I56: =('Model inputs'!O98+'Model inputs'!I101)*IFERROR('Model inputs'!I44/SUM('Model inputs'!I43,'Model inputs'!I44),0) -> 12.363758 | J56: =('Model inputs'!O98+'Model inputs'!J101)*IFERROR('Model inputs'!J44/SUM('Model inputs'!J43,'Model inputs'!J44),0) -> 12.273497 | K56: =('Model inputs'!O98+'Model inputs'!K101)*IFERROR('Model inputs'!K44/SUM('Model inputs'!K43,'Model inputs'!K44),0) -> 12.178968 | L56: =('Model inputs'!O98+'Model inputs'!L101)*IFERROR('Model inputs'!L44/SUM('Model inputs'!L43,'Model inputs'!L44),0) -> 12.081835 | M56: =('Model inputs'!O98+'Model inputs'!M101)*IFERROR('Model inputs'!M44/SUM('Model inputs'!M43,'Model inputs'!M44),0) -> 11.983283 | N56: =('Model inputs'!O98+'Model inputs'!N101)*IFERROR('Model inputs'!N44/SUM('Model inputs'!N43,'Model inputs'!N44),0) -> 11.884178
A57: Inference cost (USD, estimate) | B57: =SUM('Model inputs'!B58,'Model inputs'!B59) -> 0 | C57: =SUM('Model inputs'!C58,'Model inputs'!C59) -> 188.9573 | D57: =SUM('Model inputs'!D58,'Model inputs'!D59) -> 203.16695 | E57: =SUM('Model inputs'!E58,'Model inputs'!E59) -> 216.63887 | F57: =SUM('Model inputs'!F58,'Model inputs'!F59) -> 229.42012 | G57: =SUM('Model inputs'!G58,'Model inputs'!G59) -> 241.55433 | H57: =SUM('Model inputs'!H58,'Model inputs'!H59) -> 253.082 | I57: =SUM('Model inputs'!I58,'Model inputs'!I59) -> 264.04074 | ... N57: =SUM('Model inputs'!N58,'Model inputs'!N59) -> 311.43963
A58: Inference cost (USD, estimate) > Classroom | B58: =0 -> 0 | C58: ='Model inputs'!C121*'Model inputs'!O84 -> 125.7678 | D58: ='Model inputs'!D121*'Model inputs'!O84 -> 133.74877 | E58: ='Model inputs'!E121*'Model inputs'!O84 -> 141.4903 | F58: ='Model inputs'!F121*'Model inputs'!O84 -> 148.99959 | G58: ='Model inputs'!G121*'Model inputs'!O84 -> 156.28361 | H58: ='Model inputs'!H121*'Model inputs'!O84 -> 163.3491 | I58: ='Model inputs'!I121*'Model inputs'!O84 -> 170.20262 | J58: ='Model inputs'!J121*'Model inputs'!O84 -> 176.85055 | K58: ='Model inputs'!K121*'Model inputs'!O84 -> 183.29903 | L58: ='Model inputs'!L121*'Model inputs'!O84 -> 189.55406 | M58: ='Model inputs'!M121*'Model inputs'!O84 -> 195.62144 | N58: ='Model inputs'!N121*'Model inputs'!O84 -> 201.50679
A59: Inference cost (USD, estimate) > Household | B59: =0 -> 0 | C59: ='Model inputs'!C122*'Model inputs'!O84 -> 63.189504 | D59: ='Model inputs'!D122*'Model inputs'!O84 -> 69.418184 | E59: ='Model inputs'!E122*'Model inputs'!O84 -> 75.148569 | F59: ='Model inputs'!F122*'Model inputs'!O84 -> 80.420523 | G59: ='Model inputs'!G122*'Model inputs'!O84 -> 85.270722 | H59: ='Model inputs'!H122*'Model inputs'!O84 -> 89.732904 | I59: ='Model inputs'!I122*'Model inputs'!O84 -> 93.838112 | J59: ='Model inputs'!J122*'Model inputs'!O84 -> 97.614903 | K59: ='Model inputs'!K122*'Model inputs'!O84 -> 101.08955 | L59: ='Model inputs'!L122*'Model inputs'!O84 -> 104.28623 | M59: ='Model inputs'!M122*'Model inputs'!O84 -> 107.22717 | N59: ='Model inputs'!N122*'Model inputs'!O84 -> 109.93283
A60: Inference cost (USD, estimate) | B60: =SUM('Model inputs'!B61,'Model inputs'!B62) -> 0 | C60: =SUM('Model inputs'!C61,'Model inputs'!C62) -> 329.70576 | D60: =SUM('Model inputs'!D61,'Model inputs'!D62) -> 342.09108 | E60: =SUM('Model inputs'!E61,'Model inputs'!E62) -> 353.34122 | F60: =SUM('Model inputs'!F61,'Model inputs'!F62) -> 363.5831 | G60: =SUM('Model inputs'!G61,'Model inputs'!G62) -> 372.92721 | H60: =SUM('Model inputs'!H61,'Model inputs'!H62) -> 381.4699 | I60: =SUM('Model inputs'!I61,'Model inputs'!I62) -> 389.29536 | ... N60: =SUM('Model inputs'!N61,'Model inputs'!N62) -> 419.9537
A61: Inference cost (USD, estimate) > Classroom | B61: ='Model inputs'!B58 -> 0 | C61: ='Model inputs'!C124*'Model inputs'!O85 -> 222.0816 | D61: ='Model inputs'!D124*'Model inputs'!O85 -> 230.1107 | E61: ='Model inputs'!E124*'Model inputs'!O85 -> 237.65806 | F61: ='Model inputs'!F124*'Model inputs'!O85 -> 244.75258 | G61: ='Model inputs'!G124*'Model inputs'!O85 -> 251.42142 | H61: ='Model inputs'!H124*'Model inputs'!O85 -> 257.69014 | I61: ='Model inputs'!I124*'Model inputs'!O85 -> 263.58273 | J61: ='Model inputs'!J124*'Model inputs'!O85 -> 269.12177 | K61: ='Model inputs'!K124*'Model inputs'!O85 -> 274.32846 | L61: ='Model inputs'!L124*'Model inputs'!O85 -> 279.22275 | M61: ='Model inputs'!M124*'Model inputs'!O85 -> 283.82339 | N61: ='Model inputs'!N124*'Model inputs'!O85 -> 288.14798
A62: Inference cost (USD, estimate) > Household | B62: ='Model inputs'!B59 -> 0 | C62: ='Model inputs'!C125*'Model inputs'!O85 -> 107.62416 | D62: ='Model inputs'!D125*'Model inputs'!O85 -> 111.98038 | E62: ='Model inputs'!E125*'Model inputs'!O85 -> 115.68316 | F62: ='Model inputs'!F125*'Model inputs'!O85 -> 118.83053 | G62: ='Model inputs'!G125*'Model inputs'!O85 -> 121.50579 | H62: ='Model inputs'!H125*'Model inputs'!O85 -> 123.77976 | I62: ='Model inputs'!I125*'Model inputs'!O85 -> 125.71263 | J62: ='Model inputs'!J125*'Model inputs'!O85 -> 127.35558 | K62: ='Model inputs'!K125*'Model inputs'!O85 -> 128.75208 | L62: ='Model inputs'!L125*'Model inputs'!O85 -> 129.93911 | M62: ='Model inputs'!M125*'Model inputs'!O85 -> 130.94808 | N62: ='Model inputs'!N125*'Model inputs'!O85 -> 131.80571
A63: Inference cost (USD, estimate) | B63: =SUM('Model inputs'!B64,'Model inputs'!B65) -> 0 | C63: =SUM('Model inputs'!C64,'Model inputs'!C65) -> 316.97795 | D63: =SUM('Model inputs'!D64,'Model inputs'!D65) -> 384.1188 | E63: =SUM('Model inputs'!E64,'Model inputs'!E65) -> 448.06889 | F63: =SUM('Model inputs'!F64,'Model inputs'!F65) -> 509.01808 | G63: =SUM('Model inputs'!G64,'Model inputs'!G65) -> 567.14297 | H63: =SUM('Model inputs'!H64,'Model inputs'!H65) -> 622.60797 | I63: =SUM('Model inputs'!I64,'Model inputs'!I65) -> 675.56616 | ... N63: =SUM('Model inputs'!N64,'Model inputs'!N65) -> 907.42337
A64: Inference cost (USD, estimate) > Classroom | B64: ='Model inputs'!B58 -> 0 | C64: ='Model inputs'!C127*'Model inputs'!O86 -> 211.47405 | D64: ='Model inputs'!D127*'Model inputs'!O86 -> 255.08433 | E64: ='Model inputs'!E127*'Model inputs'!O86 -> 297.3863 | F64: ='Model inputs'!F127*'Model inputs'!O86 -> 338.41921 | G64: ='Model inputs'!G127*'Model inputs'!O86 -> 378.22113 | H64: ='Model inputs'!H127*'Model inputs'!O86 -> 416.829 | I64: ='Model inputs'!I127*'Model inputs'!O86 -> 454.27863 | J64: ='Model inputs'!J127*'Model inputs'!O86 -> 490.60477 | K64: ='Model inputs'!K127*'Model inputs'!O86 -> 525.84113 | L64: ='Model inputs'!L127*'Model inputs'!O86 -> 560.02039 | M64: ='Model inputs'!M127*'Model inputs'!O86 -> 593.17428 | N64: ='Model inputs'!N127*'Model inputs'!O86 -> 625.33355
A65: Inference cost (USD, estimate) > Household | B65: ='Model inputs'!B59 -> 0 | C65: ='Model inputs'!C128*'Model inputs'!O86 -> 105.5039 | D65: ='Model inputs'!D128*'Model inputs'!O86 -> 129.03447 | E65: ='Model inputs'!E128*'Model inputs'!O86 -> 150.68259 | F65: ='Model inputs'!F128*'Model inputs'!O86 -> 170.59887 | G65: ='Model inputs'!G128*'Model inputs'!O86 -> 188.92184 | H65: ='Model inputs'!H128*'Model inputs'!O86 -> 205.77897 | I65: ='Model inputs'!I128*'Model inputs'!O86 -> 221.28753 | J65: ='Model inputs'!J128*'Model inputs'!O86 -> 235.55541 | K65: ='Model inputs'!K128*'Model inputs'!O86 -> 248.68186 | L65: ='Model inputs'!L128*'Model inputs'!O86 -> 260.75819 | M65: ='Model inputs'!M128*'Model inputs'!O86 -> 271.86841 | N65: ='Model inputs'!N128*'Model inputs'!O86 -> 282.08982
A66: Overage revenue (USD) | B66: =SUM('Model inputs'!B67,'Model inputs'!B68) -> 0 | C66: =SUM('Model inputs'!C67,'Model inputs'!C68) -> 0 | D66: =SUM('Model inputs'!D67,'Model inputs'!D68) -> 0 | E66: =SUM('Model inputs'!E67,'Model inputs'!E68) -> 0 | F66: =SUM('Model inputs'!F67,'Model inputs'!F68) -> 0 | G66: =SUM('Model inputs'!G67,'Model inputs'!G68) -> 0 | H66: =SUM('Model inputs'!H67,'Model inputs'!H68) -> 0 | I66: =SUM('Model inputs'!I67,'Model inputs'!I68) -> 0 | ... N66: =SUM('Model inputs'!N67,'Model inputs'!N68) -> 0
A67: Overage revenue (USD) > Classroom | B67: =0 -> 0 | C67: ='Model inputs'!C88*IF(IF(IF(IF(ISERROR('Model inputs'!O139>'Model inputs'!O130),'Model inputs'!O139>'Model inputs'!O130,IF(OR('Model inputs'!O139="",'Model inputs'!O130=""),"",'Model inputs'!O139>'Model inputs'!O130))="",FALSE,IF(ISERROR('Model inputs'!O139>'Model inputs'!O130),'Model inputs'!O139>'Model inputs'!O130,IF(OR('Model inputs'!O139="",'Model inputs'!O130=""),"",'Model inputs'!O139>'Model inputs'!O130))),('Model inputs'!O139-'Model inputs'!O130)*'Model inputs'!O103,0)="",0,IF(IF(IF(ISERROR('Model inputs'!O139>'Model inputs'!O130),'Model inputs'!O139>'Model inputs'!O130,IF(OR('Model inputs'!O139="",'Model inputs'!O130=""),"",'Model inputs'!O139>'Model inputs'!O130))="",FALSE,IF(ISERROR('Model inputs'!O139>'Model inputs'!O130),'Model inputs'!O139>'Model inputs'!O130,IF(OR('Model inputs'!O139="",'Model inputs'!O130=""),"",'Model inputs'!O139>'Model inputs'!O130))),('Model inputs'!O139-'Model inputs'!O130)*'Model inputs'!O103,0)) -> 0 | D67: ='Model inputs'!D88*IF(IF(IF(IF(ISERROR('Model inputs'!O139>'Model inputs'!O130),'Model inputs'!O139>'Model inputs'!O130,IF(OR('Model inputs'!O139="",'Model inputs'!O130=""),"",'Model inputs'!O139>'Model inputs'!O130))="",FALSE,IF(ISERROR('Model inputs'!O139>'Model inputs'!O130),'Model inputs'!O139>'Model inputs'!O130,IF(OR('Model inputs'!O139="",'Model inputs'!O130=""),"",'Model inputs'!O139>'Model inputs'!O130))),('Model inputs'!O139-'Model inputs'!O130)*'Model inputs'!O103,0)="",0,IF(IF(IF(ISERROR('Model inputs'!O139>'Model inputs'!O130),'Model inputs'!O139>'Model inputs'!O130,IF(OR('Model inputs'!O139="",'Model inputs'!O130=""),"",'Model inputs'!O139>'Model inputs'!O130))="",FALSE,IF(ISERROR('Model inputs'!O139>'Model inputs'!O130),'Model inputs'!O139>'Model inputs'!O130,IF(OR('Model inputs'!O139="",'Model inputs'!O130=""),"",'Model inputs'!O139>'Model inputs'!O130))),('Model inputs'!O139-'Model inputs'!O130)*'Model inputs'!O103,0)) -> 0 | E67: ='Model inputs'!E88*IF(IF(IF(IF(ISERROR('Model inputs'!O139>'Model inputs'!O130),'Model inputs'!O139>'Model inputs'!O130,IF(OR('Model inputs'!O139="",'Model inputs'!O130=""),"",'Model inputs'!O139>'Model inputs'!O130))="",FALSE,IF(ISERROR('Model inputs'!O139>'Model inputs'!O130),'Model inputs'!O139>'Model inputs'!O130,IF(OR('Model inputs'!O139="",'Model inputs'!O130=""),"",'Model inputs'!O139>'Model inputs'!O130))),('Model inputs'!O139-'Model inputs'!O130)*'Model inputs'!O103,0)="",0,IF(IF(IF(ISERROR('Model inputs'!O139>'Model inputs'!O130),'Model inputs'!O139>'Model inputs'!O130,IF(OR('Model inputs'!O139="",'Model inputs'!O130=""),"",'Model inputs'!O139>'Model inputs'!O130))="",FALSE,IF(ISERROR('Model inputs'!O139>'Model inputs'!O130),'Model inputs'!O139>'Model inputs'!O130,IF(OR('Model inputs'!O139="",'Model inputs'!O130=""),"",'Model inputs'!O139>'Model inputs'!O130))),('Model inputs'!O139-'Model inputs'!O130)*'Model inputs'!O103,0)) -> 0 | F67: ='Model inputs'!F88*IF(IF(IF(IF(ISERROR('Model inputs'!O139>'Model inputs'!O130),'Model inputs'!O139>'Model inputs'!O130,IF(OR('Model inputs'!O139="",'Model inputs'!O130=""),"",'Model inputs'!O139>'Model inputs'!O130))="",FALSE,IF(ISERROR('Model inputs'!O139>'Model inputs'!O130),'Model inputs'!O139>'Model inputs'!O130,IF(OR('Model inputs'!O139="",'Model inputs'!O130=""),"",'Model inputs'!O139>'Model inputs'!O130))),('Model inputs'!O139-'Model inputs'!O130)*'Model inputs'!O103,0)="",0,IF(IF(IF(ISERROR('Model inputs'!O139>'Model inputs'!O130),'Model inputs'!O139>'Model inputs'!O130,IF(OR('Model inputs'!O139="",'Model inputs'!O130=""),"",'Model inputs'!O139>'Model inputs'!O130))="",FALSE,IF(ISERROR('Model inputs'!O139>'Model inputs'!O130),'Model inputs'!O139>'Model inputs'!O130,IF(OR('Model inputs'!O139="",'Model inputs'!O130=""),"",'Model inputs'!O139>'Model inputs'!O130))),('Model inputs'!O139-'Model inputs'!O130)*'Model inputs'!O103,0)) -> 0 | G67: ='Model inputs'!G88*IF(IF(IF(IF(ISERROR('Model inputs'!O139>'Model inputs'!O130),'Model inputs'!O139>'Model inputs'!O130,IF(OR('Model inputs'!O139="",'Model inputs'!O130=""),"",'Model inputs'!O139>'Model inputs'!O130))="",FALSE,IF(ISERROR('Model inputs'!O139>'Model inputs'!O130),'Model inputs'!O139>'Model inputs'!O130,IF(OR('Model inputs'!O139="",'Model inputs'!O130=""),"",'Model inputs'!O139>'Model inputs'!O130))),('Model inputs'!O139-'Model inputs'!O130)*'Model inputs'!O103,0)="",0,IF(IF(IF(ISERROR('Model inputs'!O139>'Model inputs'!O130),'Model inputs'!O139>'Model inputs'!O130,IF(OR('Model inputs'!O139="",'Model inputs'!O130=""),"",'Model inputs'!O139>'Model inputs'!O130))="",FALSE,IF(ISERROR('Model inputs'!O139>'Model inputs'!O130),'Model inputs'!O139>'Model inputs'!O130,IF(OR('Model inputs'!O139="",'Model inputs'!O130=""),"",'Model inputs'!O139>'Model inputs'!O130))),('Model inputs'!O139-'Model inputs'!O130)*'Model inputs'!O103,0)) -> 0 | H67: ='Model inputs'!H88*IF(IF(IF(IF(ISERROR('Model inputs'!O139>'Model inputs'!O130),'Model inputs'!O139>'Model inputs'!O130,IF(OR('Model inputs'!O139="",'Model inputs'!O130=""),"",'Model inputs'!O139>'Model inputs'!O130))="",FALSE,IF(ISERROR('Model inputs'!O139>'Model inputs'!O130),'Model inputs'!O139>'Model inputs'!O130,IF(OR('Model inputs'!O139="",'Model inputs'!O130=""),"",'Model inputs'!O139>'Model inputs'!O130))),('Model inputs'!O139-'Model inputs'!O130)*'Model inputs'!O103,0)="",0,IF(IF(IF(ISERROR('Model inputs'!O139>'Model inputs'!O130),'Model inputs'!O139>'Model inputs'!O130,IF(OR('Model inputs'!O139="",'Model inputs'!O130=""),"",'Model inputs'!O139>'Model inputs'!O130))="",FALSE,IF(ISERROR('Model inputs'!O139>'Model inputs'!O130),'Model inputs'!O139>'Model inputs'!O130,IF(OR('Model inputs'!O139="",'Model inputs'!O130=""),"",'Model inputs'!O139>'Model inputs'!O130))),('Model inputs'!O139-'Model inputs'!O130)*'Model inputs'!O103,0)) -> 0 | I67: ='Model inputs'!I88*IF(IF(IF(IF(ISERROR('Model inputs'!O139>'Model inputs'!O130),'Model inputs'!O139>'Model inputs'!O130,IF(OR('Model inputs'!O139="",'Model inputs'!O130=""),"",'Model inputs'!O139>'Model inputs'!O130))="",FALSE,IF(ISERROR('Model inputs'!O139>'Model inputs'!O130),'Model inputs'!O139>'Model inputs'!O130,IF(OR('Model inputs'!O139="",'Model inputs'!O130=""),"",'Model inputs'!O139>'Model inputs'!O130))),('Model inputs'!O139-'Model inputs'!O130)*'Model inputs'!O103,0)="",0,IF(IF(IF(ISERROR('Model inputs'!O139>'Model inputs'!O130),'Model inputs'!O139>'Model inputs'!O130,IF(OR('Model inputs'!O139="",'Model inputs'!O130=""),"",'Model inputs'!O139>'Model inputs'!O130))="",FALSE,IF(ISERROR('Model inputs'!O139>'Model inputs'!O130),'Model inputs'!O139>'Model inputs'!O130,IF(OR('Model inputs'!O139="",'Model inputs'!O130=""),"",'Model inputs'!O139>'Model inputs'!O130))),('Model inputs'!O139-'Model inputs'!O130)*'Model inputs'!O103,0)) -> 0 | J67: ='Model inputs'!J88*IF(IF(IF(IF(ISERROR('Model inputs'!O139>'Model inputs'!O130),'Model inputs'!O139>'Model inputs'!O130,IF(OR('Model inputs'!O139="",'Model inputs'!O130=""),"",'Model inputs'!O139>'Model inputs'!O130))="",FALSE,IF(ISERROR('Model inputs'!O139>'Model inputs'!O130),'Model inputs'!O139>'Model inputs'!O130,IF(OR('Model inputs'!O139="",'Model inputs'!O130=""),"",'Model inputs'!O139>'Model inputs'!O130))),('Model inputs'!O139-'Model inputs'!O130)*'Model inputs'!O103,0)="",0,IF(IF(IF(ISERROR('Model inputs'!O139>'Model inputs'!O130),'Model inputs'!O139>'Model inputs'!O130,IF(OR('Model inputs'!O139="",'Model inputs'!O130=""),"",'Model inputs'!O139>'Model inputs'!O130))="",FALSE,IF(ISERROR('Model inputs'!O139>'Model inputs'!O130),'Model inputs'!O139>'Model inputs'!O130,IF(OR('Model inputs'!O139="",'Model inputs'!O130=""),"",'Model inputs'!O139>'Model inputs'!O130))),('Model inputs'!O139-'Model inputs'!O130)*'Model inputs'!O103,0)) -> 0 | K67: ='Model inputs'!K88*IF(IF(IF(IF(ISERROR('Model inputs'!O139>'Model inputs'!O130),'Model inputs'!O139>'Model inputs'!O130,IF(OR('Model inputs'!O139="",'Model inputs'!O130=""),"",'Model inputs'!O139>'Model inputs'!O130))="",FALSE,IF(ISERROR('Model inputs'!O139>'Model inputs'!O130),'Model inputs'!O139>'Model inputs'!O130,IF(OR('Model inputs'!O139="",'Model inputs'!O130=""),"",'Model inputs'!O139>'Model inputs'!O130))),('Model inputs'!O139-'Model inputs'!O130)*'Model inputs'!O103,0)="",0,IF(IF(IF(ISERROR('Model inputs'!O139>'Model inputs'!O130),'Model inputs'!O139>'Model inputs'!O130,IF(OR('Model inputs'!O139="",'Model inputs'!O130=""),"",'Model inputs'!O139>'Model inputs'!O130))="",FALSE,IF(ISERROR('Model inputs'!O139>'Model inputs'!O130),'Model inputs'!O139>'Model inputs'!O130,IF(OR('Model inputs'!O139="",'Model inputs'!O130=""),"",'Model inputs'!O139>'Model inputs'!O130))),('Model inputs'!O139-'Model inputs'!O130)*'Model inputs'!O103,0)) -> 0 | L67: ='Model inputs'!L88*IF(IF(IF(IF(ISERROR('Model inputs'!O139>'Model inputs'!O130),'Model inputs'!O139>'Model inputs'!O130,IF(OR('Model inputs'!O139="",'Model inputs'!O130=""),"",'Model inputs'!O139>'Model inputs'!O130))="",FALSE,IF(ISERROR('Model inputs'!O139>'Model inputs'!O130),'Model inputs'!O139>'Model inputs'!O130,IF(OR('Model inputs'!O139="",'Model inputs'!O130=""),"",'Model inputs'!O139>'Model inputs'!O130))),('Model inputs'!O139-'Model inputs'!O130)*'Model inputs'!O103,0)="",0,IF(IF(IF(ISERROR('Model inputs'!O139>'Model inputs'!O130),'Model inputs'!O139>'Model inputs'!O130,IF(OR('Model inputs'!O139="",'Model inputs'!O130=""),"",'Model inputs'!O139>'Model inputs'!O130))="",FALSE,IF(ISERROR('Model inputs'!O139>'Model inputs'!O130),'Model inputs'!O139>'Model inputs'!O130,IF(OR('Model inputs'!O139="",'Model inputs'!O130=""),"",'Model inputs'!O139>'Model inputs'!O130))),('Model inputs'!O139-'Model inputs'!O130)*'Model inputs'!O103,0)) -> 0 | M67: ='Model inputs'!M88*IF(IF(IF(IF(ISERROR('Model inputs'!O139>'Model inputs'!O130),'Model inputs'!O139>'Model inputs'!O130,IF(OR('Model inputs'!O139="",'Model inputs'!O130=""),"",'Model inputs'!O139>'Model inputs'!O130))="",FALSE,IF(ISERROR('Model inputs'!O139>'Model inputs'!O130),'Model inputs'!O139>'Model inputs'!O130,IF(OR('Model inputs'!O139="",'Model inputs'!O130=""),"",'Model inputs'!O139>'Model inputs'!O130))),('Model inputs'!O139-'Model inputs'!O130)*'Model inputs'!O103,0)="",0,IF(IF(IF(ISERROR('Model inputs'!O139>'Model inputs'!O130),'Model inputs'!O139>'Model inputs'!O130,IF(OR('Model inputs'!O139="",'Model inputs'!O130=""),"",'Model inputs'!O139>'Model inputs'!O130))="",FALSE,IF(ISERROR('Model inputs'!O139>'Model inputs'!O130),'Model inputs'!O139>'Model inputs'!O130,IF(OR('Model inputs'!O139="",'Model inputs'!O130=""),"",'Model inputs'!O139>'Model inputs'!O130))),('Model inputs'!O139-'Model inputs'!O130)*'Model inputs'!O103,0)) -> 0 | N67: ='Model inputs'!N88*IF(IF(IF(IF(ISERROR('Model inputs'!O139>'Model inputs'!O130),'Model inputs'!O139>'Model inputs'!O130,IF(OR('Model inputs'!O139="",'Model inputs'!O130=""),"",'Model inputs'!O139>'Model inputs'!O130))="",FALSE,IF(ISERROR('Model inputs'!O139>'Model inputs'!O130),'Model inputs'!O139>'Model inputs'!O130,IF(OR('Model inputs'!O139="",'Model inputs'!O130=""),"",'Model inputs'!O139>'Model inputs'!O130))),('Model inputs'!O139-'Model inputs'!O130)*'Model inputs'!O103,0)="",0,IF(IF(IF(ISERROR('Model inputs'!O139>'Model inputs'!O130),'Model inputs'!O139>'Model inputs'!O130,IF(OR('Model inputs'!O139="",'Model inputs'!O130=""),"",'Model inputs'!O139>'Model inputs'!O130))="",FALSE,IF(ISERROR('Model inputs'!O139>'Model inputs'!O130),'Model inputs'!O139>'Model inputs'!O130,IF(OR('Model inputs'!O139="",'Model inputs'!O130=""),"",'Model inputs'!O139>'Model inputs'!O130))),('Model inputs'!O139-'Model inputs'!O130)*'Model inputs'!O103,0)) -> 0
A68: Overage revenue (USD) > Household | B68: =0 -> 0 | C68: ='Model inputs'!C89*IF(IF(IF(IF(ISERROR('Model inputs'!O140>'Model inputs'!O131),'Model inputs'!O140>'Model inputs'!O131,IF(OR('Model inputs'!O140="",'Model inputs'!O131=""),"",'Model inputs'!O140>'Model inputs'!O131))="",FALSE,IF(ISERROR('Model inputs'!O140>'Model inputs'!O131),'Model inputs'!O140>'Model inputs'!O131,IF(OR('Model inputs'!O140="",'Model inputs'!O131=""),"",'Model inputs'!O140>'Model inputs'!O131))),('Model inputs'!O140-'Model inputs'!O131)*'Model inputs'!O104,0)="",0,IF(IF(IF(ISERROR('Model inputs'!O140>'Model inputs'!O131),'Model inputs'!O140>'Model inputs'!O131,IF(OR('Model inputs'!O140="",'Model inputs'!O131=""),"",'Model inputs'!O140>'Model inputs'!O131))="",FALSE,IF(ISERROR('Model inputs'!O140>'Model inputs'!O131),'Model inputs'!O140>'Model inputs'!O131,IF(OR('Model inputs'!O140="",'Model inputs'!O131=""),"",'Model inputs'!O140>'Model inputs'!O131))),('Model inputs'!O140-'Model inputs'!O131)*'Model inputs'!O104,0)) -> 0 | D68: ='Model inputs'!D89*IF(IF(IF(IF(ISERROR('Model inputs'!O140>'Model inputs'!O131),'Model inputs'!O140>'Model inputs'!O131,IF(OR('Model inputs'!O140="",'Model inputs'!O131=""),"",'Model inputs'!O140>'Model inputs'!O131))="",FALSE,IF(ISERROR('Model inputs'!O140>'Model inputs'!O131),'Model inputs'!O140>'Model inputs'!O131,IF(OR('Model inputs'!O140="",'Model inputs'!O131=""),"",'Model inputs'!O140>'Model inputs'!O131))),('Model inputs'!O140-'Model inputs'!O131)*'Model inputs'!O104,0)="",0,IF(IF(IF(ISERROR('Model inputs'!O140>'Model inputs'!O131),'Model inputs'!O140>'Model inputs'!O131,IF(OR('Model inputs'!O140="",'Model inputs'!O131=""),"",'Model inputs'!O140>'Model inputs'!O131))="",FALSE,IF(ISERROR('Model inputs'!O140>'Model inputs'!O131),'Model inputs'!O140>'Model inputs'!O131,IF(OR('Model inputs'!O140="",'Model inputs'!O131=""),"",'Model inputs'!O140>'Model inputs'!O131))),('Model inputs'!O140-'Model inputs'!O131)*'Model inputs'!O104,0)) -> 0 | E68: ='Model inputs'!E89*IF(IF(IF(IF(ISERROR('Model inputs'!O140>'Model inputs'!O131),'Model inputs'!O140>'Model inputs'!O131,IF(OR('Model inputs'!O140="",'Model inputs'!O131=""),"",'Model inputs'!O140>'Model inputs'!O131))="",FALSE,IF(ISERROR('Model inputs'!O140>'Model inputs'!O131),'Model inputs'!O140>'Model inputs'!O131,IF(OR('Model inputs'!O140="",'Model inputs'!O131=""),"",'Model inputs'!O140>'Model inputs'!O131))),('Model inputs'!O140-'Model inputs'!O131)*'Model inputs'!O104,0)="",0,IF(IF(IF(ISERROR('Model inputs'!O140>'Model inputs'!O131),'Model inputs'!O140>'Model inputs'!O131,IF(OR('Model inputs'!O140="",'Model inputs'!O131=""),"",'Model inputs'!O140>'Model inputs'!O131))="",FALSE,IF(ISERROR('Model inputs'!O140>'Model inputs'!O131),'Model inputs'!O140>'Model inputs'!O131,IF(OR('Model inputs'!O140="",'Model inputs'!O131=""),"",'Model inputs'!O140>'Model inputs'!O131))),('Model inputs'!O140-'Model inputs'!O131)*'Model inputs'!O104,0)) -> 0 | F68: ='Model inputs'!F89*IF(IF(IF(IF(ISERROR('Model inputs'!O140>'Model inputs'!O131),'Model inputs'!O140>'Model inputs'!O131,IF(OR('Model inputs'!O140="",'Model inputs'!O131=""),"",'Model inputs'!O140>'Model inputs'!O131))="",FALSE,IF(ISERROR('Model inputs'!O140>'Model inputs'!O131),'Model inputs'!O140>'Model inputs'!O131,IF(OR('Model inputs'!O140="",'Model inputs'!O131=""),"",'Model inputs'!O140>'Model inputs'!O131))),('Model inputs'!O140-'Model inputs'!O131)*'Model inputs'!O104,0)="",0,IF(IF(IF(ISERROR('Model inputs'!O140>'Model inputs'!O131),'Model inputs'!O140>'Model inputs'!O131,IF(OR('Model inputs'!O140="",'Model inputs'!O131=""),"",'Model inputs'!O140>'Model inputs'!O131))="",FALSE,IF(ISERROR('Model inputs'!O140>'Model inputs'!O131),'Model inputs'!O140>'Model inputs'!O131,IF(OR('Model inputs'!O140="",'Model inputs'!O131=""),"",'Model inputs'!O140>'Model inputs'!O131))),('Model inputs'!O140-'Model inputs'!O131)*'Model inputs'!O104,0)) -> 0 | G68: ='Model inputs'!G89*IF(IF(IF(IF(ISERROR('Model inputs'!O140>'Model inputs'!O131),'Model inputs'!O140>'Model inputs'!O131,IF(OR('Model inputs'!O140="",'Model inputs'!O131=""),"",'Model inputs'!O140>'Model inputs'!O131))="",FALSE,IF(ISERROR('Model inputs'!O140>'Model inputs'!O131),'Model inputs'!O140>'Model inputs'!O131,IF(OR('Model inputs'!O140="",'Model inputs'!O131=""),"",'Model inputs'!O140>'Model inputs'!O131))),('Model inputs'!O140-'Model inputs'!O131)*'Model inputs'!O104,0)="",0,IF(IF(IF(ISERROR('Model inputs'!O140>'Model inputs'!O131),'Model inputs'!O140>'Model inputs'!O131,IF(OR('Model inputs'!O140="",'Model inputs'!O131=""),"",'Model inputs'!O140>'Model inputs'!O131))="",FALSE,IF(ISERROR('Model inputs'!O140>'Model inputs'!O131),'Model inputs'!O140>'Model inputs'!O131,IF(OR('Model inputs'!O140="",'Model inputs'!O131=""),"",'Model inputs'!O140>'Model inputs'!O131))),('Model inputs'!O140-'Model inputs'!O131)*'Model inputs'!O104,0)) -> 0 | H68: ='Model inputs'!H89*IF(IF(IF(IF(ISERROR('Model inputs'!O140>'Model inputs'!O131),'Model inputs'!O140>'Model inputs'!O131,IF(OR('Model inputs'!O140="",'Model inputs'!O131=""),"",'Model inputs'!O140>'Model inputs'!O131))="",FALSE,IF(ISERROR('Model inputs'!O140>'Model inputs'!O131),'Model inputs'!O140>'Model inputs'!O131,IF(OR('Model inputs'!O140="",'Model inputs'!O131=""),"",'Model inputs'!O140>'Model inputs'!O131))),('Model inputs'!O140-'Model inputs'!O131)*'Model inputs'!O104,0)="",0,IF(IF(IF(ISERROR('Model inputs'!O140>'Model inputs'!O131),'Model inputs'!O140>'Model inputs'!O131,IF(OR('Model inputs'!O140="",'Model inputs'!O131=""),"",'Model inputs'!O140>'Model inputs'!O131))="",FALSE,IF(ISERROR('Model inputs'!O140>'Model inputs'!O131),'Model inputs'!O140>'Model inputs'!O131,IF(OR('Model inputs'!O140="",'Model inputs'!O131=""),"",'Model inputs'!O140>'Model inputs'!O131))),('Model inputs'!O140-'Model inputs'!O131)*'Model inputs'!O104,0)) -> 0 | I68: ='Model inputs'!I89*IF(IF(IF(IF(ISERROR('Model inputs'!O140>'Model inputs'!O131),'Model inputs'!O140>'Model inputs'!O131,IF(OR('Model inputs'!O140="",'Model inputs'!O131=""),"",'Model inputs'!O140>'Model inputs'!O131))="",FALSE,IF(ISERROR('Model inputs'!O140>'Model inputs'!O131),'Model inputs'!O140>'Model inputs'!O131,IF(OR('Model inputs'!O140="",'Model inputs'!O131=""),"",'Model inputs'!O140>'Model inputs'!O131))),('Model inputs'!O140-'Model inputs'!O131)*'Model inputs'!O104,0)="",0,IF(IF(IF(ISERROR('Model inputs'!O140>'Model inputs'!O131),'Model inputs'!O140>'Model inputs'!O131,IF(OR('Model inputs'!O140="",'Model inputs'!O131=""),"",'Model inputs'!O140>'Model inputs'!O131))="",FALSE,IF(ISERROR('Model inputs'!O140>'Model inputs'!O131),'Model inputs'!O140>'Model inputs'!O131,IF(OR('Model inputs'!O140="",'Model inputs'!O131=""),"",'Model inputs'!O140>'Model inputs'!O131))),('Model inputs'!O140-'Model inputs'!O131)*'Model inputs'!O104,0)) -> 0 | J68: ='Model inputs'!J89*IF(IF(IF(IF(ISERROR('Model inputs'!O140>'Model inputs'!O131),'Model inputs'!O140>'Model inputs'!O131,IF(OR('Model inputs'!O140="",'Model inputs'!O131=""),"",'Model inputs'!O140>'Model inputs'!O131))="",FALSE,IF(ISERROR('Model inputs'!O140>'Model inputs'!O131),'Model inputs'!O140>'Model inputs'!O131,IF(OR('Model inputs'!O140="",'Model inputs'!O131=""),"",'Model inputs'!O140>'Model inputs'!O131))),('Model inputs'!O140-'Model inputs'!O131)*'Model inputs'!O104,0)="",0,IF(IF(IF(ISERROR('Model inputs'!O140>'Model inputs'!O131),'Model inputs'!O140>'Model inputs'!O131,IF(OR('Model inputs'!O140="",'Model inputs'!O131=""),"",'Model inputs'!O140>'Model inputs'!O131))="",FALSE,IF(ISERROR('Model inputs'!O140>'Model inputs'!O131),'Model inputs'!O140>'Model inputs'!O131,IF(OR('Model inputs'!O140="",'Model inputs'!O131=""),"",'Model inputs'!O140>'Model inputs'!O131))),('Model inputs'!O140-'Model inputs'!O131)*'Model inputs'!O104,0)) -> 0 | K68: ='Model inputs'!K89*IF(IF(IF(IF(ISERROR('Model inputs'!O140>'Model inputs'!O131),'Model inputs'!O140>'Model inputs'!O131,IF(OR('Model inputs'!O140="",'Model inputs'!O131=""),"",'Model inputs'!O140>'Model inputs'!O131))="",FALSE,IF(ISERROR('Model inputs'!O140>'Model inputs'!O131),'Model inputs'!O140>'Model inputs'!O131,IF(OR('Model inputs'!O140="",'Model inputs'!O131=""),"",'Model inputs'!O140>'Model inputs'!O131))),('Model inputs'!O140-'Model inputs'!O131)*'Model inputs'!O104,0)="",0,IF(IF(IF(ISERROR('Model inputs'!O140>'Model inputs'!O131),'Model inputs'!O140>'Model inputs'!O131,IF(OR('Model inputs'!O140="",'Model inputs'!O131=""),"",'Model inputs'!O140>'Model inputs'!O131))="",FALSE,IF(ISERROR('Model inputs'!O140>'Model inputs'!O131),'Model inputs'!O140>'Model inputs'!O131,IF(OR('Model inputs'!O140="",'Model inputs'!O131=""),"",'Model inputs'!O140>'Model inputs'!O131))),('Model inputs'!O140-'Model inputs'!O131)*'Model inputs'!O104,0)) -> 0 | L68: ='Model inputs'!L89*IF(IF(IF(IF(ISERROR('Model inputs'!O140>'Model inputs'!O131),'Model inputs'!O140>'Model inputs'!O131,IF(OR('Model inputs'!O140="",'Model inputs'!O131=""),"",'Model inputs'!O140>'Model inputs'!O131))="",FALSE,IF(ISERROR('Model inputs'!O140>'Model inputs'!O131),'Model inputs'!O140>'Model inputs'!O131,IF(OR('Model inputs'!O140="",'Model inputs'!O131=""),"",'Model inputs'!O140>'Model inputs'!O131))),('Model inputs'!O140-'Model inputs'!O131)*'Model inputs'!O104,0)="",0,IF(IF(IF(ISERROR('Model inputs'!O140>'Model inputs'!O131),'Model inputs'!O140>'Model inputs'!O131,IF(OR('Model inputs'!O140="",'Model inputs'!O131=""),"",'Model inputs'!O140>'Model inputs'!O131))="",FALSE,IF(ISERROR('Model inputs'!O140>'Model inputs'!O131),'Model inputs'!O140>'Model inputs'!O131,IF(OR('Model inputs'!O140="",'Model inputs'!O131=""),"",'Model inputs'!O140>'Model inputs'!O131))),('Model inputs'!O140-'Model inputs'!O131)*'Model inputs'!O104,0)) -> 0 | M68: ='Model inputs'!M89*IF(IF(IF(IF(ISERROR('Model inputs'!O140>'Model inputs'!O131),'Model inputs'!O140>'Model inputs'!O131,IF(OR('Model inputs'!O140="",'Model inputs'!O131=""),"",'Model inputs'!O140>'Model inputs'!O131))="",FALSE,IF(ISERROR('Model inputs'!O140>'Model inputs'!O131),'Model inputs'!O140>'Model inputs'!O131,IF(OR('Model inputs'!O140="",'Model inputs'!O131=""),"",'Model inputs'!O140>'Model inputs'!O131))),('Model inputs'!O140-'Model inputs'!O131)*'Model inputs'!O104,0)="",0,IF(IF(IF(ISERROR('Model inputs'!O140>'Model inputs'!O131),'Model inputs'!O140>'Model inputs'!O131,IF(OR('Model inputs'!O140="",'Model inputs'!O131=""),"",'Model inputs'!O140>'Model inputs'!O131))="",FALSE,IF(ISERROR('Model inputs'!O140>'Model inputs'!O131),'Model inputs'!O140>'Model inputs'!O131,IF(OR('Model inputs'!O140="",'Model inputs'!O131=""),"",'Model inputs'!O140>'Model inputs'!O131))),('Model inputs'!O140-'Model inputs'!O131)*'Model inputs'!O104,0)) -> 0 | N68: ='Model inputs'!N89*IF(IF(IF(IF(ISERROR('Model inputs'!O140>'Model inputs'!O131),'Model inputs'!O140>'Model inputs'!O131,IF(OR('Model inputs'!O140="",'Model inputs'!O131=""),"",'Model inputs'!O140>'Model inputs'!O131))="",FALSE,IF(ISERROR('Model inputs'!O140>'Model inputs'!O131),'Model inputs'!O140>'Model inputs'!O131,IF(OR('Model inputs'!O140="",'Model inputs'!O131=""),"",'Model inputs'!O140>'Model inputs'!O131))),('Model inputs'!O140-'Model inputs'!O131)*'Model inputs'!O104,0)="",0,IF(IF(IF(ISERROR('Model inputs'!O140>'Model inputs'!O131),'Model inputs'!O140>'Model inputs'!O131,IF(OR('Model inputs'!O140="",'Model inputs'!O131=""),"",'Model inputs'!O140>'Model inputs'!O131))="",FALSE,IF(ISERROR('Model inputs'!O140>'Model inputs'!O131),'Model inputs'!O140>'Model inputs'!O131,IF(OR('Model inputs'!O140="",'Model inputs'!O131=""),"",'Model inputs'!O140>'Model inputs'!O131))),('Model inputs'!O140-'Model inputs'!O131)*'Model inputs'!O104,0)) -> 0
A69: Overage revenue (USD) | B69: =SUM('Model inputs'!B70,'Model inputs'!B71) -> 0 | C69: =SUM('Model inputs'!C70,'Model inputs'!C71) -> 0 | D69: =SUM('Model inputs'!D70,'Model inputs'!D71) -> 0 | E69: =SUM('Model inputs'!E70,'Model inputs'!E71) -> 0 | F69: =SUM('Model inputs'!F70,'Model inputs'!F71) -> 0 | G69: =SUM('Model inputs'!G70,'Model inputs'!G71) -> 0 | H69: =SUM('Model inputs'!H70,'Model inputs'!H71) -> 0 | I69: =SUM('Model inputs'!I70,'Model inputs'!I71) -> 0 | ... N69: =SUM('Model inputs'!N70,'Model inputs'!N71) -> 0
A70: Overage revenue (USD) > Classroom | B70: ='Model inputs'!B67 -> 0 | C70: ='Model inputs'!C91*IF(IF(IF(IF(ISERROR('Model inputs'!O142>'Model inputs'!O133),'Model inputs'!O142>'Model inputs'!O133,IF(OR('Model inputs'!O142="",'Model inputs'!O133=""),"",'Model inputs'!O142>'Model inputs'!O133))="",FALSE,IF(ISERROR('Model inputs'!O142>'Model inputs'!O133),'Model inputs'!O142>'Model inputs'!O133,IF(OR('Model inputs'!O142="",'Model inputs'!O133=""),"",'Model inputs'!O142>'Model inputs'!O133))),('Model inputs'!O142-'Model inputs'!O133)*'Model inputs'!O106,0)="",0,IF(IF(IF(ISERROR('Model inputs'!O142>'Model inputs'!O133),'Model inputs'!O142>'Model inputs'!O133,IF(OR('Model inputs'!O142="",'Model inputs'!O133=""),"",'Model inputs'!O142>'Model inputs'!O133))="",FALSE,IF(ISERROR('Model inputs'!O142>'Model inputs'!O133),'Model inputs'!O142>'Model inputs'!O133,IF(OR('Model inputs'!O142="",'Model inputs'!O133=""),"",'Model inputs'!O142>'Model inputs'!O133))),('Model inputs'!O142-'Model inputs'!O133)*'Model inputs'!O106,0)) -> 0 | D70: ='Model inputs'!D91*IF(IF(IF(IF(ISERROR('Model inputs'!O142>'Model inputs'!O133),'Model inputs'!O142>'Model inputs'!O133,IF(OR('Model inputs'!O142="",'Model inputs'!O133=""),"",'Model inputs'!O142>'Model inputs'!O133))="",FALSE,IF(ISERROR('Model inputs'!O142>'Model inputs'!O133),'Model inputs'!O142>'Model inputs'!O133,IF(OR('Model inputs'!O142="",'Model inputs'!O133=""),"",'Model inputs'!O142>'Model inputs'!O133))),('Model inputs'!O142-'Model inputs'!O133)*'Model inputs'!O106,0)="",0,IF(IF(IF(ISERROR('Model inputs'!O142>'Model inputs'!O133),'Model inputs'!O142>'Model inputs'!O133,IF(OR('Model inputs'!O142="",'Model inputs'!O133=""),"",'Model inputs'!O142>'Model inputs'!O133))="",FALSE,IF(ISERROR('Model inputs'!O142>'Model inputs'!O133),'Model inputs'!O142>'Model inputs'!O133,IF(OR('Model inputs'!O142="",'Model inputs'!O133=""),"",'Model inputs'!O142>'Model inputs'!O133))),('Model inputs'!O142-'Model inputs'!O133)*'Model inputs'!O106,0)) -> 0 | E70: ='Model inputs'!E91*IF(IF(IF(IF(ISERROR('Model inputs'!O142>'Model inputs'!O133),'Model inputs'!O142>'Model inputs'!O133,IF(OR('Model inputs'!O142="",'Model inputs'!O133=""),"",'Model inputs'!O142>'Model inputs'!O133))="",FALSE,IF(ISERROR('Model inputs'!O142>'Model inputs'!O133),'Model inputs'!O142>'Model inputs'!O133,IF(OR('Model inputs'!O142="",'Model inputs'!O133=""),"",'Model inputs'!O142>'Model inputs'!O133))),('Model inputs'!O142-'Model inputs'!O133)*'Model inputs'!O106,0)="",0,IF(IF(IF(ISERROR('Model inputs'!O142>'Model inputs'!O133),'Model inputs'!O142>'Model inputs'!O133,IF(OR('Model inputs'!O142="",'Model inputs'!O133=""),"",'Model inputs'!O142>'Model inputs'!O133))="",FALSE,IF(ISERROR('Model inputs'!O142>'Model inputs'!O133),'Model inputs'!O142>'Model inputs'!O133,IF(OR('Model inputs'!O142="",'Model inputs'!O133=""),"",'Model inputs'!O142>'Model inputs'!O133))),('Model inputs'!O142-'Model inputs'!O133)*'Model inputs'!O106,0)) -> 0 | F70: ='Model inputs'!F91*IF(IF(IF(IF(ISERROR('Model inputs'!O142>'Model inputs'!O133),'Model inputs'!O142>'Model inputs'!O133,IF(OR('Model inputs'!O142="",'Model inputs'!O133=""),"",'Model inputs'!O142>'Model inputs'!O133))="",FALSE,IF(ISERROR('Model inputs'!O142>'Model inputs'!O133),'Model inputs'!O142>'Model inputs'!O133,IF(OR('Model inputs'!O142="",'Model inputs'!O133=""),"",'Model inputs'!O142>'Model inputs'!O133))),('Model inputs'!O142-'Model inputs'!O133)*'Model inputs'!O106,0)="",0,IF(IF(IF(ISERROR('Model inputs'!O142>'Model inputs'!O133),'Model inputs'!O142>'Model inputs'!O133,IF(OR('Model inputs'!O142="",'Model inputs'!O133=""),"",'Model inputs'!O142>'Model inputs'!O133))="",FALSE,IF(ISERROR('Model inputs'!O142>'Model inputs'!O133),'Model inputs'!O142>'Model inputs'!O133,IF(OR('Model inputs'!O142="",'Model inputs'!O133=""),"",'Model inputs'!O142>'Model inputs'!O133))),('Model inputs'!O142-'Model inputs'!O133)*'Model inputs'!O106,0)) -> 0 | G70: ='Model inputs'!G91*IF(IF(IF(IF(ISERROR('Model inputs'!O142>'Model inputs'!O133),'Model inputs'!O142>'Model inputs'!O133,IF(OR('Model inputs'!O142="",'Model inputs'!O133=""),"",'Model inputs'!O142>'Model inputs'!O133))="",FALSE,IF(ISERROR('Model inputs'!O142>'Model inputs'!O133),'Model inputs'!O142>'Model inputs'!O133,IF(OR('Model inputs'!O142="",'Model inputs'!O133=""),"",'Model inputs'!O142>'Model inputs'!O133))),('Model inputs'!O142-'Model inputs'!O133)*'Model inputs'!O106,0)="",0,IF(IF(IF(ISERROR('Model inputs'!O142>'Model inputs'!O133),'Model inputs'!O142>'Model inputs'!O133,IF(OR('Model inputs'!O142="",'Model inputs'!O133=""),"",'Model inputs'!O142>'Model inputs'!O133))="",FALSE,IF(ISERROR('Model inputs'!O142>'Model inputs'!O133),'Model inputs'!O142>'Model inputs'!O133,IF(OR('Model inputs'!O142="",'Model inputs'!O133=""),"",'Model inputs'!O142>'Model inputs'!O133))),('Model inputs'!O142-'Model inputs'!O133)*'Model inputs'!O106,0)) -> 0 | H70: ='Model inputs'!H91*IF(IF(IF(IF(ISERROR('Model inputs'!O142>'Model inputs'!O133),'Model inputs'!O142>'Model inputs'!O133,IF(OR('Model inputs'!O142="",'Model inputs'!O133=""),"",'Model inputs'!O142>'Model inputs'!O133))="",FALSE,IF(ISERROR('Model inputs'!O142>'Model inputs'!O133),'Model inputs'!O142>'Model inputs'!O133,IF(OR('Model inputs'!O142="",'Model inputs'!O133=""),"",'Model inputs'!O142>'Model inputs'!O133))),('Model inputs'!O142-'Model inputs'!O133)*'Model inputs'!O106,0)="",0,IF(IF(IF(ISERROR('Model inputs'!O142>'Model inputs'!O133),'Model inputs'!O142>'Model inputs'!O133,IF(OR('Model inputs'!O142="",'Model inputs'!O133=""),"",'Model inputs'!O142>'Model inputs'!O133))="",FALSE,IF(ISERROR('Model inputs'!O142>'Model inputs'!O133),'Model inputs'!O142>'Model inputs'!O133,IF(OR('Model inputs'!O142="",'Model inputs'!O133=""),"",'Model inputs'!O142>'Model inputs'!O133))),('Model inputs'!O142-'Model inputs'!O133)*'Model inputs'!O106,0)) -> 0 | I70: ='Model inputs'!I91*IF(IF(IF(IF(ISERROR('Model inputs'!O142>'Model inputs'!O133),'Model inputs'!O142>'Model inputs'!O133,IF(OR('Model inputs'!O142="",'Model inputs'!O133=""),"",'Model inputs'!O142>'Model inputs'!O133))="",FALSE,IF(ISERROR('Model inputs'!O142>'Model inputs'!O133),'Model inputs'!O142>'Model inputs'!O133,IF(OR('Model inputs'!O142="",'Model inputs'!O133=""),"",'Model inputs'!O142>'Model inputs'!O133))),('Model inputs'!O142-'Model inputs'!O133)*'Model inputs'!O106,0)="",0,IF(IF(IF(ISERROR('Model inputs'!O142>'Model inputs'!O133),'Model inputs'!O142>'Model inputs'!O133,IF(OR('Model inputs'!O142="",'Model inputs'!O133=""),"",'Model inputs'!O142>'Model inputs'!O133))="",FALSE,IF(ISERROR('Model inputs'!O142>'Model inputs'!O133),'Model inputs'!O142>'Model inputs'!O133,IF(OR('Model inputs'!O142="",'Model inputs'!O133=""),"",'Model inputs'!O142>'Model inputs'!O133))),('Model inputs'!O142-'Model inputs'!O133)*'Model inputs'!O106,0)) -> 0 | J70: ='Model inputs'!J91*IF(IF(IF(IF(ISERROR('Model inputs'!O142>'Model inputs'!O133),'Model inputs'!O142>'Model inputs'!O133,IF(OR('Model inputs'!O142="",'Model inputs'!O133=""),"",'Model inputs'!O142>'Model inputs'!O133))="",FALSE,IF(ISERROR('Model inputs'!O142>'Model inputs'!O133),'Model inputs'!O142>'Model inputs'!O133,IF(OR('Model inputs'!O142="",'Model inputs'!O133=""),"",'Model inputs'!O142>'Model inputs'!O133))),('Model inputs'!O142-'Model inputs'!O133)*'Model inputs'!O106,0)="",0,IF(IF(IF(ISERROR('Model inputs'!O142>'Model inputs'!O133),'Model inputs'!O142>'Model inputs'!O133,IF(OR('Model inputs'!O142="",'Model inputs'!O133=""),"",'Model inputs'!O142>'Model inputs'!O133))="",FALSE,IF(ISERROR('Model inputs'!O142>'Model inputs'!O133),'Model inputs'!O142>'Model inputs'!O133,IF(OR('Model inputs'!O142="",'Model inputs'!O133=""),"",'Model inputs'!O142>'Model inputs'!O133))),('Model inputs'!O142-'Model inputs'!O133)*'Model inputs'!O106,0)) -> 0 | K70: ='Model inputs'!K91*IF(IF(IF(IF(ISERROR('Model inputs'!O142>'Model inputs'!O133),'Model inputs'!O142>'Model inputs'!O133,IF(OR('Model inputs'!O142="",'Model inputs'!O133=""),"",'Model inputs'!O142>'Model inputs'!O133))="",FALSE,IF(ISERROR('Model inputs'!O142>'Model inputs'!O133),'Model inputs'!O142>'Model inputs'!O133,IF(OR('Model inputs'!O142="",'Model inputs'!O133=""),"",'Model inputs'!O142>'Model inputs'!O133))),('Model inputs'!O142-'Model inputs'!O133)*'Model inputs'!O106,0)="",0,IF(IF(IF(ISERROR('Model inputs'!O142>'Model inputs'!O133),'Model inputs'!O142>'Model inputs'!O133,IF(OR('Model inputs'!O142="",'Model inputs'!O133=""),"",'Model inputs'!O142>'Model inputs'!O133))="",FALSE,IF(ISERROR('Model inputs'!O142>'Model inputs'!O133),'Model inputs'!O142>'Model inputs'!O133,IF(OR('Model inputs'!O142="",'Model inputs'!O133=""),"",'Model inputs'!O142>'Model inputs'!O133))),('Model inputs'!O142-'Model inputs'!O133)*'Model inputs'!O106,0)) -> 0 | L70: ='Model inputs'!L91*IF(IF(IF(IF(ISERROR('Model inputs'!O142>'Model inputs'!O133),'Model inputs'!O142>'Model inputs'!O133,IF(OR('Model inputs'!O142="",'Model inputs'!O133=""),"",'Model inputs'!O142>'Model inputs'!O133))="",FALSE,IF(ISERROR('Model inputs'!O142>'Model inputs'!O133),'Model inputs'!O142>'Model inputs'!O133,IF(OR('Model inputs'!O142="",'Model inputs'!O133=""),"",'Model inputs'!O142>'Model inputs'!O133))),('Model inputs'!O142-'Model inputs'!O133)*'Model inputs'!O106,0)="",0,IF(IF(IF(ISERROR('Model inputs'!O142>'Model inputs'!O133),'Model inputs'!O142>'Model inputs'!O133,IF(OR('Model inputs'!O142="",'Model inputs'!O133=""),"",'Model inputs'!O142>'Model inputs'!O133))="",FALSE,IF(ISERROR('Model inputs'!O142>'Model inputs'!O133),'Model inputs'!O142>'Model inputs'!O133,IF(OR('Model inputs'!O142="",'Model inputs'!O133=""),"",'Model inputs'!O142>'Model inputs'!O133))),('Model inputs'!O142-'Model inputs'!O133)*'Model inputs'!O106,0)) -> 0 | M70: ='Model inputs'!M91*IF(IF(IF(IF(ISERROR('Model inputs'!O142>'Model inputs'!O133),'Model inputs'!O142>'Model inputs'!O133,IF(OR('Model inputs'!O142="",'Model inputs'!O133=""),"",'Model inputs'!O142>'Model inputs'!O133))="",FALSE,IF(ISERROR('Model inputs'!O142>'Model inputs'!O133),'Model inputs'!O142>'Model inputs'!O133,IF(OR('Model inputs'!O142="",'Model inputs'!O133=""),"",'Model inputs'!O142>'Model inputs'!O133))),('Model inputs'!O142-'Model inputs'!O133)*'Model inputs'!O106,0)="",0,IF(IF(IF(ISERROR('Model inputs'!O142>'Model inputs'!O133),'Model inputs'!O142>'Model inputs'!O133,IF(OR('Model inputs'!O142="",'Model inputs'!O133=""),"",'Model inputs'!O142>'Model inputs'!O133))="",FALSE,IF(ISERROR('Model inputs'!O142>'Model inputs'!O133),'Model inputs'!O142>'Model inputs'!O133,IF(OR('Model inputs'!O142="",'Model inputs'!O133=""),"",'Model inputs'!O142>'Model inputs'!O133))),('Model inputs'!O142-'Model inputs'!O133)*'Model inputs'!O106,0)) -> 0 | N70: ='Model inputs'!N91*IF(IF(IF(IF(ISERROR('Model inputs'!O142>'Model inputs'!O133),'Model inputs'!O142>'Model inputs'!O133,IF(OR('Model inputs'!O142="",'Model inputs'!O133=""),"",'Model inputs'!O142>'Model inputs'!O133))="",FALSE,IF(ISERROR('Model inputs'!O142>'Model inputs'!O133),'Model inputs'!O142>'Model inputs'!O133,IF(OR('Model inputs'!O142="",'Model inputs'!O133=""),"",'Model inputs'!O142>'Model inputs'!O133))),('Model inputs'!O142-'Model inputs'!O133)*'Model inputs'!O106,0)="",0,IF(IF(IF(ISERROR('Model inputs'!O142>'Model inputs'!O133),'Model inputs'!O142>'Model inputs'!O133,IF(OR('Model inputs'!O142="",'Model inputs'!O133=""),"",'Model inputs'!O142>'Model inputs'!O133))="",FALSE,IF(ISERROR('Model inputs'!O142>'Model inputs'!O133),'Model inputs'!O142>'Model inputs'!O133,IF(OR('Model inputs'!O142="",'Model inputs'!O133=""),"",'Model inputs'!O142>'Model inputs'!O133))),('Model inputs'!O142-'Model inputs'!O133)*'Model inputs'!O106,0)) -> 0
A71: Overage revenue (USD) > Household | B71: ='Model inputs'!B68 -> 0 | C71: ='Model inputs'!C92*IF(IF(IF(IF(ISERROR('Model inputs'!O143>'Model inputs'!O134),'Model inputs'!O143>'Model inputs'!O134,IF(OR('Model inputs'!O143="",'Model inputs'!O134=""),"",'Model inputs'!O143>'Model inputs'!O134))="",FALSE,IF(ISERROR('Model inputs'!O143>'Model inputs'!O134),'Model inputs'!O143>'Model inputs'!O134,IF(OR('Model inputs'!O143="",'Model inputs'!O134=""),"",'Model inputs'!O143>'Model inputs'!O134))),('Model inputs'!O143-'Model inputs'!O134)*'Model inputs'!O107,0)="",0,IF(IF(IF(ISERROR('Model inputs'!O143>'Model inputs'!O134),'Model inputs'!O143>'Model inputs'!O134,IF(OR('Model inputs'!O143="",'Model inputs'!O134=""),"",'Model inputs'!O143>'Model inputs'!O134))="",FALSE,IF(ISERROR('Model inputs'!O143>'Model inputs'!O134),'Model inputs'!O143>'Model inputs'!O134,IF(OR('Model inputs'!O143="",'Model inputs'!O134=""),"",'Model inputs'!O143>'Model inputs'!O134))),('Model inputs'!O143-'Model inputs'!O134)*'Model inputs'!O107,0)) -> 0 | D71: ='Model inputs'!D92*IF(IF(IF(IF(ISERROR('Model inputs'!O143>'Model inputs'!O134),'Model inputs'!O143>'Model inputs'!O134,IF(OR('Model inputs'!O143="",'Model inputs'!O134=""),"",'Model inputs'!O143>'Model inputs'!O134))="",FALSE,IF(ISERROR('Model inputs'!O143>'Model inputs'!O134),'Model inputs'!O143>'Model inputs'!O134,IF(OR('Model inputs'!O143="",'Model inputs'!O134=""),"",'Model inputs'!O143>'Model inputs'!O134))),('Model inputs'!O143-'Model inputs'!O134)*'Model inputs'!O107,0)="",0,IF(IF(IF(ISERROR('Model inputs'!O143>'Model inputs'!O134),'Model inputs'!O143>'Model inputs'!O134,IF(OR('Model inputs'!O143="",'Model inputs'!O134=""),"",'Model inputs'!O143>'Model inputs'!O134))="",FALSE,IF(ISERROR('Model inputs'!O143>'Model inputs'!O134),'Model inputs'!O143>'Model inputs'!O134,IF(OR('Model inputs'!O143="",'Model inputs'!O134=""),"",'Model inputs'!O143>'Model inputs'!O134))),('Model inputs'!O143-'Model inputs'!O134)*'Model inputs'!O107,0)) -> 0 | E71: ='Model inputs'!E92*IF(IF(IF(IF(ISERROR('Model inputs'!O143>'Model inputs'!O134),'Model inputs'!O143>'Model inputs'!O134,IF(OR('Model inputs'!O143="",'Model inputs'!O134=""),"",'Model inputs'!O143>'Model inputs'!O134))="",FALSE,IF(ISERROR('Model inputs'!O143>'Model inputs'!O134),'Model inputs'!O143>'Model inputs'!O134,IF(OR('Model inputs'!O143="",'Model inputs'!O134=""),"",'Model inputs'!O143>'Model inputs'!O134))),('Model inputs'!O143-'Model inputs'!O134)*'Model inputs'!O107,0)="",0,IF(IF(IF(ISERROR('Model inputs'!O143>'Model inputs'!O134),'Model inputs'!O143>'Model inputs'!O134,IF(OR('Model inputs'!O143="",'Model inputs'!O134=""),"",'Model inputs'!O143>'Model inputs'!O134))="",FALSE,IF(ISERROR('Model inputs'!O143>'Model inputs'!O134),'Model inputs'!O143>'Model inputs'!O134,IF(OR('Model inputs'!O143="",'Model inputs'!O134=""),"",'Model inputs'!O143>'Model inputs'!O134))),('Model inputs'!O143-'Model inputs'!O134)*'Model inputs'!O107,0)) -> 0 | F71: ='Model inputs'!F92*IF(IF(IF(IF(ISERROR('Model inputs'!O143>'Model inputs'!O134),'Model inputs'!O143>'Model inputs'!O134,IF(OR('Model inputs'!O143="",'Model inputs'!O134=""),"",'Model inputs'!O143>'Model inputs'!O134))="",FALSE,IF(ISERROR('Model inputs'!O143>'Model inputs'!O134),'Model inputs'!O143>'Model inputs'!O134,IF(OR('Model inputs'!O143="",'Model inputs'!O134=""),"",'Model inputs'!O143>'Model inputs'!O134))),('Model inputs'!O143-'Model inputs'!O134)*'Model inputs'!O107,0)="",0,IF(IF(IF(ISERROR('Model inputs'!O143>'Model inputs'!O134),'Model inputs'!O143>'Model inputs'!O134,IF(OR('Model inputs'!O143="",'Model inputs'!O134=""),"",'Model inputs'!O143>'Model inputs'!O134))="",FALSE,IF(ISERROR('Model inputs'!O143>'Model inputs'!O134),'Model inputs'!O143>'Model inputs'!O134,IF(OR('Model inputs'!O143="",'Model inputs'!O134=""),"",'Model inputs'!O143>'Model inputs'!O134))),('Model inputs'!O143-'Model inputs'!O134)*'Model inputs'!O107,0)) -> 0 | G71: ='Model inputs'!G92*IF(IF(IF(IF(ISERROR('Model inputs'!O143>'Model inputs'!O134),'Model inputs'!O143>'Model inputs'!O134,IF(OR('Model inputs'!O143="",'Model inputs'!O134=""),"",'Model inputs'!O143>'Model inputs'!O134))="",FALSE,IF(ISERROR('Model inputs'!O143>'Model inputs'!O134),'Model inputs'!O143>'Model inputs'!O134,IF(OR('Model inputs'!O143="",'Model inputs'!O134=""),"",'Model inputs'!O143>'Model inputs'!O134))),('Model inputs'!O143-'Model inputs'!O134)*'Model inputs'!O107,0)="",0,IF(IF(IF(ISERROR('Model inputs'!O143>'Model inputs'!O134),'Model inputs'!O143>'Model inputs'!O134,IF(OR('Model inputs'!O143="",'Model inputs'!O134=""),"",'Model inputs'!O143>'Model inputs'!O134))="",FALSE,IF(ISERROR('Model inputs'!O143>'Model inputs'!O134),'Model inputs'!O143>'Model inputs'!O134,IF(OR('Model inputs'!O143="",'Model inputs'!O134=""),"",'Model inputs'!O143>'Model inputs'!O134))),('Model inputs'!O143-'Model inputs'!O134)*'Model inputs'!O107,0)) -> 0 | H71: ='Model inputs'!H92*IF(IF(IF(IF(ISERROR('Model inputs'!O143>'Model inputs'!O134),'Model inputs'!O143>'Model inputs'!O134,IF(OR('Model inputs'!O143="",'Model inputs'!O134=""),"",'Model inputs'!O143>'Model inputs'!O134))="",FALSE,IF(ISERROR('Model inputs'!O143>'Model inputs'!O134),'Model inputs'!O143>'Model inputs'!O134,IF(OR('Model inputs'!O143="",'Model inputs'!O134=""),"",'Model inputs'!O143>'Model inputs'!O134))),('Model inputs'!O143-'Model inputs'!O134)*'Model inputs'!O107,0)="",0,IF(IF(IF(ISERROR('Model inputs'!O143>'Model inputs'!O134),'Model inputs'!O143>'Model inputs'!O134,IF(OR('Model inputs'!O143="",'Model inputs'!O134=""),"",'Model inputs'!O143>'Model inputs'!O134))="",FALSE,IF(ISERROR('Model inputs'!O143>'Model inputs'!O134),'Model inputs'!O143>'Model inputs'!O134,IF(OR('Model inputs'!O143="",'Model inputs'!O134=""),"",'Model inputs'!O143>'Model inputs'!O134))),('Model inputs'!O143-'Model inputs'!O134)*'Model inputs'!O107,0)) -> 0 | I71: ='Model inputs'!I92*IF(IF(IF(IF(ISERROR('Model inputs'!O143>'Model inputs'!O134),'Model inputs'!O143>'Model inputs'!O134,IF(OR('Model inputs'!O143="",'Model inputs'!O134=""),"",'Model inputs'!O143>'Model inputs'!O134))="",FALSE,IF(ISERROR('Model inputs'!O143>'Model inputs'!O134),'Model inputs'!O143>'Model inputs'!O134,IF(OR('Model inputs'!O143="",'Model inputs'!O134=""),"",'Model inputs'!O143>'Model inputs'!O134))),('Model inputs'!O143-'Model inputs'!O134)*'Model inputs'!O107,0)="",0,IF(IF(IF(ISERROR('Model inputs'!O143>'Model inputs'!O134),'Model inputs'!O143>'Model inputs'!O134,IF(OR('Model inputs'!O143="",'Model inputs'!O134=""),"",'Model inputs'!O143>'Model inputs'!O134))="",FALSE,IF(ISERROR('Model inputs'!O143>'Model inputs'!O134),'Model inputs'!O143>'Model inputs'!O134,IF(OR('Model inputs'!O143="",'Model inputs'!O134=""),"",'Model inputs'!O143>'Model inputs'!O134))),('Model inputs'!O143-'Model inputs'!O134)*'Model inputs'!O107,0)) -> 0 | J71: ='Model inputs'!J92*IF(IF(IF(IF(ISERROR('Model inputs'!O143>'Model inputs'!O134),'Model inputs'!O143>'Model inputs'!O134,IF(OR('Model inputs'!O143="",'Model inputs'!O134=""),"",'Model inputs'!O143>'Model inputs'!O134))="",FALSE,IF(ISERROR('Model inputs'!O143>'Model inputs'!O134),'Model inputs'!O143>'Model inputs'!O134,IF(OR('Model inputs'!O143="",'Model inputs'!O134=""),"",'Model inputs'!O143>'Model inputs'!O134))),('Model inputs'!O143-'Model inputs'!O134)*'Model inputs'!O107,0)="",0,IF(IF(IF(ISERROR('Model inputs'!O143>'Model inputs'!O134),'Model inputs'!O143>'Model inputs'!O134,IF(OR('Model inputs'!O143="",'Model inputs'!O134=""),"",'Model inputs'!O143>'Model inputs'!O134))="",FALSE,IF(ISERROR('Model inputs'!O143>'Model inputs'!O134),'Model inputs'!O143>'Model inputs'!O134,IF(OR('Model inputs'!O143="",'Model inputs'!O134=""),"",'Model inputs'!O143>'Model inputs'!O134))),('Model inputs'!O143-'Model inputs'!O134)*'Model inputs'!O107,0)) -> 0 | K71: ='Model inputs'!K92*IF(IF(IF(IF(ISERROR('Model inputs'!O143>'Model inputs'!O134),'Model inputs'!O143>'Model inputs'!O134,IF(OR('Model inputs'!O143="",'Model inputs'!O134=""),"",'Model inputs'!O143>'Model inputs'!O134))="",FALSE,IF(ISERROR('Model inputs'!O143>'Model inputs'!O134),'Model inputs'!O143>'Model inputs'!O134,IF(OR('Model inputs'!O143="",'Model inputs'!O134=""),"",'Model inputs'!O143>'Model inputs'!O134))),('Model inputs'!O143-'Model inputs'!O134)*'Model inputs'!O107,0)="",0,IF(IF(IF(ISERROR('Model inputs'!O143>'Model inputs'!O134),'Model inputs'!O143>'Model inputs'!O134,IF(OR('Model inputs'!O143="",'Model inputs'!O134=""),"",'Model inputs'!O143>'Model inputs'!O134))="",FALSE,IF(ISERROR('Model inputs'!O143>'Model inputs'!O134),'Model inputs'!O143>'Model inputs'!O134,IF(OR('Model inputs'!O143="",'Model inputs'!O134=""),"",'Model inputs'!O143>'Model inputs'!O134))),('Model inputs'!O143-'Model inputs'!O134)*'Model inputs'!O107,0)) -> 0 | L71: ='Model inputs'!L92*IF(IF(IF(IF(ISERROR('Model inputs'!O143>'Model inputs'!O134),'Model inputs'!O143>'Model inputs'!O134,IF(OR('Model inputs'!O143="",'Model inputs'!O134=""),"",'Model inputs'!O143>'Model inputs'!O134))="",FALSE,IF(ISERROR('Model inputs'!O143>'Model inputs'!O134),'Model inputs'!O143>'Model inputs'!O134,IF(OR('Model inputs'!O143="",'Model inputs'!O134=""),"",'Model inputs'!O143>'Model inputs'!O134))),('Model inputs'!O143-'Model inputs'!O134)*'Model inputs'!O107,0)="",0,IF(IF(IF(ISERROR('Model inputs'!O143>'Model inputs'!O134),'Model inputs'!O143>'Model inputs'!O134,IF(OR('Model inputs'!O143="",'Model inputs'!O134=""),"",'Model inputs'!O143>'Model inputs'!O134))="",FALSE,IF(ISERROR('Model inputs'!O143>'Model inputs'!O134),'Model inputs'!O143>'Model inputs'!O134,IF(OR('Model inputs'!O143="",'Model inputs'!O134=""),"",'Model inputs'!O143>'Model inputs'!O134))),('Model inputs'!O143-'Model inputs'!O134)*'Model inputs'!O107,0)) -> 0 | M71: ='Model inputs'!M92*IF(IF(IF(IF(ISERROR('Model inputs'!O143>'Model inputs'!O134),'Model inputs'!O143>'Model inputs'!O134,IF(OR('Model inputs'!O143="",'Model inputs'!O134=""),"",'Model inputs'!O143>'Model inputs'!O134))="",FALSE,IF(ISERROR('Model inputs'!O143>'Model inputs'!O134),'Model inputs'!O143>'Model inputs'!O134,IF(OR('Model inputs'!O143="",'Model inputs'!O134=""),"",'Model inputs'!O143>'Model inputs'!O134))),('Model inputs'!O143-'Model inputs'!O134)*'Model inputs'!O107,0)="",0,IF(IF(IF(ISERROR('Model inputs'!O143>'Model inputs'!O134),'Model inputs'!O143>'Model inputs'!O134,IF(OR('Model inputs'!O143="",'Model inputs'!O134=""),"",'Model inputs'!O143>'Model inputs'!O134))="",FALSE,IF(ISERROR('Model inputs'!O143>'Model inputs'!O134),'Model inputs'!O143>'Model inputs'!O134,IF(OR('Model inputs'!O143="",'Model inputs'!O134=""),"",'Model inputs'!O143>'Model inputs'!O134))),('Model inputs'!O143-'Model inputs'!O134)*'Model inputs'!O107,0)) -> 0 | N71: ='Model inputs'!N92*IF(IF(IF(IF(ISERROR('Model inputs'!O143>'Model inputs'!O134),'Model inputs'!O143>'Model inputs'!O134,IF(OR('Model inputs'!O143="",'Model inputs'!O134=""),"",'Model inputs'!O143>'Model inputs'!O134))="",FALSE,IF(ISERROR('Model inputs'!O143>'Model inputs'!O134),'Model inputs'!O143>'Model inputs'!O134,IF(OR('Model inputs'!O143="",'Model inputs'!O134=""),"",'Model inputs'!O143>'Model inputs'!O134))),('Model inputs'!O143-'Model inputs'!O134)*'Model inputs'!O107,0)="",0,IF(IF(IF(ISERROR('Model inputs'!O143>'Model inputs'!O134),'Model inputs'!O143>'Model inputs'!O134,IF(OR('Model inputs'!O143="",'Model inputs'!O134=""),"",'Model inputs'!O143>'Model inputs'!O134))="",FALSE,IF(ISERROR('Model inputs'!O143>'Model inputs'!O134),'Model inputs'!O143>'Model inputs'!O134,IF(OR('Model inputs'!O143="",'Model inputs'!O134=""),"",'Model inputs'!O143>'Model inputs'!O134))),('Model inputs'!O143-'Model inputs'!O134)*'Model inputs'!O107,0)) -> 0
A72: Overage revenue (USD) | B72: =SUM('Model inputs'!B73,'Model inputs'!B74) -> 0 | C72: =SUM('Model inputs'!C73,'Model inputs'!C74) -> 0 | D72: =SUM('Model inputs'!D73,'Model inputs'!D74) -> 0 | E72: =SUM('Model inputs'!E73,'Model inputs'!E74) -> 0 | F72: =SUM('Model inputs'!F73,'Model inputs'!F74) -> 0 | G72: =SUM('Model inputs'!G73,'Model inputs'!G74) -> 0 | H72: =SUM('Model inputs'!H73,'Model inputs'!H74) -> 0 | I72: =SUM('Model inputs'!I73,'Model inputs'!I74) -> 0 | ... N72: =SUM('Model inputs'!N73,'Model inputs'!N74) -> 0
A73: Overage revenue (USD) > Classroom | B73: ='Model inputs'!B67 -> 0 | C73: ='Model inputs'!C94*IF(IF(IF(IF(ISERROR('Model inputs'!O145>'Model inputs'!O136),'Model inputs'!O145>'Model inputs'!O136,IF(OR('Model inputs'!O145="",'Model inputs'!O136=""),"",'Model inputs'!O145>'Model inputs'!O136))="",FALSE,IF(ISERROR('Model inputs'!O145>'Model inputs'!O136),'Model inputs'!O145>'Model inputs'!O136,IF(OR('Model inputs'!O145="",'Model inputs'!O136=""),"",'Model inputs'!O145>'Model inputs'!O136))),('Model inputs'!O145-'Model inputs'!O136)*'Model inputs'!O109,0)="",0,IF(IF(IF(ISERROR('Model inputs'!O145>'Model inputs'!O136),'Model inputs'!O145>'Model inputs'!O136,IF(OR('Model inputs'!O145="",'Model inputs'!O136=""),"",'Model inputs'!O145>'Model inputs'!O136))="",FALSE,IF(ISERROR('Model inputs'!O145>'Model inputs'!O136),'Model inputs'!O145>'Model inputs'!O136,IF(OR('Model inputs'!O145="",'Model inputs'!O136=""),"",'Model inputs'!O145>'Model inputs'!O136))),('Model inputs'!O145-'Model inputs'!O136)*'Model inputs'!O109,0)) -> 0 | D73: ='Model inputs'!D94*IF(IF(IF(IF(ISERROR('Model inputs'!O145>'Model inputs'!O136),'Model inputs'!O145>'Model inputs'!O136,IF(OR('Model inputs'!O145="",'Model inputs'!O136=""),"",'Model inputs'!O145>'Model inputs'!O136))="",FALSE,IF(ISERROR('Model inputs'!O145>'Model inputs'!O136),'Model inputs'!O145>'Model inputs'!O136,IF(OR('Model inputs'!O145="",'Model inputs'!O136=""),"",'Model inputs'!O145>'Model inputs'!O136))),('Model inputs'!O145-'Model inputs'!O136)*'Model inputs'!O109,0)="",0,IF(IF(IF(ISERROR('Model inputs'!O145>'Model inputs'!O136),'Model inputs'!O145>'Model inputs'!O136,IF(OR('Model inputs'!O145="",'Model inputs'!O136=""),"",'Model inputs'!O145>'Model inputs'!O136))="",FALSE,IF(ISERROR('Model inputs'!O145>'Model inputs'!O136),'Model inputs'!O145>'Model inputs'!O136,IF(OR('Model inputs'!O145="",'Model inputs'!O136=""),"",'Model inputs'!O145>'Model inputs'!O136))),('Model inputs'!O145-'Model inputs'!O136)*'Model inputs'!O109,0)) -> 0 | E73: ='Model inputs'!E94*IF(IF(IF(IF(ISERROR('Model inputs'!O145>'Model inputs'!O136),'Model inputs'!O145>'Model inputs'!O136,IF(OR('Model inputs'!O145="",'Model inputs'!O136=""),"",'Model inputs'!O145>'Model inputs'!O136))="",FALSE,IF(ISERROR('Model inputs'!O145>'Model inputs'!O136),'Model inputs'!O145>'Model inputs'!O136,IF(OR('Model inputs'!O145="",'Model inputs'!O136=""),"",'Model inputs'!O145>'Model inputs'!O136))),('Model inputs'!O145-'Model inputs'!O136)*'Model inputs'!O109,0)="",0,IF(IF(IF(ISERROR('Model inputs'!O145>'Model inputs'!O136),'Model inputs'!O145>'Model inputs'!O136,IF(OR('Model inputs'!O145="",'Model inputs'!O136=""),"",'Model inputs'!O145>'Model inputs'!O136))="",FALSE,IF(ISERROR('Model inputs'!O145>'Model inputs'!O136),'Model inputs'!O145>'Model inputs'!O136,IF(OR('Model inputs'!O145="",'Model inputs'!O136=""),"",'Model inputs'!O145>'Model inputs'!O136))),('Model inputs'!O145-'Model inputs'!O136)*'Model inputs'!O109,0)) -> 0 | F73: ='Model inputs'!F94*IF(IF(IF(IF(ISERROR('Model inputs'!O145>'Model inputs'!O136),'Model inputs'!O145>'Model inputs'!O136,IF(OR('Model inputs'!O145="",'Model inputs'!O136=""),"",'Model inputs'!O145>'Model inputs'!O136))="",FALSE,IF(ISERROR('Model inputs'!O145>'Model inputs'!O136),'Model inputs'!O145>'Model inputs'!O136,IF(OR('Model inputs'!O145="",'Model inputs'!O136=""),"",'Model inputs'!O145>'Model inputs'!O136))),('Model inputs'!O145-'Model inputs'!O136)*'Model inputs'!O109,0)="",0,IF(IF(IF(ISERROR('Model inputs'!O145>'Model inputs'!O136),'Model inputs'!O145>'Model inputs'!O136,IF(OR('Model inputs'!O145="",'Model inputs'!O136=""),"",'Model inputs'!O145>'Model inputs'!O136))="",FALSE,IF(ISERROR('Model inputs'!O145>'Model inputs'!O136),'Model inputs'!O145>'Model inputs'!O136,IF(OR('Model inputs'!O145="",'Model inputs'!O136=""),"",'Model inputs'!O145>'Model inputs'!O136))),('Model inputs'!O145-'Model inputs'!O136)*'Model inputs'!O109,0)) -> 0 | G73: ='Model inputs'!G94*IF(IF(IF(IF(ISERROR('Model inputs'!O145>'Model inputs'!O136),'Model inputs'!O145>'Model inputs'!O136,IF(OR('Model inputs'!O145="",'Model inputs'!O136=""),"",'Model inputs'!O145>'Model inputs'!O136))="",FALSE,IF(ISERROR('Model inputs'!O145>'Model inputs'!O136),'Model inputs'!O145>'Model inputs'!O136,IF(OR('Model inputs'!O145="",'Model inputs'!O136=""),"",'Model inputs'!O145>'Model inputs'!O136))),('Model inputs'!O145-'Model inputs'!O136)*'Model inputs'!O109,0)="",0,IF(IF(IF(ISERROR('Model inputs'!O145>'Model inputs'!O136),'Model inputs'!O145>'Model inputs'!O136,IF(OR('Model inputs'!O145="",'Model inputs'!O136=""),"",'Model inputs'!O145>'Model inputs'!O136))="",FALSE,IF(ISERROR('Model inputs'!O145>'Model inputs'!O136),'Model inputs'!O145>'Model inputs'!O136,IF(OR('Model inputs'!O145="",'Model inputs'!O136=""),"",'Model inputs'!O145>'Model inputs'!O136))),('Model inputs'!O145-'Model inputs'!O136)*'Model inputs'!O109,0)) -> 0 | H73: ='Model inputs'!H94*IF(IF(IF(IF(ISERROR('Model inputs'!O145>'Model inputs'!O136),'Model inputs'!O145>'Model inputs'!O136,IF(OR('Model inputs'!O145="",'Model inputs'!O136=""),"",'Model inputs'!O145>'Model inputs'!O136))="",FALSE,IF(ISERROR('Model inputs'!O145>'Model inputs'!O136),'Model inputs'!O145>'Model inputs'!O136,IF(OR('Model inputs'!O145="",'Model inputs'!O136=""),"",'Model inputs'!O145>'Model inputs'!O136))),('Model inputs'!O145-'Model inputs'!O136)*'Model inputs'!O109,0)="",0,IF(IF(IF(ISERROR('Model inputs'!O145>'Model inputs'!O136),'Model inputs'!O145>'Model inputs'!O136,IF(OR('Model inputs'!O145="",'Model inputs'!O136=""),"",'Model inputs'!O145>'Model inputs'!O136))="",FALSE,IF(ISERROR('Model inputs'!O145>'Model inputs'!O136),'Model inputs'!O145>'Model inputs'!O136,IF(OR('Model inputs'!O145="",'Model inputs'!O136=""),"",'Model inputs'!O145>'Model inputs'!O136))),('Model inputs'!O145-'Model inputs'!O136)*'Model inputs'!O109,0)) -> 0 | I73: ='Model inputs'!I94*IF(IF(IF(IF(ISERROR('Model inputs'!O145>'Model inputs'!O136),'Model inputs'!O145>'Model inputs'!O136,IF(OR('Model inputs'!O145="",'Model inputs'!O136=""),"",'Model inputs'!O145>'Model inputs'!O136))="",FALSE,IF(ISERROR('Model inputs'!O145>'Model inputs'!O136),'Model inputs'!O145>'Model inputs'!O136,IF(OR('Model inputs'!O145="",'Model inputs'!O136=""),"",'Model inputs'!O145>'Model inputs'!O136))),('Model inputs'!O145-'Model inputs'!O136)*'Model inputs'!O109,0)="",0,IF(IF(IF(ISERROR('Model inputs'!O145>'Model inputs'!O136),'Model inputs'!O145>'Model inputs'!O136,IF(OR('Model inputs'!O145="",'Model inputs'!O136=""),"",'Model inputs'!O145>'Model inputs'!O136))="",FALSE,IF(ISERROR('Model inputs'!O145>'Model inputs'!O136),'Model inputs'!O145>'Model inputs'!O136,IF(OR('Model inputs'!O145="",'Model inputs'!O136=""),"",'Model inputs'!O145>'Model inputs'!O136))),('Model inputs'!O145-'Model inputs'!O136)*'Model inputs'!O109,0)) -> 0 | J73: ='Model inputs'!J94*IF(IF(IF(IF(ISERROR('Model inputs'!O145>'Model inputs'!O136),'Model inputs'!O145>'Model inputs'!O136,IF(OR('Model inputs'!O145="",'Model inputs'!O136=""),"",'Model inputs'!O145>'Model inputs'!O136))="",FALSE,IF(ISERROR('Model inputs'!O145>'Model inputs'!O136),'Model inputs'!O145>'Model inputs'!O136,IF(OR('Model inputs'!O145="",'Model inputs'!O136=""),"",'Model inputs'!O145>'Model inputs'!O136))),('Model inputs'!O145-'Model inputs'!O136)*'Model inputs'!O109,0)="",0,IF(IF(IF(ISERROR('Model inputs'!O145>'Model inputs'!O136),'Model inputs'!O145>'Model inputs'!O136,IF(OR('Model inputs'!O145="",'Model inputs'!O136=""),"",'Model inputs'!O145>'Model inputs'!O136))="",FALSE,IF(ISERROR('Model inputs'!O145>'Model inputs'!O136),'Model inputs'!O145>'Model inputs'!O136,IF(OR('Model inputs'!O145="",'Model inputs'!O136=""),"",'Model inputs'!O145>'Model inputs'!O136))),('Model inputs'!O145-'Model inputs'!O136)*'Model inputs'!O109,0)) -> 0 | K73: ='Model inputs'!K94*IF(IF(IF(IF(ISERROR('Model inputs'!O145>'Model inputs'!O136),'Model inputs'!O145>'Model inputs'!O136,IF(OR('Model inputs'!O145="",'Model inputs'!O136=""),"",'Model inputs'!O145>'Model inputs'!O136))="",FALSE,IF(ISERROR('Model inputs'!O145>'Model inputs'!O136),'Model inputs'!O145>'Model inputs'!O136,IF(OR('Model inputs'!O145="",'Model inputs'!O136=""),"",'Model inputs'!O145>'Model inputs'!O136))),('Model inputs'!O145-'Model inputs'!O136)*'Model inputs'!O109,0)="",0,IF(IF(IF(ISERROR('Model inputs'!O145>'Model inputs'!O136),'Model inputs'!O145>'Model inputs'!O136,IF(OR('Model inputs'!O145="",'Model inputs'!O136=""),"",'Model inputs'!O145>'Model inputs'!O136))="",FALSE,IF(ISERROR('Model inputs'!O145>'Model inputs'!O136),'Model inputs'!O145>'Model inputs'!O136,IF(OR('Model inputs'!O145="",'Model inputs'!O136=""),"",'Model inputs'!O145>'Model inputs'!O136))),('Model inputs'!O145-'Model inputs'!O136)*'Model inputs'!O109,0)) -> 0 | L73: ='Model inputs'!L94*IF(IF(IF(IF(ISERROR('Model inputs'!O145>'Model inputs'!O136),'Model inputs'!O145>'Model inputs'!O136,IF(OR('Model inputs'!O145="",'Model inputs'!O136=""),"",'Model inputs'!O145>'Model inputs'!O136))="",FALSE,IF(ISERROR('Model inputs'!O145>'Model inputs'!O136),'Model inputs'!O145>'Model inputs'!O136,IF(OR('Model inputs'!O145="",'Model inputs'!O136=""),"",'Model inputs'!O145>'Model inputs'!O136))),('Model inputs'!O145-'Model inputs'!O136)*'Model inputs'!O109,0)="",0,IF(IF(IF(ISERROR('Model inputs'!O145>'Model inputs'!O136),'Model inputs'!O145>'Model inputs'!O136,IF(OR('Model inputs'!O145="",'Model inputs'!O136=""),"",'Model inputs'!O145>'Model inputs'!O136))="",FALSE,IF(ISERROR('Model inputs'!O145>'Model inputs'!O136),'Model inputs'!O145>'Model inputs'!O136,IF(OR('Model inputs'!O145="",'Model inputs'!O136=""),"",'Model inputs'!O145>'Model inputs'!O136))),('Model inputs'!O145-'Model inputs'!O136)*'Model inputs'!O109,0)) -> 0 | M73: ='Model inputs'!M94*IF(IF(IF(IF(ISERROR('Model inputs'!O145>'Model inputs'!O136),'Model inputs'!O145>'Model inputs'!O136,IF(OR('Model inputs'!O145="",'Model inputs'!O136=""),"",'Model inputs'!O145>'Model inputs'!O136))="",FALSE,IF(ISERROR('Model inputs'!O145>'Model inputs'!O136),'Model inputs'!O145>'Model inputs'!O136,IF(OR('Model inputs'!O145="",'Model inputs'!O136=""),"",'Model inputs'!O145>'Model inputs'!O136))),('Model inputs'!O145-'Model inputs'!O136)*'Model inputs'!O109,0)="",0,IF(IF(IF(ISERROR('Model inputs'!O145>'Model inputs'!O136),'Model inputs'!O145>'Model inputs'!O136,IF(OR('Model inputs'!O145="",'Model inputs'!O136=""),"",'Model inputs'!O145>'Model inputs'!O136))="",FALSE,IF(ISERROR('Model inputs'!O145>'Model inputs'!O136),'Model inputs'!O145>'Model inputs'!O136,IF(OR('Model inputs'!O145="",'Model inputs'!O136=""),"",'Model inputs'!O145>'Model inputs'!O136))),('Model inputs'!O145-'Model inputs'!O136)*'Model inputs'!O109,0)) -> 0 | N73: ='Model inputs'!N94*IF(IF(IF(IF(ISERROR('Model inputs'!O145>'Model inputs'!O136),'Model inputs'!O145>'Model inputs'!O136,IF(OR('Model inputs'!O145="",'Model inputs'!O136=""),"",'Model inputs'!O145>'Model inputs'!O136))="",FALSE,IF(ISERROR('Model inputs'!O145>'Model inputs'!O136),'Model inputs'!O145>'Model inputs'!O136,IF(OR('Model inputs'!O145="",'Model inputs'!O136=""),"",'Model inputs'!O145>'Model inputs'!O136))),('Model inputs'!O145-'Model inputs'!O136)*'Model inputs'!O109,0)="",0,IF(IF(IF(ISERROR('Model inputs'!O145>'Model inputs'!O136),'Model inputs'!O145>'Model inputs'!O136,IF(OR('Model inputs'!O145="",'Model inputs'!O136=""),"",'Model inputs'!O145>'Model inputs'!O136))="",FALSE,IF(ISERROR('Model inputs'!O145>'Model inputs'!O136),'Model inputs'!O145>'Model inputs'!O136,IF(OR('Model inputs'!O145="",'Model inputs'!O136=""),"",'Model inputs'!O145>'Model inputs'!O136))),('Model inputs'!O145-'Model inputs'!O136)*'Model inputs'!O109,0)) -> 0
A74: Overage revenue (USD) > Household | B74: ='Model inputs'!B68 -> 0 | C74: ='Model inputs'!C95*IF(IF(IF(IF(ISERROR('Model inputs'!O146>'Model inputs'!O137),'Model inputs'!O146>'Model inputs'!O137,IF(OR('Model inputs'!O146="",'Model inputs'!O137=""),"",'Model inputs'!O146>'Model inputs'!O137))="",FALSE,IF(ISERROR('Model inputs'!O146>'Model inputs'!O137),'Model inputs'!O146>'Model inputs'!O137,IF(OR('Model inputs'!O146="",'Model inputs'!O137=""),"",'Model inputs'!O146>'Model inputs'!O137))),('Model inputs'!O146-'Model inputs'!O137)*'Model inputs'!O110,0)="",0,IF(IF(IF(ISERROR('Model inputs'!O146>'Model inputs'!O137),'Model inputs'!O146>'Model inputs'!O137,IF(OR('Model inputs'!O146="",'Model inputs'!O137=""),"",'Model inputs'!O146>'Model inputs'!O137))="",FALSE,IF(ISERROR('Model inputs'!O146>'Model inputs'!O137),'Model inputs'!O146>'Model inputs'!O137,IF(OR('Model inputs'!O146="",'Model inputs'!O137=""),"",'Model inputs'!O146>'Model inputs'!O137))),('Model inputs'!O146-'Model inputs'!O137)*'Model inputs'!O110,0)) -> 0 | D74: ='Model inputs'!D95*IF(IF(IF(IF(ISERROR('Model inputs'!O146>'Model inputs'!O137),'Model inputs'!O146>'Model inputs'!O137,IF(OR('Model inputs'!O146="",'Model inputs'!O137=""),"",'Model inputs'!O146>'Model inputs'!O137))="",FALSE,IF(ISERROR('Model inputs'!O146>'Model inputs'!O137),'Model inputs'!O146>'Model inputs'!O137,IF(OR('Model inputs'!O146="",'Model inputs'!O137=""),"",'Model inputs'!O146>'Model inputs'!O137))),('Model inputs'!O146-'Model inputs'!O137)*'Model inputs'!O110,0)="",0,IF(IF(IF(ISERROR('Model inputs'!O146>'Model inputs'!O137),'Model inputs'!O146>'Model inputs'!O137,IF(OR('Model inputs'!O146="",'Model inputs'!O137=""),"",'Model inputs'!O146>'Model inputs'!O137))="",FALSE,IF(ISERROR('Model inputs'!O146>'Model inputs'!O137),'Model inputs'!O146>'Model inputs'!O137,IF(OR('Model inputs'!O146="",'Model inputs'!O137=""),"",'Model inputs'!O146>'Model inputs'!O137))),('Model inputs'!O146-'Model inputs'!O137)*'Model inputs'!O110,0)) -> 0 | E74: ='Model inputs'!E95*IF(IF(IF(IF(ISERROR('Model inputs'!O146>'Model inputs'!O137),'Model inputs'!O146>'Model inputs'!O137,IF(OR('Model inputs'!O146="",'Model inputs'!O137=""),"",'Model inputs'!O146>'Model inputs'!O137))="",FALSE,IF(ISERROR('Model inputs'!O146>'Model inputs'!O137),'Model inputs'!O146>'Model inputs'!O137,IF(OR('Model inputs'!O146="",'Model inputs'!O137=""),"",'Model inputs'!O146>'Model inputs'!O137))),('Model inputs'!O146-'Model inputs'!O137)*'Model inputs'!O110,0)="",0,IF(IF(IF(ISERROR('Model inputs'!O146>'Model inputs'!O137),'Model inputs'!O146>'Model inputs'!O137,IF(OR('Model inputs'!O146="",'Model inputs'!O137=""),"",'Model inputs'!O146>'Model inputs'!O137))="",FALSE,IF(ISERROR('Model inputs'!O146>'Model inputs'!O137),'Model inputs'!O146>'Model inputs'!O137,IF(OR('Model inputs'!O146="",'Model inputs'!O137=""),"",'Model inputs'!O146>'Model inputs'!O137))),('Model inputs'!O146-'Model inputs'!O137)*'Model inputs'!O110,0)) -> 0 | F74: ='Model inputs'!F95*IF(IF(IF(IF(ISERROR('Model inputs'!O146>'Model inputs'!O137),'Model inputs'!O146>'Model inputs'!O137,IF(OR('Model inputs'!O146="",'Model inputs'!O137=""),"",'Model inputs'!O146>'Model inputs'!O137))="",FALSE,IF(ISERROR('Model inputs'!O146>'Model inputs'!O137),'Model inputs'!O146>'Model inputs'!O137,IF(OR('Model inputs'!O146="",'Model inputs'!O137=""),"",'Model inputs'!O146>'Model inputs'!O137))),('Model inputs'!O146-'Model inputs'!O137)*'Model inputs'!O110,0)="",0,IF(IF(IF(ISERROR('Model inputs'!O146>'Model inputs'!O137),'Model inputs'!O146>'Model inputs'!O137,IF(OR('Model inputs'!O146="",'Model inputs'!O137=""),"",'Model inputs'!O146>'Model inputs'!O137))="",FALSE,IF(ISERROR('Model inputs'!O146>'Model inputs'!O137),'Model inputs'!O146>'Model inputs'!O137,IF(OR('Model inputs'!O146="",'Model inputs'!O137=""),"",'Model inputs'!O146>'Model inputs'!O137))),('Model inputs'!O146-'Model inputs'!O137)*'Model inputs'!O110,0)) -> 0 | G74: ='Model inputs'!G95*IF(IF(IF(IF(ISERROR('Model inputs'!O146>'Model inputs'!O137),'Model inputs'!O146>'Model inputs'!O137,IF(OR('Model inputs'!O146="",'Model inputs'!O137=""),"",'Model inputs'!O146>'Model inputs'!O137))="",FALSE,IF(ISERROR('Model inputs'!O146>'Model inputs'!O137),'Model inputs'!O146>'Model inputs'!O137,IF(OR('Model inputs'!O146="",'Model inputs'!O137=""),"",'Model inputs'!O146>'Model inputs'!O137))),('Model inputs'!O146-'Model inputs'!O137)*'Model inputs'!O110,0)="",0,IF(IF(IF(ISERROR('Model inputs'!O146>'Model inputs'!O137),'Model inputs'!O146>'Model inputs'!O137,IF(OR('Model inputs'!O146="",'Model inputs'!O137=""),"",'Model inputs'!O146>'Model inputs'!O137))="",FALSE,IF(ISERROR('Model inputs'!O146>'Model inputs'!O137),'Model inputs'!O146>'Model inputs'!O137,IF(OR('Model inputs'!O146="",'Model inputs'!O137=""),"",'Model inputs'!O146>'Model inputs'!O137))),('Model inputs'!O146-'Model inputs'!O137)*'Model inputs'!O110,0)) -> 0 | H74: ='Model inputs'!H95*IF(IF(IF(IF(ISERROR('Model inputs'!O146>'Model inputs'!O137),'Model inputs'!O146>'Model inputs'!O137,IF(OR('Model inputs'!O146="",'Model inputs'!O137=""),"",'Model inputs'!O146>'Model inputs'!O137))="",FALSE,IF(ISERROR('Model inputs'!O146>'Model inputs'!O137),'Model inputs'!O146>'Model inputs'!O137,IF(OR('Model inputs'!O146="",'Model inputs'!O137=""),"",'Model inputs'!O146>'Model inputs'!O137))),('Model inputs'!O146-'Model inputs'!O137)*'Model inputs'!O110,0)="",0,IF(IF(IF(ISERROR('Model inputs'!O146>'Model inputs'!O137),'Model inputs'!O146>'Model inputs'!O137,IF(OR('Model inputs'!O146="",'Model inputs'!O137=""),"",'Model inputs'!O146>'Model inputs'!O137))="",FALSE,IF(ISERROR('Model inputs'!O146>'Model inputs'!O137),'Model inputs'!O146>'Model inputs'!O137,IF(OR('Model inputs'!O146="",'Model inputs'!O137=""),"",'Model inputs'!O146>'Model inputs'!O137))),('Model inputs'!O146-'Model inputs'!O137)*'Model inputs'!O110,0)) -> 0 | I74: ='Model inputs'!I95*IF(IF(IF(IF(ISERROR('Model inputs'!O146>'Model inputs'!O137),'Model inputs'!O146>'Model inputs'!O137,IF(OR('Model inputs'!O146="",'Model inputs'!O137=""),"",'Model inputs'!O146>'Model inputs'!O137))="",FALSE,IF(ISERROR('Model inputs'!O146>'Model inputs'!O137),'Model inputs'!O146>'Model inputs'!O137,IF(OR('Model inputs'!O146="",'Model inputs'!O137=""),"",'Model inputs'!O146>'Model inputs'!O137))),('Model inputs'!O146-'Model inputs'!O137)*'Model inputs'!O110,0)="",0,IF(IF(IF(ISERROR('Model inputs'!O146>'Model inputs'!O137),'Model inputs'!O146>'Model inputs'!O137,IF(OR('Model inputs'!O146="",'Model inputs'!O137=""),"",'Model inputs'!O146>'Model inputs'!O137))="",FALSE,IF(ISERROR('Model inputs'!O146>'Model inputs'!O137),'Model inputs'!O146>'Model inputs'!O137,IF(OR('Model inputs'!O146="",'Model inputs'!O137=""),"",'Model inputs'!O146>'Model inputs'!O137))),('Model inputs'!O146-'Model inputs'!O137)*'Model inputs'!O110,0)) -> 0 | J74: ='Model inputs'!J95*IF(IF(IF(IF(ISERROR('Model inputs'!O146>'Model inputs'!O137),'Model inputs'!O146>'Model inputs'!O137,IF(OR('Model inputs'!O146="",'Model inputs'!O137=""),"",'Model inputs'!O146>'Model inputs'!O137))="",FALSE,IF(ISERROR('Model inputs'!O146>'Model inputs'!O137),'Model inputs'!O146>'Model inputs'!O137,IF(OR('Model inputs'!O146="",'Model inputs'!O137=""),"",'Model inputs'!O146>'Model inputs'!O137))),('Model inputs'!O146-'Model inputs'!O137)*'Model inputs'!O110,0)="",0,IF(IF(IF(ISERROR('Model inputs'!O146>'Model inputs'!O137),'Model inputs'!O146>'Model inputs'!O137,IF(OR('Model inputs'!O146="",'Model inputs'!O137=""),"",'Model inputs'!O146>'Model inputs'!O137))="",FALSE,IF(ISERROR('Model inputs'!O146>'Model inputs'!O137),'Model inputs'!O146>'Model inputs'!O137,IF(OR('Model inputs'!O146="",'Model inputs'!O137=""),"",'Model inputs'!O146>'Model inputs'!O137))),('Model inputs'!O146-'Model inputs'!O137)*'Model inputs'!O110,0)) -> 0 | K74: ='Model inputs'!K95*IF(IF(IF(IF(ISERROR('Model inputs'!O146>'Model inputs'!O137),'Model inputs'!O146>'Model inputs'!O137,IF(OR('Model inputs'!O146="",'Model inputs'!O137=""),"",'Model inputs'!O146>'Model inputs'!O137))="",FALSE,IF(ISERROR('Model inputs'!O146>'Model inputs'!O137),'Model inputs'!O146>'Model inputs'!O137,IF(OR('Model inputs'!O146="",'Model inputs'!O137=""),"",'Model inputs'!O146>'Model inputs'!O137))),('Model inputs'!O146-'Model inputs'!O137)*'Model inputs'!O110,0)="",0,IF(IF(IF(ISERROR('Model inputs'!O146>'Model inputs'!O137),'Model inputs'!O146>'Model inputs'!O137,IF(OR('Model inputs'!O146="",'Model inputs'!O137=""),"",'Model inputs'!O146>'Model inputs'!O137))="",FALSE,IF(ISERROR('Model inputs'!O146>'Model inputs'!O137),'Model inputs'!O146>'Model inputs'!O137,IF(OR('Model inputs'!O146="",'Model inputs'!O137=""),"",'Model inputs'!O146>'Model inputs'!O137))),('Model inputs'!O146-'Model inputs'!O137)*'Model inputs'!O110,0)) -> 0 | L74: ='Model inputs'!L95*IF(IF(IF(IF(ISERROR('Model inputs'!O146>'Model inputs'!O137),'Model inputs'!O146>'Model inputs'!O137,IF(OR('Model inputs'!O146="",'Model inputs'!O137=""),"",'Model inputs'!O146>'Model inputs'!O137))="",FALSE,IF(ISERROR('Model inputs'!O146>'Model inputs'!O137),'Model inputs'!O146>'Model inputs'!O137,IF(OR('Model inputs'!O146="",'Model inputs'!O137=""),"",'Model inputs'!O146>'Model inputs'!O137))),('Model inputs'!O146-'Model inputs'!O137)*'Model inputs'!O110,0)="",0,IF(IF(IF(ISERROR('Model inputs'!O146>'Model inputs'!O137),'Model inputs'!O146>'Model inputs'!O137,IF(OR('Model inputs'!O146="",'Model inputs'!O137=""),"",'Model inputs'!O146>'Model inputs'!O137))="",FALSE,IF(ISERROR('Model inputs'!O146>'Model inputs'!O137),'Model inputs'!O146>'Model inputs'!O137,IF(OR('Model inputs'!O146="",'Model inputs'!O137=""),"",'Model inputs'!O146>'Model inputs'!O137))),('Model inputs'!O146-'Model inputs'!O137)*'Model inputs'!O110,0)) -> 0 | M74: ='Model inputs'!M95*IF(IF(IF(IF(ISERROR('Model inputs'!O146>'Model inputs'!O137),'Model inputs'!O146>'Model inputs'!O137,IF(OR('Model inputs'!O146="",'Model inputs'!O137=""),"",'Model inputs'!O146>'Model inputs'!O137))="",FALSE,IF(ISERROR('Model inputs'!O146>'Model inputs'!O137),'Model inputs'!O146>'Model inputs'!O137,IF(OR('Model inputs'!O146="",'Model inputs'!O137=""),"",'Model inputs'!O146>'Model inputs'!O137))),('Model inputs'!O146-'Model inputs'!O137)*'Model inputs'!O110,0)="",0,IF(IF(IF(ISERROR('Model inputs'!O146>'Model inputs'!O137),'Model inputs'!O146>'Model inputs'!O137,IF(OR('Model inputs'!O146="",'Model inputs'!O137=""),"",'Model inputs'!O146>'Model inputs'!O137))="",FALSE,IF(ISERROR('Model inputs'!O146>'Model inputs'!O137),'Model inputs'!O146>'Model inputs'!O137,IF(OR('Model inputs'!O146="",'Model inputs'!O137=""),"",'Model inputs'!O146>'Model inputs'!O137))),('Model inputs'!O146-'Model inputs'!O137)*'Model inputs'!O110,0)) -> 0 | N74: ='Model inputs'!N95*IF(IF(IF(IF(ISERROR('Model inputs'!O146>'Model inputs'!O137),'Model inputs'!O146>'Model inputs'!O137,IF(OR('Model inputs'!O146="",'Model inputs'!O137=""),"",'Model inputs'!O146>'Model inputs'!O137))="",FALSE,IF(ISERROR('Model inputs'!O146>'Model inputs'!O137),'Model inputs'!O146>'Model inputs'!O137,IF(OR('Model inputs'!O146="",'Model inputs'!O137=""),"",'Model inputs'!O146>'Model inputs'!O137))),('Model inputs'!O146-'Model inputs'!O137)*'Model inputs'!O110,0)="",0,IF(IF(IF(ISERROR('Model inputs'!O146>'Model inputs'!O137),'Model inputs'!O146>'Model inputs'!O137,IF(OR('Model inputs'!O146="",'Model inputs'!O137=""),"",'Model inputs'!O146>'Model inputs'!O137))="",FALSE,IF(ISERROR('Model inputs'!O146>'Model inputs'!O137),'Model inputs'!O146>'Model inputs'!O137,IF(OR('Model inputs'!O146="",'Model inputs'!O137=""),"",'Model inputs'!O146>'Model inputs'!O137))),('Model inputs'!O146-'Model inputs'!O137)*'Model inputs'!O110,0)) -> 0
A75: Subscription revenue (USD) | B75: =SUM('Model inputs'!B76,'Model inputs'!B77) -> 0 | C75: =SUM('Model inputs'!C76,'Model inputs'!C77) -> 623.452 | D75: =SUM('Model inputs'!D76,'Model inputs'!D77) -> 674.01084 | E75: =SUM('Model inputs'!E76,'Model inputs'!E77) -> 721.50952 | F75: =SUM('Model inputs'!F76,'Model inputs'!F77) -> 766.16332 | G75: =SUM('Model inputs'!G76,'Model inputs'!G77) -> 808.17119 | H75: =SUM('Model inputs'!H76,'Model inputs'!H77) -> 847.71699 | I75: =SUM('Model inputs'!I76,'Model inputs'!I77) -> 884.97074 | ... N75: =SUM('Model inputs'!N76,'Model inputs'!N77) -> 1041.9674
A76: Subscription revenue (USD) > Classroom | B76: =0 -> 0 | C76: ='Model inputs'!C88*'Model inputs'!O112 -> 310.3 | D76: ='Model inputs'!D88*'Model inputs'!O112 -> 329.991 | E76: ='Model inputs'!E88*'Model inputs'!O112 -> 349.09127 | F76: ='Model inputs'!F88*'Model inputs'!O112 -> 367.61853 | G76: ='Model inputs'!G88*'Model inputs'!O112 -> 385.58998 | H76: ='Model inputs'!H88*'Model inputs'!O112 -> 403.02228 | I76: ='Model inputs'!I88*'Model inputs'!O112 -> 419.93161 | J76: ='Model inputs'!J88*'Model inputs'!O112 -> 436.33366 | K76: ='Model inputs'!K88*'Model inputs'!O112 -> 452.24365 | L76: ='Model inputs'!L88*'Model inputs'!O112 -> 467.67634 | M76: ='Model inputs'!M88*'Model inputs'!O112 -> 482.64605 | N76: ='Model inputs'!N88*'Model inputs'!O112 -> 497.16667
A77: Subscription revenue (USD) > Household | B77: =0 -> 0 | C77: ='Model inputs'!C89*'Model inputs'!O113 -> 313.152 | D77: ='Model inputs'!D89*'Model inputs'!O113 -> 344.01984 | E77: ='Model inputs'!E89*'Model inputs'!O113 -> 372.41825 | F77: ='Model inputs'!F89*'Model inputs'!O113 -> 398.54479 | G77: ='Model inputs'!G89*'Model inputs'!O113 -> 422.58121 | H77: ='Model inputs'!H89*'Model inputs'!O113 -> 444.69471 | I77: ='Model inputs'!I89*'Model inputs'!O113 -> 465.03914 | J77: ='Model inputs'!J89*'Model inputs'!O113 -> 483.756 | K77: ='Model inputs'!K89*'Model inputs'!O113 -> 500.97552 | L77: ='Model inputs'!L89*'Model inputs'!O113 -> 516.81748 | M77: ='Model inputs'!M89*'Model inputs'!O113 -> 531.39208 | N77: ='Model inputs'!N89*'Model inputs'!O113 -> 544.80072
A78: Subscription revenue (USD) | B78: =SUM('Model inputs'!B79,'Model inputs'!B80) -> 0 | C78: =SUM('Model inputs'!C79,'Model inputs'!C80) -> 595.18 | D78: =SUM('Model inputs'!D79,'Model inputs'!D80) -> 617.967 | E78: =SUM('Model inputs'!E79,'Model inputs'!E80) -> 638.31731 | F78: =SUM('Model inputs'!F79,'Model inputs'!F80) -> 656.53755 | G78: =SUM('Model inputs'!G79,'Model inputs'!G80) -> 672.89189 | H78: =SUM('Model inputs'!H79,'Model inputs'!H80) -> 687.60817 | I78: =SUM('Model inputs'!I79,'Model inputs'!I80) -> 700.88321 | ... N78: =SUM('Model inputs'!N79,'Model inputs'!N80) -> 750.86514
A79: Subscription revenue (USD) > Classroom | B79: ='Model inputs'!B76 -> 0 | C79: ='Model inputs'!C91*'Model inputs'!O115 -> 301.6 | D79: ='Model inputs'!D91*'Model inputs'!O115 -> 312.504 | E79: ='Model inputs'!E91*'Model inputs'!O115 -> 322.75376 | F79: ='Model inputs'!F91*'Model inputs'!O115 -> 332.38853 | G79: ='Model inputs'!G91*'Model inputs'!O115 -> 341.44522 | H79: ='Model inputs'!H91*'Model inputs'!O115 -> 349.95851 | I79: ='Model inputs'!I91*'Model inputs'!O115 -> 357.961 | J79: ='Model inputs'!J91*'Model inputs'!O115 -> 365.48334 | K79: ='Model inputs'!K91*'Model inputs'!O115 -> 372.55434 | L79: ='Model inputs'!L91*'Model inputs'!O115 -> 379.20108 | M79: ='Model inputs'!M91*'Model inputs'!O115 -> 385.44901 | N79: ='Model inputs'!N91*'Model inputs'!O115 -> 391.32207
A80: Subscription revenue (USD) > Household | B80: ='Model inputs'!B77 -> 0 | C80: ='Model inputs'!C92*'Model inputs'!O116 -> 293.58 | D80: ='Model inputs'!D92*'Model inputs'!O116 -> 305.463 | E80: ='Model inputs'!E92*'Model inputs'!O116 -> 315.56355 | F80: ='Model inputs'!F92*'Model inputs'!O116 -> 324.14902 | G80: ='Model inputs'!G92*'Model inputs'!O116 -> 331.44666 | H80: ='Model inputs'!H92*'Model inputs'!O116 -> 337.64967 | I80: ='Model inputs'!I92*'Model inputs'!O116 -> 342.92222 | J80: ='Model inputs'!J92*'Model inputs'!O116 -> 347.40388 | K80: ='Model inputs'!K92*'Model inputs'!O116 -> 351.2133 | L80: ='Model inputs'!L92*'Model inputs'!O116 -> 354.45131 | M80: ='Model inputs'!M92*'Model inputs'!O116 -> 357.20361 | N80: ='Model inputs'!N92*'Model inputs'!O116 -> 359.54307
A81: Subscription revenue (USD) | B81: =SUM('Model inputs'!B82,'Model inputs'!B83) -> 0 | C81: =SUM('Model inputs'!C82,'Model inputs'!C83) -> 737.372 | D81: =SUM('Model inputs'!D82,'Model inputs'!D83) -> 895.63724 | E81: =SUM('Model inputs'!E82,'Model inputs'!E83) -> 1045.0388 | F81: =SUM('Model inputs'!F82,'Model inputs'!F83) -> 1186.1719 | G81: =SUM('Model inputs'!G82,'Model inputs'!G83) -> 1319.5874 | H81: =SUM('Model inputs'!H82,'Model inputs'!H83) -> 1445.7956 | I81: =SUM('Model inputs'!I82,'Model inputs'!I83) -> 1565.2691 | ... N81: =SUM('Model inputs'!N82,'Model inputs'!N83) -> 2075.8733
A82: Subscription revenue (USD) > Classroom | B82: ='Model inputs'!B76 -> 0 | C82: ='Model inputs'!C94*'Model inputs'!O118 -> 368.3 | D82: ='Model inputs'!D94*'Model inputs'!O118 -> 444.251 | E82: ='Model inputs'!E94*'Model inputs'!O118 -> 517.92347 | F82: ='Model inputs'!F94*'Model inputs'!O118 -> 589.38577 | G82: ='Model inputs'!G94*'Model inputs'!O118 -> 658.70419 | H82: ='Model inputs'!H94*'Model inputs'!O118 -> 725.94307 | I82: ='Model inputs'!I94*'Model inputs'!O118 -> 791.16478 | J82: ='Model inputs'!J94*'Model inputs'!O118 -> 854.42983 | K82: ='Model inputs'!K94*'Model inputs'!O118 -> 915.79694 | L82: ='Model inputs'!L94*'Model inputs'!O118 -> 975.32303 | M82: ='Model inputs'!M94*'Model inputs'!O118 -> 1033.0633 | N82: ='Model inputs'!N94*'Model inputs'!O118 -> 1089.0714
A83: Subscription revenue (USD) > Household | B83: ='Model inputs'!B77 -> 0 | C83: ='Model inputs'!C95*'Model inputs'!O119 -> 369.072 | D83: ='Model inputs'!D95*'Model inputs'!O119 -> 451.38624 | E83: ='Model inputs'!E95*'Model inputs'!O119 -> 527.11534 | F83: ='Model inputs'!F95*'Model inputs'!O119 -> 596.78611 | G83: ='Model inputs'!G95*'Model inputs'!O119 -> 660.88322 | H83: ='Model inputs'!H95*'Model inputs'!O119 -> 719.85257 | I83: ='Model inputs'!I95*'Model inputs'!O119 -> 774.10436 | J83: ='Model inputs'!J95*'Model inputs'!O119 -> 824.01601 | K83: ='Model inputs'!K95*'Model inputs'!O119 -> 869.93473 | L83: ='Model inputs'!L95*'Model inputs'!O119 -> 912.17995 | M83: ='Model inputs'!M95*'Model inputs'!O119 -> 951.04556 | N83: ='Model inputs'!N95*'Model inputs'!O119 -> 986.80191
A84: Cost per story, selected policy (USD, estimate) · Inference cost (USD, estimate) · Main Scenario · Main Scenario | O84: =SUM('Model inputs'!O193,'Model inputs'!O194)+SUM('Model inputs'!O181,'Model inputs'!O182,'Model inputs'!O183) -> 0.1959
A85: Cost per story, selected policy (USD, estimate) · Inference cost (USD, estimate) · Downside · Downside | O85: =SUM('Model inputs'!O196,'Model inputs'!O197)+SUM('Model inputs'!O185,'Model inputs'!O186,'Model inputs'!O187) -> 0.3559
A86: Cost per story, selected policy (USD, estimate) · Inference cost (USD, estimate) · Growth · Growth | O86: =SUM('Model inputs'!O199,'Model inputs'!O200)+SUM('Model inputs'!O189,'Model inputs'!O190,'Model inputs'!O191) -> 0.1959
A87: Ending customers | B87: =SUM('Model inputs'!B88,'Model inputs'!B89) -> 50 | C87: =SUM('Model inputs'!C88,'Model inputs'!C89) -> 55.5 | D87: =SUM('Model inputs'!D88,'Model inputs'!D89) -> 60.595 | E87: =SUM('Model inputs'!E88,'Model inputs'!E89) -> 65.31635 | F87: =SUM('Model inputs'!F88,'Model inputs'!F89) -> 69.692923 | G87: =SUM('Model inputs'!G88,'Model inputs'!G89) -> 73.751315 | H87: =SUM('Model inputs'!H88,'Model inputs'!H89) -> 77.51602 | I87: =SUM('Model inputs'!I88,'Model inputs'!I89) -> 81.009604 | ... N87: =SUM('Model inputs'!N88,'Model inputs'!N89) -> 95.083695
A88: Ending customers > Classroom | B88: =IF('Model inputs'!O205="","",'Model inputs'!O205) -> 10 | C88: ='Model inputs'!B88+'Model inputs'!C172-'Model inputs'!C148 -> 10.7 | D88: ='Model inputs'!C88+'Model inputs'!D172-'Model inputs'!D148 -> 11.379 | E88: ='Model inputs'!D88+'Model inputs'!E172-'Model inputs'!E148 -> 12.03763 | F88: ='Model inputs'!E88+'Model inputs'!F172-'Model inputs'!F148 -> 12.676501 | G88: ='Model inputs'!F88+'Model inputs'!G172-'Model inputs'!G148 -> 13.296206 | H88: ='Model inputs'!G88+'Model inputs'!H172-'Model inputs'!H148 -> 13.89732 | I88: ='Model inputs'!H88+'Model inputs'!I172-'Model inputs'!I148 -> 14.4804 | J88: ='Model inputs'!I88+'Model inputs'!J172-'Model inputs'!J148 -> 15.045988 | ... N88: ='Model inputs'!M88+'Model inputs'!N172-'Model inputs'!N148 -> 17.143678
A89: Ending customers > Household | B89: =IF('Model inputs'!O206="","",'Model inputs'!O206) -> 40 | C89: ='Model inputs'!B89+'Model inputs'!C173-'Model inputs'!C149 -> 44.8 | D89: ='Model inputs'!C89+'Model inputs'!D173-'Model inputs'!D149 -> 49.216 | E89: ='Model inputs'!D89+'Model inputs'!E173-'Model inputs'!E149 -> 53.27872 | F89: ='Model inputs'!E89+'Model inputs'!F173-'Model inputs'!F149 -> 57.016422 | G89: ='Model inputs'!F89+'Model inputs'!G173-'Model inputs'!G149 -> 60.455109 | H89: ='Model inputs'!G89+'Model inputs'!H173-'Model inputs'!H149 -> 63.6187 | I89: ='Model inputs'!H89+'Model inputs'!I173-'Model inputs'!I149 -> 66.529204 | J89: ='Model inputs'!I89+'Model inputs'!J173-'Model inputs'!J149 -> 69.206868 | ... N89: ='Model inputs'!M89+'Model inputs'!N173-'Model inputs'!N149 -> 77.940017
A90: Ending customers | B90: =SUM('Model inputs'!B91,'Model inputs'!B92) -> 50 | C90: =SUM('Model inputs'!C91,'Model inputs'!C92) -> 52.4 | D90: =SUM('Model inputs'!D91,'Model inputs'!D92) -> 54.476 | E90: =SUM('Model inputs'!E91,'Model inputs'!E92) -> 56.27444 | F90: =SUM('Model inputs'!F91,'Model inputs'!F92) -> 57.834924 | G90: =SUM('Model inputs'!G91,'Model inputs'!G92) -> 59.191236 | H90: =SUM('Model inputs'!H91,'Model inputs'!H92) -> 60.372208 | I90: =SUM('Model inputs'!I91,'Model inputs'!I92) -> 61.402455 | ... N90: =SUM('Model inputs'!N91,'Model inputs'!N92) -> 64.930641
A91: Ending customers > Classroom | B91: =IF('Model inputs'!O208="","",'Model inputs'!O208) -> 10 | C91: ='Model inputs'!B91+'Model inputs'!C175-'Model inputs'!C151 -> 10.4 | D91: ='Model inputs'!C91+'Model inputs'!D175-'Model inputs'!D151 -> 10.776 | E91: ='Model inputs'!D91+'Model inputs'!E175-'Model inputs'!E151 -> 11.12944 | F91: ='Model inputs'!E91+'Model inputs'!F175-'Model inputs'!F151 -> 11.461674 | G91: ='Model inputs'!F91+'Model inputs'!G175-'Model inputs'!G151 -> 11.773973 | H91: ='Model inputs'!G91+'Model inputs'!H175-'Model inputs'!H151 -> 12.067535 | I91: ='Model inputs'!H91+'Model inputs'!I175-'Model inputs'!I151 -> 12.343483 | J91: ='Model inputs'!I91+'Model inputs'!J175-'Model inputs'!J151 -> 12.602874 | ... N91: ='Model inputs'!M91+'Model inputs'!N175-'Model inputs'!N151 -> 13.493865
A92: Ending customers > Household | B92: =IF('Model inputs'!O209="","",'Model inputs'!O209) -> 40 | C92: ='Model inputs'!B92+'Model inputs'!C176-'Model inputs'!C152 -> 42 | D92: ='Model inputs'!C92+'Model inputs'!D176-'Model inputs'!D152 -> 43.7 | E92: ='Model inputs'!D92+'Model inputs'!E176-'Model inputs'!E152 -> 45.145 | F92: ='Model inputs'!E92+'Model inputs'!F176-'Model inputs'!F152 -> 46.37325 | G92: ='Model inputs'!F92+'Model inputs'!G176-'Model inputs'!G152 -> 47.417263 | H92: ='Model inputs'!G92+'Model inputs'!H176-'Model inputs'!H152 -> 48.304673 | I92: ='Model inputs'!H92+'Model inputs'!I176-'Model inputs'!I152 -> 49.058972 | J92: ='Model inputs'!I92+'Model inputs'!J176-'Model inputs'!J152 -> 49.700126 | ... N92: ='Model inputs'!M92+'Model inputs'!N176-'Model inputs'!N152 -> 51.436777
A93: Ending customers | B93: =SUM('Model inputs'!B94,'Model inputs'!B95) -> 50 | C93: =SUM('Model inputs'!C94,'Model inputs'!C95) -> 65.5 | D93: =SUM('Model inputs'!D94,'Model inputs'!D95) -> 79.895 | E93: =SUM('Model inputs'!E94,'Model inputs'!E95) -> 93.26935 | F93: =SUM('Model inputs'!F94,'Model inputs'!F95) -> 105.70077 | G93: =SUM('Model inputs'!G94,'Model inputs'!G95) -> 117.26089 | H93: =SUM('Model inputs'!H94,'Model inputs'!H95) -> 128.01572 | I93: =SUM('Model inputs'!I94,'Model inputs'!I95) -> 138.02609 | ... N93: =SUM('Model inputs'!N94,'Model inputs'!N95) -> 178.72757
A94: Ending customers > Classroom | B94: =IF('Model inputs'!O211="","",'Model inputs'!O211) -> 10 | C94: ='Model inputs'!B94+'Model inputs'!C178-'Model inputs'!C154 -> 12.7 | D94: ='Model inputs'!C94+'Model inputs'!D178-'Model inputs'!D154 -> 15.319 | E94: ='Model inputs'!D94+'Model inputs'!E178-'Model inputs'!E154 -> 17.85943 | F94: ='Model inputs'!E94+'Model inputs'!F178-'Model inputs'!F154 -> 20.323647 | G94: ='Model inputs'!F94+'Model inputs'!G178-'Model inputs'!G154 -> 22.713938 | H94: ='Model inputs'!G94+'Model inputs'!H178-'Model inputs'!H154 -> 25.03252 | I94: ='Model inputs'!H94+'Model inputs'!I178-'Model inputs'!I154 -> 27.281544 | J94: ='Model inputs'!I94+'Model inputs'!J178-'Model inputs'!J154 -> 29.463098 | ... N94: ='Model inputs'!M94+'Model inputs'!N178-'Model inputs'!N154 -> 37.554188
A95: Ending customers > Household | B95: =IF('Model inputs'!O212="","",'Model inputs'!O212) -> 40 | C95: ='Model inputs'!B95+'Model inputs'!C179-'Model inputs'!C155 -> 52.8 | D95: ='Model inputs'!C95+'Model inputs'!D179-'Model inputs'!D155 -> 64.576 | E95: ='Model inputs'!D95+'Model inputs'!E179-'Model inputs'!E155 -> 75.40992 | F95: ='Model inputs'!E95+'Model inputs'!F179-'Model inputs'!F155 -> 85.377126 | G95: ='Model inputs'!F95+'Model inputs'!G179-'Model inputs'!G155 -> 94.546956 | H95: ='Model inputs'!G95+'Model inputs'!H179-'Model inputs'!H155 -> 102.9832 | I95: ='Model inputs'!H95+'Model inputs'!I179-'Model inputs'!I155 -> 110.74454 | J95: ='Model inputs'!I95+'Model inputs'!J179-'Model inputs'!J155 -> 117.88498 | ... N95: ='Model inputs'!M95+'Model inputs'!N179-'Model inputs'!N155 -> 141.17338
A96: Hosting per month (USD, assumed) · Hosting and neatlogs allocated by revenue (USD) · Main Scenario · Main Scenario | O96: =25 -> 25
A97: Hosting per month (USD, assumed) · Hosting and neatlogs allocated by revenue (USD) · Downside · Downside | O97: ='Model inputs'!O96 -> 25
A98: Hosting per month (USD, assumed) · Hosting and neatlogs allocated by revenue (USD) · Growth · Growth | O98: ='Model inputs'!O96 -> 25
A99: neatlogs bill (USD, derived) · Main Scenario | B99: 0 | C99: =IF(IF(IF(ISERROR('Model inputs'!O156=1),'Model inputs'!O156=1,IF('Model inputs'!O156="","",'Model inputs'!O156=1))="",FALSE,IF(ISERROR('Model inputs'!O156=1),'Model inputs'!O156=1,IF('Model inputs'!O156="","",'Model inputs'!O156=1))),0,IF(IF(IF(ISERROR('Model inputs'!C201<='Model inputs'!O159),'Model inputs'!C201<='Model inputs'!O159,IF(OR('Model inputs'!C201="",'Model inputs'!O159=""),"",'Model inputs'!C201<='Model inputs'!O159))="",FALSE,IF(ISERROR('Model inputs'!C201<='Model inputs'!O159),'Model inputs'!C201<='Model inputs'!O159,IF(OR('Model inputs'!C201="",'Model inputs'!O159=""),"",'Model inputs'!C201<='Model inputs'!O159))),0,IF(IF(IF(ISERROR('Model inputs'!C201<='Model inputs'!O165),'Model inputs'!C201<='Model inputs'!O165,IF(OR('Model inputs'!C201="",'Model inputs'!O165=""),"",'Model inputs'!C201<='Model inputs'!O165))="",FALSE,IF(ISERROR('Model inputs'!C201<='Model inputs'!O165),'Model inputs'!C201<='Model inputs'!O165,IF(OR('Model inputs'!C201="",'Model inputs'!O165=""),"",'Model inputs'!C201<='Model inputs'!O165))),IF('Model inputs'!O168="","",'Model inputs'!O168),'Model inputs'!O168+CEILING(('Model inputs'!C201-'Model inputs'!O165)/100000,1)*'Model inputs'!O162))) -> 0 | D99: =IF(IF(IF(ISERROR('Model inputs'!O156=1),'Model inputs'!O156=1,IF('Model inputs'!O156="","",'Model inputs'!O156=1))="",FALSE,IF(ISERROR('Model inputs'!O156=1),'Model inputs'!O156=1,IF('Model inputs'!O156="","",'Model inputs'!O156=1))),0,IF(IF(IF(ISERROR('Model inputs'!D201<='Model inputs'!O159),'Model inputs'!D201<='Model inputs'!O159,IF(OR('Model inputs'!D201="",'Model inputs'!O159=""),"",'Model inputs'!D201<='Model inputs'!O159))="",FALSE,IF(ISERROR('Model inputs'!D201<='Model inputs'!O159),'Model inputs'!D201<='Model inputs'!O159,IF(OR('Model inputs'!D201="",'Model inputs'!O159=""),"",'Model inputs'!D201<='Model inputs'!O159))),0,IF(IF(IF(ISERROR('Model inputs'!D201<='Model inputs'!O165),'Model inputs'!D201<='Model inputs'!O165,IF(OR('Model inputs'!D201="",'Model inputs'!O165=""),"",'Model inputs'!D201<='Model inputs'!O165))="",FALSE,IF(ISERROR('Model inputs'!D201<='Model inputs'!O165),'Model inputs'!D201<='Model inputs'!O165,IF(OR('Model inputs'!D201="",'Model inputs'!O165=""),"",'Model inputs'!D201<='Model inputs'!O165))),IF('Model inputs'!O168="","",'Model inputs'!O168),'Model inputs'!O168+CEILING(('Model inputs'!D201-'Model inputs'!O165)/100000,1)*'Model inputs'!O162))) -> 0 | E99: =IF(IF(IF(ISERROR('Model inputs'!O156=1),'Model inputs'!O156=1,IF('Model inputs'!O156="","",'Model inputs'!O156=1))="",FALSE,IF(ISERROR('Model inputs'!O156=1),'Model inputs'!O156=1,IF('Model inputs'!O156="","",'Model inputs'!O156=1))),0,IF(IF(IF(ISERROR('Model inputs'!E201<='Model inputs'!O159),'Model inputs'!E201<='Model inputs'!O159,IF(OR('Model inputs'!E201="",'Model inputs'!O159=""),"",'Model inputs'!E201<='Model inputs'!O159))="",FALSE,IF(ISERROR('Model inputs'!E201<='Model inputs'!O159),'Model inputs'!E201<='Model inputs'!O159,IF(OR('Model inputs'!E201="",'Model inputs'!O159=""),"",'Model inputs'!E201<='Model inputs'!O159))),0,IF(IF(IF(ISERROR('Model inputs'!E201<='Model inputs'!O165),'Model inputs'!E201<='Model inputs'!O165,IF(OR('Model inputs'!E201="",'Model inputs'!O165=""),"",'Model inputs'!E201<='Model inputs'!O165))="",FALSE,IF(ISERROR('Model inputs'!E201<='Model inputs'!O165),'Model inputs'!E201<='Model inputs'!O165,IF(OR('Model inputs'!E201="",'Model inputs'!O165=""),"",'Model inputs'!E201<='Model inputs'!O165))),IF('Model inputs'!O168="","",'Model inputs'!O168),'Model inputs'!O168+CEILING(('Model inputs'!E201-'Model inputs'!O165)/100000,1)*'Model inputs'!O162))) -> 0 | F99: =IF(IF(IF(ISERROR('Model inputs'!O156=1),'Model inputs'!O156=1,IF('Model inputs'!O156="","",'Model inputs'!O156=1))="",FALSE,IF(ISERROR('Model inputs'!O156=1),'Model inputs'!O156=1,IF('Model inputs'!O156="","",'Model inputs'!O156=1))),0,IF(IF(IF(ISERROR('Model inputs'!F201<='Model inputs'!O159),'Model inputs'!F201<='Model inputs'!O159,IF(OR('Model inputs'!F201="",'Model inputs'!O159=""),"",'Model inputs'!F201<='Model inputs'!O159))="",FALSE,IF(ISERROR('Model inputs'!F201<='Model inputs'!O159),'Model inputs'!F201<='Model inputs'!O159,IF(OR('Model inputs'!F201="",'Model inputs'!O159=""),"",'Model inputs'!F201<='Model inputs'!O159))),0,IF(IF(IF(ISERROR('Model inputs'!F201<='Model inputs'!O165),'Model inputs'!F201<='Model inputs'!O165,IF(OR('Model inputs'!F201="",'Model inputs'!O165=""),"",'Model inputs'!F201<='Model inputs'!O165))="",FALSE,IF(ISERROR('Model inputs'!F201<='Model inputs'!O165),'Model inputs'!F201<='Model inputs'!O165,IF(OR('Model inputs'!F201="",'Model inputs'!O165=""),"",'Model inputs'!F201<='Model inputs'!O165))),IF('Model inputs'!O168="","",'Model inputs'!O168),'Model inputs'!O168+CEILING(('Model inputs'!F201-'Model inputs'!O165)/100000,1)*'Model inputs'!O162))) -> 0 | G99: =IF(IF(IF(ISERROR('Model inputs'!O156=1),'Model inputs'!O156=1,IF('Model inputs'!O156="","",'Model inputs'!O156=1))="",FALSE,IF(ISERROR('Model inputs'!O156=1),'Model inputs'!O156=1,IF('Model inputs'!O156="","",'Model inputs'!O156=1))),0,IF(IF(IF(ISERROR('Model inputs'!G201<='Model inputs'!O159),'Model inputs'!G201<='Model inputs'!O159,IF(OR('Model inputs'!G201="",'Model inputs'!O159=""),"",'Model inputs'!G201<='Model inputs'!O159))="",FALSE,IF(ISERROR('Model inputs'!G201<='Model inputs'!O159),'Model inputs'!G201<='Model inputs'!O159,IF(OR('Model inputs'!G201="",'Model inputs'!O159=""),"",'Model inputs'!G201<='Model inputs'!O159))),0,IF(IF(IF(ISERROR('Model inputs'!G201<='Model inputs'!O165),'Model inputs'!G201<='Model inputs'!O165,IF(OR('Model inputs'!G201="",'Model inputs'!O165=""),"",'Model inputs'!G201<='Model inputs'!O165))="",FALSE,IF(ISERROR('Model inputs'!G201<='Model inputs'!O165),'Model inputs'!G201<='Model inputs'!O165,IF(OR('Model inputs'!G201="",'Model inputs'!O165=""),"",'Model inputs'!G201<='Model inputs'!O165))),IF('Model inputs'!O168="","",'Model inputs'!O168),'Model inputs'!O168+CEILING(('Model inputs'!G201-'Model inputs'!O165)/100000,1)*'Model inputs'!O162))) -> 0 | H99: =IF(IF(IF(ISERROR('Model inputs'!O156=1),'Model inputs'!O156=1,IF('Model inputs'!O156="","",'Model inputs'!O156=1))="",FALSE,IF(ISERROR('Model inputs'!O156=1),'Model inputs'!O156=1,IF('Model inputs'!O156="","",'Model inputs'!O156=1))),0,IF(IF(IF(ISERROR('Model inputs'!H201<='Model inputs'!O159),'Model inputs'!H201<='Model inputs'!O159,IF(OR('Model inputs'!H201="",'Model inputs'!O159=""),"",'Model inputs'!H201<='Model inputs'!O159))="",FALSE,IF(ISERROR('Model inputs'!H201<='Model inputs'!O159),'Model inputs'!H201<='Model inputs'!O159,IF(OR('Model inputs'!H201="",'Model inputs'!O159=""),"",'Model inputs'!H201<='Model inputs'!O159))),0,IF(IF(IF(ISERROR('Model inputs'!H201<='Model inputs'!O165),'Model inputs'!H201<='Model inputs'!O165,IF(OR('Model inputs'!H201="",'Model inputs'!O165=""),"",'Model inputs'!H201<='Model inputs'!O165))="",FALSE,IF(ISERROR('Model inputs'!H201<='Model inputs'!O165),'Model inputs'!H201<='Model inputs'!O165,IF(OR('Model inputs'!H201="",'Model inputs'!O165=""),"",'Model inputs'!H201<='Model inputs'!O165))),IF('Model inputs'!O168="","",'Model inputs'!O168),'Model inputs'!O168+CEILING(('Model inputs'!H201-'Model inputs'!O165)/100000,1)*'Model inputs'!O162))) -> 0 | I99: =IF(IF(IF(ISERROR('Model inputs'!O156=1),'Model inputs'!O156=1,IF('Model inputs'!O156="","",'Model inputs'!O156=1))="",FALSE,IF(ISERROR('Model inputs'!O156=1),'Model inputs'!O156=1,IF('Model inputs'!O156="","",'Model inputs'!O156=1))),0,IF(IF(IF(ISERROR('Model inputs'!I201<='Model inputs'!O159),'Model inputs'!I201<='Model inputs'!O159,IF(OR('Model inputs'!I201="",'Model inputs'!O159=""),"",'Model inputs'!I201<='Model inputs'!O159))="",FALSE,IF(ISERROR('Model inputs'!I201<='Model inputs'!O159),'Model inputs'!I201<='Model inputs'!O159,IF(OR('Model inputs'!I201="",'Model inputs'!O159=""),"",'Model inputs'!I201<='Model inputs'!O159))),0,IF(IF(IF(ISERROR('Model inputs'!I201<='Model inputs'!O165),'Model inputs'!I201<='Model inputs'!O165,IF(OR('Model inputs'!I201="",'Model inputs'!O165=""),"",'Model inputs'!I201<='Model inputs'!O165))="",FALSE,IF(ISERROR('Model inputs'!I201<='Model inputs'!O165),'Model inputs'!I201<='Model inputs'!O165,IF(OR('Model inputs'!I201="",'Model inputs'!O165=""),"",'Model inputs'!I201<='Model inputs'!O165))),IF('Model inputs'!O168="","",'Model inputs'!O168),'Model inputs'!O168+CEILING(('Model inputs'!I201-'Model inputs'!O165)/100000,1)*'Model inputs'!O162))) -> 0 | J99: =IF(IF(IF(ISERROR('Model inputs'!O156=1),'Model inputs'!O156=1,IF('Model inputs'!O156="","",'Model inputs'!O156=1))="",FALSE,IF(ISERROR('Model inputs'!O156=1),'Model inputs'!O156=1,IF('Model inputs'!O156="","",'Model inputs'!O156=1))),0,IF(IF(IF(ISERROR('Model inputs'!J201<='Model inputs'!O159),'Model inputs'!J201<='Model inputs'!O159,IF(OR('Model inputs'!J201="",'Model inputs'!O159=""),"",'Model inputs'!J201<='Model inputs'!O159))="",FALSE,IF(ISERROR('Model inputs'!J201<='Model inputs'!O159),'Model inputs'!J201<='Model inputs'!O159,IF(OR('Model inputs'!J201="",'Model inputs'!O159=""),"",'Model inputs'!J201<='Model inputs'!O159))),0,IF(IF(IF(ISERROR('Model inputs'!J201<='Model inputs'!O165),'Model inputs'!J201<='Model inputs'!O165,IF(OR('Model inputs'!J201="",'Model inputs'!O165=""),"",'Model inputs'!J201<='Model inputs'!O165))="",FALSE,IF(ISERROR('Model inputs'!J201<='Model inputs'!O165),'Model inputs'!J201<='Model inputs'!O165,IF(OR('Model inputs'!J201="",'Model inputs'!O165=""),"",'Model inputs'!J201<='Model inputs'!O165))),IF('Model inputs'!O168="","",'Model inputs'!O168),'Model inputs'!O168+CEILING(('Model inputs'!J201-'Model inputs'!O165)/100000,1)*'Model inputs'!O162))) -> 0 | K99: =IF(IF(IF(ISERROR('Model inputs'!O156=1),'Model inputs'!O156=1,IF('Model inputs'!O156="","",'Model inputs'!O156=1))="",FALSE,IF(ISERROR('Model inputs'!O156=1),'Model inputs'!O156=1,IF('Model inputs'!O156="","",'Model inputs'!O156=1))),0,IF(IF(IF(ISERROR('Model inputs'!K201<='Model inputs'!O159),'Model inputs'!K201<='Model inputs'!O159,IF(OR('Model inputs'!K201="",'Model inputs'!O159=""),"",'Model inputs'!K201<='Model inputs'!O159))="",FALSE,IF(ISERROR('Model inputs'!K201<='Model inputs'!O159),'Model inputs'!K201<='Model inputs'!O159,IF(OR('Model inputs'!K201="",'Model inputs'!O159=""),"",'Model inputs'!K201<='Model inputs'!O159))),0,IF(IF(IF(ISERROR('Model inputs'!K201<='Model inputs'!O165),'Model inputs'!K201<='Model inputs'!O165,IF(OR('Model inputs'!K201="",'Model inputs'!O165=""),"",'Model inputs'!K201<='Model inputs'!O165))="",FALSE,IF(ISERROR('Model inputs'!K201<='Model inputs'!O165),'Model inputs'!K201<='Model inputs'!O165,IF(OR('Model inputs'!K201="",'Model inputs'!O165=""),"",'Model inputs'!K201<='Model inputs'!O165))),IF('Model inputs'!O168="","",'Model inputs'!O168),'Model inputs'!O168+CEILING(('Model inputs'!K201-'Model inputs'!O165)/100000,1)*'Model inputs'!O162))) -> 0 | L99: =IF(IF(IF(ISERROR('Model inputs'!O156=1),'Model inputs'!O156=1,IF('Model inputs'!O156="","",'Model inputs'!O156=1))="",FALSE,IF(ISERROR('Model inputs'!O156=1),'Model inputs'!O156=1,IF('Model inputs'!O156="","",'Model inputs'!O156=1))),0,IF(IF(IF(ISERROR('Model inputs'!L201<='Model inputs'!O159),'Model inputs'!L201<='Model inputs'!O159,IF(OR('Model inputs'!L201="",'Model inputs'!O159=""),"",'Model inputs'!L201<='Model inputs'!O159))="",FALSE,IF(ISERROR('Model inputs'!L201<='Model inputs'!O159),'Model inputs'!L201<='Model inputs'!O159,IF(OR('Model inputs'!L201="",'Model inputs'!O159=""),"",'Model inputs'!L201<='Model inputs'!O159))),0,IF(IF(IF(ISERROR('Model inputs'!L201<='Model inputs'!O165),'Model inputs'!L201<='Model inputs'!O165,IF(OR('Model inputs'!L201="",'Model inputs'!O165=""),"",'Model inputs'!L201<='Model inputs'!O165))="",FALSE,IF(ISERROR('Model inputs'!L201<='Model inputs'!O165),'Model inputs'!L201<='Model inputs'!O165,IF(OR('Model inputs'!L201="",'Model inputs'!O165=""),"",'Model inputs'!L201<='Model inputs'!O165))),IF('Model inputs'!O168="","",'Model inputs'!O168),'Model inputs'!O168+CEILING(('Model inputs'!L201-'Model inputs'!O165)/100000,1)*'Model inputs'!O162))) -> 0 | M99: =IF(IF(IF(ISERROR('Model inputs'!O156=1),'Model inputs'!O156=1,IF('Model inputs'!O156="","",'Model inputs'!O156=1))="",FALSE,IF(ISERROR('Model inputs'!O156=1),'Model inputs'!O156=1,IF('Model inputs'!O156="","",'Model inputs'!O156=1))),0,IF(IF(IF(ISERROR('Model inputs'!M201<='Model inputs'!O159),'Model inputs'!M201<='Model inputs'!O159,IF(OR('Model inputs'!M201="",'Model inputs'!O159=""),"",'Model inputs'!M201<='Model inputs'!O159))="",FALSE,IF(ISERROR('Model inputs'!M201<='Model inputs'!O159),'Model inputs'!M201<='Model inputs'!O159,IF(OR('Model inputs'!M201="",'Model inputs'!O159=""),"",'Model inputs'!M201<='Model inputs'!O159))),0,IF(IF(IF(ISERROR('Model inputs'!M201<='Model inputs'!O165),'Model inputs'!M201<='Model inputs'!O165,IF(OR('Model inputs'!M201="",'Model inputs'!O165=""),"",'Model inputs'!M201<='Model inputs'!O165))="",FALSE,IF(ISERROR('Model inputs'!M201<='Model inputs'!O165),'Model inputs'!M201<='Model inputs'!O165,IF(OR('Model inputs'!M201="",'Model inputs'!O165=""),"",'Model inputs'!M201<='Model inputs'!O165))),IF('Model inputs'!O168="","",'Model inputs'!O168),'Model inputs'!O168+CEILING(('Model inputs'!M201-'Model inputs'!O165)/100000,1)*'Model inputs'!O162))) -> 0 | N99: =IF(IF(IF(ISERROR('Model inputs'!O156=1),'Model inputs'!O156=1,IF('Model inputs'!O156="","",'Model inputs'!O156=1))="",FALSE,IF(ISERROR('Model inputs'!O156=1),'Model inputs'!O156=1,IF('Model inputs'!O156="","",'Model inputs'!O156=1))),0,IF(IF(IF(ISERROR('Model inputs'!N201<='Model inputs'!O159),'Model inputs'!N201<='Model inputs'!O159,IF(OR('Model inputs'!N201="",'Model inputs'!O159=""),"",'Model inputs'!N201<='Model inputs'!O159))="",FALSE,IF(ISERROR('Model inputs'!N201<='Model inputs'!O159),'Model inputs'!N201<='Model inputs'!O159,IF(OR('Model inputs'!N201="",'Model inputs'!O159=""),"",'Model inputs'!N201<='Model inputs'!O159))),0,IF(IF(IF(ISERROR('Model inputs'!N201<='Model inputs'!O165),'Model inputs'!N201<='Model inputs'!O165,IF(OR('Model inputs'!N201="",'Model inputs'!O165=""),"",'Model inputs'!N201<='Model inputs'!O165))="",FALSE,IF(ISERROR('Model inputs'!N201<='Model inputs'!O165),'Model inputs'!N201<='Model inputs'!O165,IF(OR('Model inputs'!N201="",'Model inputs'!O165=""),"",'Model inputs'!N201<='Model inputs'!O165))),IF('Model inputs'!O168="","",'Model inputs'!O168),'Model inputs'!O168+CEILING(('Model inputs'!N201-'Model inputs'!O165)/100000,1)*'Model inputs'!O162))) -> 0
A100: neatlogs bill (USD, derived) · Downside | B100: 0 | C100: =IF(IF(IF(ISERROR('Model inputs'!O157=1),'Model inputs'!O157=1,IF('Model inputs'!O157="","",'Model inputs'!O157=1))="",FALSE,IF(ISERROR('Model inputs'!O157=1),'Model inputs'!O157=1,IF('Model inputs'!O157="","",'Model inputs'!O157=1))),0,IF(IF(IF(ISERROR('Model inputs'!C202<='Model inputs'!O160),'Model inputs'!C202<='Model inputs'!O160,IF(OR('Model inputs'!C202="",'Model inputs'!O160=""),"",'Model inputs'!C202<='Model inputs'!O160))="",FALSE,IF(ISERROR('Model inputs'!C202<='Model inputs'!O160),'Model inputs'!C202<='Model inputs'!O160,IF(OR('Model inputs'!C202="",'Model inputs'!O160=""),"",'Model inputs'!C202<='Model inputs'!O160))),0,IF(IF(IF(ISERROR('Model inputs'!C202<='Model inputs'!O166),'Model inputs'!C202<='Model inputs'!O166,IF(OR('Model inputs'!C202="",'Model inputs'!O166=""),"",'Model inputs'!C202<='Model inputs'!O166))="",FALSE,IF(ISERROR('Model inputs'!C202<='Model inputs'!O166),'Model inputs'!C202<='Model inputs'!O166,IF(OR('Model inputs'!C202="",'Model inputs'!O166=""),"",'Model inputs'!C202<='Model inputs'!O166))),IF('Model inputs'!O169="","",'Model inputs'!O169),'Model inputs'!O169+CEILING(('Model inputs'!C202-'Model inputs'!O166)/100000,1)*'Model inputs'!O163))) -> 0 | D100: =IF(IF(IF(ISERROR('Model inputs'!O157=1),'Model inputs'!O157=1,IF('Model inputs'!O157="","",'Model inputs'!O157=1))="",FALSE,IF(ISERROR('Model inputs'!O157=1),'Model inputs'!O157=1,IF('Model inputs'!O157="","",'Model inputs'!O157=1))),0,IF(IF(IF(ISERROR('Model inputs'!D202<='Model inputs'!O160),'Model inputs'!D202<='Model inputs'!O160,IF(OR('Model inputs'!D202="",'Model inputs'!O160=""),"",'Model inputs'!D202<='Model inputs'!O160))="",FALSE,IF(ISERROR('Model inputs'!D202<='Model inputs'!O160),'Model inputs'!D202<='Model inputs'!O160,IF(OR('Model inputs'!D202="",'Model inputs'!O160=""),"",'Model inputs'!D202<='Model inputs'!O160))),0,IF(IF(IF(ISERROR('Model inputs'!D202<='Model inputs'!O166),'Model inputs'!D202<='Model inputs'!O166,IF(OR('Model inputs'!D202="",'Model inputs'!O166=""),"",'Model inputs'!D202<='Model inputs'!O166))="",FALSE,IF(ISERROR('Model inputs'!D202<='Model inputs'!O166),'Model inputs'!D202<='Model inputs'!O166,IF(OR('Model inputs'!D202="",'Model inputs'!O166=""),"",'Model inputs'!D202<='Model inputs'!O166))),IF('Model inputs'!O169="","",'Model inputs'!O169),'Model inputs'!O169+CEILING(('Model inputs'!D202-'Model inputs'!O166)/100000,1)*'Model inputs'!O163))) -> 0 | E100: =IF(IF(IF(ISERROR('Model inputs'!O157=1),'Model inputs'!O157=1,IF('Model inputs'!O157="","",'Model inputs'!O157=1))="",FALSE,IF(ISERROR('Model inputs'!O157=1),'Model inputs'!O157=1,IF('Model inputs'!O157="","",'Model inputs'!O157=1))),0,IF(IF(IF(ISERROR('Model inputs'!E202<='Model inputs'!O160),'Model inputs'!E202<='Model inputs'!O160,IF(OR('Model inputs'!E202="",'Model inputs'!O160=""),"",'Model inputs'!E202<='Model inputs'!O160))="",FALSE,IF(ISERROR('Model inputs'!E202<='Model inputs'!O160),'Model inputs'!E202<='Model inputs'!O160,IF(OR('Model inputs'!E202="",'Model inputs'!O160=""),"",'Model inputs'!E202<='Model inputs'!O160))),0,IF(IF(IF(ISERROR('Model inputs'!E202<='Model inputs'!O166),'Model inputs'!E202<='Model inputs'!O166,IF(OR('Model inputs'!E202="",'Model inputs'!O166=""),"",'Model inputs'!E202<='Model inputs'!O166))="",FALSE,IF(ISERROR('Model inputs'!E202<='Model inputs'!O166),'Model inputs'!E202<='Model inputs'!O166,IF(OR('Model inputs'!E202="",'Model inputs'!O166=""),"",'Model inputs'!E202<='Model inputs'!O166))),IF('Model inputs'!O169="","",'Model inputs'!O169),'Model inputs'!O169+CEILING(('Model inputs'!E202-'Model inputs'!O166)/100000,1)*'Model inputs'!O163))) -> 0 | F100: =IF(IF(IF(ISERROR('Model inputs'!O157=1),'Model inputs'!O157=1,IF('Model inputs'!O157="","",'Model inputs'!O157=1))="",FALSE,IF(ISERROR('Model inputs'!O157=1),'Model inputs'!O157=1,IF('Model inputs'!O157="","",'Model inputs'!O157=1))),0,IF(IF(IF(ISERROR('Model inputs'!F202<='Model inputs'!O160),'Model inputs'!F202<='Model inputs'!O160,IF(OR('Model inputs'!F202="",'Model inputs'!O160=""),"",'Model inputs'!F202<='Model inputs'!O160))="",FALSE,IF(ISERROR('Model inputs'!F202<='Model inputs'!O160),'Model inputs'!F202<='Model inputs'!O160,IF(OR('Model inputs'!F202="",'Model inputs'!O160=""),"",'Model inputs'!F202<='Model inputs'!O160))),0,IF(IF(IF(ISERROR('Model inputs'!F202<='Model inputs'!O166),'Model inputs'!F202<='Model inputs'!O166,IF(OR('Model inputs'!F202="",'Model inputs'!O166=""),"",'Model inputs'!F202<='Model inputs'!O166))="",FALSE,IF(ISERROR('Model inputs'!F202<='Model inputs'!O166),'Model inputs'!F202<='Model inputs'!O166,IF(OR('Model inputs'!F202="",'Model inputs'!O166=""),"",'Model inputs'!F202<='Model inputs'!O166))),IF('Model inputs'!O169="","",'Model inputs'!O169),'Model inputs'!O169+CEILING(('Model inputs'!F202-'Model inputs'!O166)/100000,1)*'Model inputs'!O163))) -> 0 | G100: =IF(IF(IF(ISERROR('Model inputs'!O157=1),'Model inputs'!O157=1,IF('Model inputs'!O157="","",'Model inputs'!O157=1))="",FALSE,IF(ISERROR('Model inputs'!O157=1),'Model inputs'!O157=1,IF('Model inputs'!O157="","",'Model inputs'!O157=1))),0,IF(IF(IF(ISERROR('Model inputs'!G202<='Model inputs'!O160),'Model inputs'!G202<='Model inputs'!O160,IF(OR('Model inputs'!G202="",'Model inputs'!O160=""),"",'Model inputs'!G202<='Model inputs'!O160))="",FALSE,IF(ISERROR('Model inputs'!G202<='Model inputs'!O160),'Model inputs'!G202<='Model inputs'!O160,IF(OR('Model inputs'!G202="",'Model inputs'!O160=""),"",'Model inputs'!G202<='Model inputs'!O160))),0,IF(IF(IF(ISERROR('Model inputs'!G202<='Model inputs'!O166),'Model inputs'!G202<='Model inputs'!O166,IF(OR('Model inputs'!G202="",'Model inputs'!O166=""),"",'Model inputs'!G202<='Model inputs'!O166))="",FALSE,IF(ISERROR('Model inputs'!G202<='Model inputs'!O166),'Model inputs'!G202<='Model inputs'!O166,IF(OR('Model inputs'!G202="",'Model inputs'!O166=""),"",'Model inputs'!G202<='Model inputs'!O166))),IF('Model inputs'!O169="","",'Model inputs'!O169),'Model inputs'!O169+CEILING(('Model inputs'!G202-'Model inputs'!O166)/100000,1)*'Model inputs'!O163))) -> 0 | H100: =IF(IF(IF(ISERROR('Model inputs'!O157=1),'Model inputs'!O157=1,IF('Model inputs'!O157="","",'Model inputs'!O157=1))="",FALSE,IF(ISERROR('Model inputs'!O157=1),'Model inputs'!O157=1,IF('Model inputs'!O157="","",'Model inputs'!O157=1))),0,IF(IF(IF(ISERROR('Model inputs'!H202<='Model inputs'!O160),'Model inputs'!H202<='Model inputs'!O160,IF(OR('Model inputs'!H202="",'Model inputs'!O160=""),"",'Model inputs'!H202<='Model inputs'!O160))="",FALSE,IF(ISERROR('Model inputs'!H202<='Model inputs'!O160),'Model inputs'!H202<='Model inputs'!O160,IF(OR('Model inputs'!H202="",'Model inputs'!O160=""),"",'Model inputs'!H202<='Model inputs'!O160))),0,IF(IF(IF(ISERROR('Model inputs'!H202<='Model inputs'!O166),'Model inputs'!H202<='Model inputs'!O166,IF(OR('Model inputs'!H202="",'Model inputs'!O166=""),"",'Model inputs'!H202<='Model inputs'!O166))="",FALSE,IF(ISERROR('Model inputs'!H202<='Model inputs'!O166),'Model inputs'!H202<='Model inputs'!O166,IF(OR('Model inputs'!H202="",'Model inputs'!O166=""),"",'Model inputs'!H202<='Model inputs'!O166))),IF('Model inputs'!O169="","",'Model inputs'!O169),'Model inputs'!O169+CEILING(('Model inputs'!H202-'Model inputs'!O166)/100000,1)*'Model inputs'!O163))) -> 0 | I100: =IF(IF(IF(ISERROR('Model inputs'!O157=1),'Model inputs'!O157=1,IF('Model inputs'!O157="","",'Model inputs'!O157=1))="",FALSE,IF(ISERROR('Model inputs'!O157=1),'Model inputs'!O157=1,IF('Model inputs'!O157="","",'Model inputs'!O157=1))),0,IF(IF(IF(ISERROR('Model inputs'!I202<='Model inputs'!O160),'Model inputs'!I202<='Model inputs'!O160,IF(OR('Model inputs'!I202="",'Model inputs'!O160=""),"",'Model inputs'!I202<='Model inputs'!O160))="",FALSE,IF(ISERROR('Model inputs'!I202<='Model inputs'!O160),'Model inputs'!I202<='Model inputs'!O160,IF(OR('Model inputs'!I202="",'Model inputs'!O160=""),"",'Model inputs'!I202<='Model inputs'!O160))),0,IF(IF(IF(ISERROR('Model inputs'!I202<='Model inputs'!O166),'Model inputs'!I202<='Model inputs'!O166,IF(OR('Model inputs'!I202="",'Model inputs'!O166=""),"",'Model inputs'!I202<='Model inputs'!O166))="",FALSE,IF(ISERROR('Model inputs'!I202<='Model inputs'!O166),'Model inputs'!I202<='Model inputs'!O166,IF(OR('Model inputs'!I202="",'Model inputs'!O166=""),"",'Model inputs'!I202<='Model inputs'!O166))),IF('Model inputs'!O169="","",'Model inputs'!O169),'Model inputs'!O169+CEILING(('Model inputs'!I202-'Model inputs'!O166)/100000,1)*'Model inputs'!O163))) -> 0 | J100: =IF(IF(IF(ISERROR('Model inputs'!O157=1),'Model inputs'!O157=1,IF('Model inputs'!O157="","",'Model inputs'!O157=1))="",FALSE,IF(ISERROR('Model inputs'!O157=1),'Model inputs'!O157=1,IF('Model inputs'!O157="","",'Model inputs'!O157=1))),0,IF(IF(IF(ISERROR('Model inputs'!J202<='Model inputs'!O160),'Model inputs'!J202<='Model inputs'!O160,IF(OR('Model inputs'!J202="",'Model inputs'!O160=""),"",'Model inputs'!J202<='Model inputs'!O160))="",FALSE,IF(ISERROR('Model inputs'!J202<='Model inputs'!O160),'Model inputs'!J202<='Model inputs'!O160,IF(OR('Model inputs'!J202="",'Model inputs'!O160=""),"",'Model inputs'!J202<='Model inputs'!O160))),0,IF(IF(IF(ISERROR('Model inputs'!J202<='Model inputs'!O166),'Model inputs'!J202<='Model inputs'!O166,IF(OR('Model inputs'!J202="",'Model inputs'!O166=""),"",'Model inputs'!J202<='Model inputs'!O166))="",FALSE,IF(ISERROR('Model inputs'!J202<='Model inputs'!O166),'Model inputs'!J202<='Model inputs'!O166,IF(OR('Model inputs'!J202="",'Model inputs'!O166=""),"",'Model inputs'!J202<='Model inputs'!O166))),IF('Model inputs'!O169="","",'Model inputs'!O169),'Model inputs'!O169+CEILING(('Model inputs'!J202-'Model inputs'!O166)/100000,1)*'Model inputs'!O163))) -> 0 | K100: =IF(IF(IF(ISERROR('Model inputs'!O157=1),'Model inputs'!O157=1,IF('Model inputs'!O157="","",'Model inputs'!O157=1))="",FALSE,IF(ISERROR('Model inputs'!O157=1),'Model inputs'!O157=1,IF('Model inputs'!O157="","",'Model inputs'!O157=1))),0,IF(IF(IF(ISERROR('Model inputs'!K202<='Model inputs'!O160),'Model inputs'!K202<='Model inputs'!O160,IF(OR('Model inputs'!K202="",'Model inputs'!O160=""),"",'Model inputs'!K202<='Model inputs'!O160))="",FALSE,IF(ISERROR('Model inputs'!K202<='Model inputs'!O160),'Model inputs'!K202<='Model inputs'!O160,IF(OR('Model inputs'!K202="",'Model inputs'!O160=""),"",'Model inputs'!K202<='Model inputs'!O160))),0,IF(IF(IF(ISERROR('Model inputs'!K202<='Model inputs'!O166),'Model inputs'!K202<='Model inputs'!O166,IF(OR('Model inputs'!K202="",'Model inputs'!O166=""),"",'Model inputs'!K202<='Model inputs'!O166))="",FALSE,IF(ISERROR('Model inputs'!K202<='Model inputs'!O166),'Model inputs'!K202<='Model inputs'!O166,IF(OR('Model inputs'!K202="",'Model inputs'!O166=""),"",'Model inputs'!K202<='Model inputs'!O166))),IF('Model inputs'!O169="","",'Model inputs'!O169),'Model inputs'!O169+CEILING(('Model inputs'!K202-'Model inputs'!O166)/100000,1)*'Model inputs'!O163))) -> 0 | L100: =IF(IF(IF(ISERROR('Model inputs'!O157=1),'Model inputs'!O157=1,IF('Model inputs'!O157="","",'Model inputs'!O157=1))="",FALSE,IF(ISERROR('Model inputs'!O157=1),'Model inputs'!O157=1,IF('Model inputs'!O157="","",'Model inputs'!O157=1))),0,IF(IF(IF(ISERROR('Model inputs'!L202<='Model inputs'!O160),'Model inputs'!L202<='Model inputs'!O160,IF(OR('Model inputs'!L202="",'Model inputs'!O160=""),"",'Model inputs'!L202<='Model inputs'!O160))="",FALSE,IF(ISERROR('Model inputs'!L202<='Model inputs'!O160),'Model inputs'!L202<='Model inputs'!O160,IF(OR('Model inputs'!L202="",'Model inputs'!O160=""),"",'Model inputs'!L202<='Model inputs'!O160))),0,IF(IF(IF(ISERROR('Model inputs'!L202<='Model inputs'!O166),'Model inputs'!L202<='Model inputs'!O166,IF(OR('Model inputs'!L202="",'Model inputs'!O166=""),"",'Model inputs'!L202<='Model inputs'!O166))="",FALSE,IF(ISERROR('Model inputs'!L202<='Model inputs'!O166),'Model inputs'!L202<='Model inputs'!O166,IF(OR('Model inputs'!L202="",'Model inputs'!O166=""),"",'Model inputs'!L202<='Model inputs'!O166))),IF('Model inputs'!O169="","",'Model inputs'!O169),'Model inputs'!O169+CEILING(('Model inputs'!L202-'Model inputs'!O166)/100000,1)*'Model inputs'!O163))) -> 0 | M100: =IF(IF(IF(ISERROR('Model inputs'!O157=1),'Model inputs'!O157=1,IF('Model inputs'!O157="","",'Model inputs'!O157=1))="",FALSE,IF(ISERROR('Model inputs'!O157=1),'Model inputs'!O157=1,IF('Model inputs'!O157="","",'Model inputs'!O157=1))),0,IF(IF(IF(ISERROR('Model inputs'!M202<='Model inputs'!O160),'Model inputs'!M202<='Model inputs'!O160,IF(OR('Model inputs'!M202="",'Model inputs'!O160=""),"",'Model inputs'!M202<='Model inputs'!O160))="",FALSE,IF(ISERROR('Model inputs'!M202<='Model inputs'!O160),'Model inputs'!M202<='Model inputs'!O160,IF(OR('Model inputs'!M202="",'Model inputs'!O160=""),"",'Model inputs'!M202<='Model inputs'!O160))),0,IF(IF(IF(ISERROR('Model inputs'!M202<='Model inputs'!O166),'Model inputs'!M202<='Model inputs'!O166,IF(OR('Model inputs'!M202="",'Model inputs'!O166=""),"",'Model inputs'!M202<='Model inputs'!O166))="",FALSE,IF(ISERROR('Model inputs'!M202<='Model inputs'!O166),'Model inputs'!M202<='Model inputs'!O166,IF(OR('Model inputs'!M202="",'Model inputs'!O166=""),"",'Model inputs'!M202<='Model inputs'!O166))),IF('Model inputs'!O169="","",'Model inputs'!O169),'Model inputs'!O169+CEILING(('Model inputs'!M202-'Model inputs'!O166)/100000,1)*'Model inputs'!O163))) -> 0 | N100: =IF(IF(IF(ISERROR('Model inputs'!O157=1),'Model inputs'!O157=1,IF('Model inputs'!O157="","",'Model inputs'!O157=1))="",FALSE,IF(ISERROR('Model inputs'!O157=1),'Model inputs'!O157=1,IF('Model inputs'!O157="","",'Model inputs'!O157=1))),0,IF(IF(IF(ISERROR('Model inputs'!N202<='Model inputs'!O160),'Model inputs'!N202<='Model inputs'!O160,IF(OR('Model inputs'!N202="",'Model inputs'!O160=""),"",'Model inputs'!N202<='Model inputs'!O160))="",FALSE,IF(ISERROR('Model inputs'!N202<='Model inputs'!O160),'Model inputs'!N202<='Model inputs'!O160,IF(OR('Model inputs'!N202="",'Model inputs'!O160=""),"",'Model inputs'!N202<='Model inputs'!O160))),0,IF(IF(IF(ISERROR('Model inputs'!N202<='Model inputs'!O166),'Model inputs'!N202<='Model inputs'!O166,IF(OR('Model inputs'!N202="",'Model inputs'!O166=""),"",'Model inputs'!N202<='Model inputs'!O166))="",FALSE,IF(ISERROR('Model inputs'!N202<='Model inputs'!O166),'Model inputs'!N202<='Model inputs'!O166,IF(OR('Model inputs'!N202="",'Model inputs'!O166=""),"",'Model inputs'!N202<='Model inputs'!O166))),IF('Model inputs'!O169="","",'Model inputs'!O169),'Model inputs'!O169+CEILING(('Model inputs'!N202-'Model inputs'!O166)/100000,1)*'Model inputs'!O163))) -> 0
A101: neatlogs bill (USD, derived) · Growth | B101: 0 | C101: =IF(IF(IF(ISERROR('Model inputs'!O158=1),'Model inputs'!O158=1,IF('Model inputs'!O158="","",'Model inputs'!O158=1))="",FALSE,IF(ISERROR('Model inputs'!O158=1),'Model inputs'!O158=1,IF('Model inputs'!O158="","",'Model inputs'!O158=1))),0,IF(IF(IF(ISERROR('Model inputs'!C203<='Model inputs'!O161),'Model inputs'!C203<='Model inputs'!O161,IF(OR('Model inputs'!C203="",'Model inputs'!O161=""),"",'Model inputs'!C203<='Model inputs'!O161))="",FALSE,IF(ISERROR('Model inputs'!C203<='Model inputs'!O161),'Model inputs'!C203<='Model inputs'!O161,IF(OR('Model inputs'!C203="",'Model inputs'!O161=""),"",'Model inputs'!C203<='Model inputs'!O161))),0,IF(IF(IF(ISERROR('Model inputs'!C203<='Model inputs'!O167),'Model inputs'!C203<='Model inputs'!O167,IF(OR('Model inputs'!C203="",'Model inputs'!O167=""),"",'Model inputs'!C203<='Model inputs'!O167))="",FALSE,IF(ISERROR('Model inputs'!C203<='Model inputs'!O167),'Model inputs'!C203<='Model inputs'!O167,IF(OR('Model inputs'!C203="",'Model inputs'!O167=""),"",'Model inputs'!C203<='Model inputs'!O167))),IF('Model inputs'!O170="","",'Model inputs'!O170),'Model inputs'!O170+CEILING(('Model inputs'!C203-'Model inputs'!O167)/100000,1)*'Model inputs'!O164))) -> 0 | D101: =IF(IF(IF(ISERROR('Model inputs'!O158=1),'Model inputs'!O158=1,IF('Model inputs'!O158="","",'Model inputs'!O158=1))="",FALSE,IF(ISERROR('Model inputs'!O158=1),'Model inputs'!O158=1,IF('Model inputs'!O158="","",'Model inputs'!O158=1))),0,IF(IF(IF(ISERROR('Model inputs'!D203<='Model inputs'!O161),'Model inputs'!D203<='Model inputs'!O161,IF(OR('Model inputs'!D203="",'Model inputs'!O161=""),"",'Model inputs'!D203<='Model inputs'!O161))="",FALSE,IF(ISERROR('Model inputs'!D203<='Model inputs'!O161),'Model inputs'!D203<='Model inputs'!O161,IF(OR('Model inputs'!D203="",'Model inputs'!O161=""),"",'Model inputs'!D203<='Model inputs'!O161))),0,IF(IF(IF(ISERROR('Model inputs'!D203<='Model inputs'!O167),'Model inputs'!D203<='Model inputs'!O167,IF(OR('Model inputs'!D203="",'Model inputs'!O167=""),"",'Model inputs'!D203<='Model inputs'!O167))="",FALSE,IF(ISERROR('Model inputs'!D203<='Model inputs'!O167),'Model inputs'!D203<='Model inputs'!O167,IF(OR('Model inputs'!D203="",'Model inputs'!O167=""),"",'Model inputs'!D203<='Model inputs'!O167))),IF('Model inputs'!O170="","",'Model inputs'!O170),'Model inputs'!O170+CEILING(('Model inputs'!D203-'Model inputs'!O167)/100000,1)*'Model inputs'!O164))) -> 0 | E101: =IF(IF(IF(ISERROR('Model inputs'!O158=1),'Model inputs'!O158=1,IF('Model inputs'!O158="","",'Model inputs'!O158=1))="",FALSE,IF(ISERROR('Model inputs'!O158=1),'Model inputs'!O158=1,IF('Model inputs'!O158="","",'Model inputs'!O158=1))),0,IF(IF(IF(ISERROR('Model inputs'!E203<='Model inputs'!O161),'Model inputs'!E203<='Model inputs'!O161,IF(OR('Model inputs'!E203="",'Model inputs'!O161=""),"",'Model inputs'!E203<='Model inputs'!O161))="",FALSE,IF(ISERROR('Model inputs'!E203<='Model inputs'!O161),'Model inputs'!E203<='Model inputs'!O161,IF(OR('Model inputs'!E203="",'Model inputs'!O161=""),"",'Model inputs'!E203<='Model inputs'!O161))),0,IF(IF(IF(ISERROR('Model inputs'!E203<='Model inputs'!O167),'Model inputs'!E203<='Model inputs'!O167,IF(OR('Model inputs'!E203="",'Model inputs'!O167=""),"",'Model inputs'!E203<='Model inputs'!O167))="",FALSE,IF(ISERROR('Model inputs'!E203<='Model inputs'!O167),'Model inputs'!E203<='Model inputs'!O167,IF(OR('Model inputs'!E203="",'Model inputs'!O167=""),"",'Model inputs'!E203<='Model inputs'!O167))),IF('Model inputs'!O170="","",'Model inputs'!O170),'Model inputs'!O170+CEILING(('Model inputs'!E203-'Model inputs'!O167)/100000,1)*'Model inputs'!O164))) -> 0 | F101: =IF(IF(IF(ISERROR('Model inputs'!O158=1),'Model inputs'!O158=1,IF('Model inputs'!O158="","",'Model inputs'!O158=1))="",FALSE,IF(ISERROR('Model inputs'!O158=1),'Model inputs'!O158=1,IF('Model inputs'!O158="","",'Model inputs'!O158=1))),0,IF(IF(IF(ISERROR('Model inputs'!F203<='Model inputs'!O161),'Model inputs'!F203<='Model inputs'!O161,IF(OR('Model inputs'!F203="",'Model inputs'!O161=""),"",'Model inputs'!F203<='Model inputs'!O161))="",FALSE,IF(ISERROR('Model inputs'!F203<='Model inputs'!O161),'Model inputs'!F203<='Model inputs'!O161,IF(OR('Model inputs'!F203="",'Model inputs'!O161=""),"",'Model inputs'!F203<='Model inputs'!O161))),0,IF(IF(IF(ISERROR('Model inputs'!F203<='Model inputs'!O167),'Model inputs'!F203<='Model inputs'!O167,IF(OR('Model inputs'!F203="",'Model inputs'!O167=""),"",'Model inputs'!F203<='Model inputs'!O167))="",FALSE,IF(ISERROR('Model inputs'!F203<='Model inputs'!O167),'Model inputs'!F203<='Model inputs'!O167,IF(OR('Model inputs'!F203="",'Model inputs'!O167=""),"",'Model inputs'!F203<='Model inputs'!O167))),IF('Model inputs'!O170="","",'Model inputs'!O170),'Model inputs'!O170+CEILING(('Model inputs'!F203-'Model inputs'!O167)/100000,1)*'Model inputs'!O164))) -> 0 | G101: =IF(IF(IF(ISERROR('Model inputs'!O158=1),'Model inputs'!O158=1,IF('Model inputs'!O158="","",'Model inputs'!O158=1))="",FALSE,IF(ISERROR('Model inputs'!O158=1),'Model inputs'!O158=1,IF('Model inputs'!O158="","",'Model inputs'!O158=1))),0,IF(IF(IF(ISERROR('Model inputs'!G203<='Model inputs'!O161),'Model inputs'!G203<='Model inputs'!O161,IF(OR('Model inputs'!G203="",'Model inputs'!O161=""),"",'Model inputs'!G203<='Model inputs'!O161))="",FALSE,IF(ISERROR('Model inputs'!G203<='Model inputs'!O161),'Model inputs'!G203<='Model inputs'!O161,IF(OR('Model inputs'!G203="",'Model inputs'!O161=""),"",'Model inputs'!G203<='Model inputs'!O161))),0,IF(IF(IF(ISERROR('Model inputs'!G203<='Model inputs'!O167),'Model inputs'!G203<='Model inputs'!O167,IF(OR('Model inputs'!G203="",'Model inputs'!O167=""),"",'Model inputs'!G203<='Model inputs'!O167))="",FALSE,IF(ISERROR('Model inputs'!G203<='Model inputs'!O167),'Model inputs'!G203<='Model inputs'!O167,IF(OR('Model inputs'!G203="",'Model inputs'!O167=""),"",'Model inputs'!G203<='Model inputs'!O167))),IF('Model inputs'!O170="","",'Model inputs'!O170),'Model inputs'!O170+CEILING(('Model inputs'!G203-'Model inputs'!O167)/100000,1)*'Model inputs'!O164))) -> 0 | H101: =IF(IF(IF(ISERROR('Model inputs'!O158=1),'Model inputs'!O158=1,IF('Model inputs'!O158="","",'Model inputs'!O158=1))="",FALSE,IF(ISERROR('Model inputs'!O158=1),'Model inputs'!O158=1,IF('Model inputs'!O158="","",'Model inputs'!O158=1))),0,IF(IF(IF(ISERROR('Model inputs'!H203<='Model inputs'!O161),'Model inputs'!H203<='Model inputs'!O161,IF(OR('Model inputs'!H203="",'Model inputs'!O161=""),"",'Model inputs'!H203<='Model inputs'!O161))="",FALSE,IF(ISERROR('Model inputs'!H203<='Model inputs'!O161),'Model inputs'!H203<='Model inputs'!O161,IF(OR('Model inputs'!H203="",'Model inputs'!O161=""),"",'Model inputs'!H203<='Model inputs'!O161))),0,IF(IF(IF(ISERROR('Model inputs'!H203<='Model inputs'!O167),'Model inputs'!H203<='Model inputs'!O167,IF(OR('Model inputs'!H203="",'Model inputs'!O167=""),"",'Model inputs'!H203<='Model inputs'!O167))="",FALSE,IF(ISERROR('Model inputs'!H203<='Model inputs'!O167),'Model inputs'!H203<='Model inputs'!O167,IF(OR('Model inputs'!H203="",'Model inputs'!O167=""),"",'Model inputs'!H203<='Model inputs'!O167))),IF('Model inputs'!O170="","",'Model inputs'!O170),'Model inputs'!O170+CEILING(('Model inputs'!H203-'Model inputs'!O167)/100000,1)*'Model inputs'!O164))) -> 0 | I101: =IF(IF(IF(ISERROR('Model inputs'!O158=1),'Model inputs'!O158=1,IF('Model inputs'!O158="","",'Model inputs'!O158=1))="",FALSE,IF(ISERROR('Model inputs'!O158=1),'Model inputs'!O158=1,IF('Model inputs'!O158="","",'Model inputs'!O158=1))),0,IF(IF(IF(ISERROR('Model inputs'!I203<='Model inputs'!O161),'Model inputs'!I203<='Model inputs'!O161,IF(OR('Model inputs'!I203="",'Model inputs'!O161=""),"",'Model inputs'!I203<='Model inputs'!O161))="",FALSE,IF(ISERROR('Model inputs'!I203<='Model inputs'!O161),'Model inputs'!I203<='Model inputs'!O161,IF(OR('Model inputs'!I203="",'Model inputs'!O161=""),"",'Model inputs'!I203<='Model inputs'!O161))),0,IF(IF(IF(ISERROR('Model inputs'!I203<='Model inputs'!O167),'Model inputs'!I203<='Model inputs'!O167,IF(OR('Model inputs'!I203="",'Model inputs'!O167=""),"",'Model inputs'!I203<='Model inputs'!O167))="",FALSE,IF(ISERROR('Model inputs'!I203<='Model inputs'!O167),'Model inputs'!I203<='Model inputs'!O167,IF(OR('Model inputs'!I203="",'Model inputs'!O167=""),"",'Model inputs'!I203<='Model inputs'!O167))),IF('Model inputs'!O170="","",'Model inputs'!O170),'Model inputs'!O170+CEILING(('Model inputs'!I203-'Model inputs'!O167)/100000,1)*'Model inputs'!O164))) -> 0 | J101: =IF(IF(IF(ISERROR('Model inputs'!O158=1),'Model inputs'!O158=1,IF('Model inputs'!O158="","",'Model inputs'!O158=1))="",FALSE,IF(ISERROR('Model inputs'!O158=1),'Model inputs'!O158=1,IF('Model inputs'!O158="","",'Model inputs'!O158=1))),0,IF(IF(IF(ISERROR('Model inputs'!J203<='Model inputs'!O161),'Model inputs'!J203<='Model inputs'!O161,IF(OR('Model inputs'!J203="",'Model inputs'!O161=""),"",'Model inputs'!J203<='Model inputs'!O161))="",FALSE,IF(ISERROR('Model inputs'!J203<='Model inputs'!O161),'Model inputs'!J203<='Model inputs'!O161,IF(OR('Model inputs'!J203="",'Model inputs'!O161=""),"",'Model inputs'!J203<='Model inputs'!O161))),0,IF(IF(IF(ISERROR('Model inputs'!J203<='Model inputs'!O167),'Model inputs'!J203<='Model inputs'!O167,IF(OR('Model inputs'!J203="",'Model inputs'!O167=""),"",'Model inputs'!J203<='Model inputs'!O167))="",FALSE,IF(ISERROR('Model inputs'!J203<='Model inputs'!O167),'Model inputs'!J203<='Model inputs'!O167,IF(OR('Model inputs'!J203="",'Model inputs'!O167=""),"",'Model inputs'!J203<='Model inputs'!O167))),IF('Model inputs'!O170="","",'Model inputs'!O170),'Model inputs'!O170+CEILING(('Model inputs'!J203-'Model inputs'!O167)/100000,1)*'Model inputs'!O164))) -> 0 | K101: =IF(IF(IF(ISERROR('Model inputs'!O158=1),'Model inputs'!O158=1,IF('Model inputs'!O158="","",'Model inputs'!O158=1))="",FALSE,IF(ISERROR('Model inputs'!O158=1),'Model inputs'!O158=1,IF('Model inputs'!O158="","",'Model inputs'!O158=1))),0,IF(IF(IF(ISERROR('Model inputs'!K203<='Model inputs'!O161),'Model inputs'!K203<='Model inputs'!O161,IF(OR('Model inputs'!K203="",'Model inputs'!O161=""),"",'Model inputs'!K203<='Model inputs'!O161))="",FALSE,IF(ISERROR('Model inputs'!K203<='Model inputs'!O161),'Model inputs'!K203<='Model inputs'!O161,IF(OR('Model inputs'!K203="",'Model inputs'!O161=""),"",'Model inputs'!K203<='Model inputs'!O161))),0,IF(IF(IF(ISERROR('Model inputs'!K203<='Model inputs'!O167),'Model inputs'!K203<='Model inputs'!O167,IF(OR('Model inputs'!K203="",'Model inputs'!O167=""),"",'Model inputs'!K203<='Model inputs'!O167))="",FALSE,IF(ISERROR('Model inputs'!K203<='Model inputs'!O167),'Model inputs'!K203<='Model inputs'!O167,IF(OR('Model inputs'!K203="",'Model inputs'!O167=""),"",'Model inputs'!K203<='Model inputs'!O167))),IF('Model inputs'!O170="","",'Model inputs'!O170),'Model inputs'!O170+CEILING(('Model inputs'!K203-'Model inputs'!O167)/100000,1)*'Model inputs'!O164))) -> 0 | L101: =IF(IF(IF(ISERROR('Model inputs'!O158=1),'Model inputs'!O158=1,IF('Model inputs'!O158="","",'Model inputs'!O158=1))="",FALSE,IF(ISERROR('Model inputs'!O158=1),'Model inputs'!O158=1,IF('Model inputs'!O158="","",'Model inputs'!O158=1))),0,IF(IF(IF(ISERROR('Model inputs'!L203<='Model inputs'!O161),'Model inputs'!L203<='Model inputs'!O161,IF(OR('Model inputs'!L203="",'Model inputs'!O161=""),"",'Model inputs'!L203<='Model inputs'!O161))="",FALSE,IF(ISERROR('Model inputs'!L203<='Model inputs'!O161),'Model inputs'!L203<='Model inputs'!O161,IF(OR('Model inputs'!L203="",'Model inputs'!O161=""),"",'Model inputs'!L203<='Model inputs'!O161))),0,IF(IF(IF(ISERROR('Model inputs'!L203<='Model inputs'!O167),'Model inputs'!L203<='Model inputs'!O167,IF(OR('Model inputs'!L203="",'Model inputs'!O167=""),"",'Model inputs'!L203<='Model inputs'!O167))="",FALSE,IF(ISERROR('Model inputs'!L203<='Model inputs'!O167),'Model inputs'!L203<='Model inputs'!O167,IF(OR('Model inputs'!L203="",'Model inputs'!O167=""),"",'Model inputs'!L203<='Model inputs'!O167))),IF('Model inputs'!O170="","",'Model inputs'!O170),'Model inputs'!O170+CEILING(('Model inputs'!L203-'Model inputs'!O167)/100000,1)*'Model inputs'!O164))) -> 0 | M101: =IF(IF(IF(ISERROR('Model inputs'!O158=1),'Model inputs'!O158=1,IF('Model inputs'!O158="","",'Model inputs'!O158=1))="",FALSE,IF(ISERROR('Model inputs'!O158=1),'Model inputs'!O158=1,IF('Model inputs'!O158="","",'Model inputs'!O158=1))),0,IF(IF(IF(ISERROR('Model inputs'!M203<='Model inputs'!O161),'Model inputs'!M203<='Model inputs'!O161,IF(OR('Model inputs'!M203="",'Model inputs'!O161=""),"",'Model inputs'!M203<='Model inputs'!O161))="",FALSE,IF(ISERROR('Model inputs'!M203<='Model inputs'!O161),'Model inputs'!M203<='Model inputs'!O161,IF(OR('Model inputs'!M203="",'Model inputs'!O161=""),"",'Model inputs'!M203<='Model inputs'!O161))),0,IF(IF(IF(ISERROR('Model inputs'!M203<='Model inputs'!O167),'Model inputs'!M203<='Model inputs'!O167,IF(OR('Model inputs'!M203="",'Model inputs'!O167=""),"",'Model inputs'!M203<='Model inputs'!O167))="",FALSE,IF(ISERROR('Model inputs'!M203<='Model inputs'!O167),'Model inputs'!M203<='Model inputs'!O167,IF(OR('Model inputs'!M203="",'Model inputs'!O167=""),"",'Model inputs'!M203<='Model inputs'!O167))),IF('Model inputs'!O170="","",'Model inputs'!O170),'Model inputs'!O170+CEILING(('Model inputs'!M203-'Model inputs'!O167)/100000,1)*'Model inputs'!O164))) -> 0 | N101: =IF(IF(IF(ISERROR('Model inputs'!O158=1),'Model inputs'!O158=1,IF('Model inputs'!O158="","",'Model inputs'!O158=1))="",FALSE,IF(ISERROR('Model inputs'!O158=1),'Model inputs'!O158=1,IF('Model inputs'!O158="","",'Model inputs'!O158=1))),0,IF(IF(IF(ISERROR('Model inputs'!N203<='Model inputs'!O161),'Model inputs'!N203<='Model inputs'!O161,IF(OR('Model inputs'!N203="",'Model inputs'!O161=""),"",'Model inputs'!N203<='Model inputs'!O161))="",FALSE,IF(ISERROR('Model inputs'!N203<='Model inputs'!O161),'Model inputs'!N203<='Model inputs'!O161,IF(OR('Model inputs'!N203="",'Model inputs'!O161=""),"",'Model inputs'!N203<='Model inputs'!O161))),0,IF(IF(IF(ISERROR('Model inputs'!N203<='Model inputs'!O167),'Model inputs'!N203<='Model inputs'!O167,IF(OR('Model inputs'!N203="",'Model inputs'!O167=""),"",'Model inputs'!N203<='Model inputs'!O167))="",FALSE,IF(ISERROR('Model inputs'!N203<='Model inputs'!O167),'Model inputs'!N203<='Model inputs'!O167,IF(OR('Model inputs'!N203="",'Model inputs'!O167=""),"",'Model inputs'!N203<='Model inputs'!O167))),IF('Model inputs'!O170="","",'Model inputs'!O170),'Model inputs'!O170+CEILING(('Model inputs'!N203-'Model inputs'!O167)/100000,1)*'Model inputs'!O164))) -> 0
...

Sheet Export notes
A1: Export notes
A2: These cells hold the value cfo.ai calculated instead of a formula. They do not recalculate when you edit an input.
A4: Sheet | B4: Cell | C4: Variable | D4: Period | E4: Scenario | F4: Why
A5: Model inputs | B5: O318 | C5: Share of gated uplift paid (derived) | E5: Main Scenario | F5: It reads Verification policy, which this workbook does not contain.
A6: Model inputs | B6: O321 | C6: Share of gated uplift paid (derived) | E6: Downside | F6: It reads Verification policy, which this workbook does not contain.
A7: Model inputs | B7: O324 | C7: Share of gated uplift paid (derived) | E7: Growth | F7: It reads Verification policy, which this workbook does not contain.
