Workbook

Sheet Verification and illustration p
A1: Verification and illustration policy: cost, margin and bar
A2: Verification and illustration policy · Main Scenario
A4: Variable / dimension | B4: Full (8 pictures) | C4: Half (4 pictures) | D4: Text only (0)
A5: Cost per story (USD, estimate) | B5: ="" | C5: ="" | D5: =""
A6: Sampled | B6: ='Model inputs'!C36+'Model inputs'!C15+'Model inputs'!C38 -> 0.35284 | C6: ='Model inputs'!C36+'Model inputs'!C16+'Model inputs'!C38 -> 0.19284 | D6: ='Model inputs'!C36+'Model inputs'!C17+'Model inputs'!C38 -> 0.03284
A7: Verify all | B7: ='Model inputs'!C37+'Model inputs'!C15+'Model inputs'!C38 -> 0.3559 | C7: ='Model inputs'!C37+'Model inputs'!C16+'Model inputs'!C38 -> 0.1959 | D7: ='Model inputs'!C37+'Model inputs'!C17+'Model inputs'!C38 -> 0.0359
A8: Gross margin at month 6 (derived) | B8: ="" | C8: ="" | D8: =""
A9: Sampled | B9: =IFERROR(('Month 6 reference (company, sel'!B5-'Month 6 reference (company, sel'!B7-'Month 6 reference (company, sel'!B6*'Verification and illustration p'!B6)/'Month 6 reference (company, sel'!B5,0) -> 0.43279204 | C9: =IFERROR(('Month 6 reference (company, sel'!B5-'Month 6 reference (company, sel'!B7-'Month 6 reference (company, sel'!B6*'Verification and illustration p'!C6)/'Month 6 reference (company, sel'!B5,0) -> 0.67662698 | D9: =IFERROR(('Month 6 reference (company, sel'!B5-'Month 6 reference (company, sel'!B7-'Month 6 reference (company, sel'!B6*'Verification and illustration p'!D6)/'Month 6 reference (company, sel'!B5,0) -> 0.92046191
A10: Verify all | B10: =IFERROR(('Month 6 reference (company, sel'!B5-'Month 6 reference (company, sel'!B7-'Month 6 reference (company, sel'!B6*'Verification and illustration p'!B7)/'Month 6 reference (company, sel'!B5,0) -> 0.4281287 | C10: =IFERROR(('Month 6 reference (company, sel'!B5-'Month 6 reference (company, sel'!B7-'Month 6 reference (company, sel'!B6*'Verification and illustration p'!C7)/'Month 6 reference (company, sel'!B5,0) -> 0.67196363 | D10: =IFERROR(('Month 6 reference (company, sel'!B5-'Month 6 reference (company, sel'!B7-'Month 6 reference (company, sel'!B6*'Verification and illustration p'!D7)/'Month 6 reference (company, sel'!B5,0) -> 0.91579856
A11: Clears the gross margin bar at month 6 (1 = yes) | B11: ="" | C11: ="" | D11: =""
A12: Sampled | B12: =IF(IF(IF(ISERROR('Verification and illustration p'!B9>='Model inputs'!C7),'Verification and illustration p'!B9>='Model inputs'!C7,IF(OR('Verification and illustration p'!B9="",'Model inputs'!C7=""),"",'Verification and illustration p'!B9>='Model inputs'!C7))="",FALSE,IF(ISERROR('Verification and illustration p'!B9>='Model inputs'!C7),'Verification and illustration p'!B9>='Model inputs'!C7,IF(OR('Verification and illustration p'!B9="",'Model inputs'!C7=""),"",'Verification and illustration p'!B9>='Model inputs'!C7))),1,0) -> 0 | C12: =IF(IF(IF(ISERROR('Verification and illustration p'!C9>='Model inputs'!C7),'Verification and illustration p'!C9>='Model inputs'!C7,IF(OR('Verification and illustration p'!C9="",'Model inputs'!C7=""),"",'Verification and illustration p'!C9>='Model inputs'!C7))="",FALSE,IF(ISERROR('Verification and illustration p'!C9>='Model inputs'!C7),'Verification and illustration p'!C9>='Model inputs'!C7,IF(OR('Verification and illustration p'!C9="",'Model inputs'!C7=""),"",'Verification and illustration p'!C9>='Model inputs'!C7))),1,0) -> 1 | D12: =IF(IF(IF(ISERROR('Verification and illustration p'!D9>='Model inputs'!C7),'Verification and illustration p'!D9>='Model inputs'!C7,IF(OR('Verification and illustration p'!D9="",'Model inputs'!C7=""),"",'Verification and illustration p'!D9>='Model inputs'!C7))="",FALSE,IF(ISERROR('Verification and illustration p'!D9>='Model inputs'!C7),'Verification and illustration p'!D9>='Model inputs'!C7,IF(OR('Verification and illustration p'!D9="",'Model inputs'!C7=""),"",'Verification and illustration p'!D9>='Model inputs'!C7))),1,0) -> 1
A13: Verify all | B13: =IF(IF(IF(ISERROR('Verification and illustration p'!B10>='Model inputs'!C7),'Verification and illustration p'!B10>='Model inputs'!C7,IF(OR('Verification and illustration p'!B10="",'Model inputs'!C7=""),"",'Verification and illustration p'!B10>='Model inputs'!C7))="",FALSE,IF(ISERROR('Verification and illustration p'!B10>='Model inputs'!C7),'Verification and illustration p'!B10>='Model inputs'!C7,IF(OR('Verification and illustration p'!B10="",'Model inputs'!C7=""),"",'Verification and illustration p'!B10>='Model inputs'!C7))),1,0) -> 0 | C13: =IF(IF(IF(ISERROR('Verification and illustration p'!C10>='Model inputs'!C7),'Verification and illustration p'!C10>='Model inputs'!C7,IF(OR('Verification and illustration p'!C10="",'Model inputs'!C7=""),"",'Verification and illustration p'!C10>='Model inputs'!C7))="",FALSE,IF(ISERROR('Verification and illustration p'!C10>='Model inputs'!C7),'Verification and illustration p'!C10>='Model inputs'!C7,IF(OR('Verification and illustration p'!C10="",'Model inputs'!C7=""),"",'Verification and illustration p'!C10>='Model inputs'!C7))),1,0) -> 1 | D13: =IF(IF(IF(ISERROR('Verification and illustration p'!D10>='Model inputs'!C7),'Verification and illustration p'!D10>='Model inputs'!C7,IF(OR('Verification and illustration p'!D10="",'Model inputs'!C7=""),"",'Verification and illustration p'!D10>='Model inputs'!C7))="",FALSE,IF(ISERROR('Verification and illustration p'!D10>='Model inputs'!C7),'Verification and illustration p'!D10>='Model inputs'!C7,IF(OR('Verification and illustration p'!D10="",'Model inputs'!C7=""),"",'Verification and illustration p'!D10>='Model inputs'!C7))),1,0) -> 1
A14: Headroom under the per-story budget (USD, derived) | B14: ="" | C14: ="" | D14: =""
A15: Sampled | B15: ='Month 6 reference (company, sel'!B8-'Verification and illustration p'!B6 -> -0.10971879 | C15: ='Month 6 reference (company, sel'!B8-'Verification and illustration p'!C6 -> 0.050281213 | D15: ='Month 6 reference (company, sel'!B8-'Verification and illustration p'!D6 -> 0.21028121
A16: Verify all | B16: ='Month 6 reference (company, sel'!B8-'Verification and illustration p'!B7 -> -0.11277879 | C16: ='Month 6 reference (company, sel'!B8-'Verification and illustration p'!C7 -> 0.047221213 | D16: ='Month 6 reference (company, sel'!B8-'Verification and illustration p'!D7 -> 0.20722121

Sheet Month 6 reference (company, sel
A1: Month 6 reference (company, selected policy)
A2: Verification and illustration policy · Main Scenario
A4: Variable / dimension | B4: Value
A5: Revenue at month 6 (USD, derived) | B5: =SUM('Model inputs'!B19,'Model inputs'!B20) -> 847.71699
A6: Stories delivered at month 6 (derived) | B6: =SUM('Model inputs'!B31,'Model inputs'!B32) -> 1291.8938
A7: Hosting and neatlogs at month 6 (USD, derived) | B7: ='Model inputs'!D11+'Model inputs'!B12 -> 25
A8: Per-story budget that clears the bar at month 6 (USD, derived) | B8: =IFERROR(('Month 6 reference (company, sel'!B5*(1-'Model inputs'!C7)-'Month 6 reference (company, sel'!B7)/'Month 6 reference (company, sel'!B6,0) -> 0.24312121
A9: Gross margin at month 6, selected policy (monthly table) | B9: =IF('Model inputs'!B6="","",'Model inputs'!B6) -> 0.67196363
A10: Gross margin at month 6, selected policy (policy arithmetic) | B10: =IFERROR(('Month 6 reference (company, sel'!B5-'Month 6 reference (company, sel'!B7-'Month 6 reference (company, sel'!B6*'Selected policy'!B5)/'Month 6 reference (company, sel'!B5,0) -> 0.67196363
A11: Reconciliation difference (should be 0) | B11: ='Month 6 reference (company, sel'!B9-'Month 6 reference (company, sel'!B10 -> 0

Sheet Selected policy
A1: Selected policy
A2: Verification and illustration policy · Main Scenario
A4: Variable / dimension | B4: Value
A5: Cost per story, selected policy (USD, estimate) | B5: =SUM('Model inputs'!D28,'Model inputs'!D29)+SUM('Model inputs'!D24,'Model inputs'!D25,'Model inputs'!D26) -> 0.1959

Sheet Model inputs
A1: Model inputs
A2: Integration values are aggregated snapshots; raw source records are not included.
A4: Variables
A5: Variable / segment | B5: 2027-03 | C5: Value | D5: Value | E5: 2026-09 | F5: 2026-10 | G5: 2026-11 | H5: 2026-12 | I5: 2027-01 | J5: 2027-02 | K5: 2027-04 | L5: 2027-05 | M5: 2027-06 | N5: 2027-07 | O5: 2027-08 | P5: 2027-09
A6: Gross margin | B6: =IFERROR('Model inputs'!B50/'Model inputs'!B18,0) -> 0.67196363
A7: Gross margin bar (ours, stated) · Verification and illustration policy: cost, margin and bar | C7: =0.6 -> 0.6
A8: Gross margin bar (ours, stated) · Month 6 reference (company, selected policy) | D8: ='Model inputs'!C7 -> 0.6
A9: Hosting and neatlogs at month 6 (USD, derived) · Verification and illustration policy: cost, margin and bar | C9: ='Model inputs'!D11+'Model inputs'!B12 -> 25
A10: Hosting and neatlogs at month 6 (USD, derived) · Month 6 reference (company, selected policy) | D10: ='Model inputs'!D11+'Model inputs'!B12 -> 25
A11: Hosting per month (USD, assumed) · Month 6 reference (company, selected policy) | D11: =25 -> 25
A12: neatlogs bill (USD, derived) · Month 6 reference (company, selected policy) | B12: =IF(IF(IF(ISERROR('Model inputs'!C55=1),'Model inputs'!C55=1,IF('Model inputs'!C55="","",'Model inputs'!C55=1))="",FALSE,IF(ISERROR('Model inputs'!C55=1),'Model inputs'!C55=1,IF('Model inputs'!C55="","",'Model inputs'!C55=1))),0,IF(IF(IF(ISERROR('Model inputs'!B75<='Model inputs'!C56),'Model inputs'!B75<='Model inputs'!C56,IF(OR('Model inputs'!B75="",'Model inputs'!C56=""),"",'Model inputs'!B75<='Model inputs'!C56))="",FALSE,IF(ISERROR('Model inputs'!B75<='Model inputs'!C56),'Model inputs'!B75<='Model inputs'!C56,IF(OR('Model inputs'!B75="",'Model inputs'!C56=""),"",'Model inputs'!B75<='Model inputs'!C56))),0,IF(IF(IF(ISERROR('Model inputs'!B75<='Model inputs'!C58),'Model inputs'!B75<='Model inputs'!C58,IF(OR('Model inputs'!B75="",'Model inputs'!C58=""),"",'Model inputs'!B75<='Model inputs'!C58))="",FALSE,IF(ISERROR('Model inputs'!B75<='Model inputs'!C58),'Model inputs'!B75<='Model inputs'!C58,IF(OR('Model inputs'!B75="",'Model inputs'!C58=""),"",'Model inputs'!B75<='Model inputs'!C58))),IF('Model inputs'!C59="","",'Model inputs'!C59),'Model inputs'!C59+CEILING(('Model inputs'!B75-'Model inputs'!C58)/100000,1)*'Model inputs'!C57))) -> 0
A13: Per-story budget that clears the bar at month 6 (USD, derived) | C13: =IFERROR(('Model inputs'!C21*(1-'Model inputs'!C7)-'Model inputs'!C9)/'Model inputs'!C33,0) -> 0.24312121
A14: Picture and narration cost per story (USD, derived) | C14: ='Model inputs'!C67*'Model inputs'!C43+'Model inputs'!C41*'Model inputs'!C42 -> 0.016
A15: Picture and narration cost per story (USD, derived) > Full (8 pictures) | C15: ='Model inputs'!C68*'Model inputs'!C43+'Model inputs'!C41*'Model inputs'!C42 -> 0.336
A16: Picture and narration cost per story (USD, derived) > Half (4 pictures) | C16: ='Model inputs'!C69*'Model inputs'!C43+'Model inputs'!C41*'Model inputs'!C42 -> 0.176
A17: Picture and narration cost per story (USD, derived) > Text only (0) | C17: ='Model inputs'!C70*'Model inputs'!C43+'Model inputs'!C41*'Model inputs'!C42 -> 0.016
A18: Revenue (USD) | B18: =SUM('Model inputs'!B19,'Model inputs'!B20) -> 847.71699 | E18: =SUM('Model inputs'!E19,'Model inputs'!E20) -> 0 | F18: =SUM('Model inputs'!F19,'Model inputs'!F20) -> 623.452 | G18: =SUM('Model inputs'!G19,'Model inputs'!G20) -> 674.01084 | H18: =SUM('Model inputs'!H19,'Model inputs'!H20) -> 721.50952 | I18: =SUM('Model inputs'!I19,'Model inputs'!I20) -> 766.16332 | J18: =SUM('Model inputs'!J19,'Model inputs'!J20) -> 808.17119 | K18: =SUM('Model inputs'!K19,'Model inputs'!K20) -> 884.97074 | L18: =SUM('Model inputs'!L19,'Model inputs'!L20) -> 920.08966 | ... P18: =SUM('Model inputs'!P19,'Model inputs'!P20) -> 1041.9674
A19: Revenue (USD) > Classroom | B19: ='Model inputs'!B80+'Model inputs'!B61 -> 403.02228 | E19: =0 -> 0 | F19: ='Model inputs'!F80+'Model inputs'!F61 -> 310.3 | G19: ='Model inputs'!G80+'Model inputs'!G61 -> 329.991 | H19: ='Model inputs'!H80+'Model inputs'!H61 -> 349.09127 | I19: ='Model inputs'!I80+'Model inputs'!I61 -> 367.61853 | J19: ='Model inputs'!J80+'Model inputs'!J61 -> 385.58998 | K19: ='Model inputs'!K80+'Model inputs'!K61 -> 419.93161 | L19: ='Model inputs'!L80+'Model inputs'!L61 -> 436.33366 | M19: ='Model inputs'!M80+'Model inputs'!M61 -> 452.24365 | ... P19: ='Model inputs'!P80+'Model inputs'!P61 -> 497.16667
A20: Revenue (USD) > Household | B20: ='Model inputs'!B81+'Model inputs'!B62 -> 444.69471 | E20: =0 -> 0 | F20: ='Model inputs'!F81+'Model inputs'!F62 -> 313.152 | G20: ='Model inputs'!G81+'Model inputs'!G62 -> 344.01984 | H20: ='Model inputs'!H81+'Model inputs'!H62 -> 372.41825 | I20: ='Model inputs'!I81+'Model inputs'!I62 -> 398.54479 | J20: ='Model inputs'!J81+'Model inputs'!J62 -> 422.58121 | K20: ='Model inputs'!K81+'Model inputs'!K62 -> 465.03914 | L20: ='Model inputs'!L81+'Model inputs'!L62 -> 483.756 | M20: ='Model inputs'!M81+'Model inputs'!M62 -> 500.97552 | ... P20: ='Model inputs'!P81+'Model inputs'!P62 -> 544.80072
A21: Revenue at month 6 (USD, derived) · Verification and illustration policy: cost, margin and bar | C21: =SUM('Model inputs'!B19,'Model inputs'!B20) -> 847.71699
A22: Revenue at month 6 (USD, derived) · Month 6 reference (company, selected policy) | D22: =SUM('Model inputs'!B19,'Model inputs'!B20) -> 847.71699
A23: Selected picture and narration cost (USD, derived) | D23: ='Model inputs'!C14*'Model inputs'!D51 -> 0
A24: Selected picture and narration cost (USD, derived) > Full (8 pictures) | D24: ='Model inputs'!C15*'Model inputs'!D52 -> 0
A25: Selected picture and narration cost (USD, derived) > Half (4 pictures) | D25: ='Model inputs'!C16*'Model inputs'!D53 -> 0.176
A26: Selected picture and narration cost (USD, derived) > Text only (0) | D26: ='Model inputs'!C17*'Model inputs'!D54 -> 0
A27: Selected text and verification cost (USD, derived) | D27: ='Model inputs'!C35*'Model inputs'!D85 -> 0
A28: Selected text and verification cost (USD, derived) > Sampled | D28: ='Model inputs'!C36*'Model inputs'!D86 -> 0
A29: Selected text and verification cost (USD, derived) > Verify all | D29: ='Model inputs'!C37*'Model inputs'!D87 -> 0.0199
A30: Stories delivered | B30: =SUM('Model inputs'!B31,'Model inputs'!B32) -> 1291.8938 | E30: =SUM('Model inputs'!E31,'Model inputs'!E32) -> 0 | F30: =SUM('Model inputs'!F31,'Model inputs'!F32) -> 964.56 | G30: =SUM('Model inputs'!G31,'Model inputs'!G32) -> 1037.0952 | H30: =SUM('Model inputs'!H31,'Model inputs'!H32) -> 1105.8646 | I30: =SUM('Model inputs'!I31,'Model inputs'!I32) -> 1171.1083 | J30: =SUM('Model inputs'!J31,'Model inputs'!J32) -> 1233.0491 | K30: =SUM('Model inputs'!K31,'Model inputs'!K32) -> 1347.8343 | L30: =SUM('Model inputs'!L31,'Model inputs'!L32) -> 1401.0487 | ... P30: =SUM('Model inputs'!P31,'Model inputs'!P32) -> 1589.7888
A31: Stories delivered > Classroom | B31: ='Model inputs'!B48*'Model inputs'!C77 -> 833.83919 | E31: =0 -> 0 | F31: ='Model inputs'!F48*'Model inputs'!C77 -> 642 | G31: ='Model inputs'!G48*'Model inputs'!C77 -> 682.74 | H31: ='Model inputs'!H48*'Model inputs'!C77 -> 722.2578 | I31: ='Model inputs'!I48*'Model inputs'!C77 -> 760.59007 | J31: ='Model inputs'!J48*'Model inputs'!C77 -> 797.77236 | K31: ='Model inputs'!K48*'Model inputs'!C77 -> 868.82402 | L31: ='Model inputs'!L48*'Model inputs'!C77 -> 902.7593 | M31: ='Model inputs'!M48*'Model inputs'!C77 -> 935.67652 | N31: ='Model inputs'!N48*'Model inputs'!C77 -> 967.60622 | O31: ='Model inputs'!O48*'Model inputs'!C77 -> 998.57804 | P31: ='Model inputs'!P48*'Model inputs'!C77 -> 1028.6207
A32: Stories delivered > Household | B32: ='Model inputs'!B49*'Model inputs'!C78 -> 458.05464 | E32: =0 -> 0 | F32: ='Model inputs'!F49*'Model inputs'!C78 -> 322.56 | G32: ='Model inputs'!G49*'Model inputs'!C78 -> 354.3552 | H32: ='Model inputs'!H49*'Model inputs'!C78 -> 383.60678 | I32: ='Model inputs'!I49*'Model inputs'!C78 -> 410.51824 | J32: ='Model inputs'!J49*'Model inputs'!C78 -> 435.27678 | K32: ='Model inputs'!K49*'Model inputs'!C78 -> 479.01027 | L32: ='Model inputs'!L49*'Model inputs'!C78 -> 498.28945 | M32: ='Model inputs'!M49*'Model inputs'!C78 -> 516.02629 | N32: ='Model inputs'!N49*'Model inputs'!C78 -> 532.34419 | O32: ='Model inputs'!O49*'Model inputs'!C78 -> 547.35665 | P32: ='Model inputs'!P49*'Model inputs'!C78 -> 561.16812
A33: Stories delivered at month 6 (derived) · Verification and illustration policy: cost, margin and bar | C33: =SUM('Model inputs'!B31,'Model inputs'!B32) -> 1291.8938
A34: Stories delivered at month 6 (derived) · Month 6 reference (company, selected policy) | D34: =SUM('Model inputs'!B31,'Model inputs'!B32) -> 1291.8938
A35: Text and verification cost per story (USD, derived) | C35: ='Model inputs'!C45+'Model inputs'!C72*('Model inputs'!C46-'Model inputs'!C45) -> 0.01684
A36: Text and verification cost per story (USD, derived) > Sampled | C36: ='Model inputs'!C45+'Model inputs'!C73*('Model inputs'!C46-'Model inputs'!C45) -> 0.01684
A37: Text and verification cost per story (USD, derived) > Verify all | C37: ='Model inputs'!C45+'Model inputs'!C74*('Model inputs'!C46-'Model inputs'!C45) -> 0.0199
A38: Video cost per story (USD, derived) | C38: ='Model inputs'!C88*('Model inputs'!C71*'Model inputs'!C89*'Model inputs'!C90+'Model inputs'!C39) -> 0
A39: Clip check cost per clip (USD, two judges, estimate) | C39: =0.02 -> 0.02
A40: Cost input value | C40: 0
A41: Cost input value > Narration price per page | C41: =0.002 -> 0.002
A42: Cost input value > Pages per story | C42: =8 -> 8
A43: Cost input value > Picture price each | C43: =0.04 -> 0.04
A44: Cost input value > Sampled share of gated uplift | C44: =0.7 -> 0.7
A45: Cost input value > Text and verification B0 ungated | C45: =0.0097 -> 0.0097
A46: Cost input value > Text and verification B1 gated | C46: =0.0199 -> 0.0199
A47: Ending customers | B47: =SUM('Model inputs'!B48,'Model inputs'!B49) -> 77.51602 | E47: =SUM('Model inputs'!E48,'Model inputs'!E49) -> 50 | F47: =SUM('Model inputs'!F48,'Model inputs'!F49) -> 55.5 | G47: =SUM('Model inputs'!G48,'Model inputs'!G49) -> 60.595 | H47: =SUM('Model inputs'!H48,'Model inputs'!H49) -> 65.31635 | I47: =SUM('Model inputs'!I48,'Model inputs'!I49) -> 69.692923 | J47: =SUM('Model inputs'!J48,'Model inputs'!J49) -> 73.751315 | K47: =SUM('Model inputs'!K48,'Model inputs'!K49) -> 81.009604 | L47: =SUM('Model inputs'!L48,'Model inputs'!L49) -> 84.252856 | ... P47: =SUM('Model inputs'!P48,'Model inputs'!P49) -> 95.083695
A48: Ending customers > Classroom | B48: ='Model inputs'!J48+'Model inputs'!B99-'Model inputs'!B93 -> 13.89732 | E48: =IF('Model inputs'!C109="","",'Model inputs'!C109) -> 10 | F48: ='Model inputs'!E48+'Model inputs'!F99-'Model inputs'!F93 -> 10.7 | G48: ='Model inputs'!F48+'Model inputs'!G99-'Model inputs'!G93 -> 11.379 | H48: ='Model inputs'!G48+'Model inputs'!H99-'Model inputs'!H93 -> 12.03763 | I48: ='Model inputs'!H48+'Model inputs'!I99-'Model inputs'!I93 -> 12.676501 | J48: ='Model inputs'!I48+'Model inputs'!J99-'Model inputs'!J93 -> 13.296206 | K48: ='Model inputs'!B48+'Model inputs'!K99-'Model inputs'!K93 -> 14.4804 | L48: ='Model inputs'!K48+'Model inputs'!L99-'Model inputs'!L93 -> 15.045988 | M48: ='Model inputs'!L48+'Model inputs'!M99-'Model inputs'!M93 -> 15.594609 | N48: ='Model inputs'!M48+'Model inputs'!N99-'Model inputs'!N93 -> 16.12677 | O48: ='Model inputs'!N48+'Model inputs'!O99-'Model inputs'!O93 -> 16.642967 | P48: ='Model inputs'!O48+'Model inputs'!P99-'Model inputs'!P93 -> 17.143678
A49: Ending customers > Household | B49: ='Model inputs'!J49+'Model inputs'!B100-'Model inputs'!B94 -> 63.6187 | E49: =IF('Model inputs'!C110="","",'Model inputs'!C110) -> 40 | F49: ='Model inputs'!E49+'Model inputs'!F100-'Model inputs'!F94 -> 44.8 | G49: ='Model inputs'!F49+'Model inputs'!G100-'Model inputs'!G94 -> 49.216 | H49: ='Model inputs'!G49+'Model inputs'!H100-'Model inputs'!H94 -> 53.27872 | I49: ='Model inputs'!H49+'Model inputs'!I100-'Model inputs'!I94 -> 57.016422 | J49: ='Model inputs'!I49+'Model inputs'!J100-'Model inputs'!J94 -> 60.455109 | K49: ='Model inputs'!B49+'Model inputs'!K100-'Model inputs'!K94 -> 66.529204 | L49: ='Model inputs'!K49+'Model inputs'!L100-'Model inputs'!L94 -> 69.206868 | M49: ='Model inputs'!L49+'Model inputs'!M100-'Model inputs'!M94 -> 71.670318 | N49: ='Model inputs'!M49+'Model inputs'!N100-'Model inputs'!N94 -> 73.936693 | O49: ='Model inputs'!N49+'Model inputs'!O100-'Model inputs'!O94 -> 76.021757 | P49: ='Model inputs'!O49+'Model inputs'!P100-'Model inputs'!P94 -> 77.940017
A50: Gross profit (USD) · Gross margin | B50: =SUM('Model inputs'!B96,'Model inputs'!B97) -> 569.63499
A51: Illustration policy selected (1 = yes, assumed) | D51: 0
A52: Illustration policy selected (1 = yes, assumed) > Full (8 pictures) | D52: =0 -> 0
A53: Illustration policy selected (1 = yes, assumed) > Half (4 pictures) | D53: =1 -> 1
A54: Illustration policy selected (1 = yes, assumed) > Text only (0) | D54: =0 -> 0
A55: neatlogs covered by hackathon credits (1 = yes, assumed) · Verification and illustration policy: cost, margin and bar | C55: =1 -> 1
A56: neatlogs Free plan span cap (published price, unverified for credits) · Verification and illustration policy: cost, margin and bar | C56: =100000 -> 100000
A57: neatlogs price per extra 100k spans (USD, published price) · Verification and illustration policy: cost, margin and bar | C57: =10 -> 10
A58: neatlogs Starter plan included spans (published price) · Verification and illustration policy: cost, margin and bar | C58: =250000 -> 250000
A59: neatlogs Starter plan price per month (USD, published price) · Verification and illustration policy: cost, margin and bar | C59: =99 -> 99
A60: Overage revenue (USD) | B60: =SUM('Model inputs'!B61,'Model inputs'!B62) -> 0 | E60: =SUM('Model inputs'!E61,'Model inputs'!E62) -> 0 | F60: =SUM('Model inputs'!F61,'Model inputs'!F62) -> 0 | G60: =SUM('Model inputs'!G61,'Model inputs'!G62) -> 0 | H60: =SUM('Model inputs'!H61,'Model inputs'!H62) -> 0 | I60: =SUM('Model inputs'!I61,'Model inputs'!I62) -> 0 | J60: =SUM('Model inputs'!J61,'Model inputs'!J62) -> 0 | K60: =SUM('Model inputs'!K61,'Model inputs'!K62) -> 0 | L60: =SUM('Model inputs'!L61,'Model inputs'!L62) -> 0 | ... P60: =SUM('Model inputs'!P61,'Model inputs'!P62) -> 0
A61: Overage revenue (USD) > Classroom | B61: ='Model inputs'!B48*IF(IF(IF(IF(ISERROR('Model inputs'!C77>'Model inputs'!C112),'Model inputs'!C77>'Model inputs'!C112,IF(OR('Model inputs'!C77="",'Model inputs'!C112=""),"",'Model inputs'!C77>'Model inputs'!C112))="",FALSE,IF(ISERROR('Model inputs'!C77>'Model inputs'!C112),'Model inputs'!C77>'Model inputs'!C112,IF(OR('Model inputs'!C77="",'Model inputs'!C112=""),"",'Model inputs'!C77>'Model inputs'!C112))),('Model inputs'!C77-'Model inputs'!C112)*'Model inputs'!C102,0)="",0,IF(IF(IF(ISERROR('Model inputs'!C77>'Model inputs'!C112),'Model inputs'!C77>'Model inputs'!C112,IF(OR('Model inputs'!C77="",'Model inputs'!C112=""),"",'Model inputs'!C77>'Model inputs'!C112))="",FALSE,IF(ISERROR('Model inputs'!C77>'Model inputs'!C112),'Model inputs'!C77>'Model inputs'!C112,IF(OR('Model inputs'!C77="",'Model inputs'!C112=""),"",'Model inputs'!C77>'Model inputs'!C112))),('Model inputs'!C77-'Model inputs'!C112)*'Model inputs'!C102,0)) -> 0 | E61: =0 -> 0 | F61: ='Model inputs'!F48*IF(IF(IF(IF(ISERROR('Model inputs'!C77>'Model inputs'!C112),'Model inputs'!C77>'Model inputs'!C112,IF(OR('Model inputs'!C77="",'Model inputs'!C112=""),"",'Model inputs'!C77>'Model inputs'!C112))="",FALSE,IF(ISERROR('Model inputs'!C77>'Model inputs'!C112),'Model inputs'!C77>'Model inputs'!C112,IF(OR('Model inputs'!C77="",'Model inputs'!C112=""),"",'Model inputs'!C77>'Model inputs'!C112))),('Model inputs'!C77-'Model inputs'!C112)*'Model inputs'!C102,0)="",0,IF(IF(IF(ISERROR('Model inputs'!C77>'Model inputs'!C112),'Model inputs'!C77>'Model inputs'!C112,IF(OR('Model inputs'!C77="",'Model inputs'!C112=""),"",'Model inputs'!C77>'Model inputs'!C112))="",FALSE,IF(ISERROR('Model inputs'!C77>'Model inputs'!C112),'Model inputs'!C77>'Model inputs'!C112,IF(OR('Model inputs'!C77="",'Model inputs'!C112=""),"",'Model inputs'!C77>'Model inputs'!C112))),('Model inputs'!C77-'Model inputs'!C112)*'Model inputs'!C102,0)) -> 0 | G61: ='Model inputs'!G48*IF(IF(IF(IF(ISERROR('Model inputs'!C77>'Model inputs'!C112),'Model inputs'!C77>'Model inputs'!C112,IF(OR('Model inputs'!C77="",'Model inputs'!C112=""),"",'Model inputs'!C77>'Model inputs'!C112))="",FALSE,IF(ISERROR('Model inputs'!C77>'Model inputs'!C112),'Model inputs'!C77>'Model inputs'!C112,IF(OR('Model inputs'!C77="",'Model inputs'!C112=""),"",'Model inputs'!C77>'Model inputs'!C112))),('Model inputs'!C77-'Model inputs'!C112)*'Model inputs'!C102,0)="",0,IF(IF(IF(ISERROR('Model inputs'!C77>'Model inputs'!C112),'Model inputs'!C77>'Model inputs'!C112,IF(OR('Model inputs'!C77="",'Model inputs'!C112=""),"",'Model inputs'!C77>'Model inputs'!C112))="",FALSE,IF(ISERROR('Model inputs'!C77>'Model inputs'!C112),'Model inputs'!C77>'Model inputs'!C112,IF(OR('Model inputs'!C77="",'Model inputs'!C112=""),"",'Model inputs'!C77>'Model inputs'!C112))),('Model inputs'!C77-'Model inputs'!C112)*'Model inputs'!C102,0)) -> 0 | H61: ='Model inputs'!H48*IF(IF(IF(IF(ISERROR('Model inputs'!C77>'Model inputs'!C112),'Model inputs'!C77>'Model inputs'!C112,IF(OR('Model inputs'!C77="",'Model inputs'!C112=""),"",'Model inputs'!C77>'Model inputs'!C112))="",FALSE,IF(ISERROR('Model inputs'!C77>'Model inputs'!C112),'Model inputs'!C77>'Model inputs'!C112,IF(OR('Model inputs'!C77="",'Model inputs'!C112=""),"",'Model inputs'!C77>'Model inputs'!C112))),('Model inputs'!C77-'Model inputs'!C112)*'Model inputs'!C102,0)="",0,IF(IF(IF(ISERROR('Model inputs'!C77>'Model inputs'!C112),'Model inputs'!C77>'Model inputs'!C112,IF(OR('Model inputs'!C77="",'Model inputs'!C112=""),"",'Model inputs'!C77>'Model inputs'!C112))="",FALSE,IF(ISERROR('Model inputs'!C77>'Model inputs'!C112),'Model inputs'!C77>'Model inputs'!C112,IF(OR('Model inputs'!C77="",'Model inputs'!C112=""),"",'Model inputs'!C77>'Model inputs'!C112))),('Model inputs'!C77-'Model inputs'!C112)*'Model inputs'!C102,0)) -> 0 | I61: ='Model inputs'!I48*IF(IF(IF(IF(ISERROR('Model inputs'!C77>'Model inputs'!C112),'Model inputs'!C77>'Model inputs'!C112,IF(OR('Model inputs'!C77="",'Model inputs'!C112=""),"",'Model inputs'!C77>'Model inputs'!C112))="",FALSE,IF(ISERROR('Model inputs'!C77>'Model inputs'!C112),'Model inputs'!C77>'Model inputs'!C112,IF(OR('Model inputs'!C77="",'Model inputs'!C112=""),"",'Model inputs'!C77>'Model inputs'!C112))),('Model inputs'!C77-'Model inputs'!C112)*'Model inputs'!C102,0)="",0,IF(IF(IF(ISERROR('Model inputs'!C77>'Model inputs'!C112),'Model inputs'!C77>'Model inputs'!C112,IF(OR('Model inputs'!C77="",'Model inputs'!C112=""),"",'Model inputs'!C77>'Model inputs'!C112))="",FALSE,IF(ISERROR('Model inputs'!C77>'Model inputs'!C112),'Model inputs'!C77>'Model inputs'!C112,IF(OR('Model inputs'!C77="",'Model inputs'!C112=""),"",'Model inputs'!C77>'Model inputs'!C112))),('Model inputs'!C77-'Model inputs'!C112)*'Model inputs'!C102,0)) -> 0 | J61: ='Model inputs'!J48*IF(IF(IF(IF(ISERROR('Model inputs'!C77>'Model inputs'!C112),'Model inputs'!C77>'Model inputs'!C112,IF(OR('Model inputs'!C77="",'Model inputs'!C112=""),"",'Model inputs'!C77>'Model inputs'!C112))="",FALSE,IF(ISERROR('Model inputs'!C77>'Model inputs'!C112),'Model inputs'!C77>'Model inputs'!C112,IF(OR('Model inputs'!C77="",'Model inputs'!C112=""),"",'Model inputs'!C77>'Model inputs'!C112))),('Model inputs'!C77-'Model inputs'!C112)*'Model inputs'!C102,0)="",0,IF(IF(IF(ISERROR('Model inputs'!C77>'Model inputs'!C112),'Model inputs'!C77>'Model inputs'!C112,IF(OR('Model inputs'!C77="",'Model inputs'!C112=""),"",'Model inputs'!C77>'Model inputs'!C112))="",FALSE,IF(ISERROR('Model inputs'!C77>'Model inputs'!C112),'Model inputs'!C77>'Model inputs'!C112,IF(OR('Model inputs'!C77="",'Model inputs'!C112=""),"",'Model inputs'!C77>'Model inputs'!C112))),('Model inputs'!C77-'Model inputs'!C112)*'Model inputs'!C102,0)) -> 0 | K61: ='Model inputs'!K48*IF(IF(IF(IF(ISERROR('Model inputs'!C77>'Model inputs'!C112),'Model inputs'!C77>'Model inputs'!C112,IF(OR('Model inputs'!C77="",'Model inputs'!C112=""),"",'Model inputs'!C77>'Model inputs'!C112))="",FALSE,IF(ISERROR('Model inputs'!C77>'Model inputs'!C112),'Model inputs'!C77>'Model inputs'!C112,IF(OR('Model inputs'!C77="",'Model inputs'!C112=""),"",'Model inputs'!C77>'Model inputs'!C112))),('Model inputs'!C77-'Model inputs'!C112)*'Model inputs'!C102,0)="",0,IF(IF(IF(ISERROR('Model inputs'!C77>'Model inputs'!C112),'Model inputs'!C77>'Model inputs'!C112,IF(OR('Model inputs'!C77="",'Model inputs'!C112=""),"",'Model inputs'!C77>'Model inputs'!C112))="",FALSE,IF(ISERROR('Model inputs'!C77>'Model inputs'!C112),'Model inputs'!C77>'Model inputs'!C112,IF(OR('Model inputs'!C77="",'Model inputs'!C112=""),"",'Model inputs'!C77>'Model inputs'!C112))),('Model inputs'!C77-'Model inputs'!C112)*'Model inputs'!C102,0)) -> 0 | L61: ='Model inputs'!L48*IF(IF(IF(IF(ISERROR('Model inputs'!C77>'Model inputs'!C112),'Model inputs'!C77>'Model inputs'!C112,IF(OR('Model inputs'!C77="",'Model inputs'!C112=""),"",'Model inputs'!C77>'Model inputs'!C112))="",FALSE,IF(ISERROR('Model inputs'!C77>'Model inputs'!C112),'Model inputs'!C77>'Model inputs'!C112,IF(OR('Model inputs'!C77="",'Model inputs'!C112=""),"",'Model inputs'!C77>'Model inputs'!C112))),('Model inputs'!C77-'Model inputs'!C112)*'Model inputs'!C102,0)="",0,IF(IF(IF(ISERROR('Model inputs'!C77>'Model inputs'!C112),'Model inputs'!C77>'Model inputs'!C112,IF(OR('Model inputs'!C77="",'Model inputs'!C112=""),"",'Model inputs'!C77>'Model inputs'!C112))="",FALSE,IF(ISERROR('Model inputs'!C77>'Model inputs'!C112),'Model inputs'!C77>'Model inputs'!C112,IF(OR('Model inputs'!C77="",'Model inputs'!C112=""),"",'Model inputs'!C77>'Model inputs'!C112))),('Model inputs'!C77-'Model inputs'!C112)*'Model inputs'!C102,0)) -> 0 | M61: ='Model inputs'!M48*IF(IF(IF(IF(ISERROR('Model inputs'!C77>'Model inputs'!C112),'Model inputs'!C77>'Model inputs'!C112,IF(OR('Model inputs'!C77="",'Model inputs'!C112=""),"",'Model inputs'!C77>'Model inputs'!C112))="",FALSE,IF(ISERROR('Model inputs'!C77>'Model inputs'!C112),'Model inputs'!C77>'Model inputs'!C112,IF(OR('Model inputs'!C77="",'Model inputs'!C112=""),"",'Model inputs'!C77>'Model inputs'!C112))),('Model inputs'!C77-'Model inputs'!C112)*'Model inputs'!C102,0)="",0,IF(IF(IF(ISERROR('Model inputs'!C77>'Model inputs'!C112),'Model inputs'!C77>'Model inputs'!C112,IF(OR('Model inputs'!C77="",'Model inputs'!C112=""),"",'Model inputs'!C77>'Model inputs'!C112))="",FALSE,IF(ISERROR('Model inputs'!C77>'Model inputs'!C112),'Model inputs'!C77>'Model inputs'!C112,IF(OR('Model inputs'!C77="",'Model inputs'!C112=""),"",'Model inputs'!C77>'Model inputs'!C112))),('Model inputs'!C77-'Model inputs'!C112)*'Model inputs'!C102,0)) -> 0 | N61: ='Model inputs'!N48*IF(IF(IF(IF(ISERROR('Model inputs'!C77>'Model inputs'!C112),'Model inputs'!C77>'Model inputs'!C112,IF(OR('Model inputs'!C77="",'Model inputs'!C112=""),"",'Model inputs'!C77>'Model inputs'!C112))="",FALSE,IF(ISERROR('Model inputs'!C77>'Model inputs'!C112),'Model inputs'!C77>'Model inputs'!C112,IF(OR('Model inputs'!C77="",'Model inputs'!C112=""),"",'Model inputs'!C77>'Model inputs'!C112))),('Model inputs'!C77-'Model inputs'!C112)*'Model inputs'!C102,0)="",0,IF(IF(IF(ISERROR('Model inputs'!C77>'Model inputs'!C112),'Model inputs'!C77>'Model inputs'!C112,IF(OR('Model inputs'!C77="",'Model inputs'!C112=""),"",'Model inputs'!C77>'Model inputs'!C112))="",FALSE,IF(ISERROR('Model inputs'!C77>'Model inputs'!C112),'Model inputs'!C77>'Model inputs'!C112,IF(OR('Model inputs'!C77="",'Model inputs'!C112=""),"",'Model inputs'!C77>'Model inputs'!C112))),('Model inputs'!C77-'Model inputs'!C112)*'Model inputs'!C102,0)) -> 0 | O61: ='Model inputs'!O48*IF(IF(IF(IF(ISERROR('Model inputs'!C77>'Model inputs'!C112),'Model inputs'!C77>'Model inputs'!C112,IF(OR('Model inputs'!C77="",'Model inputs'!C112=""),"",'Model inputs'!C77>'Model inputs'!C112))="",FALSE,IF(ISERROR('Model inputs'!C77>'Model inputs'!C112),'Model inputs'!C77>'Model inputs'!C112,IF(OR('Model inputs'!C77="",'Model inputs'!C112=""),"",'Model inputs'!C77>'Model inputs'!C112))),('Model inputs'!C77-'Model inputs'!C112)*'Model inputs'!C102,0)="",0,IF(IF(IF(ISERROR('Model inputs'!C77>'Model inputs'!C112),'Model inputs'!C77>'Model inputs'!C112,IF(OR('Model inputs'!C77="",'Model inputs'!C112=""),"",'Model inputs'!C77>'Model inputs'!C112))="",FALSE,IF(ISERROR('Model inputs'!C77>'Model inputs'!C112),'Model inputs'!C77>'Model inputs'!C112,IF(OR('Model inputs'!C77="",'Model inputs'!C112=""),"",'Model inputs'!C77>'Model inputs'!C112))),('Model inputs'!C77-'Model inputs'!C112)*'Model inputs'!C102,0)) -> 0 | P61: ='Model inputs'!P48*IF(IF(IF(IF(ISERROR('Model inputs'!C77>'Model inputs'!C112),'Model inputs'!C77>'Model inputs'!C112,IF(OR('Model inputs'!C77="",'Model inputs'!C112=""),"",'Model inputs'!C77>'Model inputs'!C112))="",FALSE,IF(ISERROR('Model inputs'!C77>'Model inputs'!C112),'Model inputs'!C77>'Model inputs'!C112,IF(OR('Model inputs'!C77="",'Model inputs'!C112=""),"",'Model inputs'!C77>'Model inputs'!C112))),('Model inputs'!C77-'Model inputs'!C112)*'Model inputs'!C102,0)="",0,IF(IF(IF(ISERROR('Model inputs'!C77>'Model inputs'!C112),'Model inputs'!C77>'Model inputs'!C112,IF(OR('Model inputs'!C77="",'Model inputs'!C112=""),"",'Model inputs'!C77>'Model inputs'!C112))="",FALSE,IF(ISERROR('Model inputs'!C77>'Model inputs'!C112),'Model inputs'!C77>'Model inputs'!C112,IF(OR('Model inputs'!C77="",'Model inputs'!C112=""),"",'Model inputs'!C77>'Model inputs'!C112))),('Model inputs'!C77-'Model inputs'!C112)*'Model inputs'!C102,0)) -> 0
A62: Overage revenue (USD) > Household | B62: ='Model inputs'!B49*IF(IF(IF(IF(ISERROR('Model inputs'!C78>'Model inputs'!C113),'Model inputs'!C78>'Model inputs'!C113,IF(OR('Model inputs'!C78="",'Model inputs'!C113=""),"",'Model inputs'!C78>'Model inputs'!C113))="",FALSE,IF(ISERROR('Model inputs'!C78>'Model inputs'!C113),'Model inputs'!C78>'Model inputs'!C113,IF(OR('Model inputs'!C78="",'Model inputs'!C113=""),"",'Model inputs'!C78>'Model inputs'!C113))),('Model inputs'!C78-'Model inputs'!C113)*'Model inputs'!C103,0)="",0,IF(IF(IF(ISERROR('Model inputs'!C78>'Model inputs'!C113),'Model inputs'!C78>'Model inputs'!C113,IF(OR('Model inputs'!C78="",'Model inputs'!C113=""),"",'Model inputs'!C78>'Model inputs'!C113))="",FALSE,IF(ISERROR('Model inputs'!C78>'Model inputs'!C113),'Model inputs'!C78>'Model inputs'!C113,IF(OR('Model inputs'!C78="",'Model inputs'!C113=""),"",'Model inputs'!C78>'Model inputs'!C113))),('Model inputs'!C78-'Model inputs'!C113)*'Model inputs'!C103,0)) -> 0 | E62: =0 -> 0 | F62: ='Model inputs'!F49*IF(IF(IF(IF(ISERROR('Model inputs'!C78>'Model inputs'!C113),'Model inputs'!C78>'Model inputs'!C113,IF(OR('Model inputs'!C78="",'Model inputs'!C113=""),"",'Model inputs'!C78>'Model inputs'!C113))="",FALSE,IF(ISERROR('Model inputs'!C78>'Model inputs'!C113),'Model inputs'!C78>'Model inputs'!C113,IF(OR('Model inputs'!C78="",'Model inputs'!C113=""),"",'Model inputs'!C78>'Model inputs'!C113))),('Model inputs'!C78-'Model inputs'!C113)*'Model inputs'!C103,0)="",0,IF(IF(IF(ISERROR('Model inputs'!C78>'Model inputs'!C113),'Model inputs'!C78>'Model inputs'!C113,IF(OR('Model inputs'!C78="",'Model inputs'!C113=""),"",'Model inputs'!C78>'Model inputs'!C113))="",FALSE,IF(ISERROR('Model inputs'!C78>'Model inputs'!C113),'Model inputs'!C78>'Model inputs'!C113,IF(OR('Model inputs'!C78="",'Model inputs'!C113=""),"",'Model inputs'!C78>'Model inputs'!C113))),('Model inputs'!C78-'Model inputs'!C113)*'Model inputs'!C103,0)) -> 0 | G62: ='Model inputs'!G49*IF(IF(IF(IF(ISERROR('Model inputs'!C78>'Model inputs'!C113),'Model inputs'!C78>'Model inputs'!C113,IF(OR('Model inputs'!C78="",'Model inputs'!C113=""),"",'Model inputs'!C78>'Model inputs'!C113))="",FALSE,IF(ISERROR('Model inputs'!C78>'Model inputs'!C113),'Model inputs'!C78>'Model inputs'!C113,IF(OR('Model inputs'!C78="",'Model inputs'!C113=""),"",'Model inputs'!C78>'Model inputs'!C113))),('Model inputs'!C78-'Model inputs'!C113)*'Model inputs'!C103,0)="",0,IF(IF(IF(ISERROR('Model inputs'!C78>'Model inputs'!C113),'Model inputs'!C78>'Model inputs'!C113,IF(OR('Model inputs'!C78="",'Model inputs'!C113=""),"",'Model inputs'!C78>'Model inputs'!C113))="",FALSE,IF(ISERROR('Model inputs'!C78>'Model inputs'!C113),'Model inputs'!C78>'Model inputs'!C113,IF(OR('Model inputs'!C78="",'Model inputs'!C113=""),"",'Model inputs'!C78>'Model inputs'!C113))),('Model inputs'!C78-'Model inputs'!C113)*'Model inputs'!C103,0)) -> 0 | H62: ='Model inputs'!H49*IF(IF(IF(IF(ISERROR('Model inputs'!C78>'Model inputs'!C113),'Model inputs'!C78>'Model inputs'!C113,IF(OR('Model inputs'!C78="",'Model inputs'!C113=""),"",'Model inputs'!C78>'Model inputs'!C113))="",FALSE,IF(ISERROR('Model inputs'!C78>'Model inputs'!C113),'Model inputs'!C78>'Model inputs'!C113,IF(OR('Model inputs'!C78="",'Model inputs'!C113=""),"",'Model inputs'!C78>'Model inputs'!C113))),('Model inputs'!C78-'Model inputs'!C113)*'Model inputs'!C103,0)="",0,IF(IF(IF(ISERROR('Model inputs'!C78>'Model inputs'!C113),'Model inputs'!C78>'Model inputs'!C113,IF(OR('Model inputs'!C78="",'Model inputs'!C113=""),"",'Model inputs'!C78>'Model inputs'!C113))="",FALSE,IF(ISERROR('Model inputs'!C78>'Model inputs'!C113),'Model inputs'!C78>'Model inputs'!C113,IF(OR('Model inputs'!C78="",'Model inputs'!C113=""),"",'Model inputs'!C78>'Model inputs'!C113))),('Model inputs'!C78-'Model inputs'!C113)*'Model inputs'!C103,0)) -> 0 | I62: ='Model inputs'!I49*IF(IF(IF(IF(ISERROR('Model inputs'!C78>'Model inputs'!C113),'Model inputs'!C78>'Model inputs'!C113,IF(OR('Model inputs'!C78="",'Model inputs'!C113=""),"",'Model inputs'!C78>'Model inputs'!C113))="",FALSE,IF(ISERROR('Model inputs'!C78>'Model inputs'!C113),'Model inputs'!C78>'Model inputs'!C113,IF(OR('Model inputs'!C78="",'Model inputs'!C113=""),"",'Model inputs'!C78>'Model inputs'!C113))),('Model inputs'!C78-'Model inputs'!C113)*'Model inputs'!C103,0)="",0,IF(IF(IF(ISERROR('Model inputs'!C78>'Model inputs'!C113),'Model inputs'!C78>'Model inputs'!C113,IF(OR('Model inputs'!C78="",'Model inputs'!C113=""),"",'Model inputs'!C78>'Model inputs'!C113))="",FALSE,IF(ISERROR('Model inputs'!C78>'Model inputs'!C113),'Model inputs'!C78>'Model inputs'!C113,IF(OR('Model inputs'!C78="",'Model inputs'!C113=""),"",'Model inputs'!C78>'Model inputs'!C113))),('Model inputs'!C78-'Model inputs'!C113)*'Model inputs'!C103,0)) -> 0 | J62: ='Model inputs'!J49*IF(IF(IF(IF(ISERROR('Model inputs'!C78>'Model inputs'!C113),'Model inputs'!C78>'Model inputs'!C113,IF(OR('Model inputs'!C78="",'Model inputs'!C113=""),"",'Model inputs'!C78>'Model inputs'!C113))="",FALSE,IF(ISERROR('Model inputs'!C78>'Model inputs'!C113),'Model inputs'!C78>'Model inputs'!C113,IF(OR('Model inputs'!C78="",'Model inputs'!C113=""),"",'Model inputs'!C78>'Model inputs'!C113))),('Model inputs'!C78-'Model inputs'!C113)*'Model inputs'!C103,0)="",0,IF(IF(IF(ISERROR('Model inputs'!C78>'Model inputs'!C113),'Model inputs'!C78>'Model inputs'!C113,IF(OR('Model inputs'!C78="",'Model inputs'!C113=""),"",'Model inputs'!C78>'Model inputs'!C113))="",FALSE,IF(ISERROR('Model inputs'!C78>'Model inputs'!C113),'Model inputs'!C78>'Model inputs'!C113,IF(OR('Model inputs'!C78="",'Model inputs'!C113=""),"",'Model inputs'!C78>'Model inputs'!C113))),('Model inputs'!C78-'Model inputs'!C113)*'Model inputs'!C103,0)) -> 0 | K62: ='Model inputs'!K49*IF(IF(IF(IF(ISERROR('Model inputs'!C78>'Model inputs'!C113),'Model inputs'!C78>'Model inputs'!C113,IF(OR('Model inputs'!C78="",'Model inputs'!C113=""),"",'Model inputs'!C78>'Model inputs'!C113))="",FALSE,IF(ISERROR('Model inputs'!C78>'Model inputs'!C113),'Model inputs'!C78>'Model inputs'!C113,IF(OR('Model inputs'!C78="",'Model inputs'!C113=""),"",'Model inputs'!C78>'Model inputs'!C113))),('Model inputs'!C78-'Model inputs'!C113)*'Model inputs'!C103,0)="",0,IF(IF(IF(ISERROR('Model inputs'!C78>'Model inputs'!C113),'Model inputs'!C78>'Model inputs'!C113,IF(OR('Model inputs'!C78="",'Model inputs'!C113=""),"",'Model inputs'!C78>'Model inputs'!C113))="",FALSE,IF(ISERROR('Model inputs'!C78>'Model inputs'!C113),'Model inputs'!C78>'Model inputs'!C113,IF(OR('Model inputs'!C78="",'Model inputs'!C113=""),"",'Model inputs'!C78>'Model inputs'!C113))),('Model inputs'!C78-'Model inputs'!C113)*'Model inputs'!C103,0)) -> 0 | L62: ='Model inputs'!L49*IF(IF(IF(IF(ISERROR('Model inputs'!C78>'Model inputs'!C113),'Model inputs'!C78>'Model inputs'!C113,IF(OR('Model inputs'!C78="",'Model inputs'!C113=""),"",'Model inputs'!C78>'Model inputs'!C113))="",FALSE,IF(ISERROR('Model inputs'!C78>'Model inputs'!C113),'Model inputs'!C78>'Model inputs'!C113,IF(OR('Model inputs'!C78="",'Model inputs'!C113=""),"",'Model inputs'!C78>'Model inputs'!C113))),('Model inputs'!C78-'Model inputs'!C113)*'Model inputs'!C103,0)="",0,IF(IF(IF(ISERROR('Model inputs'!C78>'Model inputs'!C113),'Model inputs'!C78>'Model inputs'!C113,IF(OR('Model inputs'!C78="",'Model inputs'!C113=""),"",'Model inputs'!C78>'Model inputs'!C113))="",FALSE,IF(ISERROR('Model inputs'!C78>'Model inputs'!C113),'Model inputs'!C78>'Model inputs'!C113,IF(OR('Model inputs'!C78="",'Model inputs'!C113=""),"",'Model inputs'!C78>'Model inputs'!C113))),('Model inputs'!C78-'Model inputs'!C113)*'Model inputs'!C103,0)) -> 0 | M62: ='Model inputs'!M49*IF(IF(IF(IF(ISERROR('Model inputs'!C78>'Model inputs'!C113),'Model inputs'!C78>'Model inputs'!C113,IF(OR('Model inputs'!C78="",'Model inputs'!C113=""),"",'Model inputs'!C78>'Model inputs'!C113))="",FALSE,IF(ISERROR('Model inputs'!C78>'Model inputs'!C113),'Model inputs'!C78>'Model inputs'!C113,IF(OR('Model inputs'!C78="",'Model inputs'!C113=""),"",'Model inputs'!C78>'Model inputs'!C113))),('Model inputs'!C78-'Model inputs'!C113)*'Model inputs'!C103,0)="",0,IF(IF(IF(ISERROR('Model inputs'!C78>'Model inputs'!C113),'Model inputs'!C78>'Model inputs'!C113,IF(OR('Model inputs'!C78="",'Model inputs'!C113=""),"",'Model inputs'!C78>'Model inputs'!C113))="",FALSE,IF(ISERROR('Model inputs'!C78>'Model inputs'!C113),'Model inputs'!C78>'Model inputs'!C113,IF(OR('Model inputs'!C78="",'Model inputs'!C113=""),"",'Model inputs'!C78>'Model inputs'!C113))),('Model inputs'!C78-'Model inputs'!C113)*'Model inputs'!C103,0)) -> 0 | N62: ='Model inputs'!N49*IF(IF(IF(IF(ISERROR('Model inputs'!C78>'Model inputs'!C113),'Model inputs'!C78>'Model inputs'!C113,IF(OR('Model inputs'!C78="",'Model inputs'!C113=""),"",'Model inputs'!C78>'Model inputs'!C113))="",FALSE,IF(ISERROR('Model inputs'!C78>'Model inputs'!C113),'Model inputs'!C78>'Model inputs'!C113,IF(OR('Model inputs'!C78="",'Model inputs'!C113=""),"",'Model inputs'!C78>'Model inputs'!C113))),('Model inputs'!C78-'Model inputs'!C113)*'Model inputs'!C103,0)="",0,IF(IF(IF(ISERROR('Model inputs'!C78>'Model inputs'!C113),'Model inputs'!C78>'Model inputs'!C113,IF(OR('Model inputs'!C78="",'Model inputs'!C113=""),"",'Model inputs'!C78>'Model inputs'!C113))="",FALSE,IF(ISERROR('Model inputs'!C78>'Model inputs'!C113),'Model inputs'!C78>'Model inputs'!C113,IF(OR('Model inputs'!C78="",'Model inputs'!C113=""),"",'Model inputs'!C78>'Model inputs'!C113))),('Model inputs'!C78-'Model inputs'!C113)*'Model inputs'!C103,0)) -> 0 | O62: ='Model inputs'!O49*IF(IF(IF(IF(ISERROR('Model inputs'!C78>'Model inputs'!C113),'Model inputs'!C78>'Model inputs'!C113,IF(OR('Model inputs'!C78="",'Model inputs'!C113=""),"",'Model inputs'!C78>'Model inputs'!C113))="",FALSE,IF(ISERROR('Model inputs'!C78>'Model inputs'!C113),'Model inputs'!C78>'Model inputs'!C113,IF(OR('Model inputs'!C78="",'Model inputs'!C113=""),"",'Model inputs'!C78>'Model inputs'!C113))),('Model inputs'!C78-'Model inputs'!C113)*'Model inputs'!C103,0)="",0,IF(IF(IF(ISERROR('Model inputs'!C78>'Model inputs'!C113),'Model inputs'!C78>'Model inputs'!C113,IF(OR('Model inputs'!C78="",'Model inputs'!C113=""),"",'Model inputs'!C78>'Model inputs'!C113))="",FALSE,IF(ISERROR('Model inputs'!C78>'Model inputs'!C113),'Model inputs'!C78>'Model inputs'!C113,IF(OR('Model inputs'!C78="",'Model inputs'!C113=""),"",'Model inputs'!C78>'Model inputs'!C113))),('Model inputs'!C78-'Model inputs'!C113)*'Model inputs'!C103,0)) -> 0 | P62: ='Model inputs'!P49*IF(IF(IF(IF(ISERROR('Model inputs'!C78>'Model inputs'!C113),'Model inputs'!C78>'Model inputs'!C113,IF(OR('Model inputs'!C78="",'Model inputs'!C113=""),"",'Model inputs'!C78>'Model inputs'!C113))="",FALSE,IF(ISERROR('Model inputs'!C78>'Model inputs'!C113),'Model inputs'!C78>'Model inputs'!C113,IF(OR('Model inputs'!C78="",'Model inputs'!C113=""),"",'Model inputs'!C78>'Model inputs'!C113))),('Model inputs'!C78-'Model inputs'!C113)*'Model inputs'!C103,0)="",0,IF(IF(IF(ISERROR('Model inputs'!C78>'Model inputs'!C113),'Model inputs'!C78>'Model inputs'!C113,IF(OR('Model inputs'!C78="",'Model inputs'!C113=""),"",'Model inputs'!C78>'Model inputs'!C113))="",FALSE,IF(ISERROR('Model inputs'!C78>'Model inputs'!C113),'Model inputs'!C78>'Model inputs'!C113,IF(OR('Model inputs'!C78="",'Model inputs'!C113=""),"",'Model inputs'!C78>'Model inputs'!C113))),('Model inputs'!C78-'Model inputs'!C113)*'Model inputs'!C103,0)) -> 0
A63: Picture and narration cost per story (USD, derived) | D63: ='Model inputs'!C67*'Model inputs'!C43+'Model inputs'!C41*'Model inputs'!C42 -> 0.016
A64: Picture and narration cost per story (USD, derived) > Full (8 pictures) | D64: ='Model inputs'!C68*'Model inputs'!C43+'Model inputs'!C41*'Model inputs'!C42 -> 0.336
A65: Picture and narration cost per story (USD, derived) > Half (4 pictures) | D65: ='Model inputs'!C69*'Model inputs'!C43+'Model inputs'!C41*'Model inputs'!C42 -> 0.176
A66: Picture and narration cost per story (USD, derived) > Text only (0) | D66: ='Model inputs'!C70*'Model inputs'!C43+'Model inputs'!C41*'Model inputs'!C42 -> 0.016
A67: Pictures per story (policy) | C67: 0
A68: Pictures per story (policy) > Full (8 pictures) | C68: =8 -> 8
A69: Pictures per story (policy) > Half (4 pictures) | C69: =4 -> 4
A70: Pictures per story (policy) > Text only (0) | C70: =0 -> 0
A71: Seconds per video clip (assumed) | C71: =4 -> 4
A72: Share of gated uplift paid (derived) | C72: 0.7
A73: Share of gated uplift paid (derived) > Sampled | C73: =IF(EXACT("Sampled","Verify all"),1,IF('Model inputs'!C44="","",'Model inputs'!C44)) -> 0.7
A74: Share of gated uplift paid (derived) > Verify all | C74: =IF(EXACT("Verify all","Verify all"),1,IF('Model inputs'!C44="","",'Model inputs'!C44)) -> 1
A75: Spans per month (derived) · neatlogs bill (USD, derived) · Month 6 reference (company, selected policy) | B75: ='Model inputs'!B30*'Model inputs'!C107 -> 193784.07
A76: Stories used per customer (derived) | C76: ='Model inputs'!C114*'Model inputs'!C111 -> 0
A77: Stories used per customer (derived) > Classroom | C77: ='Model inputs'!C115*'Model inputs'!C112 -> 60
A78: Stories used per customer (derived) > Household | C78: ='Model inputs'!C116*'Model inputs'!C113 -> 7.2
A79: Subscription revenue (USD) | B79: =SUM('Model inputs'!B80,'Model inputs'!B81) -> 847.71699 | E79: =SUM('Model inputs'!E80,'Model inputs'!E81) -> 0 | F79: =SUM('Model inputs'!F80,'Model inputs'!F81) -> 623.452 | G79: =SUM('Model inputs'!G80,'Model inputs'!G81) -> 674.01084 | H79: =SUM('Model inputs'!H80,'Model inputs'!H81) -> 721.50952 | I79: =SUM('Model inputs'!I80,'Model inputs'!I81) -> 766.16332 | J79: =SUM('Model inputs'!J80,'Model inputs'!J81) -> 808.17119 | K79: =SUM('Model inputs'!K80,'Model inputs'!K81) -> 884.97074 | L79: =SUM('Model inputs'!L80,'Model inputs'!L81) -> 920.08966 | ... P79: =SUM('Model inputs'!P80,'Model inputs'!P81) -> 1041.9674
A80: Subscription revenue (USD) > Classroom | B80: ='Model inputs'!B48*'Model inputs'!C105 -> 403.02228 | E80: =0 -> 0 | F80: ='Model inputs'!F48*'Model inputs'!C105 -> 310.3 | G80: ='Model inputs'!G48*'Model inputs'!C105 -> 329.991 | H80: ='Model inputs'!H48*'Model inputs'!C105 -> 349.09127 | I80: ='Model inputs'!I48*'Model inputs'!C105 -> 367.61853 | J80: ='Model inputs'!J48*'Model inputs'!C105 -> 385.58998 | K80: ='Model inputs'!K48*'Model inputs'!C105 -> 419.93161 | L80: ='Model inputs'!L48*'Model inputs'!C105 -> 436.33366 | M80: ='Model inputs'!M48*'Model inputs'!C105 -> 452.24365 | N80: ='Model inputs'!N48*'Model inputs'!C105 -> 467.67634 | O80: ='Model inputs'!O48*'Model inputs'!C105 -> 482.64605 | P80: ='Model inputs'!P48*'Model inputs'!C105 -> 497.16667
A81: Subscription revenue (USD) > Household | B81: ='Model inputs'!B49*'Model inputs'!C106 -> 444.69471 | E81: =0 -> 0 | F81: ='Model inputs'!F49*'Model inputs'!C106 -> 313.152 | G81: ='Model inputs'!G49*'Model inputs'!C106 -> 344.01984 | H81: ='Model inputs'!H49*'Model inputs'!C106 -> 372.41825 | I81: ='Model inputs'!I49*'Model inputs'!C106 -> 398.54479 | J81: ='Model inputs'!J49*'Model inputs'!C106 -> 422.58121 | K81: ='Model inputs'!K49*'Model inputs'!C106 -> 465.03914 | L81: ='Model inputs'!L49*'Model inputs'!C106 -> 483.756 | M81: ='Model inputs'!M49*'Model inputs'!C106 -> 500.97552 | N81: ='Model inputs'!N49*'Model inputs'!C106 -> 516.81748 | O81: ='Model inputs'!O49*'Model inputs'!C106 -> 531.39208 | P81: ='Model inputs'!P49*'Model inputs'!C106 -> 544.80072
A82: Text and verification cost per story (USD, derived) | D82: ='Model inputs'!C45+'Model inputs'!C72*('Model inputs'!C46-'Model inputs'!C45) -> 0.01684
A83: Text and verification cost per story (USD, derived) > Sampled | D83: ='Model inputs'!C45+'Model inputs'!C73*('Model inputs'!C46-'Model inputs'!C45) -> 0.01684
A84: Text and verification cost per story (USD, derived) > Verify all | D84: ='Model inputs'!C45+'Model inputs'!C74*('Model inputs'!C46-'Model inputs'!C45) -> 0.0199
A85: Verification policy selected (1 = yes, assumed) | D85: 0
A86: Verification policy selected (1 = yes, assumed) > Sampled | D86: =0 -> 0
A87: Verification policy selected (1 = yes, assumed) > Verify all | D87: =1 -> 1
A88: Video clips per story (0 = deterministic motion only, as today) | C88: =0 -> 0
A89: Video model price per second (USD, list price estimate) | C89: =0.05 -> 0.05
A90: Video retry allowance (x clips made per clip kept, assumed) | C90: =1.4 -> 1.4
A91: Hosting per month (USD, assumed) · Verification and illustration policy: cost, margin and bar | C91: ='Model inputs'!D11 -> 25
A92: Churned customers | B92: =SUM('Model inputs'!B93,'Model inputs'!B94) -> 5.2352949 | E92: =SUM('Model inputs'!E93,'Model inputs'!E94) -> 0 | F92: =SUM('Model inputs'!F93,'Model inputs'!F94) -> 3.5 | G92: =SUM('Model inputs'!G93,'Model inputs'!G94) -> 3.905 | H92: =SUM('Model inputs'!H93,'Model inputs'!H94) -> 4.27865 | I92: =SUM('Model inputs'!I93,'Model inputs'!I94) -> 4.6234265 | J92: =SUM('Model inputs'!J93,'Model inputs'!J94) -> 4.9416088 | K92: =SUM('Model inputs'!K93,'Model inputs'!K94) -> 5.5064156 | L92: =SUM('Model inputs'!L93,'Model inputs'!L94) -> 5.7567483 | ... P92: =SUM('Model inputs'!P93,'Model inputs'!P94) -> 6.5810296
A93: Churned customers > Classroom | B93: ='Model inputs'!J48*'Model inputs'!C135 -> 0.39888618 | E93: =0 -> 0 | F93: ='Model inputs'!E48*'Model inputs'!C135 -> 0.3 | G93: ='Model inputs'!F48*'Model inputs'!C135 -> 0.321 | H93: ='Model inputs'!G48*'Model inputs'!C135 -> 0.34137 | I93: ='Model inputs'!H48*'Model inputs'!C135 -> 0.3611289 | J93: ='Model inputs'!I48*'Model inputs'!C135 -> 0.38029503 | K93: ='Model inputs'!B48*'Model inputs'!C135 -> 0.4169196 | L93: ='Model inputs'!K48*'Model inputs'!C135 -> 0.43441201 | M93: ='Model inputs'!L48*'Model inputs'!C135 -> 0.45137965 | N93: ='Model inputs'!M48*'Model inputs'!C135 -> 0.46783826 | O93: ='Model inputs'!N48*'Model inputs'!C135 -> 0.48380311 | P93: ='Model inputs'!O48*'Model inputs'!C135 -> 0.49928902
A94: Churned customers > Household | B94: ='Model inputs'!J49*'Model inputs'!C136 -> 4.8364087 | E94: =0 -> 0 | F94: ='Model inputs'!E49*'Model inputs'!C136 -> 3.2 | G94: ='Model inputs'!F49*'Model inputs'!C136 -> 3.584 | H94: ='Model inputs'!G49*'Model inputs'!C136 -> 3.93728 | I94: ='Model inputs'!H49*'Model inputs'!C136 -> 4.2622976 | J94: ='Model inputs'!I49*'Model inputs'!C136 -> 4.5613138 | K94: ='Model inputs'!B49*'Model inputs'!C136 -> 5.089496 | L94: ='Model inputs'!K49*'Model inputs'!C136 -> 5.3223363 | M94: ='Model inputs'!L49*'Model inputs'!C136 -> 5.5365494 | N94: ='Model inputs'!M49*'Model inputs'!C136 -> 5.7336255 | O94: ='Model inputs'!N49*'Model inputs'!C136 -> 5.9149354 | P94: ='Model inputs'!O49*'Model inputs'!C136 -> 6.0817406
A95: Gross profit (USD) | B95: =IF('Model inputs'!B50="","",'Model inputs'!B50) -> 569.63499 | E95: =SUM('Model inputs'!E96,'Model inputs'!E97) -> 0 | F95: =SUM('Model inputs'!F96,'Model inputs'!F97) -> 409.4947 | G95: =SUM('Model inputs'!G96,'Model inputs'!G97) -> 445.84389 | H95: =SUM('Model inputs'!H96,'Model inputs'!H97) -> 479.87065 | I95: =SUM('Model inputs'!I96,'Model inputs'!I97) -> 511.74321 | J95: =SUM('Model inputs'!J96,'Model inputs'!J97) -> 541.61686
A96: Gross profit (USD) > Classroom | B96: ='Model inputs'!B19-'Model inputs'!B132 -> 227.78766 | E96: =0 -> 0 | F96: ='Model inputs'!F19-'Model inputs'!F132 -> 172.08938 | G96: ='Model inputs'!G19-'Model inputs'!G132 -> 184.00241 | H96: ='Model inputs'!H19-'Model inputs'!H132 -> 195.5051 | I96: ='Model inputs'!I19-'Model inputs'!I132 -> 206.6235 | J96: ='Model inputs'!J19-'Model inputs'!J132 -> 217.37851
A97: Gross profit (USD) > Household | B97: ='Model inputs'!B20-'Model inputs'!B133 -> 341.84733 | E97: =0 -> 0 | F97: ='Model inputs'!F20-'Model inputs'!F133 -> 237.40531 | G97: ='Model inputs'!G20-'Model inputs'!G133 -> 261.84148 | H97: ='Model inputs'!H20-'Model inputs'!H133 -> 284.36555 | I97: ='Model inputs'!I20-'Model inputs'!I133 -> 305.11971 | J97: ='Model inputs'!J20-'Model inputs'!J133 -> 324.23834
A98: New customers | B98: =SUM('Model inputs'!B99,'Model inputs'!B100) -> 9 | E98: =SUM('Model inputs'!E99,'Model inputs'!E100) -> 0 | F98: =SUM('Model inputs'!F99,'Model inputs'!F100) -> 9 | G98: =SUM('Model inputs'!G99,'Model inputs'!G100) -> 9 | H98: =SUM('Model inputs'!H99,'Model inputs'!H100) -> 9 | I98: =SUM('Model inputs'!I99,'Model inputs'!I100) -> 9 | J98: =SUM('Model inputs'!J99,'Model inputs'!J100) -> 9 | K98: =SUM('Model inputs'!K99,'Model inputs'!K100) -> 9 | L98: =SUM('Model inputs'!L99,'Model inputs'!L100) -> 9 | ... P98: =SUM('Model inputs'!P99,'Model inputs'!P100) -> 9
A99: New customers > Classroom | B99: =IF('Model inputs'!C138="","",'Model inputs'!C138) -> 1 | E99: =0 -> 0 | F99: =IF('Model inputs'!C138="","",'Model inputs'!C138) -> 1 | G99: =IF('Model inputs'!C138="","",'Model inputs'!C138) -> 1 | H99: =IF('Model inputs'!C138="","",'Model inputs'!C138) -> 1 | I99: =IF('Model inputs'!C138="","",'Model inputs'!C138) -> 1 | J99: =IF('Model inputs'!C138="","",'Model inputs'!C138) -> 1 | K99: =IF('Model inputs'!C138="","",'Model inputs'!C138) -> 1 | L99: =IF('Model inputs'!C138="","",'Model inputs'!C138) -> 1 | M99: =IF('Model inputs'!C138="","",'Model inputs'!C138) -> 1 | N99: =IF('Model inputs'!C138="","",'Model inputs'!C138) -> 1 | O99: =IF('Model inputs'!C138="","",'Model inputs'!C138) -> 1 | P99: =IF('Model inputs'!C138="","",'Model inputs'!C138) -> 1
A100: New customers > Household | B100: =IF('Model inputs'!C139="","",'Model inputs'!C139) -> 8 | E100: =0 -> 0 | F100: =IF('Model inputs'!C139="","",'Model inputs'!C139) -> 8 | G100: =IF('Model inputs'!C139="","",'Model inputs'!C139) -> 8 | H100: =IF('Model inputs'!C139="","",'Model inputs'!C139) -> 8 | I100: =IF('Model inputs'!C139="","",'Model inputs'!C139) -> 8 | J100: =IF('Model inputs'!C139="","",'Model inputs'!C139) -> 8 | K100: =IF('Model inputs'!C139="","",'Model inputs'!C139) -> 8 | L100: =IF('Model inputs'!C139="","",'Model inputs'!C139) -> 8 | M100: =IF('Model inputs'!C139="","",'Model inputs'!C139) -> 8 | N100: =IF('Model inputs'!C139="","",'Model inputs'!C139) -> 8 | O100: =IF('Model inputs'!C139="","",'Model inputs'!C139) -> 8 | P100: =IF('Model inputs'!C139="","",'Model inputs'!C139) -> 8
A101: Overage price per extra story (USD, assumed) | C101: 0
...

Sheet Export notes
A1: Export notes
A2: These cells hold the value cfo.ai calculated instead of a formula. They do not recalculate when you edit an input.
A4: Sheet | B4: Cell | C4: Variable | D4: Period | E4: Scenario | F4: Why
A5: Model inputs | B5: C72 | C5: Share of gated uplift paid (derived) | E5: Main Scenario | F5: It reads Verification policy, which this workbook does not contain.
A6: Model inputs | B6: D128 | C6: Share of gated uplift paid (derived) | E6: Main Scenario | F6: It reads Verification policy, which this workbook does not contain.
